Workbook

Sheet 0. CAPA
A1: MODELO DE ANÁLISE ECM — EQUITY CAPITAL MARKETS
A2: Investment Banking | Área de Equity Capital Markets
A4: EMPRESA ANALISADA
A5: SETOR / SEGMENTO
A6: DATA DA ANÁLISE
A7: ANALISTA RESPONSÁVEL
A8: APROVADO POR (MD/Director)
A9: VERSÃO DO MODELO | B9: v1.0
A10: STATUS | B10: DRAFT
A12: ÍNDICE DO MODELO
A13: 0. CAPA | B13: Identificação e índice do modelo
A14: 1. PREMISSAS | B14: Macro (CDI, IPCA, PIB, câmbio) e operacionais (crescimento, margens, CAPEX)
A15: 2. DRE | B15: Demonstração de Resultado: histórico 2021-2024 + projeções 2025-2029
A16: 3. BALANÇO | B16: Balanço patrimonial projetado — NCG, capital investido, ROIC, ROE
A17: 4. FLUXO | B17: FCO, FCFF, FCFE — índices de qualidade de caixa
A18: 5. WACC | B18: Custo de capital (CAPM) + sensibilidade beta x ERP
A19: 6. DCF | B19: Valuation por fluxo de caixa descontado — Gordon Growth + Exit Multiple
A20: 7. MÚLTIPLOS | B20: Peer group (8 empresas) + transações precedentes
A21: 8. OFERTA | B21: Simulador da oferta — primária/secundária, diluição, greenshoe, fees
A22: 9. RETORNO | B22: TSR, EPS accretion/dilution, dividendos, buyback
A23: 10. SENSIBILIDADE | B23: Análise de cenários e tabelas de sensibilidade bidimensional
A25: CONVENÇÃO DE CORES
A26: Texto nesta cor | B26: Inputs / Premissas (hardcoded — usuário pode alterar)
A27: Texto nesta cor | B27: Fórmulas e cálculos automáticos
A28: Texto nesta cor | B28: Links para outras abas
A29: Texto nesta cor | B29: Links externos / alertas

Sheet 1. PREMISSAS
A1: 1. PREMISSAS MACROECONÔMICAS E OPERACIONAIS — ECM
A2: LINHA / PREMISSA | B2: UNID. | C2: NOTA / FONTE | D2: 2021A | E2: 2022A | F2: 2023A | G2: 2024A | H2: 2025E | I2: 2026E | J2: 2027E | K2: 2028E | L2: 2029E
A3: PREMISSAS MACROECONÔMICAS
A4: CDI (% a.a.) | B4: % | C4: Fonte: Focus/BACEN | D4: 0.042 | E4: 0.1238 | F4: 0.1175 | G4: 0.1065 | H4: 0.125 | I4: 0.115 | J4: 0.105 | K4: 0.098 | L4: 0.092
A5: IPCA (% a.a.) | B5: % | C5: Fonte: Focus/BACEN | D5: 0.101 | E5: 0.058 | F5: 0.046 | G5: 0.048 | H5: 0.042 | I5: 0.038 | J5: 0.035 | K5: 0.033 | L5: 0.032
A6: PIB Real (% a.a.) | B6: % | C6: Fonte: Focus/BACEN | D6: 0.048 | E6: 0.031 | F6: 0.029 | G6: 0.033 | H6: 0.025 | I6: 0.022 | J6: 0.025 | K6: 0.025 | L6: 0.025
A7: USD/BRL (fim de ano) | B7: R$ | C7: Cotação fim de período | D7: 5.58 | E7: 5.29 | F7: 4.84 | G7: 5.7 | H7: 5.8 | I7: 5.7 | J7: 5.6 | K7: 5.5 | L7: 5.4
A8: Selic Meta (fim ano) | B8: % | C8: Fonte: Copom/BACEN | D8: 0.04 | E8: 0.1375 | F8: 0.1175 | G8: 0.1215 | H8: 0.127 | I8: 0.117 | J8: 0.107 | K8: 0.1 | L8: 0.092
A10: PREMISSAS DE RECEITA E MARGENS
A11: Crescimento Receita Líq. (% a.a.) | B11: % | C11: Premissa central de crescimento | D11: - | E11: 0.18 | F11: 0.12 | G11: 0.09 | H11: 0.22 | I11: 0.18 | J11: 0.15 | K11: 0.12 | L11: 0.1
A12: Margem Bruta (%) | B12: % | C12: % sobre Receita Líquida | D12: 0.48 | E12: 0.46 | F12: 0.47 | G12: 0.48 | H12: 0.49 | I12: 0.5 | J12: 0.51 | K12: 0.51 | L12: 0.52
A13: Margem EBITDA (%) | B13: % | C13: % sobre Receita Líquida | D13: 0.22 | E13: 0.21 | F13: 0.23 | G13: 0.24 | H13: 0.25 | I13: 0.26 | J13: 0.27 | K13: 0.27 | L13: 0.28
A14: Margem EBIT (%) | B14: % | C14: Antes de IR/CS | D14: 0.16 | E14: 0.15 | F14: 0.17 | G14: 0.18 | H14: 0.19 | I14: 0.2 | J14: 0.21 | K14: 0.22 | L14: 0.22
A15: Margem Líquida (%) | B15: % | C15: Lucro Líquido / Receita | D15: 0.1 | E15: 0.09 | F15: 0.11 | G15: 0.12 | H15: 0.13 | I15: 0.14 | J15: 0.15 | K15: 0.15 | L15: 0.16
A17: CAPEX, CAPITAL DE GIRO E FINANCIAMENTO
A18: CAPEX / Receita Líquida (%) | B18: % | C18: Investimentos / RL | D18: 0.05 | E18: 0.06 | F18: 0.05 | G18: 0.05 | H18: 0.06 | I18: 0.06 | J18: 0.05 | K18: 0.05 | L18: 0.04
A19: Dias de Contas a Receber | B19: dias | C19: PMR | D19: 45 | E19: 42 | F19: 40 | G19: 38 | H19: 38 | I19: 37 | J19: 36 | K19: 35 | L19: 35
A20: Dias de Estoques | B20: dias | C20: PME | D20: 55 | E20: 52 | F20: 50 | G20: 48 | H20: 47 | I20: 46 | J20: 45 | K20: 44 | L20: 44
A21: Dias de Fornecedores | B21: dias | C21: PMP | D21: 40 | E21: 42 | F21: 45 | G21: 47 | H21: 48 | I21: 50 | J21: 52 | K21: 53 | L21: 54
A22: Alíquota Efetiva IR/CS (%) | B22: % | C22: IR+CS efetivo | D22: 0.28 | E22: 0.27 | F22: 0.27 | G22: 0.26 | H22: 0.26 | I22: 0.25 | J22: 0.25 | K22: 0.25 | L22: 0.25
A23: Payout de Dividendos (%) | B23: % | C23: % LL distribuído | D23: 0.25 | E23: 0.25 | F23: 0.3 | G23: 0.3 | H23: 0.3 | I23: 0.35 | J23: 0.35 | K23: 0.4 | L23: 0.4
A24: D/EBITDA Alvo (covenant) | B24: x | C24: Limite máximo | D24: 2.5 | E24: 2.5 | F24: 2 | G24: 2 | H24: 2 | I24: 1.8 | J24: 1.8 | K24: 1.5 | L24: 1.5

Sheet 2. DRE
A1: 2. DEMONSTRAÇÃO DE RESULTADO DO EXERCÍCIO (DRE) — R$ MIL
A2: LINHA DA DRE | B2: REF. | C2: 2021A | D2: 2022A | E2: 2023A | F2: 2024A | G2: 2025E | H2: 2026E | I2: 2027E | J2: 2028E | K2: 2029E
A3: DEMONSTRAÇÃO DE RESULTADO — R$ MIL
A4: Receita Bruta | B4: RL+ | C4: 950000 | D4: 1120000 | E4: 1254000 | F4: 1372000 | G4: =F4*(1+'1. PREMISSAS'!H11) -> 1673840 | H4: =G4*(1+'1. PREMISSAS'!I11) -> 1975131.2 | I4: =H4*(1+'1. PREMISSAS'!J11) -> 2271400.9 | J4: =I4*(1+'1. PREMISSAS'!K11) -> 2543969 | K4: =J4*(1+'1. PREMISSAS'!L11) -> 2798365.9
A5: (-) Deduções de Receita | B5: RL- | C5: -95000 | D5: -112000 | E5: -125400 | F5: -137200 | G5: =-G4*0.1 -> -167384 | H5: =-H4*0.1 -> -197513.12 | I5: =-I4*0.1 -> -227140.09 | J5: =-J4*0.1 -> -254396.9 | K5: =-K4*0.1 -> -279836.59
A6: (=) Receita Líquida | B6: RL | C6: =C4+C5 -> 855000 | D6: =D4+D5 -> 1008000 | E6: =E4+E5 -> 1128600 | F6: =F4+F5 -> 1234800 | G6: =G4+G5 -> 1506456 | H6: =H4+H5 -> 1777618.1 | I6: =I4+I5 -> 2044260.8 | J6: =J4+J5 -> 2289572.1 | K6: =K4+K5 -> 2518529.3
A7: (-) CPV/CSV | B7: CPV | C7: =-C6*(1-'1. PREMISSAS'!D12) -> -444600 | D7: =-D6*(1-'1. PREMISSAS'!E12) -> -544320 | E7: =-E6*(1-'1. PREMISSAS'!F12) -> -598158 | F7: =-F6*(1-'1. PREMISSAS'!G12) -> -642096 | G7: =-G6*(1-'1. PREMISSAS'!H12) -> -768292.56 | H7: =-H6*(1-'1. PREMISSAS'!I12) -> -888809.04 | I7: =-I6*(1-'1. PREMISSAS'!J12) -> -1001687.8 | J7: =-J6*(1-'1. PREMISSAS'!K12) -> -1121890.3 | K7: =-K6*(1-'1. PREMISSAS'!L12) -> -1208894.1
A8: (=) Lucro Bruto | B8: LB | C8: =C6+C7 -> 410400 | D8: =D6+D7 -> 463680 | E8: =E6+E7 -> 530442 | F8: =F6+F7 -> 592704 | G8: =G6+G7 -> 738163.44 | H8: =H6+H7 -> 888809.04 | I8: =I6+I7 -> 1042573 | J8: =J6+J7 -> 1167681.8 | K8: =K6+K7 -> 1309635.2
A9: Margem Bruta (%) | B9: MB%
A10: (-) Despesas Comerciais | B10: DC | C10: -76000 | D10: -89600 | E10: -100320 | F10: -109760 | G10: =-G6*0.08 -> -120516.48 | H10: =-H6*0.08 -> -142209.45 | I10: =-I6*0.08 -> -163540.86 | J10: =-J6*0.08 -> -183165.77 | K10: =-K6*0.08 -> -201482.34
A11: (-) Despesas G&A | B11: GA | C11: -47500 | D11: -55000 | E11: -62700 | F11: -68600 | G11: =-G6*0.05 -> -75322.8 | H11: =-H6*0.05 -> -88880.904 | I11: =-I6*0.05 -> -102213.04 | J11: =-J6*0.05 -> -114478.6 | K11: =-K6*0.05 -> -125926.46
A12: (+) Outras Rec/Desp Op. | B12: OUT | C12: 9500 | D12: 11200 | E12: 12540 | F12: 13720 | G12: =G6*0.01 -> 15064.56 | H12: =H6*0.01 -> 17776.181 | I12: =I6*0.01 -> 20442.608 | J12: =J6*0.01 -> 22895.721 | K12: =K6*0.01 -> 25185.293
A13: (=) EBITDA | B13: EBITDA | C13: =C8+C10+C11+C12 -> 296400 | D13: =D8+D10+D11+D12 -> 330280 | E13: =E8+E10+E11+E12 -> 379962 | F13: =F8+F10+F11+F12 -> 428064 | G13: =G8+G10+G11+G12 -> 557388.72 | H13: =H8+H10+H11+H12 -> 675494.87 | I13: =I8+I10+I11+I12 -> 797261.71 | J13: =J8+J10+J11+J12 -> 892933.11 | K13: =K8+K10+K11+K12 -> 1007411.7
A14: Margem EBITDA (%) | B14: MB% | C14: =IF(C6<>0,C8/C6,0) -> 0.48 | D14: =IF(D6<>0,D8/D6,0) -> 0.46 | E14: =IF(E6<>0,E8/E6,0) -> 0.47 | F14: =IF(F6<>0,F8/F6,0) -> 0.48 | G14: =IF(G6<>0,G13/G6,0) -> 0.37 | H14: =IF(H6<>0,H13/H6,0) -> 0.38 | I14: =IF(I6<>0,I13/I6,0) -> 0.39 | J14: =IF(J6<>0,J13/J6,0) -> 0.39 | K14: =IF(K6<>0,K13/K6,0) -> 0.4
A15: (-) D&A | B15: DA | C15: =IF(C6<>0,C13/C6,0) -> 0.34666667 | D15: =IF(D6<>0,D13/D6,0) -> 0.32765873 | E15: =IF(E6<>0,E13/E6,0) -> 0.33666667 | F15: =IF(F6<>0,F13/F6,0) -> 0.34666667 | G15: =-G6*0.03 -> -45193.68 | H15: =-H6*0.03 -> -53328.542 | I15: =-I6*0.03 -> -61327.824 | J15: =-J6*0.03 -> -68687.163 | K15: =-K6*0.03 -> -75555.879
A16: (=) EBIT | B16: EBIT | C16: =C13+C15 -> 296400.35 | D16: =D13+D15 -> 330280.33 | E16: =E13+E15 -> 379962.34 | F16: =F13+F15 -> 428064.35 | G16: =G13+G15 -> 512195.04 | H16: =H13+H15 -> 622166.33 | I16: =I13+I15 -> 735933.89 | J16: =J13+J15 -> 824245.95 | K16: =K13+K15 -> 931855.84
A17: Margem EBIT (%) | B17: ME% | C17: =IF(C6<>0,C16/C6,0) -> 0.34666707 | D17: =IF(D6<>0,D16/D6,0) -> 0.32765906 | E17: =IF(E6<>0,E16/E6,0) -> 0.33666696 | F17: =IF(F6<>0,F16/F6,0) -> 0.34666695 | G17: =IF(G6<>0,G16/G6,0) -> 0.34 | H17: =IF(H6<>0,H16/H6,0) -> 0.35 | I17: =IF(I6<>0,I16/I6,0) -> 0.36 | J17: =IF(J6<>0,J16/J6,0) -> 0.36 | K17: =IF(K6<>0,K16/K6,0) -> 0.37
A18: Resultado Financeiro | B18: RF | C18: -28500 | D18: -44800 | E18: -36360 | F18: -34300 | G18: =-G6*0.025 -> -37661.4 | H18: =-H6*0.025 -> -44440.452 | I18: =-I6*0.025 -> -51106.52 | J18: =-J6*0.025 -> -57239.302 | K18: =-K6*0.025 -> -62963.232
A19: (=) EBT | B19: EBT | C19: =C16+C18 -> 267900.35 | D19: =D16+D18 -> 285480.33 | E19: =E16+E18 -> 343602.34 | F19: =F16+F18 -> 393764.35 | G19: =G16+G18 -> 474533.64 | H19: =H16+H18 -> 577725.88 | I19: =I16+I18 -> 684827.37 | J19: =J16+J18 -> 767006.65 | K19: =K16+K18 -> 868892.61
A20: (-) IR/CS | B20: IR | C20: =IF(C19>0,-C19*'1. PREMISSAS'!D22,0) -> -75012.097 | D20: =IF(D19>0,-D19*'1. PREMISSAS'!E22,0) -> -77079.688 | E20: =IF(E19>0,-E19*'1. PREMISSAS'!F22,0) -> -92772.631 | F20: =IF(F19>0,-F19*'1. PREMISSAS'!G22,0) -> -102378.73 | G20: =IF(G19>0,-G19*'1. PREMISSAS'!H22,0) -> -123378.75 | H20: =IF(H19>0,-H19*'1. PREMISSAS'!I22,0) -> -144431.47 | I20: =IF(I19>0,-I19*'1. PREMISSAS'!J22,0) -> -171206.84 | J20: =IF(J19>0,-J19*'1. PREMISSAS'!K22,0) -> -191751.66 | K20: =IF(K19>0,-K19*'1. PREMISSAS'!L22,0) -> -217223.15
A21: (=) Lucro Líquido | B21: LL | C21: =C19+C20 -> 192888.25 | D21: =D19+D20 -> 208400.64 | E21: =E19+E20 -> 250829.71 | F21: =F19+F20 -> 291385.62 | G21: =G19+G20 -> 351154.89 | H21: =H19+H20 -> 433294.41 | I21: =I19+I20 -> 513620.52 | J21: =J19+J20 -> 575254.99 | K21: =K19+K20 -> 651669.46
A22: Margem Líquida (%) | B22: ML% | C22: =IF(C6<>0,C21/C6,0) -> 0.22560029 | D22: =IF(D6<>0,D21/D6,0) -> 0.20674667 | E22: =IF(E6<>0,E21/E6,0) -> 0.22224854 | F22: =IF(F6<>0,F21/F6,0) -> 0.23597799 | G22: =IF(G6<>0,G21/G6,0) -> 0.2331 | H22: =IF(H6<>0,H21/H6,0) -> 0.24375 | I22: =IF(I6<>0,I21/I6,0) -> 0.25125 | J22: =IF(J6<>0,J21/J6,0) -> 0.25125 | K22: =IF(K6<>0,K21/K6,0) -> 0.25875

Sheet 3. BALANÇO
A1: 3. BALANÇO PATRIMONIAL PROJETADO — R$ MIL
A2: LINHA | B2: REF. | C2: 2021A | D2: 2022A | E2: 2023A | F2: 2024A | G2: 2025E | H2: 2026E | I2: 2027E | J2: 2028E | K2: 2029E
A3: ATIVO | B3: ATT
A4: Caixa e Equivalentes | B4: CX | C4: 180000 | D4: 210000 | E4: 245000 | F4: 270000
A5: Contas a Receber | B5: CR | C5: 131250 | D5: 129067 | E5: 137644 | F5: 143040 | G5: ='2. DRE'!G6*'1. PREMISSAS'!H19/365 -> 156836.52 | H5: ='2. DRE'!H6*'1. PREMISSAS'!I19/365 -> 180196.9 | I5: ='2. DRE'!I6*'1. PREMISSAS'!J19/365 -> 201625.72 | J5: ='2. DRE'!J6*'1. PREMISSAS'!K19/365 -> 219548.01 | K5: ='2. DRE'!K6*'1. PREMISSAS'!L19/365 -> 241502.81
A6: Estoques | B6: EST | C6: 143233 | D6: 160411 | E6: 171370 | F6: 180416 | G6: =ABS('2. DRE'!G7)*'1. PREMISSAS'!H20/365 -> 98930.823 | H6: =ABS('2. DRE'!H7)*'1. PREMISSAS'!I20/365 -> 112014.29 | I6: =ABS('2. DRE'!I7)*'1. PREMISSAS'!J20/365 -> 123495.75 | J6: =ABS('2. DRE'!J7)*'1. PREMISSAS'!K20/365 -> 135241.57 | K6: =ABS('2. DRE'!K7)*'1. PREMISSAS'!L20/365 -> 145729.7
A7: Outros Ativos Circulantes | B7: OAC | C7: 30000 | D7: 35000 | E7: 40000 | F7: 42000 | G7: =F7*1.05 -> 44100 | H7: =G7*1.05 -> 46305 | I7: =H7*1.05 -> 48620.25 | J7: =I7*1.05 -> 51051.262 | K7: =J7*1.05 -> 53603.826
A8: Total Ativo Circulante | B8: TAC | C8: =C4+C5+C6+C7 -> 484483 | D8: =D4+D5+D6+D7 -> 534478 | E8: =E4+E5+E6+E7 -> 594014 | F8: =F4+F5+F6+F7 -> 635456 | G8: =G4+G5+G6+G7 -> 299867.34 | H8: =H4+H5+H6+H7 -> 338516.19 | I8: =I4+I5+I6+I7 -> 373741.73 | J8: =J4+J5+J6+J7 -> 405840.84 | K8: =K4+K5+K6+K7 -> 440836.33
A9: Imobilizado Líquido | B9: IMO | C9: 350000 | D9: 365000 | E9: 372000 | F9: 380000 | G9: =F9+'2. DRE'!G6*'1. PREMISSAS'!H18+('2. DRE'!G15) -> 425193.68 | H9: =G9+'2. DRE'!H6*'1. PREMISSAS'!I18+('2. DRE'!H15) -> 478522.22 | I9: =H9+'2. DRE'!I6*'1. PREMISSAS'!J18+('2. DRE'!I15) -> 519407.44 | J9: =I9+'2. DRE'!J6*'1. PREMISSAS'!K18+('2. DRE'!J15) -> 565198.88 | K9: =J9+'2. DRE'!K6*'1. PREMISSAS'!L18+('2. DRE'!K15) -> 590384.17
A10: Intangível e Goodwill | B10: INT | C10: 80000 | D10: 78000 | E10: 76000 | F10: 74000 | G10: =F10-2000 -> 72000 | H10: =G10-2000 -> 70000 | I10: =H10-2000 -> 68000 | J10: =I10-2000 -> 66000 | K10: =J10-2000 -> 64000
A11: Outros Ativos NC | B11: OANC | C11: 25000 | D11: 27000 | E11: 28000 | F11: 30000 | G11: =F11*1.03 -> 30900 | H11: =G11*1.03 -> 31827 | I11: =H11*1.03 -> 32781.81 | J11: =I11*1.03 -> 33765.264 | K11: =J11*1.03 -> 34778.222
A12: Total Ativo Não Circulante | B12: TANC | C12: =C9+C10+C11 -> 455000 | D12: =D9+D10+D11 -> 470000 | E12: =E9+E10+E11 -> 476000 | F12: =F9+F10+F11 -> 484000 | G12: =G9+G10+G11 -> 528093.68 | H12: =H9+H10+H11 -> 580349.22 | I12: =I9+I10+I11 -> 620189.25 | J12: =J9+J10+J11 -> 664964.14 | K12: =K9+K10+K11 -> 689162.4
A13: TOTAL ATIVO | B13: TA | C13: =C8+C12 -> 939483 | D13: =D8+D12 -> 1004478 | E13: =E8+E12 -> 1070014 | F13: =F8+F12 -> 1119456 | G13: =G8+G12 -> 827961.02 | H13: =H8+H12 -> 918865.41 | I13: =I8+I12 -> 993930.97 | J13: =J8+J12 -> 1070805 | K13: =K8+K12 -> 1129998.7
A14: PASSIVO E PL | B14: PLT
A15: Fornecedores | B15: FOR | C15: =ABS('2. DRE'!C7)*'1. PREMISSAS'!D21/365 -> 48723.288 | D15: =ABS('2. DRE'!D7)*'1. PREMISSAS'!E21/365 -> 62634.082 | E15: =ABS('2. DRE'!E7)*'1. PREMISSAS'!F21/365 -> 73745.507 | F15: =ABS('2. DRE'!F7)*'1. PREMISSAS'!G21/365 -> 82680.855 | G15: =ABS('2. DRE'!G7)*'1. PREMISSAS'!H21/365 -> 101035.73 | H15: =ABS('2. DRE'!H7)*'1. PREMISSAS'!I21/365 -> 121754.66 | I15: =ABS('2. DRE'!I7)*'1. PREMISSAS'!J21/365 -> 142706.21 | J15: =ABS('2. DRE'!J7)*'1. PREMISSAS'!K21/365 -> 162904.62 | K15: =ABS('2. DRE'!K7)*'1. PREMISSAS'!L21/365 -> 178850.08
A16: Dívida CP | B16: DCP | C16: -80000 | D16: -90000 | E16: -95000 | F16: -100000 | G16: =F16*1.05 -> -105000 | H16: =G16*1.05 -> -110250 | I16: =H16*1.05 -> -115762.5 | J16: =I16*1.05 -> -121550.62 | K16: =J16*1.05 -> -127628.16
A17: Outros Passivos Circulantes | B17: OPC | C17: -60000 | D17: -65000 | E17: -70000 | F17: -75000 | G17: =F17*1.04 -> -78000 | H17: =G17*1.04 -> -81120 | I17: =H17*1.04 -> -84364.8 | J17: =I17*1.04 -> -87739.392 | K17: =J17*1.04 -> -91248.968
A18: Total Passivo Circulante | B18: TPC | C18: =C15+C16+C17 -> -91276.712 | D18: =D15+D16+D17 -> -92365.918 | E18: =E15+E16+E17 -> -91254.493 | F18: =F15+F16+F17 -> -92319.145 | G18: =G15+G16+G17 -> -81964.266 | H18: =H15+H16+H17 -> -69615.337 | I18: =I15+I16+I17 -> -57421.095 | J18: =J15+J16+J17 -> -46385.395 | K18: =K15+K16+K17 -> -40027.044
A19: Dívida LP | B19: DLP | C19: -320000 | D19: -300000 | E19: -280000 | F19: -260000 | G19: =F19*0.95 -> -247000 | H19: =G19*0.95 -> -234650 | I19: =H19*0.95 -> -222917.5 | J19: =I19*0.95 -> -211771.62 | K19: =J19*0.95 -> -201183.04
A20: Outros Passivos NC | B20: OPNC | C20: -40000 | D20: -42000 | E20: -44000 | F20: -46000 | G20: =F20*1.03 -> -47380 | H20: =G20*1.03 -> -48801.4 | I20: =H20*1.03 -> -50265.442 | J20: =I20*1.03 -> -51773.405 | K20: =J20*1.03 -> -53326.607
A21: Total Passivo Não Circulante | B21: TPNC | C21: =C19+C20 -> -360000 | D21: =D19+D20 -> -342000 | E21: =E19+E20 -> -324000 | F21: =F19+F20 -> -306000 | G21: =G19+G20 -> -294380 | H21: =H19+H20 -> -283451.4 | I21: =I19+I20 -> -273182.94 | J21: =J19+J20 -> -263545.03 | K21: =K19+K20 -> -254509.65
A22: Patrimônio Líquido | B22: PL
A23: Capital Social | B23: CS | C23: 400000 | D23: 400000 | E23: 400000 | F23: 400000 | G23: 400000 | H23: 400000 | I23: 400000 | J23: 400000 | K23: 400000
A24: Reservas e Lucros Acumulados | B24: RLA | C24: =C13-(C18+C21+C23) -> 990759.71 | D24: =D13-(D18+D21+D23) -> 1038843.9 | E24: =E13-(E18+E21+E23) -> 1085268.5 | F24: =F13-(F18+F21+F23) -> 1117775.1 | G24: =G13-(G18+G21+G23) -> 804305.28 | H24: =H13-(H18+H21+H23) -> 871932.15 | I24: =I13-(I18+I21+I23) -> 924535.01 | J24: =J13-(J18+J21+J23) -> 980735.41 | K24: =K13-(K18+K21+K23) -> 1024535.4
A25: Total PL | B25: TPL | C25: =C23+C24 -> 1390759.7 | D25: =D23+D24 -> 1438843.9 | E25: =E23+E24 -> 1485268.5 | F25: =F23+F24 -> 1517775.1 | G25: =G23+G24 -> 1204305.3 | H25: =H23+H24 -> 1271932.2 | I25: =I23+I24 -> 1324535 | J25: =J23+J24 -> 1380735.4 | K25: =K23+K24 -> 1424535.4
A26: TOTAL PASSIVO + PL | B26: TTP | C26: =C18+C21+C25 -> 939483 | D26: =D18+D21+D25 -> 1004478 | E26: =E18+E21+E25 -> 1070014 | F26: =F18+F21+F25 -> 1119456 | G26: =G18+G21+G25 -> 827961.02 | H26: =H18+H21+H25 -> 918865.41 | I26: =I18+I21+I25 -> 993930.97 | J26: =J18+J21+J25 -> 1070805 | K26: =K18+K21+K25 -> 1129998.7
A27: ── INDICADORES ── | B27: IND
A28: Dívida Líquida | B28: DL | C28: =ABS(C16)+ABS(C19)-C4 -> 220000 | D28: =ABS(D16)+ABS(D19)-D4 -> 180000 | E28: =ABS(E16)+ABS(E19)-E4 -> 130000 | F28: =ABS(F16)+ABS(F19)-F4 -> 90000 | G28: =ABS(G16)+ABS(G19)-G4 -> 352000 | H28: =ABS(H16)+ABS(H19)-H4 -> 344900 | I28: =ABS(I16)+ABS(I19)-I4 -> 338680 | J28: =ABS(J16)+ABS(J19)-J4 -> 333322.25 | K28: =ABS(K16)+ABS(K19)-K4 -> 328811.2
A29: Capital Investido (CI) | B29: CI | C29: =C13-C4-C11 -> 734483 | D29: =D13-D4-D11 -> 767478 | E29: =E13-E4-E11 -> 797014 | F29: =F13-F4-F11 -> 819456 | G29: =G13-G4-G11 -> 797061.02 | H29: =H13-H4-H11 -> 887038.41 | I29: =I13-I4-I11 -> 961149.16 | J29: =J13-J4-J11 -> 1037039.7 | K29: =K13-K4-K11 -> 1095220.5
A30: NCG (Necessidade Cap. Giro) | B30: NCG | C30: =C5+C6-ABS(C15) -> 225759.71 | D30: =D5+D6-ABS(D15) -> 226843.92 | E30: =E5+E6-ABS(E15) -> 235268.49 | F30: =F5+F6-ABS(F15) -> 240775.15 | G30: =G5+G6-ABS(G15) -> 154731.6 | H30: =H5+H6-ABS(H15) -> 170456.53 | I30: =I5+I6-ABS(I15) -> 182415.27 | J30: =J5+J6-ABS(J15) -> 191884.96 | K30: =K5+K6-ABS(K15) -> 208382.42
A31: ROIC (%) | B31: ROIC | C31: =IF(C29<>0,'2. DRE'!C16*(1-'1. PREMISSAS'!D22)/C29,0) -> 0.29055574 | D31: =IF(D29<>0,'2. DRE'!D16*(1-'1. PREMISSAS'!E22)/D29,0) -> 0.31415186 | E31: =IF(E29<>0,'2. DRE'!E16*(1-'1. PREMISSAS'!F22)/E29,0) -> 0.3480146 | F31: =IF(F29<>0,'2. DRE'!F16*(1-'1. PREMISSAS'!G22)/F29,0) -> 0.38655842 | G31: =IF(G29<>0,'2. DRE'!G16*(1-'1. PREMISSAS'!H22)/G29,0) -> 0.47552737 | H31: =IF(H29<>0,'2. DRE'!H16*(1-'1. PREMISSAS'!I22)/H29,0) -> 0.52604796 | I31: =IF(I29<>0,'2. DRE'!I16*(1-'1. PREMISSAS'!J22)/I29,0) -> 0.57426093 | J31: =IF(J29<>0,'2. DRE'!J16*(1-'1. PREMISSAS'!K22)/J29,0) -> 0.5961049 | K31: =IF(K29<>0,'2. DRE'!K16*(1-'1. PREMISSAS'!L22)/K29,0) -> 0.63812892
A32: ROE (%) | B32: ROE | C32: =IF(C25<>0,'2. DRE'!C21/C25,0) -> 0.13869272 | D32: =IF(D25<>0,'2. DRE'!D21/D25,0) -> 0.14483895 | E32: =IF(E25<>0,'2. DRE'!E21/E25,0) -> 0.16887836 | F32: =IF(F25<>0,'2. DRE'!F21/F25,0) -> 0.19198207 | G32: =IF(G25<>0,'2. DRE'!G21/G25,0) -> 0.29158296 | H32: =IF(H25<>0,'2. DRE'!H21/H25,0) -> 0.34065843 | I32: =IF(I25<>0,'2. DRE'!I21/I25,0) -> 0.38777421 | J32: =IF(J25<>0,'2. DRE'!J21/J25,0) -> 0.41662941 | K32: =IF(K25<>0,'2. DRE'!K21/K25,0) -> 0.45746104
A33: Dívida Líq./EBITDA (x) | B33: DLEB | C33: =IF('2. DRE'!C13<>0,C28/'2. DRE'!C13,0) -> 0.74224022 | D33: =IF('2. DRE'!D13<>0,D28/'2. DRE'!D13,0) -> 0.54499213 | E33: =IF('2. DRE'!E13<>0,E28/'2. DRE'!E13,0) -> 0.34213948 | F33: =IF('2. DRE'!F13<>0,F28/'2. DRE'!F13,0) -> 0.21024893 | G33: =IF('2. DRE'!G13<>0,G28/'2. DRE'!G13,0) -> 0.63151619 | H33: =IF('2. DRE'!H13<>0,H28/'2. DRE'!H13,0) -> 0.51058863 | I33: =IF('2. DRE'!I13<>0,I28/'2. DRE'!I13,0) -> 0.42480405 | J33: =IF('2. DRE'!J13<>0,J28/'2. DRE'!J13,0) -> 0.37328916 | K33: =IF('2. DRE'!K13<>0,K28/'2. DRE'!K13,0) -> 0.32639207

Sheet 4. FLUXO
A1: 4. DEMONSTRAÇÃO DO FLUXO DE CAIXA — R$ MIL
A2: LINHA | B2: REF. | C2: 2021A | D2: 2022A | E2: 2023A | F2: 2024A | G2: 2025E | H2: 2026E | I2: 2027E | J2: 2028E | K2: 2029E
A3: FCO — FLUXO DE CAIXA OPERACIONAL | B3: FCO_T
A4: EBITDA | B4: EBITDA | C4: ='2. DRE'!C13 -> 296400 | D4: ='2. DRE'!D13 -> 330280 | E4: ='2. DRE'!E13 -> 379962 | F4: ='2. DRE'!F13 -> 428064 | G4: ='2. DRE'!G13 -> 557388.72 | H4: ='2. DRE'!H13 -> 675494.87 | I4: ='2. DRE'!I13 -> 797261.71 | J4: ='2. DRE'!J13 -> 892933.11 | K4: ='2. DRE'!K13 -> 1007411.7
A5: (-) Variação de NCG | B5: DNCG | C5: 0 | D5: =-('3. BALANÇO'!D30-'3. BALANÇO'!C30) -> -1084.2055 | E5: =-('3. BALANÇO'!E30-'3. BALANÇO'!D30) -> -8424.5753 | F5: =-('3. BALANÇO'!F30-'3. BALANÇO'!E30) -> -5506.6521 | G5: =-('3. BALANÇO'!G30-'3. BALANÇO'!F30) -> 86043.541 | H5: =-('3. BALANÇO'!H30-'3. BALANÇO'!G30) -> -15724.924 | I5: =-('3. BALANÇO'!I30-'3. BALANÇO'!H30) -> -11958.743 | J5: =-('3. BALANÇO'!J30-'3. BALANÇO'!I30) -> -9469.6881 | K5: =-('3. BALANÇO'!K30-'3. BALANÇO'!J30) -> -16497.465
A6: (-) IR/CS Pago | B6: IRP | C6: ='2. DRE'!C20 -> -75012.097 | D6: ='2. DRE'!D20 -> -77079.688 | E6: ='2. DRE'!E20 -> -92772.631 | F6: ='2. DRE'!F20 -> -102378.73 | G6: ='2. DRE'!G20 -> -123378.75 | H6: ='2. DRE'!H20 -> -144431.47 | I6: ='2. DRE'!I20 -> -171206.84 | J6: ='2. DRE'!J20 -> -191751.66 | K6: ='2. DRE'!K20 -> -217223.15
A7: (=) FCO | B7: FCO | C7: =C4+C5+C6 -> 221387.9 | D7: =D4+D5+D6 -> 252116.11 | E7: =E4+E5+E6 -> 278764.79 | F7: =F4+F5+F6 -> 320178.62 | G7: =G4+G5+G6 -> 520053.51 | H7: =H4+H5+H6 -> 515338.48 | I7: =I4+I5+I6 -> 614096.12 | J7: =J4+J5+J6 -> 691711.76 | K7: =K4+K5+K6 -> 773691.1
A8: FCI — FLUXO DE CAIXA DE INVESTIMENTO | B8: FCI_T
A9: CAPEX | B9: CAPEX | C9: =-'2. DRE'!C6*'1. PREMISSAS'!D18 -> -42750 | D9: =-'2. DRE'!D6*'1. PREMISSAS'!E18 -> -60480 | E9: =-'2. DRE'!E6*'1. PREMISSAS'!F18 -> -56430 | F9: =-'2. DRE'!F6*'1. PREMISSAS'!G18 -> -61740 | G9: =-'2. DRE'!G6*'1. PREMISSAS'!H18 -> -90387.36 | H9: =-'2. DRE'!H6*'1. PREMISSAS'!I18 -> -106657.08 | I9: =-'2. DRE'!I6*'1. PREMISSAS'!J18 -> -102213.04 | J9: =-'2. DRE'!J6*'1. PREMISSAS'!K18 -> -114478.6 | K9: =-'2. DRE'!K6*'1. PREMISSAS'!L18 -> -100741.17
A10: Aquisições / Desinvestimentos | B10: ACQ | C10: 0 | D10: 0 | E10: 0 | F10: 0 | G10: 0 | H10: 0 | I10: 0 | J10: 0 | K10: 0
A11: (=) FCI | B11: FCI | C11: =C9+C10 -> -42750 | D11: =D9+D10 -> -60480 | E11: =E9+E10 -> -56430 | F11: =F9+F10 -> -61740 | G11: =G9+G10 -> -90387.36 | H11: =H9+H10 -> -106657.08 | I11: =I9+I10 -> -102213.04 | J11: =J9+J10 -> -114478.6 | K11: =K9+K10 -> -100741.17
A12: FCFF — FREE CASH FLOW TO FIRM | B12: FCFF_T
A13: (=) FCFF = FCO + FCI | B13: FCFF | C13: =C7+C11 -> 178637.9 | D13: =D7+D11 -> 191636.11 | E13: =E7+E11 -> 222334.79 | F13: =F7+F11 -> 258438.62 | G13: =G7+G11 -> 429666.15 | H13: =H7+H11 -> 408681.39 | I13: =I7+I11 -> 511883.08 | J13: =J7+J11 -> 577233.16 | K13: =K7+K11 -> 672949.93
A14: FCF — FLUXO DE CAIXA DE FINANCIAMENTO | B14: FCF_T
A15: Captação / (Amortização) Dívida | B15: CAP | C15: 0 | D15: =(ABS('3. BALANÇO'!D16)+ABS('3. BALANÇO'!D19))-(ABS('3. BALANÇO'!C16)+ABS('3. BALANÇO'!C19)) -> -10000 | E15: =(ABS('3. BALANÇO'!E16)+ABS('3. BALANÇO'!E19))-(ABS('3. BALANÇO'!D16)+ABS('3. BALANÇO'!D19)) -> -15000 | F15: =(ABS('3. BALANÇO'!F16)+ABS('3. BALANÇO'!F19))-(ABS('3. BALANÇO'!E16)+ABS('3. BALANÇO'!E19)) -> -15000 | G15: =(ABS('3. BALANÇO'!G16)+ABS('3. BALANÇO'!G19))-(ABS('3. BALANÇO'!F16)+ABS('3. BALANÇO'!F19)) -> -8000 | H15: =(ABS('3. BALANÇO'!H16)+ABS('3. BALANÇO'!H19))-(ABS('3. BALANÇO'!G16)+ABS('3. BALANÇO'!G19)) -> -7100 | I15: =(ABS('3. BALANÇO'!I16)+ABS('3. BALANÇO'!I19))-(ABS('3. BALANÇO'!H16)+ABS('3. BALANÇO'!H19)) -> -6220 | J15: =(ABS('3. BALANÇO'!J16)+ABS('3. BALANÇO'!J19))-(ABS('3. BALANÇO'!I16)+ABS('3. BALANÇO'!I19)) -> -5357.75 | K15: =(ABS('3. BALANÇO'!K16)+ABS('3. BALANÇO'!K19))-(ABS('3. BALANÇO'!J16)+ABS('3. BALANÇO'!J19)) -> -4511.05
A16: Resultado Financeiro (caixa) | B16: RFCX | C16: ='2. DRE'!C18 -> -28500 | D16: ='2. DRE'!D18 -> -44800 | E16: ='2. DRE'!E18 -> -36360 | F16: ='2. DRE'!F18 -> -34300 | G16: ='2. DRE'!G18 -> -37661.4 | H16: ='2. DRE'!H18 -> -44440.452 | I16: ='2. DRE'!I18 -> -51106.52 | J16: ='2. DRE'!J18 -> -57239.302 | K16: ='2. DRE'!K18 -> -62963.232
A17: Dividendos Pagos | B17: DIV | C17: =-MAX(0,'2. DRE'!C21)*'1. PREMISSAS'!D23 -> -48222.062 | D17: =-MAX(0,'2. DRE'!D21)*'1. PREMISSAS'!E23 -> -52100.16 | E17: =-MAX(0,'2. DRE'!E21)*'1. PREMISSAS'!F23 -> -75248.912 | F17: =-MAX(0,'2. DRE'!F21)*'1. PREMISSAS'!G23 -> -87415.685 | G17: =-MAX(0,'2. DRE'!G21)*'1. PREMISSAS'!H23 -> -105346.47 | H17: =-MAX(0,'2. DRE'!H21)*'1. PREMISSAS'!I23 -> -151653.04 | I17: =-MAX(0,'2. DRE'!I21)*'1. PREMISSAS'!J23 -> -179767.18 | J17: =-MAX(0,'2. DRE'!J21)*'1. PREMISSAS'!K23 -> -230101.99 | K17: =-MAX(0,'2. DRE'!K21)*'1. PREMISSAS'!L23 -> -260667.78
A18: (=) FCF | B18: FCF | C18: =C15+C16+C17 -> -76722.062 | D18: =D15+D16+D17 -> -106900.16 | E18: =E15+E16+E17 -> -126608.91 | F18: =F15+F16+F17 -> -136715.68 | G18: =G15+G16+G17 -> -151007.87 | H18: =H15+H16+H17 -> -203193.49 | I18: =I15+I16+I17 -> -237093.7 | J18: =J15+J16+J17 -> -292699.05 | K18: =K15+K16+K17 -> -328142.06
A19: FCFE — FREE CASH FLOW TO EQUITY | B19: FCFE_T
A20: (=) FCFE = FCFF + Captação + RF | B20: FCFE | C20: =C13+C15+C16 -> 150137.9 | D20: =D13+D15+D16 -> 136836.11 | E20: =E13+E15+E16 -> 170974.79 | F20: =F13+F15+F16 -> 209138.62 | G20: =G13+G15+G16 -> 384004.75 | H20: =H13+H15+H16 -> 357140.94 | I20: =I13+I15+I16 -> 454556.57 | J20: =J13+J15+J16 -> 514636.11 | K20: =K13+K15+K16 -> 605475.65
A21: ── QUALIDADE DE CAIXA ── | B21: QC_T
A22: FCO / EBITDA (%) | B22: FCOEB | C22: =IF(C4<>0,C7/C4,0) -> 0.74692275 | D22: =IF(D4<>0,D7/D4,0) -> 0.76334052 | E22: =IF(E4<>0,E7/E4,0) -> 0.73366493 | F22: =IF(F4<>0,F7/F4,0) -> 0.74796904 | G22: =IF(G4<>0,G7/G4,0) -> 0.93301765 | H22: =IF(H4<>0,H7/H4,0) -> 0.76290509 | I22: =IF(I4<>0,I7/I4,0) -> 0.77025664 | J22: =IF(J4<>0,J7/J4,0) -> 0.77465126 | K22: =IF(K4<>0,K7/K4,0) -> 0.76799891
A23: FCFF / EBITDA (%) | B23: FCFFEB | C23: =IF(C4<>0,C13/C4,0) -> 0.60269198 | D23: =IF(D4<>0,D13/D4,0) -> 0.58022316 | E23: =IF(E4<>0,E13/E4,0) -> 0.58515008 | F23: =IF(F4<>0,F13/F4,0) -> 0.60373827 | G23: =IF(G4<>0,G13/G4,0) -> 0.77085549 | H23: =IF(H4<>0,H13/H4,0) -> 0.60501036 | I23: =IF(I4<>0,I13/I4,0) -> 0.64205151 | J23: =IF(J4<>0,J13/J4,0) -> 0.64644613 | K23: =IF(K4<>0,K13/K4,0) -> 0.66799891
A24: Conversão EBITDA → Caixa (%) | B24: CONV | C24: =C22 -> 0.74692275 | D24: =D22 -> 0.76334052 | E24: =E22 -> 0.73366493 | F24: =F22 -> 0.74796904 | G24: =G22 -> 0.93301765 | H24: =H22 -> 0.76290509 | I24: =I22 -> 0.77025664 | J24: =J22 -> 0.77465126 | K24: =K22 -> 0.76799891

Sheet 5. WACC
A1: 5. CUSTO DE CAPITAL (WACC) — METODOLOGIA CAPM
A2: INPUTS DO CAPM — CUSTO DO EQUITY (Ke)
A3: Taxa livre de risco (Rf) | B3: 0.055 | C3: Rf | D3: US T-Bond 10Y (jun/2024)
A4: Prêmio de risco de mercado (ERP) | B4: 0.055 | C4: ERP | D4: Damodaran EM 2024
A5: Beta desalavancado (βu) | B5: 0.82 | C5: BU | D5: Mediana peers listados
A6: D/E ratio (estrutura alvo) | B6: 0.35 | C6: DE | D6: Dívida Líq. / PL target
A7: Alíquota IR/CS (t) | B7: 0.26 | C7: T | D7: Taxa efetiva
A8: Beta realavancado (βL) | B8: =B5*(1+(1-B7)*B6) -> 1.03238 | C8: BL | D8: Bu*(1+(1-t)*D/E)
A9: Ke (USD) = Rf + βL*ERP | B9: =B3+B8*B4 -> 0.1117809 | C9: KEUSD | D9: Ke em dólares
A10: Risco-Brasil (CDS 5Y spread) | B10: 0.024 | C10: CDS | D10: CDS Brasil 5Y
A11: Inflação USA (%) | B11: 0.025 | C11: IFUSA | D11: CPI projetado
A12: Inflação Brasil (%) | B12: 0.042 | C12: IFBR | D12: IPCA projetado
A13: Ke (BRL) — Fisher equation | B13: =(1+B9)*(1+B12)/(1+B11)-1 -> 0.13022019 | C13: KEBRL | D13: Ke convertido para BRL
A15: CUSTO DA DÍVIDA (Kd) E ESTRUTURA DE CAPITAL
A16: Kd bruto (CDI + spread) | B16: 0.155 | C16: KD | D16: CDI 12,5% + spread 3pp
A17: Kd líquido = Kd*(1-t) | B17: =B16*(1-B7) -> 0.1147 | C17: KDLIQ | D17: Shield fiscal IR/CS
A18: E/(D+E) — peso Equity | B18: 0.74 | C18: WE | D18: % do valor total
A19: D/(D+E) — peso Dívida | B19: =1-B18 -> 0.26 | C19: WD | D19: 1 - WE
A20: WACC = Ke*WE + Kd*(1-t)*WD | B20: =B13*B18+B17*B19 -> 0.12618494 | C20: WACC | D20: Custo médio ponderado
A23: SENSIBILIDADE WACC — Beta x ERP
A24: Beta / ERP → | B24: 0.045 | C24: 0.05 | D24: 0.055 | E24: 0.06 | F24: 0.065
A25: 0.7 | B25: =((1+B3+0.7*0.045)*(1+B12)/(1+B11)-1)*B18+B17*B19 -> 0.1071668 | C25: =((1+B3+0.7*0.05)*(1+B12)/(1+B11)-1)*B18+B17*B19 -> 0.10979976 | D25: =((1+B3+0.7*0.055)*(1+B12)/(1+B11)-1)*B18+B17*B19 -> 0.11243271 | E25: =((1+B3+0.7*0.06)*(1+B12)/(1+B11)-1)*B18+B17*B19 -> 0.11506567 | F25: =((1+B3+0.7*0.065)*(1+B12)/(1+B11)-1)*B18+B17*B19 -> 0.11769862
A26: 0.8 | B26: =((1+B3+0.8*0.045)*(1+B12)/(1+B11)-1)*B18+B17*B19 -> 0.11055203 | C26: =((1+B3+0.8*0.05)*(1+B12)/(1+B11)-1)*B18+B17*B19 -> 0.11356112 | D26: =((1+B3+0.8*0.055)*(1+B12)/(1+B11)-1)*B18+B17*B19 -> 0.11657021 | E26: =((1+B3+0.8*0.06)*(1+B12)/(1+B11)-1)*B18+B17*B19 -> 0.11957931 | F26: =((1+B3+0.8*0.065)*(1+B12)/(1+B11)-1)*B18+B17*B19 -> 0.1225884
A27: 0.9 | B27: =((1+B3+0.9*0.045)*(1+B12)/(1+B11)-1)*B18+B17*B19 -> 0.11393726 | C27: =((1+B3+0.9*0.05)*(1+B12)/(1+B11)-1)*B18+B17*B19 -> 0.11732249 | D27: =((1+B3+0.9*0.055)*(1+B12)/(1+B11)-1)*B18+B17*B19 -> 0.12070772 | E27: =((1+B3+0.9*0.06)*(1+B12)/(1+B11)-1)*B18+B17*B19 -> 0.12409295 | F27: =((1+B3+0.9*0.065)*(1+B12)/(1+B11)-1)*B18+B17*B19 -> 0.12747818
A28: 1 | B28: =((1+B3+1*0.045)*(1+B12)/(1+B11)-1)*B18+B17*B19 -> 0.11732249 | C28: =((1+B3+1*0.05)*(1+B12)/(1+B11)-1)*B18+B17*B19 -> 0.12108385 | D28: =((1+B3+1*0.055)*(1+B12)/(1+B11)-1)*B18+B17*B19 -> 0.12484522 | E28: =((1+B3+1*0.06)*(1+B12)/(1+B11)-1)*B18+B17*B19 -> 0.12860659 | F28: =((1+B3+1*0.065)*(1+B12)/(1+B11)-1)*B18+B17*B19 -> 0.13236795
A29: 1.1 | B29: =((1+B3+1.1*0.045)*(1+B12)/(1+B11)-1)*B18+B17*B19 -> 0.12070772 | C29: =((1+B3+1.1*0.05)*(1+B12)/(1+B11)-1)*B18+B17*B19 -> 0.12484522 | D29: =((1+B3+1.1*0.055)*(1+B12)/(1+B11)-1)*B18+B17*B19 -> 0.12898272 | E29: =((1+B3+1.1*0.06)*(1+B12)/(1+B11)-1)*B18+B17*B19 -> 0.13312022 | F29: =((1+B3+1.1*0.065)*(1+B12)/(1+B11)-1)*B18+B17*B19 -> 0.13725773

Sheet 6. DCF
A1: 6. VALUATION POR DCF — FLUXO DE CAIXA DESCONTADO (R$ MIL)
A2: LINHA | B2: REF. | C2: 2025E | D2: 2026E | E2: 2027E | F2: 2028E | G2: 2029E
A3: FCFF PROJETADO | B3: FCFF_T
A4: EBIT | B4: EBIT | C4: ='2. DRE'!G16 -> 512195.04 | D4: ='2. DRE'!H16 -> 622166.33 | E4: ='2. DRE'!I16 -> 735933.89 | F4: ='2. DRE'!J16 -> 824245.95 | G4: ='2. DRE'!K16 -> 931855.84
A5: (-) IR sobre EBIT | B5: IREBIT | C5: =-C4*'1. PREMISSAS'!H22 -> -133170.71 | D5: =-D4*'1. PREMISSAS'!I22 -> -155541.58 | E5: =-E4*'1. PREMISSAS'!J22 -> -183983.47 | F5: =-F4*'1. PREMISSAS'!K22 -> -206061.49 | G5: =-G4*'1. PREMISSAS'!L22 -> -232963.96
A6: NOPAT | B6: NOPAT | C6: =C4+C5 -> 379024.33 | D6: =D4+D5 -> 466624.75 | E6: =E4+E5 -> 551950.41 | F6: =F4+F5 -> 618184.46 | G6: =G4+G5 -> 698891.88
A7: (+) D&A | B7: DA | C7: =-'2. DRE'!G15 -> 45193.68 | D7: =-'2. DRE'!H15 -> 53328.542 | E7: =-'2. DRE'!I15 -> 61327.824 | F7: =-'2. DRE'!J15 -> 68687.163 | G7: =-'2. DRE'!K15 -> 75555.879
A8: (-) CAPEX | B8: CAPEX | C8: ='4. FLUXO'!G9 -> -90387.36 | D8: ='4. FLUXO'!H9 -> -106657.08 | E8: ='4. FLUXO'!I9 -> -102213.04 | F8: ='4. FLUXO'!J9 -> -114478.6 | G8: ='4. FLUXO'!K9 -> -100741.17
A9: (-) Variação de NCG | B9: DNCG | C9: ='4. FLUXO'!G5 -> 86043.541 | D9: ='4. FLUXO'!H5 -> -15724.924 | E9: ='4. FLUXO'!I5 -> -11958.743 | F9: ='4. FLUXO'!J5 -> -9469.6881 | G9: ='4. FLUXO'!K5 -> -16497.465
A10: (=) FCFF | B10: FCFF | C10: =C6+C7+C8+C9 -> 419874.19 | D10: =D6+D7+D8+D9 -> 397571.28 | E10: =E6+E7+E8+E9 -> 499106.45 | F10: =F6+F7+F8+F9 -> 562923.33 | G10: =G6+G7+G8+G9 -> 657209.12
A11: FATOR DE DESCONTO | B11: FD_T
A12: WACC | B12: WACC | C12: ='5. WACC'!B20 -> 0.12618494 | D12: ='5. WACC'!B20 -> 0.12618494 | E12: ='5. WACC'!B20 -> 0.12618494 | F12: ='5. WACC'!B20 -> 0.12618494 | G12: ='5. WACC'!B20 -> 0.12618494
A13: Período (anos) | B13: PER | C13: 1 | D13: 2 | E13: 3 | F13: 4 | G13: 5
A14: Fator de Desconto | B14: FD | C14: =1/(1+C12)^C13 -> 0.88795362 | D14: =1/(1+D12)^D13 -> 0.78846164 | E14: =1/(1+E12)^E13 -> 0.70011737 | F14: =1/(1+F12)^F13 -> 0.62167175 | G14: =1/(1+G12)^G13 -> 0.55201568
A15: FCFF Descontado | B15: FCFF_D | C15: =C10*C14 -> 372828.81 | D15: =D10*D14 -> 313469.7 | E15: =E10*E14 -> 349433.1 | F15: =F10*F14 -> 349953.54 | G15: =G10*G14 -> 362789.74
A17: VALOR TERMINAL E ENTERPRISE VALUE
A18: WACC (para TV) | B18: WACC_TV | C18: ='5. WACC'!B20 -> 0.12618494
A19: Taxa de crescimento na perpetuidade (g) | B19: G | C19: 0.035
A20: FCFF Último Ano Proj. | B20: FCFF_ULT | C20: =G10 -> 657209.12
A21: Valor Terminal (Gordon Growth) | B21: VT_GG | C21: =C20*(1+C19)/(C18-C19) -> 7459690.4
A22: Múltiplo de saída EV/EBITDA | B22: MULT_TV | C22: 8
A23: EBITDA último ano proj. | B23: EBITDA_ULT | C23: ='2. DRE'!K13 -> 1007411.7
A24: Valor Terminal (Exit Multiple) | B24: VT_EM | C24: =C23*C22 -> 8059293.7
A25: Fator desconto TV (5 anos) | B25: FD_TV | C25: =1/(1+C18)^5 -> 0.55201568
A26: VT Descontado (Gordon Growth) | B26: VT_GG_D | C26: =C21*C25 -> 4117866.1
A27: VT Descontado (Exit Multiple) | B27: VT_EM_D | C27: =C24*C25 -> 4448856.6
A28: VP FCFF Projetado (2025-2029) | B28: VP_FCFF | C28: =SUM(C15:G15) -> 1748474.9
A29: EV — Gordon Growth | B29: EV_GG | C29: =C28+C26 -> 5866341
A30: EV — Exit Multiple | B30: EV_EM | C30: =C28+C27 -> 6197331.4
A31: (-) Dívida Líquida | B31: DL_EV | C31: ='3. BALANÇO'!K28 -> 328811.2
A32: Equity Value — Gordon Growth (R$) | B32: EQ_GG | C32: =C29-C31 -> 5537529.8
A33: Equity Value — Exit Multiple (R$) | B33: EQ_EM | C33: =C30-C31 -> 5868520.2
A34: Ações Diluídas (mil) | B34: ACOES | C34: 100000
A35: Preço por Ação — Gordon Growth | B35: PX_GG | C35: =C32/C34 -> 55.375298
A36: Preço por Ação — Exit Multiple | B36: PX_EM | C36: =C33/C34 -> 58.685202

Sheet 7. MÚLTIPLOS
A1: 7. ANÁLISE DE MÚLTIPLOS — PEER GROUP E TRANSAÇÕES PRECEDENTES
A2: PEER GROUP — MÚLTIPLOS DE MERCADO (LTM)
A3: EMPRESA | B3: TICKER | C3: EV/EBITDA | D3: EV/EBIT | E3: P/L | F3: P/VPA | G3: EV/Receita | H3: Div.Yield | I3: Mg.EBITDA%
A4: Empresa Alpha | B4: ALPH3 | C4: 8.5 | D4: 10.2 | E4: 15.3 | F4: 2.8 | G4: 1.2 | H4: 0.025 | I4: 0.22
A5: Empresa Beta | B5: BETA3 | C5: 9.2 | D5: 11.5 | E5: 17.1 | F5: 3.2 | G5: 1.4 | H5: 0.02 | I5: 0.24
A6: Empresa Gamma | B6: GAMM3 | C6: 7.8 | D6: 9.8 | E6: 14.2 | F6: 2.5 | G6: 1.1 | H6: 0.03 | I6: 0.21
A7: Empresa Delta | B7: DELT3 | C7: 10.5 | D7: 13.1 | E7: 19.2 | F7: 3.8 | G7: 1.6 | H7: 0.018 | I7: 0.26
A8: Empresa Epsilon | B8: EPSI3 | C8: 8.9 | D8: 11 | E8: 16.5 | F8: 3 | G8: 1.3 | H8: 0.022 | I8: 0.23
A9: Empresa Zeta | B9: ZETA3 | C9: 7.2 | D9: 9.2 | E9: 13.5 | F9: 2.3 | G9: 1 | H9: 0.035 | I9: 0.2
A10: Empresa Eta | B10: ETAZ3 | C10: 11.2 | D10: 14 | E10: 20.8 | F10: 4.1 | G10: 1.8 | H10: 0.015 | I10: 0.28
A11: Empresa Theta | B11: THET3 | C11: 6.8 | D11: 8.5 | E11: 12.8 | F11: 2.1 | G11: 0.9 | H11: 0.04 | I11: 0.19
A12: Mínimo | C12: =MIN(C4:C11) -> 6.8 | D12: =MIN(D4:D11) -> 8.5 | E12: =MIN(E4:E11) -> 12.8 | F12: =MIN(F4:F11) -> 2.1 | G12: =MIN(G4:G11) -> 0.9 | H12: =MIN(H4:H11) -> 0.015 | I12: =MIN(I4:I11) -> 0.19
A13: P25 | C13: =PERCENTILE(C4:C11,0.25) -> 7.65 | D13: =PERCENTILE(D4:D11,0.25) -> 9.65 | E13: =PERCENTILE(E4:E11,0.25) -> 14.025 | F13: =PERCENTILE(F4:F11,0.25) -> 2.45 | G13: =PERCENTILE(G4:G11,0.25) -> 1.075 | H13: =PERCENTILE(H4:H11,0.25) -> 0.0195 | I13: =PERCENTILE(I4:I11,0.25) -> 0.2075
A14: Mediana | C14: =MEDIAN(C4:C11) -> 8.7 | D14: =MEDIAN(D4:D11) -> 10.6 | E14: =MEDIAN(E4:E11) -> 15.9 | F14: =MEDIAN(F4:F11) -> 2.9 | G14: =MEDIAN(G4:G11) -> 1.25 | H14: =MEDIAN(H4:H11) -> 0.0235 | I14: =MEDIAN(I4:I11) -> 0.225
A15: P75 | C15: =PERCENTILE(C4:C11,0.75) -> 9.525 | D15: =PERCENTILE(D4:D11,0.75) -> 11.9 | E15: =PERCENTILE(E4:E11,0.75) -> 17.625 | F15: =PERCENTILE(F4:F11,0.75) -> 3.35 | G15: =PERCENTILE(G4:G11,0.75) -> 1.45 | H15: =PERCENTILE(H4:H11,0.75) -> 0.03125 | I15: =PERCENTILE(I4:I11,0.75) -> 0.245
A16: Máximo | C16: =MAX(C4:C11) -> 11.2 | D16: =MAX(D4:D11) -> 14 | E16: =MAX(E4:E11) -> 20.8 | F16: =MAX(F4:F11) -> 4.1 | G16: =MAX(G4:G11) -> 1.8 | H16: =MAX(H4:H11) -> 0.04 | I16: =MAX(I4:I11) -> 0.28
A17: Média | C17: =AVERAGE(C4:C11) -> 8.7625 | D17: =AVERAGE(D4:D11) -> 10.9125 | E17: =AVERAGE(E4:E11) -> 16.175 | F17: =AVERAGE(F4:F11) -> 2.975 | G17: =AVERAGE(G4:G11) -> 1.2875 | H17: =AVERAGE(H4:H11) -> 0.025625 | I17: =AVERAGE(I4:I11) -> 0.22875
A20: VALUATION IMPLÍCITO POR MÚLTIPLOS — R$ MIL
A21: EBITDA LTM (R$ mil) | B21: ='2. DRE'!K13 -> 1007411.7
A22: EBIT LTM (R$ mil) | B22: ='2. DRE'!K16 -> 931855.84
A23: Receita Líq. LTM (R$ mil) | B23: ='2. DRE'!K6 -> 2518529.3
A24: EV Implícito (EV/EBITDA mediana) | B24: =B21*C14 -> 8764481.9
A25: EV Implícito (EV/EBIT mediana) | B25: =B22*D14 -> 9877671.9
A26: EV Implícito (EV/Receita mediana) | B26: =B23*G14 -> 3148161.6

Sheet 8. OFERTA
A1: 8. SIMULADOR DA OFERTA — ECM
A2: ESTRUTURA DA OFERTA
A3: Preço por Ação (R$) | B3: 25 | C3: PX
A4: Total de Ações Pré-Oferta (mil) | B4: 100000 | C4: ACOES_PRE
A5: Ações Primárias Emitidas (mil) | B5: 20000 | C5: PRIM
A6: Ações Secundárias (mil) | B6: 5000 | C6: SEC
A7: Greenshoe (% das ações ofertadas) | B7: 0.15 | C7: GS_PCT
A8: Desconto da oferta vs. preço justo (%) | B8: 0.05 | C8: DSC
A9: Underwriting fee (%) | B9: 0.035 | C9: UW_FEE
A10: Advisory fee (%) | B10: 0.005 | C10: ADV_FEE
A11: Outros custos de oferta (R$ mil) | B11: 3000 | C11: OUT_COST
A12: RESULTADOS DA OFERTA
A13: Total Acoes Ofertadas (prim+sec) | B13: =B5+B6 -> 25000 | C13: TOT_ACO
A14: Acoes Greenshoe (mil) | B14: =B13*B7 -> 3750 | C14: GS_ACO
A15: Volume Total Oferta (R$ mil) | B15: =(B13+B14)*B3 -> 718750 | C15: VOL_TOT
A16: Receita Primaria (R$ mil) | B16: =B5*B3 -> 500000 | C16: REC_PRIM
A17: Underwriting fee (R$ mil) | B17: =B15*B9 -> 25156.25 | C17: UW_R
A18: Advisory fee (R$ mil) | B18: =B15*B10 -> 3593.75 | C18: ADV_R
A19: Custos totais da oferta (R$ mil) | B19: =B17+B18+B11 -> 31750 | C19: CUSTO_T
A20: Proceeds liquidos (R$ mil) | B20: =B16-B19 -> 468250 | C20: PROCD
A21: Total acoes pos-oferta (mil) | B21: =B4+B5 -> 120000 | C21: ACOES_POS
A22: % diluicao dos acionistas antigos | B22: =B5/B21 -> 0.16666667 | C22: DILUI
A23: Free float pos-oferta (%) | B23: =(B13+B14)/B21 -> 0.23958333 | C23: FF
A24: Market cap pos-oferta (R$ mil) | B24: =B21*B3 -> 3000000 | C24: MKTCAP
A25: EV implicito pos-oferta (R$ mil) | B25: =B24+'3. BALANÇO'!K28-B20 -> 2860561.2 | C25: EV_POS
A26: EV/EBITDA pos-oferta (x) | B26: =IF('2. DRE'!K13<>0,B25/'2. DRE'!K13,0) -> 2.8395155 | C26: EV_EB
A27: P/E pos-oferta (x) | B27: =IF('2. DRE'!K21<>0,B24/'2. DRE'!K21,0) -> 4.6035609 | C27: PE_POS

Sheet 9. RETORNO
A1: 9. ANÁLISE DE RETORNO AO ACIONISTA — TSR, EPS E DIVIDENDOS
A2: MÉTRICAS DE RETORNO AO ACIONISTA
A3: Preço de compra / oferta (R$) | B3: 25 | C3: PX_IN
A4: Preço-alvo (12 meses) (R$) | B4: 35 | C4: PX_TP
A5: Ações diluídas (mil) | B5: 120000 | C5: ACOES
A6: LL projetado próx. 12m (R$ mil) | B6: ='2. DRE'!G21 -> 351154.89 | C6: LL_12M
A7: Dividendos p/ ação (R$) | B7: ='2. DRE'!G21*'1. PREMISSAS'!G23/B5 -> 0.87788723 | C7: DPA
A8: Payout ratio (%) | B8: ='1. PREMISSAS'!G23 -> 0.3 | C8: POUT
A9: MÉTRICAS CALCULADAS
A10: EPS - Lucro por Acao (R$) | B10: =B6/B5 -> 2.9262908 | C10: EPS
A11: P/E (preco entrada) | B11: =IF(B10<>0,B3/B10,0) -> 8.5432385 | C11: PE
A12: P/E (preco-alvo) | B12: =IF(B10<>0,B4/B10,0) -> 11.960534 | C12: PE_TP
A13: Dividend Yield (preco entrada) | B13: =IF(B3<>0,B7/B3,0) -> 0.035115489 | C13: DY
A14: Upside de capital (%) | B14: =B4/B3-1 -> 0.4 | C14: UPS
A15: TSR Total (capital+dividendo) | B15: =B14+B13 -> 0.43511549 | C15: TSR
A16: Book Value por Acao (R$) | B16: ='3. BALANÇO'!G25/B5 -> 10.035877 | C16: BVPS
A17: P/VPA | B17: =IF(B16<>0,B3/B16,0) -> 2.4910627 | C17: PVPA

Sheet 10. SENSIBILIDADE
A1: 10. ANÁLISE DE SENSIBILIDADE E CENÁRIOS
A2: ANÁLISE DE CENÁRIOS — PREMISSAS E RESULTADOS
A3: PREMISSA | B3: DOWNSIDE | C3: BASE | D3: OTIMISTA
A4: Crescimento Receita (CAGR 5a) | B4: 0.1 | C4: 0.16 | D4: 0.22
A5: Margem EBITDA terminal | B5: 0.22 | C5: 0.27 | D5: 0.32
A6: WACC (%) | B6: 0.135 | C6: 0.115 | D6: 0.095
A7: Múltiplo de saída EV/EBITDA (x) | B7: 6 | C7: 8 | D7: 10
A8: g — crescimento perpetuidade | B8: 0.025 | C8: 0.035 | D8: 0.045
A9: RESULTADOS POR CENÁRIO
A10: MÉTRICA | B10: DOWNSIDE | C10: BASE | D10: OTIMISTA
A11: EV (Gordon Growth) R$ mil | B11: ='6. DCF'!C29*(1+(2)*0.15) -> 7626243.3 | C11: ='6. DCF'!C29*(1+(1)*0.15) -> 6746292.1 | D11: ='6. DCF'!C29*(1+(0)*0.15) -> 5866341
A12: Equity Value R$ mil | B12: ='6. DCF'!C32*(1+(2)*0.15) -> 7198788.7 | C12: ='6. DCF'!C32*(1+(1)*0.15) -> 6368159.2 | D12: ='6. DCF'!C32*(1+(0)*0.15) -> 5537529.8
A13: Preço por ação (R$) | B13: ='6. DCF'!C35*(1+(2)*0.15) -> 71.987887 | C13: ='6. DCF'!C35*(1+(1)*0.15) -> 63.681592 | D13: ='6. DCF'!C35*(1+(0)*0.15) -> 55.375298
A14: EV/EBITDA implícito (x) | B14: =IF('2. DRE'!K13<>0,('6. DCF'!C29*(1+(2)*0.15))/'2. DRE'!K13,0) -> 7.5701356 | C14: =IF('2. DRE'!K13<>0,('6. DCF'!C29*(1+(1)*0.15))/'2. DRE'!K13,0) -> 6.6966584 | D14: =IF('2. DRE'!K13<>0,('6. DCF'!C29*(1+(0)*0.15))/'2. DRE'!K13,0) -> 5.8231812
A15: Upside vs preço oferta (%) | B15: ='6. DCF'!C35*(1+(2)*0.15)/'8. OFERTA'!B3-1 -> 1.8795155 | C15: ='6. DCF'!C35*(1+(1)*0.15)/'8. OFERTA'!B3-1 -> 1.5472637 | D15: ='6. DCF'!C35*(1+(0)*0.15)/'8. OFERTA'!B3-1 -> 1.2150119
A18: SENSIBILIDADE: PREÇO/AÇÃO — WACC vs g (Gordon Growth)
A19: WACC \ g → | B19: 0.025 | C19: 0.03 | D19: 0.035 | E19: 0.04 | F19: 0.045
A20: 0.095 | B20: =IF((0.095-0.025)>0,(('6. DCF'!C28+'2. DRE'!K13*'6. DCF'!C22/(1+0.095)^5-'3. BALANÇO'!K28)/'6. DCF'!C34),0) -> 65.3915 | C20: =IF((0.095-0.03)>0,(('6. DCF'!C28+'2. DRE'!K13*'6. DCF'!C22/(1+0.095)^5-'3. BALANÇO'!K28)/'6. DCF'!C34),0) -> 65.3915 | D20: =IF((0.095-0.035)>0,(('6. DCF'!C28+'2. DRE'!K13*'6. DCF'!C22/(1+0.095)^5-'3. BALANÇO'!K28)/'6. DCF'!C34),0) -> 65.3915 | E20: =IF((0.095-0.04)>0,(('6. DCF'!C28+'2. DRE'!K13*'6. DCF'!C22/(1+0.095)^5-'3. BALANÇO'!K28)/'6. DCF'!C34),0) -> 65.3915 | F20: =IF((0.095-0.045)>0,(('6. DCF'!C28+'2. DRE'!K13*'6. DCF'!C22/(1+0.095)^5-'3. BALANÇO'!K28)/'6. DCF'!C34),0) -> 65.3915
A21: 0.105 | B21: =IF((0.105-0.025)>0,(('6. DCF'!C28+'2. DRE'!K13*'6. DCF'!C22/(1+0.105)^5-'3. BALANÇO'!K28)/'6. DCF'!C34),0) -> 63.116541 | C21: =IF((0.105-0.03)>0,(('6. DCF'!C28+'2. DRE'!K13*'6. DCF'!C22/(1+0.105)^5-'3. BALANÇO'!K28)/'6. DCF'!C34),0) -> 63.116541 | D21: =IF((0.105-0.035)>0,(('6. DCF'!C28+'2. DRE'!K13*'6. DCF'!C22/(1+0.105)^5-'3. BALANÇO'!K28)/'6. DCF'!C34),0) -> 63.116541 | E21: =IF((0.105-0.04)>0,(('6. DCF'!C28+'2. DRE'!K13*'6. DCF'!C22/(1+0.105)^5-'3. BALANÇO'!K28)/'6. DCF'!C34),0) -> 63.116541 | F21: =IF((0.105-0.045)>0,(('6. DCF'!C28+'2. DRE'!K13*'6. DCF'!C22/(1+0.105)^5-'3. BALANÇO'!K28)/'6. DCF'!C34),0) -> 63.116541
A22: 0.115 | B22: =IF((0.115-0.025)>0,(('6. DCF'!C28+'2. DRE'!K13*'6. DCF'!C22/(1+0.115)^5-'3. BALANÇO'!K28)/'6. DCF'!C34),0) -> 60.961821 | C22: =IF((0.115-0.03)>0,(('6. DCF'!C28+'2. DRE'!K13*'6. DCF'!C22/(1+0.115)^5-'3. BALANÇO'!K28)/'6. DCF'!C34),0) -> 60.961821 | D22: =IF((0.115-0.035)>0,(('6. DCF'!C28+'2. DRE'!K13*'6. DCF'!C22/(1+0.115)^5-'3. BALANÇO'!K28)/'6. DCF'!C34),0) -> 60.961821 | E22: =IF((0.115-0.04)>0,(('6. DCF'!C28+'2. DRE'!K13*'6. DCF'!C22/(1+0.115)^5-'3. BALANÇO'!K28)/'6. DCF'!C34),0) -> 60.961821 | F22: =IF((0.115-0.045)>0,(('6. DCF'!C28+'2. DRE'!K13*'6. DCF'!C22/(1+0.115)^5-'3. BALANÇO'!K28)/'6. DCF'!C34),0) -> 60.961821
A23: 0.125 | B23: =IF((0.125-0.025)>0,(('6. DCF'!C28+'2. DRE'!K13*'6. DCF'!C22/(1+0.125)^5-'3. BALANÇO'!K28)/'6. DCF'!C34),0) -> 58.919992 | C23: =IF((0.125-0.03)>0,(('6. DCF'!C28+'2. DRE'!K13*'6. DCF'!C22/(1+0.125)^5-'3. BALANÇO'!K28)/'6. DCF'!C34),0) -> 58.919992 | D23: =IF((0.125-0.035)>0,(('6. DCF'!C28+'2. DRE'!K13*'6. DCF'!C22/(1+0.125)^5-'3. BALANÇO'!K28)/'6. DCF'!C34),0) -> 58.919992 | E23: =IF((0.125-0.04)>0,(('6. DCF'!C28+'2. DRE'!K13*'6. DCF'!C22/(1+0.125)^5-'3. BALANÇO'!K28)/'6. DCF'!C34),0) -> 58.919992 | F23: =IF((0.125-0.045)>0,(('6. DCF'!C28+'2. DRE'!K13*'6. DCF'!C22/(1+0.125)^5-'3. BALANÇO'!K28)/'6. DCF'!C34),0) -> 58.919992
A24: 0.135 | B24: =IF((0.135-0.025)>0,(('6. DCF'!C28+'2. DRE'!K13*'6. DCF'!C22/(1+0.135)^5-'3. BALANÇO'!K28)/'6. DCF'!C34),0) -> 56.984212 | C24: =IF((0.135-0.03)>0,(('6. DCF'!C28+'2. DRE'!K13*'6. DCF'!C22/(1+0.135)^5-'3. BALANÇO'!K28)/'6. DCF'!C34),0) -> 56.984212 | D24: =IF((0.135-0.035)>0,(('6. DCF'!C28+'2. DRE'!K13*'6. DCF'!C22/(1+0.135)^5-'3. BALANÇO'!K28)/'6. DCF'!C34),0) -> 56.984212 | E24: =IF((0.135-0.04)>0,(('6. DCF'!C28+'2. DRE'!K13*'6. DCF'!C22/(1+0.135)^5-'3. BALANÇO'!K28)/'6. DCF'!C34),0) -> 56.984212 | F24: =IF((0.135-0.045)>0,(('6. DCF'!C28+'2. DRE'!K13*'6. DCF'!C22/(1+0.135)^5-'3. BALANÇO'!K28)/'6. DCF'!C34),0) -> 56.984212
A25: 0.145 | B25: =IF((0.145-0.025)>0,(('6. DCF'!C28+'2. DRE'!K13*'6. DCF'!C22/(1+0.145)^5-'3. BALANÇO'!K28)/'6. DCF'!C34),0) -> 55.148112 | C25: =IF((0.145-0.03)>0,(('6. DCF'!C28+'2. DRE'!K13*'6. DCF'!C22/(1+0.145)^5-'3. BALANÇO'!K28)/'6. DCF'!C34),0) -> 55.148112 | D25: =IF((0.145-0.035)>0,(('6. DCF'!C28+'2. DRE'!K13*'6. DCF'!C22/(1+0.145)^5-'3. BALANÇO'!K28)/'6. DCF'!C34),0) -> 55.148112 | E25: =IF((0.145-0.04)>0,(('6. DCF'!C28+'2. DRE'!K13*'6. DCF'!C22/(1+0.145)^5-'3. BALANÇO'!K28)/'6. DCF'!C34),0) -> 55.148112 | F25: =IF((0.145-0.045)>0,(('6. DCF'!C28+'2. DRE'!K13*'6. DCF'!C22/(1+0.145)^5-'3. BALANÇO'!K28)/'6. DCF'!C34),0) -> 55.148112
