Workbook
Name a: #REF!
Name agosto: #REF!
Name ano: #REF!
Name ANUAL: #REF!
Name ANUALL: #REF!
Name asd: #REF!
Name asdd: #REF!
Name asdf: #REF!
Name bdi: #REF!
Name bdis: #REF!
Name bg: #REF!
Name BN: #REF!
Name CASAMADEIRA: #REF!
Name cash_terminal: #REF!
Name ÇÇÇ: #REF!
Name cccccc: #REF!
Name cddddd: #REF!
Name COFINS: #REF!
Name dc: #REF!
Name dcf_year: #REF!
Name dd: #REF!
Name debt_terminal: #REF!
Name DespPPubFProm: '[1]desp op prom_obras'!#REF!
Name ds: #REF!
Name e: #REF!
Name EBITDA_mult: #REF!
Name ECECR: #REF!
Name er: #REF!
Name FF: #REF!
Name FWQFWFWQFWE: #REF!
Name GFNLHKNF: #REF!
Name GUCIGKJGJKFHTDMHGTDJY: #REF!
Name indicesss: #REF!
Name informe: #REF!
Name ITBI: '[2]desp op prom_obras'!#REF!
Name jfjfjfjfj: #REF!
Name jgjgj: #REF!
Name JORGE: #REF!
Name kasl: '[2]desp op prom_obras'!#REF!
Name kdkdkd: #REF!
Name Maf: #REF!
Name MatrizOcupAdim: #REF!
Name MENSAL: #REF!
Name Mensal.: #REF!
Name MOBILIA: #REF!
Name mult_sen: #REF!
Name n: #REF!
Name ng: #REF!
Name nhhhh: #REF!
Name NJDGFUDGE: #REF!
Name novva: #REF!
Name parcelamentorfb: #REF!
Name periodo_selecionado: #REF!
Name PeriodoInPlanejado: #REF!=MEDIAN(#REF!,#REF!,#REF!+#REF!-1)
Name PeriodoInReal: #REF!=MEDIAN(#REF!,#REF!,#REF!+#REF!-1)
Name Plano: 'DRE - Grafico'!PeriodoInPlanejado*(#REF!>0)
Name POOL: #REF!
Name POOLL: #REF!
Name PorcentagemConcluída: 'DRE - Grafico'!PorcentagemConcluídaPosterior*'DRE - Grafico'!PeriodoInPlanejado
Name PorcentagemConcluídaPosterior: (#REF!=MEDIAN(#REF!,#REF!,#REF!+#REF!)*(#REF!>0))*((#REF!<(INT(#REF!+#REF!*#REF!)))+(#REF!=#REF!))*(#REF!>0)

Sheet Fluxo Consolidado
L1: 2009558.1 | BB1: =AX3+BB3 -> 36144253 | BD1: =IRR(BD59:BD179,1%) -> 0.017079045 | BE1: =(1+BD1)^12-1 -> 0.22533963
A2: CRONOGRAMA | D2: RECEITA | P2: OBRA | X2: COMERCIALIZAÇÃO | AH2: DESPESAS ADMINISTRATIVAS | AP2: MÚTUO | AS2: RESUMO SEM ALAVANCAGEM | AX2: FLUXO CRI | BF2: RESUMO COM ALAVANCAGEM
A3: % | D3: =SUM(D59:D186) -> 1.0904974e+08 | E3: =SUM(E59:E186) -> 1.7149039e+08 | F3: =SUM(F59:F186) -> 1382206.7 | G3: 0.1 | H3: =SUM(H59:H186) -> -11265591 | I3: =SUM(I59:I186) -> 11265591 | J3: 0.005 | L3: =SUM(L5:L185) -> 3.6941881e+08 | M3: =SUM(M5:M185) -> 1000000 | N3: =SUM(N5:N185) -> 1493512 | O3: =SUM(O5:O185) -> 3539928.6 | P3: =SUM(P59:P186) -> -34953227 | Q3: =SUM(Q59:Q186) -> -3805740.3 | R3: =SUM(R59:R186) -> -13729000 | S3: =SUM(S59:S186) -> -600000 | T3: =SUM(T59:T186) -> -600000 | U3: =SUM(U59:U186) -> -375081.79 | V3: =SUM(V59:V186) -> -817651.46 | W3: =SUM(W59:W186) -> -2548350.2 | ... AO3: =SUM(AO59:AO186) -> -40000 | AP3: =SUM(AP58:AP186) -> -1248000 | AQ3: =SUM(AQ58:AQ186) -> -870000 | AS3: =SUM(AS5:AS186) -> 3.7545225e+08 | AT3: =SUM(AT5:AT186) -> -1.6981533e+08 | AU3: =SUM(AU5:AU186) -> 2.0563692e+08 | AV3: =AV186 -> 2.0563692e+08 | AX3: =SUM(AX58:AX238) -> 42000000 | AY3: =SUM(AY58:AY238) -> -27676170 | AZ3: =SUM(AZ58:AZ238) -> -48558231 | BA3: =SUM(BA58:BA238) -> -5183823.9 | BB3: =SUM(BB58:BB238) -> -5855747.1 | BC3: =SUM(BC58:BC238) -> 0 | BD3: =SUM(BD58:BD238) -> -45273972 | BE3: =SUM(BE58:BE238) -> -87273972 | BF3: =SUM(BF5:BF238) -> 3.3017828e+08 | BG3: =SUM(BG5:BG238) -> -1.6981533e+08 | BH3: =SUM(BH5:BH238) -> 1.6036295e+08 | BI3: =BI180 -> 1.6036295e+08
A4: N° | B4: EVENTO | C4: MESES | D4: ESTOQUE | E4: AGING DA CARTERIA | F4: RECUPERAÇÃO INADIMPLÊNCIA AGING | G4: INADIMPLÊNCIA | I4: RECUPERAÇÃO | J4: CORREÇÃO 0,5% | L4: RECEITA TOTAL | M4: EMPRESTIMO PF | N4: EMP. MUTUO ENTRE EMPRESAS | O4: OUTRAS ENTRADAS | P4: CRONOGRAMA OBRA | Q4: TAXA DE ADMINISTRAÇÃO | R4: FF&E | S4: INFRAESTRUTURA | T4: PARQUE AQ. | U4: PROJETO | V4: LEGALIZAÇÃO OBRA | W4: GERENCIAMENTO OBRA | X4: VENDAS GERAL | Y4: COMISSÃO PREVISTO | Z4: COMISSÃO FIXO | AA4: COMISSÃO REALIZADO/ PREMIAÇÃO | AB4: CLUB CIA PREVISTO | AC4: CLUB CIA REALIZADO | AD4: FÉRIAS CLUB | AE4: PASSAPORTE REALIZADO | AF4: PASSAPORTE PREVISTO | AG4: MARKETING, PROMOÇÃO E PROPAGANDA | AH4: GESTÃO DA CARTEIRA | AI4: HONORÁRIOS ADV | AJ4: HONORÁRIOS CONTABEIS / AUDITORIA | AK4: CORRESPONDÊNCIA E MALOTE | AL4: DISTRATO DE VENDA | AM4: DESPESAS BANCÁRIAS | AN4: IMPOSTOS (RET) | AO4: IPTU | AP4: EMPRESTIMO PF | AQ4: EMP. MUTUO ENTRE EMPRESAS | AS4: TOTAL RECEITA | AT4: TOTAL DESPESAS | AU4: SALDO MENSAL | AV4: SALDO ACUMULADO | AX4: LIBERAÇÃO | AY4: 1º PMT (AMORTIZAÇÃO + JUROS) | AZ4: 2º PMT (AMORTIZAÇÃO + JUROS) | BA4: DESPESAS RECORRENTES / DESPESAS GESTÃO | BB4: CUSTOS FLAT - ESTRUTURAÇÃO | BC4: FUNDO DE LIQUIDEZ | BD4: FLUXO MENSAL ECONOMICO | BE4: FLUXO MENSAL FINANCEIRO | BF4: TOTAL RECEITA | BG4: TOTAL DESPESAS | BH4: SALDO MENSAL | BI4: FLUXO ACUMULADO
C5: 41671 | L5: 0 | M5: 0 | N5: 0 | O5: 1000 | AS5: 1000 | AT5: =-3900000+3900000 -> 0 | AU5: =SUM(AS5:AT5) -> 1000 | AV5: =AU5 -> 1000 | BF5: =AS5 -> 1000 | BG5: =AT5 -> 0 | BH5: =AU5 -> 1000 | BI5: =AV5 -> 1000
C6: 41699 | L6: 0 | M6: 0 | N6: 0 | O6: 0 | AS6: 0 | AT6: 0 | AU6: =SUM(AS6:AT6) -> 0 | AV6: =AU6+AV5 -> 1000 | BF6: =AS6 -> 0 | BG6: =AT6 -> 0 | BH6: =AU6 -> 0 | BI6: =AV6 -> 1000
C7: 41730 | L7: 0 | M7: 0 | N7: 0 | O7: 9245.14 | AS7: 9245.14 | AT7: =-1559245.14+1550000 -> -9245.14 | AU7: =SUM(AS7:AT7) -> 1.0186341e-10 | AV7: =AU7+AV6 -> 1000 | BF7: =AS7 -> 9245.14 | BG7: =AT7 -> -9245.14 | BH7: =AU7 -> 1.0186341e-10 | BI7: =AV7 -> 1000
C8: 41760 | L8: 0 | M8: 0 | N8: 46553.47 | O8: 146407.45 | AS8: 192960.92 | AT8: -188312.22 | AU8: =SUM(AS8:AT8) -> 4648.7 | AV8: =AU8+AV7 -> 5648.7 | BF8: =AS8 -> 192960.92 | BG8: =AT8 -> -188312.22 | BH8: =AU8 -> 4648.7 | BI8: =AV8 -> 5648.7
C9: 41791 | L9: 0 | M9: 0 | N9: 3142.34 | O9: 56935.17 | AS9: 60077.51 | AT9: =-1630629.61+1576198.54 -> -54431.07 | AU9: =SUM(AS9:AT9) -> 5646.44 | AV9: =AU9+AV8 -> 11295.14 | BF9: =AS9 -> 60077.51 | BG9: =AT9 -> -54431.07 | BH9: =AU9 -> 5646.44 | BI9: =AV9 -> 11295.14
C10: 41821 | L10: 0 | M10: 0 | N10: 3568.76 | O10: 235374.71 | AS10: 238943.47 | AT10: -205847.51 | AU10: =SUM(AS10:AT10) -> 33095.96 | AV10: =AU10+AV9 -> 44391.1 | BF10: =AS10 -> 238943.47 | BG10: =AT10 -> -205847.51 | BH10: =AU10 -> 33095.96 | BI10: =AV10 -> 44391.1
C11: 41852 | L11: 0 | M11: 0 | N11: 0 | O11: 281736.14 | AS11: 281736.14 | AT11: -320861.45 | AU11: =SUM(AS11:AT11) -> -39125.31 | AV11: =AU11+AV10 -> 5265.79 | BF11: =AS11 -> 281736.14 | BG11: =AT11 -> -320861.45 | BH11: =AU11 -> -39125.31 | BI11: =AV11 -> 5265.79
C12: 41883 | L12: 0 | M12: 0 | N12: 0 | O12: 294606.73 | AS12: 294606.73 | AT12: -253992.76 | AU12: =SUM(AS12:AT12) -> 40613.97 | AV12: =AU12+AV11 -> 45879.76 | BF12: =AS12 -> 294606.73 | BG12: =AT12 -> -253992.76 | BH12: =AU12 -> 40613.97 | BI12: =AV12 -> 45879.76
C13: 41913 | L13: 0 | M13: 0 | N13: 41112.59 | O13: 336906.22 | AS13: 378018.81 | AT13: -367160.57 | AU13: =SUM(AS13:AT13) -> 10858.24 | AV13: =AU13+AV12 -> 56738 | BF13: =AS13 -> 378018.81 | BG13: =AT13 -> -367160.57 | BH13: =AU13 -> 10858.24 | BI13: =AV13 -> 56738
C14: 41944 | L14: 0 | M14: 0 | N14: 0 | O14: 334185.6 | AS14: 334185.6 | AT14: -361508.56 | AU14: =SUM(AS14:AT14) -> -27322.96 | AV14: =AU14+AV13 -> 29415.04 | BF14: =AS14 -> 334185.6 | BG14: =AT14 -> -361508.56 | BH14: =AU14 -> -27322.96 | BI14: =AV14 -> 29415.04
C15: 41974 | L15: 0 | M15: 0 | N15: 30000 | O15: 143859.64 | AS15: 173859.64 | AT15: -134974.89 | AU15: =SUM(AS15:AT15) -> 38884.75 | AV15: =AU15+AV14 -> 68299.79 | BF15: =AS15 -> 173859.64 | BG15: =AT15 -> -134974.89 | BH15: =AU15 -> 38884.75 | BI15: =AV15 -> 68299.79
C16: 42005 | L16: 22800.1 | M16: 0 | N16: 0 | O16: 106536.84 | AS16: 129336.94 | AT16: -126187.82 | AU16: =SUM(AS16:AT16) -> 3149.12 | AV16: =AU16+AV15 -> 71448.91 | BF16: =AS16 -> 129336.94 | BG16: =AT16 -> -126187.82 | BH16: =AU16 -> 3149.12 | BI16: =AV16 -> 71448.91
C17: 42036 | L17: 68481.75 | M17: 0 | N17: 40000 | O17: 171915.91 | AS17: 280397.66 | AT17: -315649.39 | AU17: =SUM(AS17:AT17) -> -35251.73 | AV17: =AU17+AV16 -> 36197.18 | BF17: =AS17 -> 280397.66 | BG17: =AT17 -> -315649.39 | BH17: =AU17 -> -35251.73 | BI17: =AV17 -> 36197.18
C18: 42064 | L18: 188382.86 | M18: 0 | N18: 0 | O18: 361130.16 | AS18: 549513.02 | AT18: -436787.24 | AU18: =SUM(AS18:AT18) -> 112725.78 | AV18: =AU18+AV17 -> 148922.96 | BF18: =AS18 -> 549513.02 | BG18: =AT18 -> -436787.24 | BH18: =AU18 -> 112725.78 | BI18: =AV18 -> 148922.96
C19: 42095 | L19: 238926.06 | M19: 0 | N19: 4948.26 | O19: 148490.04 | AS19: 392364.36 | AT19: -522032.09 | AU19: =SUM(AS19:AT19) -> -129667.73 | AV19: =AU19+AV18 -> 19255.23 | BF19: =AS19 -> 392364.36 | BG19: =AT19 -> -522032.09 | BH19: =AU19 -> -129667.73 | BI19: =AV19 -> 19255.23
C20: 42125 | L20: 276060.96 | M20: 0 | N20: 6834.67 | O20: 296905.35 | AS20: 579800.98 | AT20: -559143.88 | AU20: =SUM(AS20:AT20) -> 20657.1 | AV20: =AU20+AV19 -> 39912.33 | BF20: =AS20 -> 579800.98 | BG20: =AT20 -> -559143.88 | BH20: =AU20 -> 20657.1 | BI20: =AV20 -> 39912.33
C21: 42156 | L21: 314105.92 | M21: 0 | N21: 0 | O21: 195692.3 | AS21: 509798.22 | AT21: -510482.68 | AU21: =SUM(AS21:AT21) -> -684.46 | AV21: =AU21+AV20 -> 39227.87 | BF21: =AS21 -> 509798.22 | BG21: =AT21 -> -510482.68 | BH21: =AU21 -> -684.46 | BI21: =AV21 -> 39227.87
... C56: 43221 | L56: 2028488.2 | M56: 0 | N56: 0 | O56: 31658.19 | AS56: 2060146.4 | AT56: -1991218.4 | AU56: =SUM(AS56:AT56) -> 68927.93 | AV56: =AU56+AV55 -> 169727.35 | BF56: =AS56 -> 2060146.4 | BG56: =AT56 -> -1991218.4 | BH56: =AU56 -> 68927.93 | BI56: =AV56 -> 169727.35
C57: 43252 | L57: 1823384.8 | N57: 0 | O57: 65018.01 | AS57: 1888402.8 | AT57: -1948302.6 | AU57: =SUM(AS57:AT57) -> -59899.81 | AV57: =AU57+AV56 -> 109827.54 | BF57: =AS57 -> 1888402.8 | BG57: =AT57 -> -1948302.6 | BH57: =AU57 -> -59899.81 | BI57: =AV57 -> 109827.54
A58: 1 | C58: 43282 | L58: 2009558.1 | M58: 0 | N58: 0 | O58: -6538.63 | AS58: 2003019.4 | AT58: -1901144.7 | AU58: =SUM(AS58:AT58) -> 101874.77 | AV58: =AU58+AV57 -> 211702.31 | BF58: =AS58 -> 2003019.4 | BG58: =AT58 -> -1901144.7 | BH58: =SUM(BF58:BG58) -> 101874.77 | BI58: =BH58+BI57 -> 211702.31
A59: =A58+1 -> 2 | B59: ACOMPANHAMENTO | C59: 43313 | D59: 0 | E59: 2221975.4 | F59: 0 | G59: 0.1 | H59: =-E59*G59 -> -222197.54 | I59: 0 | L59: =SUM(H59:J59,D59:F59) -> 1999777.9 | P59: -1531774.3 | Q59: -154410.94 | R59: 0 | S59: 0 | T59: 0 | U59: -103903.6 | V59: 0 | W59: -70000 | X59: -5000 | Y59: 0 | Z59: -79994.21 | AA59: -540875.64 | AB59: 0 | AC59: -41454.85 | AD59: -201192 | AE59: -165643.69 | AF59: 0 | AG59: -25711.75 | AH59: =-L1*6% -> -120573.48 | AI59: -9209.81 | AJ59: -7969 | AK59: -10571.835 | AL59: -242823.02 | AM59: =-L1*1.2% -> -24114.697 | AN59: =-L1*4% -> -80382.323 | AO59: 0 | AP59: -24000 | AQ59: 0 | AS59: =+L59 -> 1999777.9 | AT59: =+SUM(P59:AQ59) -> -3439605.1 | AU59: =SUM(AS59:AT59) -> -1439827.2 | AV59: =AU59+AV58 -> -1228124.9 | AX59: 0 | AY59: 0 | AZ59: 0 | BA59: 0 | BB59: 0 | BC59: 0 | BD59: =SUM(AX59:BC59) -> 0 | BE59: 0 | BF59: =L59+AX59+AY59+BA59+BB59 -> 1999777.9 | BG59: =AT59 -> -3439605.1 | BH59: =SUM(BF59:BG59) -> -1439827.2 | BI59: =BH59+BI58 -> -1228124.9
A60: =A59+1 -> 3 | C60: 43344 | D60: 0 | E60: 2238986.8 | F60: 0 | G60: 0.1 | H60: =-E60*G60 -> -223898.68 | I60: 0 | L60: =SUM(H60:J60,D60:F60) -> 2015088.1 | P60: -1514312.9 | Q60: -165440.3 | R60: 0 | S60: 0 | T60: 0 | U60: -103903.6 | V60: 0 | W60: -95321.162 | X60: -5000 | Y60: -26080.141 | Z60: -79994.21 | AA60: -527275.21 | AB60: 0 | AC60: -48379.83 | AD60: -142042 | AE60: -165643.69 | AF60: 0 | AG60: -25711.75 | AH60: =-L59*6% -> -119986.67 | AI60: -9209.81 | AJ60: -7969 | AK60: -12106.458 | AL60: -90637.79 | AM60: =-L59*1.2% -> -23997.335 | AN60: =-L59*4% -> -79991.115 | AO60: 0 | AP60: -24000 | AQ60: -870000 | AS60: =+L60 -> 2015088.1 | AT60: =+SUM(P60:AQ60) -> -4137003 | AU60: =SUM(AS60:AT60) -> -2121914.8 | AV60: =AU60+AV59 -> -3350039.8 | AX60: 15000000 | AY60: 0 | AZ60: 0 | BA60: 0 | BB60: -2263780.1 | BC60: 0 | BD60: =SUM(AX60:BC60) -> 12736220 | BE60: =SUM(AY60:BC60) -> -2263780.1 | BF60: =L60+AX60+AY60+BA60+BB60+BC60+AZ60 -> 14751308 | BG60: =AT60 -> -4137003 | BH60: =SUM(BF60:BG60) -> 10614305 | BI60: =BH60+BI59 -> 9386180.1
A61: =A60+1 -> 4 | C61: 43374 | D61: 0 | E61: 2420664.7 | F61: 0 | G61: 0.1 | H61: =-E61*G61 -> -242066.47 | I61: =-H58 -> 0 | L61: =SUM(H61:J61,D61:F61) -> 2178598.2 | P61: -1766698.4 | Q61: -193013.68 | R61: 0 | S61: 0 | T61: 0 | U61: -103903.6 | V61: 0 | W61: -95321.162 | X61: -5000 | Y61: -43125.711 | Z61: 0 | AA61: -492461.97 | AB61: 0 | AC61: -52259.88 | AD61: -121742 | AE61: -165643.69 | AF61: 0 | AG61: -25711.75 | AH61: =-L60*6% -> -120905.29 | AI61: -9209.81 | AJ61: -7969 | AK61: -12529.674 | AL61: -81235.26 | AM61: =-L60*1.2% -> -24181.058 | AN61: =-L60*4% -> -80603.525 | AO61: 0 | AP61: -1200000 | AS61: =+L61 -> 2178598.2 | AT61: =+SUM(P61:AQ61) -> -4601515.5 | AU61: =SUM(AS61:AT61) -> -2422917.2 | AV61: =AU61+AV60 -> -5772957 | AX61: 0 | AY61: -174843.72 | AZ61: 0 | BA61: -65844.424 | BB61: 0 | BC61: -115000 | BD61: =SUM(AX61:BB61) -> -240688.15 | BE61: =SUM(AY61:BC61) -> -355688.15 | BF61: =L61+AX61+AY61+BA61+BB61+BC61+AZ61 -> 1822910.1 | BG61: =AT61 -> -4601515.5 | BH61: =SUM(BF61:BG61) -> -2778605.3 | BI61: =BH61+BI60 -> 6607574.7
A62: =A61+1 -> 5 | C62: 43405 | D62: 95647.818 | E62: 2455737.2 | F62: 69110.337 | G62: 0.1 | H62: =-E62*G62 -> -245573.72 | I62: =-H59 -> 222197.54 | L62: =SUM(H62:J62,D62:F62) -> 2597119.2 | P62: -1918129.7 | Q62: -209557.71 | R62: 0 | S62: 0 | T62: 0 | U62: -63371 | V62: 0 | W62: -95321.162 | X62: -5000 | Y62: -64289.083 | Z62: 0 | AA62: -482413.39 | AB62: -2213.0871 | AC62: -52498.51 | AD62: -121742 | AE62: -165643.69 | AF62: -29333.333 | AG62: -25711.75 | AH62: =-L61*6% -> -130715.89 | AI62: -9209.81 | AJ62: -7969 | AK62: -13034.914 | AL62: -75391.28 | AM62: =-L61*1.2% -> -26143.179 | AN62: =-L61*4% -> -87143.93 | AO62: 0 | AP62: 0 | AS62: =+L62 -> 2597119.2 | AT62: =+SUM(P62:AQ62) -> -3584832.4 | AU62: =SUM(AS62:AT62) -> -987713.23 | AV62: =AU62+AV61 -> -6760670.2 | AX62: 0 | AY62: -174843.72 | AZ62: 0 | BA62: -67219.924 | BB62: 0 | BC62: -115000 | BD62: =SUM(AX62:BB62) -> -242063.65 | BE62: =SUM(AY62:BC62) -> -357063.65 | BF62: =L62+AX62+AY62+BA62+BB62+BC62+AZ62 -> 2240055.5 | BG62: =AT62 -> -3584832.4 | BH62: =SUM(BF62:BG62) -> -1344776.9 | BI62: =BH62+BI61 -> 5262797.9
A63: =A62+1 -> 6 | C63: 43435 | D63: 150179.71 | E63: 2461625.4 | F63: 69110.337 | G63: 0.1 | H63: =-E63*G63 -> -246162.54 | I63: =-H60 -> 223898.68 | L63: =SUM(H63:J63,D63:F63) -> 2658651.6 | P63: -1918129.7 | Q63: -209557.71 | R63: 0 | S63: 0 | T63: 0 | U63: 0 | V63: 0 | W63: -95321.162 | X63: -5000 | Y63: -77833.579 | Z63: 0 | AA63: -277514.4 | AB63: -3521.7507 | AC63: -52467.32 | AD63: 0 | AE63: -165643.69 | AF63: -46800 | AG63: -25711.75 | AH63: =-L62*6% -> -155827.15 | AI63: -9209.81 | AJ63: -7969 | AK63: -13197.86 | AL63: -66303.71 | AM63: =-L62*1.2% -> -31165.43 | AN63: =-L62*4% -> -103884.77 | AO63: 0 | AP63: 0 | AS63: =+L63 -> 2658651.6 | AT63: =+SUM(P63:AQ63) -> -3265058.8 | AU63: =SUM(AS63:AT63) -> -606407.17 | AV63: =AU63+AV62 -> -7367077.4 | AX63: 0 | AY63: -174843.72 | AZ63: 0 | BA63: -68983.924 | BB63: 0 | BC63: -115000 | BD63: =SUM(AX63:BB63) -> -243827.65 | BE63: =SUM(AY63:BC63) -> -358827.65 | BF63: =L63+AX63+AY63+BA63+BB63+BC63+AZ63 -> 2299824 | BG63: =AT63 -> -3265058.8 | BH63: =SUM(BF63:BG63) -> -965234.82 | BI63: =BH63+BI62 -> 4297563
A64: =A63+1 -> 7 | C64: 43466 | D64: 228130.47 | E64: 2468998.5 | F64: 69110.337 | G64: 0.1 | H64: =-E64*G64 -> -246899.85 | I64: =-H61 -> 242066.47 | L64: =SUM(H64:J64,D64:F64) -> 2761405.9 | P64: -1918129.7 | Q64: -209557.71 | R64: 0 | S64: 0 | T64: 0 | U64: 0 | V64: 0 | W64: -95321.162 | X64: -5000 | Y64: -139983.42 | Z64: 0 | AA64: -254589.19 | AB64: -5218.0243 | AC64: -52490.65 | AD64: 0 | AE64: -165643.69 | AF64: -69200 | AG64: 0 | AH64: =-L63*6% -> -159519.1 | AI64: -9209.81 | AJ64: -7969 | AK64: -13383.092 | AL64: -58596.62 | AM64: =-L63*1.2% -> -31903.819 | AN64: =-L63*4% -> -106346.06 | AO64: 0 | AP64: 0 | AS64: =+L64 -> 2761405.9 | AT64: =+SUM(P64:AQ64) -> -3302061 | AU64: =SUM(AS64:AT64) -> -540655.15 | AV64: =AU64+AV63 -> -7907732.6 | AX64: 27000000 | AY64: -174843.72 | AZ64: 0 | BA64: -70086.424 | BB64: -3591967 | BC64: -115000 | BD64: =SUM(AX64:BB64) -> 23163103 | BE64: =SUM(AY64:BC64) -> -3951897.1 | BF64: =L64+AX64+AY64+BA64+BB64+BC64+AZ64 -> 25809509 | BG64: =AT64 -> -3302061 | BH64: =SUM(BF64:BG64) -> 22507448 | BI64: =BH64+BI63 -> 26805011
A65: =A64+1 -> 8 | C65: 43497 | D65: 273900.62 | E65: 2473272.1 | F65: 69110.337 | G65: 0.1 | H65: =-E65*G65 -> -247327.21 | I65: =-H62 -> 245573.72 | L65: =SUM(H65:J65,D65:F65) -> 2814529.6 | P65: -1918129.7 | Q65: -209557.71 | R65: 0 | S65: 0 | T65: 0 | U65: 0 | V65: 0 | W65: -95321.162 | X65: -5000 | Y65: -178086.84 | Z65: 0 | AA65: -242080.33 | AB65: -6260.6058 | AC65: -52438.46 | AD65: 0 | AE65: -165643.69 | AF65: -83200 | AG65: 0 | AH65: =-L64*6% -> -165684.35 | AI65: -9209.81 | AJ65: -7969 | AK65: -13668.399 | AL65: -51471.91 | AM65: =-L64*1.2% -> -33136.871 | AN65: =-L64*4% -> -110456.24 | AO65: 0 | AP65: 0 | AS65: =+L65 -> 2814529.6 | AT65: =+SUM(P65:AQ65) -> -3347315.1 | AU65: =SUM(AS65:AT65) -> -532785.47 | AV65: =AU65+AV64 -> -8440518 | AX65: 0 | AY65: -174843.72 | AZ65: -314718.7 | BA65: -75535.924 | BB65: 0 | BC65: -115000 | BD65: =SUM(AX65:BB65) -> -565098.34 | BE65: =SUM(AY65:BC65) -> -680098.34 | BF65: =L65+AX65+AY65+BA65+BB65+BC65+AZ65 -> 2134431.3 | BG65: =AT65 -> -3347315.1 | BH65: =SUM(BF65:BG65) -> -1212883.8 | BI65: =BH65+BI64 -> 25592127
A66: =A65+1 -> 9 | C66: 43525 | D66: 513954.33 | E66: 2477068.1 | F66: 69110.337 | G66: 0.1 | H66: =-E66*G66 -> -247706.82 | I66: =-H63 -> 246162.54 | L66: =SUM(H66:J66,D66:F66) -> 3058588.5 | P66: -1918129.7 | Q66: -209557.71 | R66: 0 | S66: 0 | T66: 0 | U66: 0 | V66: 0 | W66: -95321.162 | X66: -5000 | Y66: -196495.61 | Z66: 0 | AA66: -221053.73 | AB66: -11547.709 | AC66: -52361.09 | AD66: 0 | AE66: -165643.69 | AF66: -152400 | AG66: 0 | AH66: =-L65*6% -> -168871.78 | AI66: -9209.81 | AJ66: -7969 | AK66: -13803.312 | AL66: -42786.68 | AM66: =-L65*1.2% -> -33774.355 | AN66: =-L65*4% -> -112581.18 | AO66: 0 | AP66: 0 | AS66: =+L66 -> 3058588.5 | AT66: =+SUM(P66:AQ66) -> -3416506.5 | AU66: =SUM(AS66:AT66) -> -357917.96 | AV66: =AU66+AV65 -> -8798436 | AX66: 0 | AY66: -174843.72 | AZ66: -314718.7 | BA66: -78370.924 | BB66: 0 | BC66: -115000 | BD66: =SUM(AX66:BB66) -> -567933.34 | BE66: =SUM(AY66:BC66) -> -682933.34 | BF66: =L66+AX66+AY66+BA66+BB66+BC66+AZ66 -> 2375655.2 | BG66: =AT66 -> -3416506.5 | BH66: =SUM(BF66:BG66) -> -1040851.3 | BI66: =BH66+BI65 -> 24551276
A67: =A66+1 -> 10 | C67: 43556 | D67: 638500.94 | E67: 2478316.3 | F67: 69110.337 | G67: 0.1 | H67: =-E67*G67 -> -247831.63 | I67: =-H64 -> 246899.85 | L67: =SUM(H67:J67,D67:F67) -> 3184995.8 | P67: -1918129.7 | Q67: -209557.71 | R67: 0 | S67: 0 | T67: 0 | U67: 0 | V67: 0 | W67: -95321.162 | X67: -5000 | Y67: -201655.71 | Z67: 0 | AA67: -176529.34 | AB67: -14607.654 | AC67: -52371.73 | AD67: 0 | AE67: -165643.69 | AF67: -193200 | AG67: 0 | AH67: =-L66*6% -> -183515.31 | AI67: -9209.81 | AJ67: -23969 | AK67: -14069.046 | AL67: -40237.62 | AM67: =-L66*1.2% -> -36703.063 | AN67: =-L66*4% -> -122343.54 | AO67: -10000 | AP67: 0 | AS67: =+L67 -> 3184995.8 | AT67: =+SUM(P67:AQ67) -> -3472064.1 | AU67: =SUM(AS67:AT67) -> -287068.25 | AV67: =AU67+AV66 -> -9085504.2 | AX67: 0 | AY67: -174843.72 | AZ67: -314718.7 | BA67: -79945.924 | BB67: 0 | BC67: -115000 | BD67: =SUM(AX67:BB67) -> -569508.34 | BE67: =SUM(AY67:BC67) -> -684508.34 | BF67: =L67+AX67+AY67+BA67+BB67+BC67+AZ67 -> 2500487.5 | BG67: =AT67 -> -3472064.1 | BH67: =SUM(BF67:BG67) -> -971576.59 | BI67: =BH67+BI66 -> 23579699
A68: =A67+1 -> 11 | C68: 43586 | D68: 725772.28 | E68: 2477298.6 | F68: 69110.337 | G68: 0.1 | H68: =-E68*G68 -> -247729.86 | I68: =-H65 -> 247327.21 | L68: =SUM(H68:J68,D68:F68) -> 3271778.6 | P68: -1918129.7 | Q68: -209557.71 | R68: 0 | S68: 0 | T68: 0 | U68: 0 | V68: 0 | W68: -95321.162 | X68: -5000 | Y68: -212904.69 | Z68: 0 | AA68: -161299.94 | AB68: -16136.347 | AC68: -52329.99 | AD68: 0 | AE68: -165643.69 | AF68: -183866.67 | AG68: 0 | AH68: =-L67*6% -> -191099.75 | AI68: -9209.81 | AJ68: -23969 | AK68: -14677.487 | AL68: -34414.14 | AM68: =-L67*1.2% -> -38219.95 | AN68: =-L67*4% -> -127399.83 | AO68: 0 | AP68: 0 | AS68: =+L68 -> 3271778.6 | AT68: =+SUM(P68:AQ68) -> -3459179.9 | AU68: =SUM(AS68:AT68) -> -187401.29 | AV68: =AU68+AV67 -> -9272905.5 | AX68: 0 | AY68: -174843.72 | AZ68: -314718.7 | BA68: -80418.424 | BB68: 0 | BC68: -115000 | BD68: =SUM(AX68:BB68) -> -569980.84 | BE68: =SUM(AY68:BC68) -> -684980.84 | BF68: =L68+AX68+AY68+BA68+BB68+BC68+AZ68 -> 2586797.7 | BG68: =AT68 -> -3459179.9 | BH68: =SUM(BF68:BG68) -> -872382.13 | BI68: =BH68+BI67 -> 22707317
A69: =A68+1 -> 12 | C69: 43617 | D69: 745105.49 | E69: 2477603.4 | F69: 69110.337 | G69: 0.1 | H69: =-E69*G69 -> -247760.34 | I69: =-H66 -> 247706.82 | L69: =SUM(H69:J69,D69:F69) -> 3291765.7 | P69: -1918129.7 | Q69: -209557.71 | R69: -972900 | S69: 0 | T69: -60000 | U69: 0 | V69: 0 | W69: -95321.162 | X69: -5000 | Y69: -226806.18 | Z69: 0 | AA69: -139008.52 | AB69: -16590.477 | AC69: -52350.45 | AD69: 0 | AE69: 0 | AF69: -172400 | AG69: 0 | AH69: =-L68*6% -> -196306.71 | AI69: -9209.81 | AJ69: -7969 | AK69: -15097.477 | AL69: -29838.75 | AM69: =-L68*1.2% -> -39261.343 | AN69: =-L68*4% -> -130871.14 | AO69: 0 | AP69: 0 | AQ69: 0 | AS69: =+L69 -> 3291765.7 | AT69: =+SUM(P69:AQ69) -> -4296618.4 | AU69: =SUM(AS69:AT69) -> -1004852.7 | AV69: =AU69+AV68 -> -10277758 | AX69: 0 | AY69: -174843.72 | AZ69: -314718.7 | BA69: -81468.424 | BB69: 0 | BC69: -115000 | BD69: =SUM(AX69:BB69) -> -571030.84 | BE69: =SUM(AY69:BC69) -> -686030.84 | BF69: =L69+AX69+AY69+BA69+BB69+BC69+AZ69 -> 2605734.9 | BG69: =AT69 -> -4296618.4 | BH69: =SUM(BF69:BG69) -> -1690883.5 | BI69: =BH69+BI68 -> 21016433
A70: =A69+1 -> 13 | C70: 43647 | D70: 787321.33 | E70: 2478692.8 | F70: 69110.337 | G70: 0.1 | H70: =-E70*G70 -> -247869.28 | I70: =-H67 -> 247831.63 | L70: =SUM(H70:J70,D70:F70) -> 3335086.8 | P70: -1918129.7 | Q70: -209557.71 | R70: -1280592.3 | S70: 0 | T70: -60000 | U70: 0 | V70: 0 | W70: -95321.162 | X70: -2000 | Y70: -244996.4 | Z70: 0 | AA70: -108182.15 | AB70: -17601.078 | AC70: -52367.49 | AD70: 0 | AE70: 0 | AF70: -163333.33 | AG70: 0 | AH70: =-L69*6% -> -197505.94 | AI70: -9209.81 | AJ70: -7969 | AK70: -15746.698 | AL70: -26964.79 | AM70: =-L69*1.2% -> -39501.189 | AN70: =-L69*4% -> -131670.63 | AO70: 0 | AP70: 0 | AQ70: 0 | AS70: =+L70 -> 3335086.8 | AT70: =+SUM(P70:AQ70) -> -4580649.4 | AU70: =SUM(AS70:AT70) -> -1245562.6 | AV70: =AU70+AV69 -> -11523321 | AX70: 0 | AY70: -174843.72 | AZ70: -314718.7 | BA70: -82780.924 | BB70: 0 | BC70: -115000 | BD70: =SUM(AX70:BB70) -> -572343.34 | BE70: =SUM(AY70:BC70) -> -687343.34 | BF70: =L70+AX70+AY70+BA70+BB70+BC70+AZ70 -> 2647743.4 | BG70: =AT70 -> -4580649.4 | BH70: =SUM(BF70:BG70) -> -1932905.9 | BI70: =BH70+BI69 -> 19083527
A71: =A70+1 -> 14 | C71: 43678 | D71: 839906.23 | E71: 2478928.9 | F71: 69110.337 | G71: 0.1 | H71: =-E71*G71 -> -247892.89 | I71: =-H68 -> 247729.86 | L71: =SUM(H71:J71,D71:F71) -> 3387782.4 | P71: -1918129.7 | Q71: -209557.71 | R71: -1280592.3 | S71: 0 | T71: -60000 | U71: 0 | V71: 0 | W71: -95321.162 | X71: -2000 | Y71: -296425.66 | Z71: 0 | AA71: -87692.41 | AB71: -18873.923 | AC71: -52300.54 | AD71: 0 | AE71: 0 | AF71: -166000 | AG71: 0 | AH71: =-L70*6% -> -200105.21 | AI71: -9209.81 | AJ71: -7969 | AK71: -16317.504 | AL71: -24397.08 | AM71: =-L70*1.2% -> -40021.041 | AN71: =-L70*4% -> -133403.47 | AO71: 0 | AP71: 0 | AQ71: 0 | AS71: =+L71 -> 3387782.4 | AT71: =+SUM(P71:AQ71) -> -4618316.5 | AU71: =SUM(AS71:AT71) -> -1230534.1 | AV71: =AU71+AV70 -> -12753855 | AX71: 0 | AY71: -174843.72 | AZ71: -314718.7 | BA71: -84355.924 | BB71: 0 | BC71: -115000 | BD71: =SUM(AX71:BB71) -> -573918.34 | BE71: =SUM(AY71:BC71) -> -688918.34 | BF71: =L71+AX71+AY71+BA71+BB71+BC71+AZ71 -> 2698864.1 | BG71: =AT71 -> -4618316.5 | BH71: =SUM(BF71:BG71) -> -1919452.4 | BI71: =BH71+BI70 -> 17164075
A72: =A71+1 -> 15 | C72: 43709 | D72: 908649.16 | E72: 2478205.6 | F72: 69110.337 | G72: 0.1 | H72: =-E72*G72 -> -247820.56 | I72: =-H69 -> 247760.34 | L72: =SUM(H72:J72,D72:F72) -> 3455904.9 | P72: -1918129.7 | Q72: -209557.71 | R72: -1280592.3 | S72: -100000 | T72: -60000 | U72: 0 | V72: -40882.573 | W72: -95321.162 | X72: -2000 | Y72: -303432.29 | Z72: 0 | AA72: -68833.8 | AB72: -20402.616 | AC72: -52294.81 | AD72: 0 | AE72: 0 | AF72: -116800 | AG72: 0 | AH72: =-L71*6% -> -203266.95 | AI72: -9209.81 | AJ72: -7969 | AK72: -16466.781 | AL72: -22365.19 | AM72: =-L71*1.2% -> -40653.389 | AN72: =-L71*4% -> -135511.3 | AO72: 0 | AP72: 0 | AQ72: 0 | AS72: =+L72 -> 3455904.9 | AT72: =+SUM(P72:AQ72) -> -4703689.4 | AU72: =SUM(AS72:AT72) -> -1247784.5 | AV72: =AU72+AV71 -> -14001639 | AX72: 0 | AY72: -174843.72 | AZ72: -314718.7 | BA72: -106112.68 | BB72: 0 | BC72: -115000 | BD72: =SUM(AX72:BB72) -> -595675.1 | BE72: =SUM(AY72:BC72) -> -710675.1 | BF72: =L72+AX72+AY72+BA72+BB72+BC72+AZ72 -> 2745229.8 | BG72: =AT72 -> -4703689.4 | BH72: =SUM(BF72:BG72) -> -1958459.6 | BI72: =BH72+BI71 -> 15205615
A73: =A72+1 -> 16 | C73: 43739 | D73: 1102815.9 | E73: 2473443.2 | F73: 69110.337 | G73: 0.1 | H73: =-E73*G73 -> -247344.32 | I73: =-H70 -> 247869.28 | L73: =SUM(H73:J73,D73:F73) -> 3645894.4 | P73: -1918129.7 | Q73: -209557.71 | R73: -1280592.3 | S73: -100000 | T73: -60000 | U73: 0 | V73: -40882.573 | W73: -95321.162 | X73: -2000 | Y73: -316118.04 | Z73: 0 | AA73: 0 | AB73: -24589.572 | AC73: -52223.05 | AD73: 0 | AE73: 0 | AF73: -130800 | AG73: 0 | AH73: =-L72*6% -> -207354.29 | AI73: -9209.81 | AJ73: -7969 | AK73: -16646.083 | AL73: -19689.79 | AM73: =-L72*1.2% -> -41470.858 | AN73: =-L72*4% -> -138236.19 | AO73: 0 | AP73: 0 | AQ73: 0 | AS73: =+L73 -> 3645894.4 | AT73: =+SUM(P73:AQ73) -> -4670790.1 | AU73: =SUM(AS73:AT73) -> -1024895.7 | AV73: =AU73+AV72 -> -15026535 | AX73: 0 | AY73: -174843.72 | AZ73: -314718.7 | BA73: -92356.924 | BB73: 0 | BC73: -115000 | BD73: =SUM(AX73:BB73) -> -581919.34 | BE73: =SUM(AY73:BC73) -> -696919.34 | BF73: =L73+AX73+AY73+BA73+BB73+BC73+AZ73 -> 2948975.1 | BG73: =AT73 -> -4670790.1 | BH73: =SUM(BF73:BG73) -> -1721815.1 | BI73: =BH73+BI72 -> 13483800
A74: =A73+1 -> 17 | C74: 43770 | D74: 1128741.5 | E74: 2472474.6 | F74: 69110.337 | G74: 0.1 | H74: =-E74*G74 -> -247247.46 | I74: =-H71 -> 247892.89 | L74: =SUM(H74:J74,D74:F74) -> 3670971.9 | P74: -1918129.7 | Q74: -209557.71 | R74: -1037367.3 | S74: -100000 | T74: -60000 | U74: 0 | V74: -40882.573 | W74: -95321.162 | X74: -2000 | Y74: -313641.88 | Z74: 0 | AA74: 0 | AB74: -25307.226 | AC74: -52191.13 | AD74: 0 | AE74: 0 | AF74: -120400 | AG74: 0 | AH74: =-L73*6% -> -218753.66 | AI74: -9209.81 | AJ74: -7969 | AK74: -16934.841 | AL74: -18481.86 | AM74: =-L73*1.2% -> -43750.733 | AN74: =-L73*4% -> -145835.78 | AO74: 0 | AP74: 0 | AQ74: 0 | AS74: =+L74 -> 3670971.9 | AT74: =+SUM(P74:AQ74) -> -4435734.4 | AU74: =SUM(AS74:AT74) -> -764762.51 | AV74: =AU74+AV73 -> -15791298 | AX74: 0 | AY74: -174843.72 | AZ74: -314718.7 | BA74: -94656.424 | BB74: 0 | BC74: -115000 | BD74: =SUM(AX74:BB74) -> -584218.84 | BE74: =SUM(AY74:BC74) -> -699218.84 | BF74: =L74+AX74+AY74+BA74+BB74+BC74+AZ74 -> 2971753 | BG74: =AT74 -> -4435734.4 | BH74: =SUM(BF74:BG74) -> -1463981.3 | BI74: =BH74+BI73 -> 12019819
A75: =A74+1 -> 18 | B75: FIM OBRA | C75: 43800 | D75: 1176086.9 | E75: 2473021.8 | F75: 69110.337 | G75: 0.1 | H75: =-E75*G75 -> -247302.18 | I75: =-H72 -> 247820.56 | J75: 0 | L75: =SUM(H75:J75,D75:F75) -> 3718737.5 | P75: -2019083.9 | Q75: -220587.06 | R75: -988722.31 | S75: -100000 | T75: -60000 | U75: 0 | V75: -40882.573 | W75: -95321.162 | X75: -2000 | Y75: -298825.36 | Z75: 0 | AA75: 0 | AB75: -26632.52 | AC75: -52208.34 | AD75: 0 | AE75: 0 | AF75: -132000 | AG75: 0 | AH75: =-L74*6% -> -220258.31 | AI75: -9209.81 | AJ75: -7969 | AK75: -16761.086 | AL75: -17629.73 | AM75: =-L74*1.2% -> -44051.662 | AN75: =-L74*4% -> -146838.87 | AO75: 0 | AP75: 0 | AQ75: 0 | AS75: =+L75 -> 3718737.5 | AT75: =+SUM(P75:AQ75) -> -4498981.7 | AU75: =SUM(AS75:AT75) -> -780244.22 | AV75: =AU75+AV74 -> -16571542 | AX75: 0 | AY75: -174843.72 | AZ75: -314718.7 | BA75: -92291.726 | BB75: 0 | BC75: -115000 | BD75: =SUM(AX75:BB75) -> -581854.14 | BE75: =SUM(AY75:BC75) -> -696854.14 | BF75: =L75+AX75+AY75+BA75+BB75+BC75+AZ75 -> 3021883.3 | BG75: =AT75 -> -4498981.7 | BH75: =SUM(BF75:BG75) -> -1477098.4 | BI75: =BH75+BI74 -> 10542721
A76: =A75+1 -> 19 | C76: 43831 | D76: 1259824.3 | E76: 2470659.1 | F76: 69110.337 | G76: 0.1 | H76: =-E76*G76 -> -247065.91 | I76: =-H73 -> 247344.32 | J76: 0 | K76: 0 | L76: =SUM(H76:J76,D76:F76) -> 3799872.1 | P76: -1413358.7 | Q76: -154410.94 | R76: -891432.31 | S76: -100000 | T76: -60000 | U76: 0 | V76: -40882.573 | W76: -95321.162 | X76: -2000 | Y76: -277661.99 | Z76: 0 | AA76: 0 | AB76: -28820.022 | AC76: -53223.15 | AD76: 0 | AE76: 0 | AF76: -149066.67 | AG76: 0 | AH76: =-L75*6% -> -223124.25 | AI76: -9209.81 | AJ76: -7969 | AK76: -16865.733 | AL76: -22476.67 | AM76: =-L75*1.2% -> -44624.85 | AN76: =-L75*4% -> -148749.5 | AO76: 0 | AP76: 0 | AQ76: 0 | AS76: =+L76 -> 3799872.1 | AT76: =+SUM(P76:AQ76) -> -3739197.3 | AU76: =SUM(AS76:AT76) -> 60674.733 | AV76: =AU76+AV75 -> -16510867 | AX76: 0 | AY76: -174843.72 | AZ76: -314718.7 | BA76: -89994.074 | BB76: 0 | BC76: -115000 | BD76: =SUM(AX76:BB76) -> -579556.49 | BE76: =SUM(AY76:BC76) -> -694556.49 | BF76: =L76+AX76+AY76+BA76+BB76+BC76+AZ76 -> 3105315.6 | BG76: =AT76 -> -3739197.3 | BH76: =SUM(BF76:BG76) -> -633881.76 | BI76: =BH76+BI75 -> 9908838.8
A77: =A76+1 -> 20 | C77: 43862 | D77: 1268342.9 | E77: 2466681.6 | F77: 69110.337 | G77: 0.1 | H77: =-E77*G77 -> -246668.16 | I77: =-H74 -> 247247.46 | J77: =FV($J$3,K77,,-SUM(D77:E77))-SUM(D77:E77) -> 18675.123 | K77: =K76+1 -> 1 | L77: =SUM(H77:J77,D77:F77) -> 3823389.3 | P77: -1009541.9 | Q77: -110293.53 | R77: -891432.31 | S77: -100000 | T77: -60000 | U77: 0 | V77: -40882.573 | W77: -95321.162 | X77: -2000 | Y77: -264117.5 | Z77: 0 | AA77: 0 | AB77: -29065.636 | AC77: -53173.71 | AD77: 0 | AE77: 0 | AF77: -135600 | AG77: 0 | AH77: =-L76*6% -> -227992.32 | AI77: -9209.81 | AJ77: -7969 | AK77: -17048.52 | AL77: -12670.56 | AM77: =-L76*1.2% -> -45598.465 | AN77: =-L76*4% -> -151994.88 | AO77: 0 | AP77: 0 | AQ77: 0 | AS77: =+L77 -> 3823389.3 | AT77: =+SUM(P77:AQ77) -> -3263911.9 | AU77: =SUM(AS77:AT77) -> 559477.33 | AV77: =AU77+AV76 -> -15951390 | AX77: 0 | AY77: -174843.72 | AZ77: -314718.7 | BA77: -87761.569 | BB77: 0 | BC77: -115000 | BD77: =SUM(AX77:BB77) -> -577323.99 | BE77: =SUM(AY77:BC77) -> -692323.99 | BF77: =L77+AX77+AY77+BA77+BB77+BC77+AZ77 -> 3131065.3 | BG77: =AT77 -> -3263911.9 | BH77: =SUM(BF77:BG77) -> -132846.65 | BI77: =BH77+BI76 -> 9775992.2
A78: =A77+1 -> 21 | C78: 43891 | D78: 1268342.9 | E78: 2460818.4 | F78: 69110.337 | G78: 0.1 | H78: =-E78*G78 -> -246081.84 | I78: =-H75 -> 247302.18 | J78: =FV($J$3,K78,,-SUM(D78:E78))-SUM(D78:E78) -> 37384.842 | K78: =K77+1 -> 2 | L78: =SUM(H78:J78,D78:F78) -> 3836876.8 | P78: -762771.36 | Q78: -83333.583 | R78: -891432.31 | S78: 0 | T78: -60000 | U78: 0 | V78: -40882.573 | W78: -95321.162 | X78: -2000 | Y78: -201967.65 | Z78: 0 | AA78: 0 | AB78: -29065.636 | AC78: -53051.34 | AD78: 0 | AE78: 0 | AF78: -115600 | AG78: 0 | AH78: =-L77*6% -> -229403.36 | AI78: -9209.81 | AJ78: -7969 | AK78: -17104.461 | AL78: -11864.03 | AM78: =-L77*1.2% -> -45880.671 | AN78: =-L77*4% -> -152935.57 | AO78: 0 | AP78: 0 | AQ78: 0 | AS78: =+L78 -> 3836876.8 | AT78: =+SUM(P78:AQ78) -> -2809792.5 | AU78: =SUM(AS78:AT78) -> 1027084.3 | AV78: =AU78+AV77 -> -14924306 | AX78: 0 | AY78: -174843.72 | AZ78: -314718.7 | BA78: -85592.362 | BB78: 0 | BC78: -115000 | BD78: =SUM(AX78:BB78) -> -575154.78 | BE78: =SUM(AY78:BC78) -> -690154.78 | BF78: =L78+AX78+AY78+BA78+BB78+BC78+AZ78 -> 3146722 | BG78: =AT78 -> -2809792.5 | BH78: =SUM(BF78:BG78) -> 336929.5 | BI78: =BH78+BI77 -> 10112922
A79: =A78+1 -> 22 | C79: 43922 | D79: 1268342.9 | E79: 2459122.3 | F79: 69110.337 | G79: 0.1 | H79: =-E79*G79 -> -245912.23 | I79: =-H76 -> 247065.91 | J79: =FV($J$3,K79,,-SUM(D79:E79))-SUM(D79:E79) -> 56192.003 | K79: =K78+1 -> 3 | L79: =SUM(H79:J79,D79:F79) -> 3853921.2 | P79: 0 | Q79: 0 | R79: -891432.31 | S79: 0 | T79: 0 | U79: 0 | V79: -40882.573 | W79: -95321.162 | X79: -2000 | Y79: -163864.23 | Z79: 0 | AA79: 0 | AB79: -29065.636 | AC79: -53011.5 | AD79: 0 | AE79: 0 | AF79: -60800 | AG79: 0 | AH79: =-L78*6% -> -230212.61 | AI79: -9209.81 | AJ79: -23969 | AK79: -17294.414 | AL79: -9614.48 | AM79: =-L78*1.2% -> -46042.522 | AN79: =-L78*4% -> -153475.07 | AO79: -10000 | AP79: 0 | AQ79: 0 | AS79: =+L79 -> 3853921.2 | AT79: =+SUM(P79:AQ79) -> -1836195.3 | AU79: =SUM(AS79:AT79) -> 2017725.8 | AV79: =AU79+AV78 -> -12906580 | AX79: 0 | AY79: -174843.72 | AZ79: -314718.7 | BA79: -83484.659 | BB79: 0 | BC79: -115000 | BD79: =SUM(AX79:BB79) -> -573047.08 | BE79: =SUM(AY79:BC79) -> -688047.08 | BF79: =L79+AX79+AY79+BA79+BB79+BC79+AZ79 -> 3165874.1 | BG79: =AT79 -> -1836195.3 | BH79: =SUM(BF79:BG79) -> 1329678.8 | BI79: =BH79+BI78 -> 11442600
A80: =A79+1 -> 23 | C80: 43952 | D80: 1268342.9 | E80: 2457836.4 | F80: 69110.337 | G80: 0.1 | H80: =-E80*G80 -> -245783.64 | I80: =-H77 -> 246668.16 | J80: =FV($J$3,K80,,-SUM(D80:E80))-SUM(D80:E80) -> 75084.378 | K80: =K79+1 -> 4 | L80: =SUM(H80:J80,D80:F80) -> 3871258.5 | P80: 0 | Q80: 0 | R80: -891432.31 | S80: 0 | T80: 0 | U80: 0 | V80: -40882.573 | W80: -95321.162 | X80: -2000 | Y80: -145455.47 | Z80: 0 | AA80: 0 | AB80: -29065.636 | AC80: -52972.13 | AD80: 0 | AE80: 0 | AF80: -51200 | AG80: 0 | AH80: =-L79*6% -> -231235.27 | AI80: -9209.81 | AJ80: -23969 | AK80: -17778.584 | AL80: -7356.99 | AM80: =-L79*1.2% -> -46247.054 | AN80: =-L79*4% -> -154156.85 | AO80: 0 | AP80: 0 | AS80: =+L80 -> 3871258.5 | AT80: =+SUM(P80:AQ80) -> -1798282.8 | AU80: =SUM(AS80:AT80) -> 2072975.7 | AV80: =AU80+AV79 -> -10833604 | AX80: 0 | AY80: -174843.72 | AZ80: -314718.7 | BA80: -81436.716 | BB80: 0 | BC80: -115000 | BD80: =SUM(AX80:BB80) -> -570999.13 | BE80: =SUM(AY80:BC80) -> -685999.13 | BF80: =L80+AX80+AY80+BA80+BB80+BC80+AZ80 -> 3185259.4 | BG80: =AT80 -> -1798282.8 | BH80: =SUM(BF80:BG80) -> 1386976.6 | BI80: =BH80+BI79 -> 12829577
A81: =A80+1 -> 24 | C81: 43983 | D81: 1268342.9 | E81: 2451791.1 | F81: 69110.337 | G81: 0.05 | H81: =-E81*G81 -> -122589.56 | I81: =-H78 -> 246081.84 | J81: =FV($J$3,K81,,-SUM(D81:E81))-SUM(D81:E81) -> 93938.045 | K81: =K80+1 -> 5 | L81: =SUM(H81:J81,D81:F81) -> 4006674.7 | P81: 0 | Q81: 0 | R81: -842787.31 | S81: 0 | T81: 0 | U81: 0 | V81: -40882.573 | W81: -95321.162 | X81: -2000 | Y81: -140295.36 | Z81: 0 | AA81: 0 | AB81: -29065.636 | AC81: -52850.59 | AD81: 0 | AE81: 0 | AF81: -33600 | AG81: 0 | AH81: =-L80*6% -> -232275.51 | AI81: -9209.81 | AJ81: -7969 | AK81: -18092.513 | AL81: -7016.44 | AM81: =-L80*1.2% -> -46455.102 | AN81: =-L80*4% -> -154850.34 | AO81: 0 | AP81: 0 | AS81: =+L81 -> 4006674.7 | AT81: =+SUM(P81:AQ81) -> -1712671.4 | AU81: =SUM(AS81:AT81) -> 2294003.3 | AV81: =AU81+AV80 -> -8539600.7 | AX81: 0 | AY81: -174843.72 | AZ81: -314718.7 | BA81: -79446.838 | BB81: 0 | BC81: -115000 | BD81: =SUM(AX81:BB81) -> -569009.26 | BE81: =SUM(AY81:BC81) -> -684009.26 | BF81: =L81+AX81+AY81+BA81+BB81+BC81+AZ81 -> 3322665.4 | BG81: =AT81 -> -1712671.4 | BH81: =SUM(BF81:BG81) -> 1609994 | BI81: =BH81+BI80 -> 14439571
A82: =A81+1 -> 25 | C82: 44013 | D82: 1268342.9 | E82: 2447213.4 | F82: 0 | G82: =+G81 -> 0.05 | H82: =-E82*G82 -> -122360.67 | I82: =-H79 -> 245912.23 | J82: =FV($J$3,K82,,-SUM(D82:E82))-SUM(D82:E82) -> 112869.35 | K82: =K81+1 -> 6 | L82: =SUM(H82:J82,D82:F82) -> 3951977.2 | P82: 0 | Q82: 0 | R82: -307692.31 | S82: 0 | T82: 0 | U82: 0 | V82: -40882.573 | W82: -95321.162 | X82: -2000 | Y82: -129046.39 | Z82: 0 | AA82: 0 | AB82: -29065.636 | AC82: -52724.92 | AD82: 0 | AE82: 0 | AF82: -3200 | AG82: 0 | AH82: =-L81*6% -> -240400.48 | AI82: -9209.81 | AJ82: -7969 | AK82: -18263.77 | AL82: -6188.93 | AM82: =-L81*1.2% -> -48080.096 | AN82: =-L81*4% -> -160266.99 | AO82: 0 | AP82: 0 | AS82: =+L82 -> 3951977.2 | AT82: =+SUM(P82:AQ82) -> -1150312.1 | AU82: =SUM(AS82:AT82) -> 2801665.1 | AV82: =AU82+AV81 -> -5737935.5 | AX82: 0 | AY82: -174843.72 | AZ82: -314718.7 | BA82: -77513.38 | BB82: 0 | BC82: -115000 | BD82: =SUM(AX82:BB82) -> -567075.8 | BE82: =SUM(AY82:BC82) -> -682075.8 | BF82: =L82+AX82+AY82+BA82+BB82+BC82+AZ82 -> 3269901.4 | BG82: =AT82 -> -1150312.1 | BH82: =SUM(BF82:BG82) -> 2119589.3 | BI82: =BH82+BI81 -> 16559160
A83: =A82+1 -> 26 | C83: 44044 | D83: 1268342.9 | E83: 2435633 | F83: 0 | G83: =+G82 -> 0.05 | H83: =-E83*G83 -> -121781.65 | I83: =-H80 -> 245783.64 | J83: =FV($J$3,K83,,-SUM(D83:E83))-SUM(D83:E83) -> 131600.03 | K83: =K82+1 -> 7 | L83: =SUM(H83:J83,D83:F83) -> 3959577.9 | P83: 0 | Q83: 0 | R83: 0 | S83: 0 | T83: 0 | U83: 0 | V83: -40882.573 | W83: -95321.162 | X83: -2000 | Y83: -115144.9 | Z83: 0 | AA83: 0 | AB83: -29065.636 | AC83: -52495.4 | AD83: 0 | AE83: 0 | AF83: 0 | AG83: 0 | AH83: =-L82*6% -> -237118.63 | AI83: -9209.81 | AJ83: -7969 | AK83: -18292.08 | AL83: -5197.02 | AM83: =-L82*1.2% -> -47423.726 | AN83: =-L82*4% -> -158079.09 | AO83: 0 | AP83: 0 | AS83: =+L83 -> 3959577.9 | AT83: =+SUM(P83:AQ83) -> -818199.03 | AU83: =SUM(AS83:AT83) -> 3141378.9 | AV83: =AU83+AV82 -> -2596556.7 | AX83: 0 | AY83: -174843.72 | AZ83: -314718.7 | BA83: -75634.742 | BB83: 0 | BC83: -115000 | BD83: =SUM(AX83:BB83) -> -565197.16 | BE83: =SUM(AY83:BC83) -> -680197.16 | BF83: =L83+AX83+AY83+BA83+BB83+BC83+AZ83 -> 3279380.7 | BG83: =AT83 -> -818199.03 | BH83: =SUM(BF83:BG83) -> 2461181.7 | BI83: =BH83+BI82 -> 19020342
A84: =A83+1 -> 27 | C84: 44075 | D84: 1268342.9 | E84: 2432436.6 | F84: 0 | G84: =+G83 -> 0.05 | H84: =-E84*G84 -> -121621.83 | I84: =-H81 -> 122589.56 | J84: =FV($J$3,K84,,-SUM(D84:E84))-SUM(D84:E84) -> 150647.79 | K84: =K83+1 -> 8 | L84: =SUM(H84:J84,D84:F84) -> 3852395 | P84: 0 | Q84: 0 | R84: 0 | S84: 0 | T84: 0 | U84: 0 | V84: -40882.573 | W84: -95321.162 | X84: -2000 | Y84: -96954.671 | Z84: 0 | AA84: 0 | AB84: -29065.636 | AC84: -52431.55 | AD84: 0 | AE84: 0 | AF84: 0 | AG84: 0 | AH84: =-L83*6% -> -237574.67 | AI84: -9209.81 | AJ84: -7969 | AK84: -18270.182 | AL84: -4441.94 | AM84: =-L83*1.2% -> -47514.935 | AN84: =-L83*4% -> -158383.12 | AO84: 0 | AP84: 0 | AS84: =+L84 -> 3852395 | AT84: =+SUM(P84:AQ84) -> -800019.25 | AU84: =SUM(AS84:AT84) -> 3052375.7 | AV84: =AU84+AV83 -> 455819.09 | AX84: 0 | AY84: -174843.72 | AZ84: -314718.7 | BA84: -89371.122 | BB84: 0 | BC84: -115000 | BD84: =SUM(AX84:BB84) -> -578933.54 | BE84: =SUM(AY84:BC84) -> -693933.54 | BF84: =L84+AX84+AY84+BA84+BB84+BC84+AZ84 -> 3158461.5 | BG84: =AT84 -> -800019.25 | BH84: =SUM(BF84:BG84) -> 2358442.2 | BI84: =BH84+BI83 -> 21378784
A85: =A84+1 -> 28 | C85: 44105 | D85: 1268342.9 | E85: 2427810.8 | F85: 0 | G85: =+G84 -> 0.05 | H85: =-E85*G85 -> -121390.54 | I85: =-H82 -> 122360.67 | J85: =FV($J$3,K85,,-SUM(D85:E85))-SUM(D85:E85) -> 169692.55 | K85: =K84+1 -> 9 | L85: =SUM(H85:J85,D85:F85) -> 3866816.3 | P85: 0 | Q85: 0 | R85: 0 | S85: 0 | T85: 0 | U85: 0 | V85: -40882.573 | W85: -95321.162 | X85: -2000 | Y85: -45525.419 | Z85: 0 | AA85: 0 | AB85: -29065.636 | AC85: -52360.02 | AD85: 0 | AE85: 0 | AF85: 0 | AG85: 0 | AH85: =-L84*6% -> -231143.7 | AI85: -9209.81 | AJ85: -7969 | AK85: -18271.593 | AL85: -4017.93 | AM85: =-L84*1.2% -> -46228.74 | AN85: =-L84*4% -> -154095.8 | AO85: 0 | AP85: 0 | AS85: =+L85 -> 3866816.3 | AT85: =+SUM(P85:AQ85) -> -736091.38 | AU85: =SUM(AS85:AT85) -> 3130724.9 | AV85: =AU85+AV84 -> 3586544 | AX85: 0 | AY85: -331093.72 | AZ85: -595968.7 | BA85: -72035.751 | BB85: 0 | BC85: 0 | BD85: =SUM(AX85:BB85) -> -999098.17 | BE85: =SUM(AY85:BC85) -> -999098.17 | BF85: =L85+AX85+AY85+BA85+BB85+BC85+AZ85 -> 2867718.2 | BG85: =AT85 -> -736091.38 | BH85: =SUM(BF85:BG85) -> 2131626.8 | BI85: =BH85+BI84 -> 23510411
A86: =A85+1 -> 29 | C86: 44136 | D86: 1268342.9 | E86: 2424441.6 | F86: 0 | G86: =+G85 -> 0.05 | H86: =-E86*G86 -> -121222.08 | I86: =-H83 -> 121781.65 | J86: =FV($J$3,K86,,-SUM(D86:E86))-SUM(D86:E86) -> 188849.49 | K86: =K85+1 -> 10 | L86: =SUM(H86:J86,D86:F86) -> 3882193.5 | P86: 0 | Q86: 0 | R86: 0 | S86: 0 | T86: 0 | U86: 0 | V86: -40882.573 | W86: 0 | X86: -2000 | Y86: -38518.789 | Z86: 0 | AA86: 0 | AB86: -29065.636 | AC86: -52274.79 | AD86: 0 | AE86: 0 | AF86: 0 | AG86: 0 | AH86: =-L85*6% -> -232008.98 | AI86: -9209.81 | AJ86: -7969 | AK86: -18244.015 | AL86: -4017.93 | AM86: =-L85*1.2% -> -46401.796 | AN86: =-L85*4% -> -154672.65 | AO86: 0 | AP86: 0 | AS86: =+L86 -> 3882193.5 | AT86: =+SUM(P86:AQ86) -> -635265.97 | AU86: =SUM(AS86:AT86) -> 3246927.5 | AV86: =AU86+AV85 -> 6833471.6 | AX86: 0 | AY86: -329272.43 | AZ86: -592690.38 | BA86: -70312.421 | BB86: 0 | BC86: 0 | BD86: =SUM(AX86:BB86) -> -992275.23 | BE86: =SUM(AY86:BC86) -> -992275.23 | BF86: =L86+AX86+AY86+BA86+BB86+BC86+AZ86 -> 2889918.3 | BG86: =AT86 -> -635265.97 | BH86: =SUM(BF86:BG86) -> 2254652.3 | BI86: =BH86+BI85 -> 25765063
A87: =A86+1 -> 30 | C87: 44166 | D87: 1268342.9 | E87: 2419594.5 | F87: 0 | G87: =+G86 -> 0.05 | H87: =-E87*G87 -> -120979.72 | I87: =-H84 -> 121621.83 | J87: =FV($J$3,K87,,-SUM(D87:E87))-SUM(D87:E87) -> 207984.3 | K87: =K86+1 -> 11 | L87: =SUM(H87:J87,D87:F87) -> 3896563.7 | P87: 0 | Q87: 0 | R87: 0 | S87: 0 | T87: 0 | U87: 0 | V87: -40882.573 | W87: 0 | X87: -2000 | Y87: -25833.037 | Z87: 0 | AA87: 0 | AB87: -29065.636 | AC87: -52155.25 | AD87: 0 | AE87: 0 | AF87: 0 | AG87: 0 | AH87: =-L86*6% -> -232931.61 | AI87: -9209.81 | AJ87: -7969 | AK87: -18224.201 | AL87: -3107.39 | AM87: =-L86*1.2% -> -46586.322 | AN87: =-L86*4% -> -155287.74 | AO87: 0 | AP87: 0 | AS87: =+L87 -> 3896563.7 | AT87: =+SUM(P87:AQ87) -> -623252.57 | AU87: =SUM(AS87:AT87) -> 3273311.2 | AV87: =AU87+AV86 -> 10106783 | AX87: 0 | AY87: -327451.14 | AZ87: -589412.06 | BA87: -68637.953 | BB87: 0 | BC87: 0 | BD87: =SUM(AX87:BB87) -> -985501.16 | BE87: =SUM(AY87:BC87) -> -985501.16 | BF87: =L87+AX87+AY87+BA87+BB87+BC87+AZ87 -> 2911062.6 | BG87: =AT87 -> -623252.57 | BH87: =SUM(BF87:BG87) -> 2287810 | BI87: =BH87+BI86 -> 28052873
A88: =A87+1 -> 31 | C88: 44197 | D88: 1268342.9 | E88: 2412144 | F88: 0 | G88: =+G87 -> 0.05 | H88: =-E88*G88 -> -120607.2 | I88: =-H85 -> 121390.54 | J88: =FV($J$3,K88,,-SUM(D88:E88))-SUM(D88:E88) -> 227004.37 | K88: =K87+1 -> 12 | L88: =SUM(H88:J88,D88:F88) -> 3908274.5 | P88: 0 | Q88: 0 | R88: 0 | S88: 0 | T88: 0 | U88: 0 | V88: -40882.573 | W88: 0 | X88: -2000 | Y88: -2229.0529 | Z88: 0 | AA88: 0 | AB88: -29065.636 | AC88: -51958.33 | AD88: 0 | AE88: 0 | AF88: 0 | AG88: 0 | AH88: =-L87*6% -> -233793.82 | AI88: -9209.81 | AJ88: -7969 | AK88: -18202.195 | AL88: -2487.53 | AM88: =-L87*1.2% -> -46758.765 | AN88: =-L87*4% -> -155862.55 | AO88: 0 | AP88: 0 | AS88: =+L88 -> 3908274.5 | AT88: =+SUM(P88:AQ88) -> -600419.27 | AU88: =SUM(AS88:AT88) -> 3307855.3 | AV88: =AU88+AV87 -> 13414638 | AX88: 0 | AY88: -325629.85 | AZ88: -586133.74 | BA88: -67010.962 | BB88: 0 | BC88: 0 | BD88: =SUM(AX88:BB88) -> -978774.56 | BE88: =SUM(AY88:BC88) -> -978774.56 | BF88: =L88+AX88+AY88+BA88+BB88+BC88+AZ88 -> 2929500 | BG88: =AT88 -> -600419.27 | BH88: =SUM(BF88:BG88) -> 2329080.7 | BI88: =BH88+BI87 -> 30381954
A89: =A88+1 -> 32 | C89: 44228 | D89: 1268342.9 | E89: 2399612 | F89: 0 | G89: =+G88 -> 0.05 | H89: =-E89*G89 -> -119980.6 | I89: =-H86 -> 121222.08 | J89: =FV($J$3,K89,,-SUM(D89:E89))-SUM(D89:E89) -> 245702.36 | K89: =K88+1 -> 13 | L89: =SUM(H89:J89,D89:F89) -> 3914898.7 | P89: 0 | Q89: 0 | R89: 0 | S89: 0 | T89: 0 | U89: 0 | V89: -40882.573 | W89: 0 | X89: -2000 | Y89: 0 | Z89: 0 | AA89: 0 | AB89: -29065.636 | AC89: -51700.55 | AD89: 0 | AE89: 0 | AF89: 0 | AG89: 0 | AH89: =-L88*6% -> -234496.47 | AI89: -9209.81 | AJ89: -7969 | AK89: -18162.545 | AL89: -1672.17 | AM89: =-L88*1.2% -> -46899.295 | AN89: =-L88*4% -> -156330.98 | AO89: 0 | AP89: 0 | AQ89: 0 | AS89: =+L89 -> 3914898.7 | AT89: =+SUM(P89:AQ89) -> -598389.03 | AU89: =SUM(AS89:AT89) -> 3316509.6 | AV89: =AU89+AV88 -> 16731148 | AX89: 0 | AY89: -323808.57 | AZ89: -582855.42 | BA89: -65430.1 | BB89: 0 | BC89: 0 | BD89: =SUM(AX89:BB89) -> -972094.09 | BE89: =SUM(AY89:BC89) -> -972094.09 | BF89: =L89+AX89+AY89+BA89+BB89+BC89+AZ89 -> 2942804.6 | BG89: =AT89 -> -598389.03 | BH89: =SUM(BF89:BG89) -> 2344415.6 | BI89: =BH89+BI88 -> 32726370
A90: =A89+1 -> 33 | C90: 44256 | D90: 1268342.9 | E90: 2375385.2 | F90: 0 | G90: =+G89 -> 0.05 | H90: =-E90*G90 -> -118769.26 | I90: =-H87 -> 120979.72 | J90: =FV($J$3,K90,,-SUM(D90:E90))-SUM(D90:E90) -> 263518.54 | K90: =K89+1 -> 14 | L90: =SUM(H90:J90,D90:F90) -> 3909457 | P90: 0 | Q90: 0 | R90: 0 | S90: 0 | T90: 0 | U90: 0 | V90: -40882.573 | W90: 0 | X90: -2000 | Y90: 0 | Z90: 0 | AA90: 0 | AB90: -29065.636 | AC90: -51158.08 | AD90: 0 | AE90: 0 | AF90: 0 | AG90: 0 | AH90: =-L89*6% -> -234893.92 | AI90: -9209.81 | AJ90: -7969 | AK90: -18103.458 | AL90: -767.84 | AM90: =-L89*1.2% -> -46978.784 | AN90: =-L89*4% -> -156595.95 | AO90: 0 | AP90: 0 | AQ90: 0 | AS90: =+L90 -> 3909457 | AT90: =+SUM(P90:AQ90) -> -597625.05 | AU90: =SUM(AS90:AT90) -> 3311832 | AV90: =AU90+AV89 -> 20042980 | AX90: 0 | AY90: -321987.28 | AZ90: -579577.1 | BA90: -63894.062 | BB90: 0 | BC90: 0 | BD90: =SUM(AX90:BB90) -> -965458.44 | BE90: =SUM(AY90:BC90) -> -965458.44 | BF90: =L90+AX90+AY90+BA90+BB90+BC90+AZ90 -> 2943998.6 | BG90: =AT90 -> -597625.05 | BH90: =SUM(BF90:BG90) -> 2346373.6 | BI90: =BH90+BI89 -> 35072743
A91: =A90+1 -> 34 | C91: 44287 | D91: 1268342.9 | E91: 2369299.8 | F91: 0 | G91: =+G90 -> 0.05 | H91: =-E91*G91 -> -118464.99 | I91: =-H88 -> 120607.2 | J91: =FV($J$3,K91,,-SUM(D91:E91))-SUM(D91:E91) -> 282582.04 | K91: =K90+1 -> 15 | L91: =SUM(H91:J91,D91:F91) -> 3922366.9 | P91: 0 | Q91: 0 | R91: 0 | S91: 0 | T91: 0 | U91: 0 | V91: -40882.573 | W91: 0 | X91: -2000 | Y91: 0 | Z91: 0 | AA91: 0 | AB91: -29065.636 | AC91: -50992.82 | AD91: 0 | AE91: 0 | AF91: 0 | AG91: 0 | AH91: =-L90*6% -> -234567.42 | AI91: -9209.81 | AJ91: -23969 | AK91: -17980.729 | AL91: -767.84 | AM91: =-L90*1.2% -> -46913.485 | AN91: =-L90*4% -> -156378.28 | AO91: -10000 | AP91: 0 | AQ91: 0 | AS91: =+L91 -> 3922366.9 | AT91: =+SUM(P91:AQ91) -> -622727.6 | AU91: =SUM(AS91:AT91) -> 3299639.3 | AV91: =AU91+AV90 -> 23342619 | AX91: 0 | AY91: -320165.99 | AZ91: -576298.78 | BA91: -62401.574 | BB91: 0 | BC91: 0 | BD91: =SUM(AX91:BB91) -> -958866.34 | BE91: =SUM(AY91:BC91) -> -958866.34 | BF91: =L91+AX91+AY91+BA91+BB91+BC91+AZ91 -> 2963500.6 | BG91: =AT91 -> -622727.6 | BH91: =SUM(BF91:BG91) -> 2340773 | BI91: =BH91+BI90 -> 37413516
A92: =A91+1 -> 35 | C92: 44317 | D92: 1268342.9 | E92: 2365370.4 | F92: 0 | G92: =+G91 -> 0.05 | H92: =-E92*G92 -> -118268.52 | I92: =-H89 -> 119980.6 | J92: =FV($J$3,K92,,-SUM(D92:E92))-SUM(D92:E92) -> 301856.74 | K92: =K91+1 -> 16 | L92: =SUM(H92:J92,D92:F92) -> 3937282.1 | P92: 0 | Q92: 0 | R92: 0 | S92: 0 | T92: 0 | U92: 0 | V92: 0 | W92: 0 | X92: -2000 | Y92: 0 | Z92: 0 | AA92: 0 | AB92: -29065.636 | AC92: -50968.94 | AD92: 0 | AE92: 0 | AF92: 0 | AG92: 0 | AH92: =-L91*6% -> -235342.02 | AI92: -9209.81 | AJ92: -23969 | AK92: -17947.318 | AL92: -767.84 | AM92: =-L91*1.2% -> -47068.403 | AN92: =-L91*4% -> -156894.68 | AO92: -10000 | AP92: 0 | AQ92: 0 | AS92: =+L92 -> 3937282.1 | AT92: =+SUM(P92:AQ92) -> -583233.64 | AU92: =SUM(AS92:AT92) -> 3354048.4 | AV92: =AU92+AV91 -> 26696667 | AX92: 0 | AY92: -318344.7 | AZ92: -573020.46 | BA92: -60951.404 | BB92: 0 | BC92: 0 | BD92: =SUM(AX92:BB92) -> -952316.56 | BE92: =SUM(AY92:BC92) -> -952316.56 | BF92: =L92+AX92+AY92+BA92+BB92+BC92+AZ92 -> 2984965.5 | BG92: =AT92 -> -583233.64 | BH92: =SUM(BF92:BG92) -> 2401731.9 | BI92: =BH92+BI91 -> 39815248
A93: =A92+1 -> 36 | C93: 44348 | D93: 1268342.9 | E93: 2357921 | F93: 0 | G93: =+G92 -> 0.05 | H93: =-E93*G93 -> -117896.05 | I93: =-H90 -> 118769.26 | J93: =FV($J$3,K93,,-SUM(D93:E93))-SUM(D93:E93) -> 320875.42 | K93: =K92+1 -> 17 | L93: =SUM(H93:J93,D93:F93) -> 3948012.5 | P93: 0 | Q93: 0 | R93: 0 | S93: 0 | T93: 0 | U93: 0 | V93: 0 | W93: 0 | X93: -2000 | Y93: 0 | Z93: 0 | AA93: 0 | AB93: -29065.636 | AC93: -50793.52 | AD93: 0 | AE93: 0 | AF93: 0 | AG93: 0 | AH93: =-L92*6% -> -236236.92 | AI93: -9209.81 | AJ93: -7969 | AK93: -17924.754 | AL93: -767.84 | AM93: =-L92*1.2% -> -47247.385 | AN93: =-L92*4% -> -157491.28 | AP93: 0 | AQ93: 0 | AS93: =+L93 -> 3948012.5 | AT93: =+SUM(P93:AQ93) -> -558706.15 | AU93: =SUM(AS93:AT93) -> 3389306.3 | AV93: =AU93+AV92 -> 30085974 | AX93: 0 | AY93: -316523.41 | AZ93: -569742.14 | BA93: -59542.35 | BB93: 0 | BC93: 0 | BD93: =SUM(AX93:BB93) -> -945807.9 | BE93: =SUM(AY93:BC93) -> -945807.9 | BF93: =L93+AX93+AY93+BA93+BB93+BC93+AZ93 -> 3002204.6 | BG93: =AT93 -> -558706.15 | BH93: =SUM(BF93:BG93) -> 2443498.4 | BI93: =BH93+BI92 -> 42258747
A94: =A93+1 -> 37 | C94: 44378 | D94: 1268342.9 | E94: 2354055 | F94: 0 | G94: =+G93 -> 0.05 | H94: =-E94*G94 -> -117702.75 | I94: =-H91 -> 118464.99 | J94: =FV($J$3,K94,,-SUM(D94:E94))-SUM(D94:E94) -> 340247.99 | K94: =K93+1 -> 18 | L94: =SUM(H94:J94,D94:F94) -> 3963408.1 | P94: 0 | Q94: 0 | R94: 0 | S94: 0 | T94: 0 | U94: 0 | V94: 0 | W94: 0 | X94: -2000 | Y94: 0 | Z94: 0 | AA94: 0 | AB94: -29065.636 | AC94: -50721.33 | AD94: 0 | AE94: 0 | AF94: 0 | AG94: 0 | AH94: =-L93*6% -> -236880.75 | AI94: -9209.81 | AJ94: -7969 | AK94: -17871.807 | AL94: -767.84 | AM94: =-L93*1.2% -> -47376.15 | AN94: =-L93*4% -> -157920.5 | AP94: 0 | AQ94: 0 | AS94: =+L94 -> 3963408.1 | AT94: =+SUM(P94:AQ94) -> -559782.82 | AU94: =SUM(AS94:AT94) -> 3403625.2 | AV94: =AU94+AV93 -> 33489599 | AX94: 0 | AY94: -314702.12 | AZ94: -566463.82 | BA94: -58173.248 | BB94: 0 | BC94: 0 | BD94: =SUM(AX94:BB94) -> -939339.19 | BE94: =SUM(AY94:BC94) -> -939339.19 | BF94: =L94+AX94+AY94+BA94+BB94+BC94+AZ94 -> 3024068.9 | BG94: =AT94 -> -559782.82 | BH94: =SUM(BF94:BG94) -> 2464286.1 | BI94: =BH94+BI93 -> 44723033
A95: =A94+1 -> 38 | C95: 44409 | D95: 1268342.9 | E95: 2324647.9 | F95: 0 | G95: =+G94 -> 0.05 | H95: =-E95*G95 -> -116232.39 | I95: =-H92 -> 118268.52 | J95: =FV($J$3,K95,,-SUM(D95:E95))-SUM(D95:E95) -> 357138.19 | K95: =K94+1 -> 19 | L95: =SUM(H95:J95,D95:F95) -> 3952165 | P95: 0 | Q95: 0 | R95: 0 | S95: 0 | T95: 0 | U95: 0 | V95: 0 | W95: 0 | X95: -2000 | Y95: 0 | Z95: 0 | AA95: 0 | AB95: -29065.636 | AC95: -50001.59 | AD95: 0 | AE95: 0 | AF95: 0 | AG95: 0 | AH95: =-L94*6% -> -237804.48 | AI95: -9209.81 | AJ95: -7969 | AK95: -17855.731 | AL95: 0 | AM95: =-L94*1.2% -> -47560.897 | AN95: =-L94*4% -> -158536.32 | AP95: 0 | AQ95: 0 | AS95: =+L95 -> 3952165 | AT95: =+SUM(P95:AQ95) -> -560003.47 | AU95: =SUM(AS95:AT95) -> 3392161.6 | AV95: =AU95+AV94 -> 36881761 | AX95: 0 | AY95: -312880.83 | AZ95: -563185.5 | BA95: -56842.964 | BB95: 0 | BC95: 0 | BD95: =SUM(AX95:BB95) -> -932909.3 | BE95: =SUM(AY95:BC95) -> -932909.3 | BF95: =L95+AX95+AY95+BA95+BB95+BC95+AZ95 -> 3019255.7 | BG95: =AT95 -> -560003.47 | BH95: =SUM(BF95:BG95) -> 2459252.3 | BI95: =BH95+BI94 -> 47182285
A96: =A95+1 -> 39 | C96: 44440 | D96: 1268342.9 | E96: 2309123.8 | F96: 0 | G96: =+G95 -> 0.05 | H96: =-E96*G96 -> -115456.19 | I96: =-H93 -> 117896.05 | J96: =FV($J$3,K96,,-SUM(D96:E96))-SUM(D96:E96) -> 375260.43 | K96: =K95+1 -> 20 | L96: =SUM(H96:J96,D96:F96) -> 3955166.9 | P96: 0 | Q96: 0 | R96: 0 | S96: 0 | T96: 0 | U96: 0 | V96: 0 | W96: 0 | X96: -2000 | Y96: 0 | Z96: 0 | AA96: 0 | AB96: -29065.636 | AC96: -49668.01 | AD96: 0 | AE96: 0 | AF96: 0 | AG96: 0 | AH96: =-L95*6% -> -237129.9 | AI96: -9209.81 | AJ96: -7969 | AK96: -17709.678 | AL96: 0 | AM96: =-L95*1.2% -> -47425.98 | AN96: =-L95*4% -> -158086.6 | AP96: 0 | AQ96: 0 | AS96: =+L96 -> 3955166.9 | AT96: =+SUM(P96:AQ96) -> -558264.62 | AU96: =SUM(AS96:AT96) -> 3396902.3 | AV96: =AU96+AV95 -> 40278663 | AX96: 0 | AY96: -311059.54 | AZ96: -559907.18 | BA96: -71112.151 | BB96: 0 | BC96: 0 | BD96: =SUM(AX96:BB96) -> -942078.88 | BE96: =SUM(AY96:BC96) -> -942078.88 | BF96: =L96+AX96+AY96+BA96+BB96+BC96+AZ96 -> 3013088 | BG96: =AT96 -> -558264.62 | BH96: =SUM(BF96:BG96) -> 2454823.4 | BI96: =BH96+BI95 -> 49637108
A97: =A96+1 -> 40 | C97: 44470 | D97: 1268342.9 | E97: 2252592.7 | F97: 0 | G97: =+G96 -> 0.05 | H97: =-E97*G97 -> -112629.64 | I97: =-H94 -> 117702.75 | J97: =FV($J$3,K97,,-SUM(D97:E97))-SUM(D97:E97) -> 388781.9 | K97: =K96+1 -> 21 | L97: =SUM(H97:J97,D97:F97) -> 3914790.6 | P97: 0 | Q97: 0 | R97: 0 | S97: 0 | T97: 0 | U97: 0 | V97: 0 | W97: 0 | X97: -2000 | Y97: 0 | Z97: 0 | AA97: 0 | AB97: -29065.636 | AC97: -48174.93 | AD97: 0 | AE97: 0 | AF97: 0 | AG97: 0 | AH97: =-L96*6% -> -237310.01 | AI97: -9209.81 | AJ97: -7969 | AK97: -17629.964 | AL97: 0 | AM97: =-L96*1.2% -> -47462.003 | AN97: =-L96*4% -> -158206.68 | AP97: 0 | AQ97: 0 | AS97: =+L97 -> 3914790.6 | AT97: =+SUM(P97:AQ97) -> -557028.03 | AU97: =SUM(AS97:AT97) -> 3357762.6 | AV97: =AU97+AV96 -> 43636425 | AX97: 0 | AY97: -309238.26 | AZ97: -556628.86 | BA97: -54294.48 | BB97: 0 | BC97: 0 | BD97: =SUM(AX97:BB97) -> -920161.6 | BE97: =SUM(AY97:BC97) -> -920161.6 | BF97: =L97+AX97+AY97+BA97+BB97+BC97+AZ97 -> 2994629 | BG97: =AT97 -> -557028.03 | BH97: =SUM(BF97:BG97) -> 2437601 | BI97: =BH97+BI96 -> 52074709
A98: =A97+1 -> 41 | C98: 44501 | D98: 1268342.9 | E98: 2232580.1 | F98: 0 | G98: =+G97 -> 0.05 | H98: =-E98*G98 -> -111629.01 | I98: =-H95 -> 116232.39 | J98: =FV($J$3,K98,,-SUM(D98:E98))-SUM(D98:E98) -> 406009.59 | K98: =K97+1 -> 22 | L98: =SUM(H98:J98,D98:F98) -> 3911536 | P98: 0 | Q98: 0 | R98: 0 | S98: 0 | T98: 0 | U98: 0 | V98: 0 | W98: 0 | X98: -2000 | Y98: 0 | Z98: 0 | AA98: 0 | AB98: -29065.636 | AC98: -47644.89 | AD98: 0 | AE98: 0 | AF98: 0 | AG98: 0 | AH98: =-L97*6% -> -234887.44 | AI98: -9209.81 | AJ98: -7969 | AK98: -17350.771 | AL98: 0 | AM98: =-L97*1.2% -> -46977.487 | AN98: =-L97*4% -> -156591.62 | AP98: 0 | AQ98: 0 | AS98: =+L98 -> 3911536 | AT98: =+SUM(P98:AQ98) -> -551696.66 | AU98: =SUM(AS98:AT98) -> 3359839.3 | AV98: =AU98+AV97 -> 46996265 | AX98: 0 | AY98: -307416.97 | AZ98: -553350.54 | BA98: -53074.172 | BB98: 0 | BC98: 0 | BD98: =SUM(AX98:BB98) -> -913841.68 | BE98: =SUM(AY98:BC98) -> -913841.68 | BF98: =L98+AX98+AY98+BA98+BB98+BC98+AZ98 -> 2997694.3 | BG98: =AT98 -> -551696.66 | BH98: =SUM(BF98:BG98) -> 2445997.6 | BI98: =BH98+BI97 -> 54520707
A99: =A98+1 -> 42 | C99: 44531 | D99: 1268342.9 | E99: 2218788.2 | F99: 0 | G99: =+G98 -> 0.05 | H99: =-E99*G99 -> -110939.41 | I99: =-H96 -> 115456.19 | J99: =FV($J$3,K99,,-SUM(D99:E99))-SUM(D99:E99) -> 423867.82 | K99: =K98+1 -> 23 | L99: =SUM(H99:J99,D99:F99) -> 3915515.7 | P99: 0 | Q99: 0 | R99: 0 | S99: 0 | T99: 0 | U99: 0 | V99: 0 | W99: 0 | X99: -2000 | Y99: 0 | Z99: 0 | AA99: 0 | AB99: -29065.636 | AC99: -47339.37 | AD99: 0 | AE99: 0 | AF99: 0 | AG99: 0 | AH99: =-L98*6% -> -234692.16 | AI99: -9209.81 | AJ99: -7969 | AK99: -17235.541 | AL99: 0 | AM99: =-L98*1.2% -> -46938.432 | AN99: =-L98*4% -> -156461.44 | AP99: 0 | AQ99: 0 | AS99: =+L99 -> 3915515.7 | AT99: =+SUM(P99:AQ99) -> -550911.39 | AU99: =SUM(AS99:AT99) -> 3364604.3 | AV99: =AU99+AV98 -> 50360869 | AX99: 0 | AY99: -305595.68 | AZ99: -550072.22 | BA99: -51888.463 | BB99: 0 | BC99: 0 | BD99: =SUM(AX99:BB99) -> -907556.36 | BE99: =SUM(AY99:BC99) -> -907556.36 | BF99: =L99+AX99+AY99+BA99+BB99+BC99+AZ99 -> 3007959.3 | BG99: =AT99 -> -550911.39 | BH99: =SUM(BF99:BG99) -> 2457048 | BI99: =BH99+BI98 -> 56977755
A100: =A99+1 -> 43 | C100: 44562 | D100: 1268342.9 | E100: 2199203.9 | F100: 0 | G100: =+G99 -> 0.05 | H100: =-E100*G100 -> -109960.2 | I100: =-H97 -> 112629.64 | J100: =FV($J$3,K100,,-SUM(D100:E100))-SUM(D100:E100) -> 440932.47 | K100: =K99+1 -> 24 | L100: =SUM(H100:J100,D100:F100) -> 3911148.7 | P100: 0 | Q100: 0 | R100: 0 | S100: 0 | T100: 0 | U100: 0 | V100: 0 | W100: 0 | X100: -2000 | Y100: 0 | Z100: 0 | AA100: 0 | AB100: -29065.636 | AC100: -46928.62 | AD100: 0 | AE100: 0 | AF100: 0 | AG100: 0 | AH100: =-L99*6% -> -234930.94 | AI100: -9209.81 | AJ100: -7969 | AK100: -17158.676 | AL100: 0 | AM100: =-L99*1.2% -> -46986.188 | AN100: =-L99*4% -> -156620.63 | AP100: 0 | AQ100: 0 | AS100: =+L100 -> 3911148.7 | AT100: =+SUM(P100:AQ100) -> -550869.5 | AU100: =SUM(AS100:AT100) -> 3360279.2 | AV100: =AU100+AV99 -> 53721148 | AX100: 0 | AY100: -303774.39 | AZ100: -546793.9 | BA100: -50736.373 | BB100: 0 | BC100: 0 | BD100: =SUM(AX100:BB100) -> -901304.66 | BE100: =SUM(AY100:BC100) -> -901304.66 | BF100: =L100+AX100+AY100+BA100+BB100+BC100+AZ100 -> 3009844 | BG100: =AT100 -> -550869.5 | BH100: =SUM(BF100:BG100) -> 2458974.5 | BI100: =BH100+BI99 -> 59436729
A101: =A100+1 -> 44 | C101: 44593 | D101: 1268342.9 | E101: 2172515.6 | F101: 0 | G101: =+G100 -> 0.05 | H101: =-E101*G101 -> -108625.78 | I101: =-H98 -> 111629.01 | J101: =FV($J$3,K101,,-SUM(D101:E101))-SUM(D101:E101) -> 456930.78 | K101: =K100+1 -> 25 | L101: =SUM(H101:J101,D101:F101) -> 3900792.5 | P101: 0 | Q101: 0 | R101: 0 | S101: 0 | T101: 0 | U101: 0 | V101: 0 | W101: 0 | X101: -2000 | Y101: 0 | Z101: 0 | AA101: 0 | AB101: -29065.636 | AC101: -46382.12 | AD101: 0 | AE101: 0 | AF101: 0 | AG101: 0 | AH101: =-L100*6% -> -234668.92 | AI101: -9209.81 | AJ101: -7969 | AK101: -17028.435 | AL101: 0 | AM101: =-L100*1.2% -> -46933.785 | AN101: =-L100*4% -> -156445.95 | AP101: 0 | AQ101: 0 | AS101: =+L101 -> 3900792.5 | AT101: =+SUM(P101:AQ101) -> -549703.66 | AU101: =SUM(AS101:AT101) -> 3351088.8 | AV101: =AU101+AV100 -> 57072237 | AX101: 0 | AY101: -301953.1 | AZ101: -543515.58 | BA101: -49616.948 | BB101: 0 | BC101: 0 | BD101: =SUM(AX101:BB101) -> -895085.63 | BE101: =SUM(AY101:BC101) -> -895085.63 | BF101: =L101+AX101+AY101+BA101+BB101+BC101+AZ101 -> 3005706.8 | BG101: =AT101 -> -549703.66 | BH101: =SUM(BF101:BG101) -> 2456003.2 | BI101: =BH101+BI100 -> 61892733
A102: =A101+1 -> 45 | C102: 44621 | D102: 1268342.9 | E102: 2140900.4 | F102: 0 | G102: =+G101 -> 0.05 | H102: =-E102*G102 -> -107045.02 | I102: =-H99 -> 110939.41 | J102: =FV($J$3,K102,,-SUM(D102:E102))-SUM(D102:E102) -> 472042.29 | K102: =K101+1 -> 26 | L102: =SUM(H102:J102,D102:F102) -> 3885179.9 | P102: 0 | Q102: 0 | R102: 0 | S102: 0 | T102: 0 | U102: 0 | V102: 0 | W102: 0 | X102: -2000 | Y102: 0 | Z102: 0 | AA102: 0 | AB102: -29065.636 | AC102: -45683.07 | AD102: 0 | AE102: 0 | AF102: 0 | AG102: 0 | AH102: =-L101*6% -> -234047.55 | AI102: -9209.81 | AJ102: -7969 | AK102: -16885.622 | AL102: 0 | AM102: =-L101*1.2% -> -46809.51 | AN102: =-L101*4% -> -156031.7 | AP102: 0 | AQ102: 0 | AS102: =+L102 -> 3885179.9 | AT102: =+SUM(P102:AQ102) -> -547701.9 | AU102: =SUM(AS102:AT102) -> 3337478 | AV102: =AU102+AV101 -> 60409715 | AX102: 0 | AY102: -300131.81 | AZ102: -540237.26 | BA102: -48529.262 | BB102: 0 | BC102: 0 | BD102: =SUM(AX102:BB102) -> -888898.34 | BE102: =SUM(AY102:BC102) -> -888898.34 | BF102: =L102+AX102+AY102+BA102+BB102+BC102+AZ102 -> 2996281.6 | BG102: =AT102 -> -547701.9 | BH102: =SUM(BF102:BG102) -> 2448579.7 | BI102: =BH102+BI101 -> 64341312
A103: =A102+1 -> 46 | C103: 44652 | D103: 1268342.9 | E103: 2101476.6 | F103: 0 | G103: =+G102 -> 0.05 | H103: =-E103*G103 -> -105073.83 | I103: =-H100 -> 109960.2 | J103: =FV($J$3,K103,,-SUM(D103:E103))-SUM(D103:E103) -> 485765.71 | K103: =K102+1 -> 27 | L103: =SUM(H103:J103,D103:F103) -> 3860471.5 | P103: 0 | Q103: 0 | R103: 0 | S103: 0 | T103: 0 | U103: 0 | V103: 0 | W103: 0 | X103: -2000 | Y103: 0 | Z103: 0 | AA103: 0 | AB103: -29065.636 | AC103: -44913.2 | AD103: 0 | AE103: 0 | AF103: 0 | AG103: 0 | AH103: =-L102*6% -> -233110.8 | AI103: -9209.81 | AJ103: -23969 | AK103: -16715.904 | AL103: 0 | AM103: =-L102*1.2% -> -46622.159 | AN103: =-L102*4% -> -155407.2 | AP103: 0 | AQ103: 0 | AS103: =+L103 -> 3860471.5 | AT103: =+SUM(P103:AQ103) -> -561013.7 | AU103: =SUM(AS103:AT103) -> 3299457.8 | AV103: =AU103+AV102 -> 63709173 | AX103: 0 | AY103: -298310.52 | AZ103: -536958.94 | BA103: -47472.416 | BB103: 0 | BC103: 0 | BD103: =SUM(AX103:BB103) -> -882741.88 | BE103: =SUM(AY103:BC103) -> -882741.88 | BF103: =L103+AX103+AY103+BA103+BB103+BC103+AZ103 -> 2977729.6 | BG103: =AT103 -> -561013.7 | BH103: =SUM(BF103:BG103) -> 2416715.9 | BI103: =BH103+BI102 -> 66758028
A104: =A103+1 -> 47 | C104: 44682 | D104: 1268342.9 | E104: 2078889.7 | F104: 0 | G104: =+G103 -> 0.05 | H104: =-E104*G104 -> -103944.48 | I104: =-H101 -> 108625.78 | J104: =FV($J$3,K104,,-SUM(D104:E104))-SUM(D104:E104) -> 501658.48 | K104: =K103+1 -> 28 | L104: =SUM(H104:J104,D104:F104) -> 3853572.3 | P104: 0 | Q104: 0 | R104: 0 | S104: 0 | T104: 0 | U104: 0 | V104: 0 | W104: 0 | X104: -2000 | Y104: 0 | Z104: 0 | AA104: 0 | AB104: -29065.636 | AC104: -44425.99 | AD104: 0 | AE104: 0 | AF104: 0 | AG104: 0 | AH104: =-L103*6% -> -231628.29 | AI104: -9209.81 | AJ104: -23969 | AK104: -16504.898 | AL104: 0 | AM104: =-L103*1.2% -> -46325.658 | AN104: =-L103*4% -> -154418.86 | AP104: 0 | AQ104: 0 | AS104: =+L104 -> 3853572.3 | AT104: =+SUM(P104:AQ104) -> -557548.15 | AU104: =SUM(AS104:AT104) -> 3296024.2 | AV104: =AU104+AV103 -> 67005197 | AX104: 0 | AY104: -296489.23 | AZ104: -533680.62 | BA104: -46445.535 | BB104: 0 | BC104: 0 | BD104: =SUM(AX104:BB104) -> -876615.39 | BE104: =SUM(AY104:BC104) -> -876615.39 | BF104: =L104+AX104+AY104+BA104+BB104+BC104+AZ104 -> 2976956.9 | BG104: =AT104 -> -557548.15 | BH104: =SUM(BF104:BG104) -> 2419408.8 | BI104: =BH104+BI103 -> 69177437
... A175: =A174+1 -> 118 | C175: 46844 | D175: 17719.02 | E175: 0 | F175: 0 | G175: =+G174 -> 0.05 | H175: =-E175*G175 -> 0 | I175: =-H172 -> 26.3095 | J175: =FV($J$3,K175,,-SUM(D175:E175))-SUM(D175:E175) -> 11313.171 | K175: =K174+1 -> 99 | L175: =SUM(H175:J175,D175:F175) -> 29058.5 | P175: 0 | Q175: 0 | R175: 0 | S175: 0 | T175: 0 | U175: 0 | V175: 0 | W175: 0 | X175: 0 | Y175: 0 | Z175: 0 | AA175: 0 | AB175: 0 | AC175: 0 | AD175: 0 | AE175: 0 | AF175: 0 | AG175: 0 | AH175: =-L174*6% -> -2120.0137 | AI175: 0 | AJ175: 0 | AK175: -0.28596121 | AL175: 0 | AM175: =-L174*1.2% -> -424.00275 | AN175: =-L174*4% -> -1413.3425 | AP175: 0 | AQ175: 0 | AS175: =+L175 -> 29058.5 | AT175: =+SUM(P175:AQ175) -> -3957.6449 | AU175: =SUM(AS175:AT175) -> 25100.856 | AV175: =AU175+AV174 -> 2.0564018e+08 | AX175: 0 | AY175: -167177.73 | AZ175: -300919.92 | BA175: -15820.814 | BB175: 0 | BC175: 0 | BD175: =SUM(AX175:BB175) -> -483918.47 | BE175: =SUM(AY175:BC175) -> -483918.47 | BF175: =L175+AX175+AY175+BA175+BB175+BC175+AZ175 -> -454859.96 | BG175: =AT175 -> -3957.6449 | BH175: =SUM(BF175:BG175) -> -458817.61 | BI175: =BH175+BI174 -> 1.5996299e+08
A176: =A175+1 -> 119 | B176: FIM CARTEIRA | C176: 46874 | D176: 0 | E176: 0 | F176: 0 | G176: =+G175 -> 0.05 | H176: =-E176*G176 -> 0 | I176: =-H173 -> 0 | J176: =FV($J$3,K176,,-SUM(D176:E176))-SUM(D176:E176) -> 0 | K176: =K175+1 -> 100 | L176: =SUM(H176:J176,D176:F176) -> 0 | P176: 0 | Q176: 0 | R176: 0 | S176: 0 | T176: 0 | U176: 0 | V176: 0 | W176: 0 | X176: 0 | Y176: 0 | Z176: 0 | AA176: 0 | AB176: 0 | AC176: 0 | AD176: 0 | AE176: 0 | AF176: 0 | AG176: 0 | AH176: =-L175*6% -> -1743.51 | AI176: 0 | AJ176: 0 | AK176: -0.28596121 | AL176: 0 | AM176: =-L175*1.2% -> -348.70201 | AN176: =-L175*4% -> -1162.34 | AP176: 0 | AQ176: 0 | AS176: =+L176 -> 0 | AT176: =+SUM(P176:AQ176) -> -3254.838 | AU176: =SUM(AS176:AT176) -> -3254.838 | AV176: =AU176+AV175 -> 2.0563692e+08 | AX176: 0 | AY176: -165356.44 | AZ176: -297641.6 | BA176: -15691.356 | BB176: 0 | BC176: 0 | BD176: =SUM(AX176:BB176) -> -478689.4 | BE176: =SUM(AY176:BC176) -> -478689.4 | BF176: =L176+AX176+AY176+BA176+BB176+BC176+AZ176 -> -478689.4 | BG176: =AT176 -> -3254.838 | BH176: =SUM(BF176:BG176) -> -481944.24 | BI176: =BH176+BI175 -> 1.5948105e+08
A177: =A176+1 -> 120 | C177: 46905 | D177: 0 | E177: 0 | F177: 0 | G177: =+G176 -> 0.05 | H177: 0 | I177: =-H174 -> 0 | J177: =FV($J$3,K177,,-SUM(D177:E177))-SUM(D177:E177) -> 0 | K177: =K176+1 -> 101 | L177: =SUM(H177:J177,D177:F177) -> 0 | P177: 0 | Q177: 0 | R177: 0 | S177: 0 | T177: 0 | U177: 0 | V177: 0 | W177: 0 | X177: 0 | Y177: 0 | Z177: 0 | AA177: 0 | AB177: 0 | AC177: 0 | AD177: 0 | AE177: 0 | AF177: 0 | AG177: 0 | AH177: =-L176*6% -> 0 | AI177: 0 | AJ177: 0 | AK177: 0 | AL177: 0 | AM177: =-L176*1.2% -> 0 | AN177: =-L176*4% -> 0 | AP177: 0 | AQ177: 0 | AS177: =+L177 -> 0 | AT177: =+SUM(P177:AQ177) -> 0 | AU177: =SUM(AS177:AT177) -> 0 | AV177: =AU177+AV176 -> 2.0563692e+08 | AX177: 0 | AY177: -163535.16 | AZ177: -294363.28 | BA177: -15565.569 | BB177: 0 | BC177: 0 | BD177: =SUM(AX177:BB177) -> -473464 | BE177: =SUM(AY177:BC177) -> -473464 | BF177: =L177+AX177+AY177+BA177+BB177+BC177+AZ177 -> -473464 | BG177: =AT177 -> 0 | BH177: =SUM(BF177:BG177) -> -473464 | BI177: =BH177+BI176 -> 1.5900759e+08
A178: =A177+1 -> 121 | C178: 46935 | D178: 0 | E178: 0 | F178: 0 | G178: =+G177 -> 0.05 | H178: 0 | I178: =-H175 -> 0 | J178: =FV($J$3,K178,,-SUM(D178:E178))-SUM(D178:E178) -> 0 | K178: =K177+1 -> 102 | L178: =SUM(H178:J178,D178:F178) -> 0 | P178: 0 | Q178: 0 | R178: 0 | S178: 0 | T178: 0 | U178: 0 | V178: 0 | W178: 0 | X178: 0 | Y178: 0 | Z178: 0 | AA178: 0 | AB178: 0 | AC178: 0 | AD178: 0 | AE178: 0 | AF178: 0 | AG178: 0 | AH178: =-L177*6% -> 0 | AI178: 0 | AJ178: 0 | AK178: 0 | AL178: 0 | AM178: =-L177*1.2% -> 0 | AN178: =-L177*4% -> 0 | AP178: 0 | AQ178: 0 | AS178: =+L178 -> 0 | AT178: =+SUM(P178:AQ178) -> 0 | AU178: =SUM(AS178:AT178) -> 0 | AV178: =AU178+AV177 -> 2.0563692e+08 | AX178: 0 | AY178: -161713.87 | AZ178: -291084.96 | BA178: -15443.349 | BB178: 0 | BC178: 0 | BD178: =SUM(AX178:BB178) -> -468242.17 | BE178: =SUM(AY178:BC178) -> -468242.17 | BF178: =L178+AX178+AY178+BA178+BB178+BC178+AZ178 -> -468242.17 | BG178: =AT178 -> 0 | BH178: =SUM(BF178:BG178) -> -468242.17 | BI178: =BH178+BI177 -> 1.5853934e+08
A179: =A178+1 -> 122 | C179: 46966 | D179: 0 | E179: 0 | F179: 0 | G179: =+G178 -> 0.05 | H179: 0 | I179: =-H176 -> 0 | J179: =FV($J$3,K179,,-SUM(D179:E179))-SUM(D179:E179) -> 0 | K179: =K178+1 -> 103 | L179: =SUM(H179:J179,D179:F179) -> 0 | P179: 0 | Q179: 0 | R179: 0 | S179: 0 | T179: 0 | U179: 0 | V179: 0 | W179: 0 | X179: 0 | Y179: 0 | Z179: 0 | AA179: 0 | AB179: 0 | AC179: 0 | AD179: 0 | AE179: 0 | AF179: 0 | AG179: 0 | AH179: =-L178*6% -> 0 | AI179: 0 | AJ179: 0 | AK179: 0 | AL179: 0 | AM179: =-L178*1.2% -> 0 | AN179: =-L178*4% -> 0 | AP179: 0 | AQ179: 0 | AS179: =+L179 -> 0 | AT179: =+SUM(P179:AQ179) -> 0 | AU179: =SUM(AS179:AT179) -> 0 | AV179: =AU179+AV178 -> 2.0563692e+08 | AX179: 0 | AY179: -159892.58 | AZ179: -287806.64 | BA179: -15324.594 | BB179: 0 | BC179: 0 | BD179: =SUM(AX179:BB179) -> -463023.81 | BE179: =SUM(AY179:BC179) -> -463023.81 | BF179: =L179+AX179+AY179+BA179+BB179+BC179+AZ179 -> -463023.81 | BG179: =AT179 -> 0 | BH179: =SUM(BF179:BG179) -> -463023.81 | BI179: =BH179+BI178 -> 1.5807632e+08
A180: =A179+1 -> 123 | C180: 46997 | D180: 0 | E180: 0 | F180: 0 | G180: =+G179 -> 0.05 | H180: 0 | I180: =-H177 -> 0 | J180: =FV($J$3,K180,,-SUM(D180:E180))-SUM(D180:E180) -> 0 | K180: =K179+1 -> 104 | L180: =SUM(H180:J180,D180:F180) -> 0 | P180: 0 | Q180: 0 | R180: 0 | S180: 0 | T180: 0 | U180: 0 | V180: 0 | W180: 0 | X180: 0 | Y180: 0 | Z180: 0 | AA180: 0 | AB180: 0 | AC180: 0 | AD180: 0 | AE180: 0 | AF180: 0 | AG180: 0 | AH180: =-L179*6% -> 0 | AI180: 0 | AJ180: 0 | AK180: 0 | AL180: 0 | AM180: =-L179*1.2% -> 0 | AN180: =-L179*4% -> 0 | AP180: 0 | AQ180: 0 | AS180: =+L180 -> 0 | AT180: =+SUM(P180:AQ180) -> 0 | AU180: =SUM(AS180:AT180) -> 0 | AV180: =AU180+AV179 -> 2.0563692e+08 | AY180: -158071.29 | AZ180: -284528.32 | BA180: -30770.959 | BB180: 0 | BC180: 2760000 | BD180: =SUM(AX180:BB180) -> -473370.57 | BE180: =SUM(AY180:BC180) -> 2286629.4 | BF180: =L180+AX180+AY180+BA180+BB180+BC180+AZ180 -> 2286629.4 | BG180: =AT180 -> 0 | BH180: =SUM(BF180:BG180) -> 2286629.4 | BI180: =BH180+BI179 -> 1.6036295e+08
A181: =A180+1 -> 124 | C181: 47027 | D181: 0 | E181: 0 | F181: 0 | G181: =+G180 -> 0.05 | H181: 0 | I181: =-H178 -> 0 | J181: =FV($J$3,K181,,-SUM(D181:E181))-SUM(D181:E181) -> 0 | K181: =K180+1 -> 105 | L181: =SUM(H181:J181,D181:F181) -> 0 | P181: 0 | Q181: 0 | R181: 0 | S181: 0 | T181: 0 | U181: 0 | V181: 0 | W181: 0 | X181: 0 | Y181: 0 | Z181: 0 | AA181: 0 | AB181: 0 | AC181: 0 | AD181: 0 | AE181: 0 | AF181: 0 | AG181: 0 | AH181: =-L180*6% -> 0 | AI181: 0 | AJ181: 0 | AK181: 0 | AL181: 0 | AM181: =-L180*1.2% -> 0 | AN181: =-L180*4% -> 0 | AP181: 0 | AQ181: 0 | AS181: =+L181 -> 0 | AT181: =+SUM(P181:AQ181) -> 0 | AU181: =SUM(AS181:AT181) -> 0 | AV181: =AU181+AV180 -> 2.0563692e+08 | AX181: 0 | AY181: 0 | BA181: 0 | BB181: 0 | BC181: 0 | BD181: =SUM(AX181:BC181) -> 0 | BE181: =SUM(AY181:BC181) -> 0 | BF181: =L181+AX181+AY181+BA181+BB181+BC181+AZ181 -> 0 | BG181: =AT181 -> 0 | BH181: =SUM(BF181:BG181) -> 0 | BI181: 0
A182: =A181+1 -> 125 | C182: 47058 | D182: 0 | E182: 0 | F182: 0 | G182: =+G181 -> 0.05 | H182: 0 | I182: =-H179 -> 0 | J182: =FV($J$3,K182,,-SUM(D182:E182))-SUM(D182:E182) -> 0 | K182: =K181+1 -> 106 | L182: =SUM(H182:J182,D182:F182) -> 0 | P182: 0 | Q182: 0 | R182: 0 | S182: 0 | T182: 0 | U182: 0 | V182: 0 | W182: 0 | X182: 0 | Y182: 0 | Z182: 0 | AA182: 0 | AB182: 0 | AC182: 0 | AD182: 0 | AE182: 0 | AF182: 0 | AG182: 0 | AH182: =-L181*6% -> 0 | AI182: 0 | AJ182: 0 | AK182: 0 | AL182: 0 | AM182: =-L181*1.2% -> 0 | AN182: =-L181*4% -> 0 | AP182: 0 | AQ182: 0 | AS182: =+L182 -> 0 | AT182: =+SUM(P182:AQ182) -> 0 | AU182: =SUM(AS182:AT182) -> 0 | AV182: =AU182+AV181 -> 2.0563692e+08 | AX182: 0 | AY182: 0 | BA182: 0 | BB182: 0 | BC182: 0 | BD182: =SUM(AX182:BC182) -> 0 | BE182: =SUM(AY182:BC182) -> 0 | BF182: =L182+AX182+AY182+BA182+BB182+BC182+AZ182 -> 0 | BG182: =AT182 -> 0 | BH182: =SUM(BF182:BG182) -> 0 | BI182: 0
A183: =A182+1 -> 126 | C183: 47088 | D183: 0 | E183: 0 | F183: 0 | G183: =+G182 -> 0.05 | H183: 0 | I183: =-H180 -> 0 | J183: =FV($J$3,K183,,-SUM(D183:E183))-SUM(D183:E183) -> 0 | K183: =K182+1 -> 107 | L183: =SUM(H183:J183,D183:F183) -> 0 | P183: 0 | Q183: 0 | R183: 0 | S183: 0 | T183: 0 | U183: 0 | V183: 0 | W183: 0 | X183: 0 | Y183: 0 | Z183: 0 | AA183: 0 | AB183: 0 | AC183: 0 | AD183: 0 | AE183: 0 | AF183: 0 | AG183: 0 | AH183: =-L182*6% -> 0 | AI183: 0 | AJ183: 0 | AK183: 0 | AL183: 0 | AM183: =-L182*1.2% -> 0 | AN183: =-L182*4% -> 0 | AP183: 0 | AQ183: 0 | AS183: =+L183 -> 0 | AT183: =+SUM(P183:AQ183) -> 0 | AU183: =SUM(AS183:AT183) -> 0 | AV183: =AU183+AV182 -> 2.0563692e+08 | AX183: 0 | AY183: 0 | BA183: 0 | BB183: 0 | BC183: 0 | BD183: =SUM(AX183:BC183) -> 0 | BE183: =SUM(AY183:BC183) -> 0 | BF183: =L183+AX183+AY183+BA183+BB183+BC183+AZ183 -> 0 | BG183: =AT183 -> 0 | BH183: =SUM(BF183:BG183) -> 0 | BI183: 0
A184: =A183+1 -> 127 | C184: 47119 | D184: 0 | E184: 0 | F184: 0 | G184: =+G183 -> 0.05 | H184: 0 | I184: =-H181 -> 0 | J184: =FV($J$3,K184,,-SUM(D184:E184))-SUM(D184:E184) -> 0 | K184: =K183+1 -> 108 | L184: =SUM(H184:J184,D184:F184) -> 0 | P184: 0 | Q184: 0 | R184: 0 | S184: 0 | T184: 0 | U184: 0 | V184: 0 | W184: 0 | X184: 0 | Y184: 0 | Z184: 0 | AA184: 0 | AB184: 0 | AC184: 0 | AD184: 0 | AE184: 0 | AF184: 0 | AG184: 0 | AH184: =-L183*6% -> 0 | AI184: 0 | AJ184: 0 | AK184: 0 | AL184: 0 | AM184: =-L183*1.2% -> 0 | AN184: =-L183*4% -> 0 | AP184: 0 | AQ184: 0 | AS184: =+L184 -> 0 | AT184: =+SUM(P184:AQ184) -> 0 | AU184: =SUM(AS184:AT184) -> 0 | AV184: =AU184+AV183 -> 2.0563692e+08 | AX184: 0 | AY184: 0 | BA184: 0 | BB184: 0 | BC184: 0 | BD184: =SUM(AX184:BC184) -> 0 | BE184: =SUM(AY184:BC184) -> 0 | BF184: =L184+AX184+AY184+BA184+BB184+BC184+AZ184 -> 0 | BG184: =AT184 -> 0 | BH184: =SUM(BF184:BG184) -> 0 | BI184: 0
A185: =A184+1 -> 128 | C185: 47150 | D185: 0 | E185: 0 | F185: 0 | G185: =+G184 -> 0.05 | H185: 0 | I185: =-H182 -> 0 | J185: =FV($J$3,K185,,-SUM(D185:E185))-SUM(D185:E185) -> 0 | K185: =K184+1 -> 109 | L185: =SUM(H185:J185,D185:F185) -> 0 | P185: 0 | Q185: 0 | R185: 0 | S185: 0 | T185: 0 | U185: 0 | V185: 0 | W185: 0 | X185: 0 | Y185: 0 | Z185: 0 | AA185: 0 | AB185: 0 | AC185: 0 | AD185: 0 | AE185: 0 | AF185: 0 | AG185: 0 | AH185: =-L184*6% -> 0 | AI185: 0 | AJ185: 0 | AK185: 0 | AL185: 0 | AM185: =-L184*1.2% -> 0 | AN185: =-L184*4% -> 0 | AP185: 0 | AQ185: 0 | AS185: =+L185 -> 0 | AT185: =+SUM(P185:AQ185) -> 0 | AU185: =SUM(AS185:AT185) -> 0 | AV185: =AU185+AV184 -> 2.0563692e+08 | AX185: 0 | AY185: 0 | BA185: 0 | BB185: 0 | BC185: 0 | BD185: =SUM(AX185:BC185) -> 0 | BE185: =SUM(AY185:BC185) -> 0 | BF185: =L185+AX185+AY185+BA185+BB185+BC185+AZ185 -> 0 | BG185: =AT185 -> 0 | BH185: =SUM(BF185:BG185) -> 0 | BI185: 0
A186: =1+A185 -> 129 | C186: 47178 | D186: 0 | E186: 0 | F186: 0 | G186: =+G185 -> 0.05 | H186: 0 | I186: =-H183 -> 0 | J186: =FV($J$3,K186,,-SUM(D186:E186))-SUM(D186:E186) -> 0 | K186: =K185+1 -> 110 | P186: 0 | Q186: 0 | R186: 0 | S186: 0 | T186: 0 | U186: 0 | V186: 0 | W186: 0 | X186: 0 | Y186: 0 | Z186: 0 | AA186: 0 | AB186: 0 | AC186: 0 | AD186: 0 | AE186: 0 | AF186: 0 | AG186: 0 | AH186: =-L185*6% -> 0 | AI186: 0 | AJ186: 0 | AK186: 0 | AL186: 0 | AM186: =-L185*1.2% -> 0 | AN186: =-L185*4% -> 0 | AP186: 0 | AQ186: 0 | AS186: =+L186 -> 0 | AT186: =+SUM(P186:AQ186) -> 0 | AU186: =SUM(AS186:AT186) -> 0 | AV186: =+AU186+AV185 -> 2.0563692e+08 | AY186: 0 | BC186: 0 | BD186: =SUM(AX186:BC186) -> 0 | BE186: =SUM(AY186:BB186) -> 0 | BF186: =L186+AX186+AY186+BA186+BB186 -> 0 | BG186: =AT186 -> 0 | BH186: =SUM(BF186:BG186) -> 0 | BI186: 0
D187: 0 | E187: 0 | F187: =SUM(F58:F186) -> 1382206.7 | H187: =SUM(H58:H186) -> -11265591 | I187: =SUM(I58:I186) -> 11265591 | J187: =SUM(J58:J186) -> 43531017 | L187: =SUM(L58:L186) -> 3.2746291e+08 | P187: 0 | Q187: 0 | R187: 0 | S187: 0 | T187: 0 | U187: 0 | V187: 0 | W187: 0 | X187: 0 | Y187: 0 | Z187: 0 | AA187: 0 | AB187: 0 | AC187: 0 | AD187: 0 | AE187: 0 | AF187: 0 | AG187: 0 | AK187: 0 | AP187: 0 | AQ187: 0

Sheet Indicadores
B3: RESULTADO SEM ALAVANCAGEM | K3: RESULTADO COM ALAVANCAGEM | T3: DIFERENÇA
B4: Receita | F4: ='Fluxo Consolidado'!L3 -> 3.6941881e+08 | K4: Receita | O4: =+F4 -> 3.6941881e+08 | T4: =+O4-F4 -> 0
B5: Emprestimo | F5: ='Fluxo Consolidado'!M3+'Fluxo Consolidado'!N3 -> 2493512 | K5: Emprestimo | O5: =+F5 -> 2493512 | T5: =+O5-F5 -> 0
B6: Despesa | F6: ='Fluxo Consolidado'!AT3 -> -1.6981533e+08 | K6: Despesa | O6: ='Fluxo Consolidado'!BG3+'Fluxo Consolidado'!BD3 -> -2.150893e+08 | T6: =+O6-F6 -> -45273972
B7: Resultado | F7: =+F4+F6+F5 -> 2.0209699e+08 | K7: Resultado | O7: =SUM(O4:R6) -> 1.5682302e+08 | T7: =+O7-F7 -> -45273972
B8: Exposição Máxima | F8: =MIN('Fluxo Consolidado'!AV59:AV186) -> -16571542 | K8: Exposição Máxima | O8: =MIN('Fluxo Consolidado'!BI59:BI186) -> -1228124.9 | T8: =+O8-F8 -> 15343417
B9: Dt. Exposição Máxima | F9: ='Fluxo Consolidado'!C75 -> 43800 | K9: Dt. Exposição Máxima | O9: ='Fluxo Consolidado'!C59 -> 43313 | T9: =+(O9-F9)/30 -> -16.233333
B10: PayBack | F10: ='Fluxo Consolidado'!C84 -> 44075 | K10: PayBack | O10: ='Fluxo Consolidado'!C60 -> 43344 | T10: =+(O10-F10)/30 -> -24.366667
B11: TIR (a.m. | a.a.) | F11: ='DRE - Grafico'!L35 -> 0.028510764 | H11: =(1+F11)^12-1 -> 0.40121924 | K11: TIR (a.m. | a.a.) | O11: ='DRE - Grafico'!L40 -> 0.030839069 | Q11: =(1+O11)^12-1 -> 0.43976112
B12: Margem (Resul. / Receita) | F12: =F7/F4 -> 0.54706741 | K12: Margem (Resul. / Receita) | O12: =O7/O4 -> 0.42451282 | T12: =+O12-F12 -> -0.12255459
B13: ROE (Resul. / Exp. Máx.) | F13: =F7/-F8 -> 12.195425 | K13: ROE (Resul. / Exp. Máx.) | O13: =O7/-O8 -> 127.69305 | T13: =+O13-F13 -> 115.49763
B15: FLUXO ANUAL DO EMPREENIDMENTO
B30: FLUXO ANUAL DO EMPREENIDMENTO
B31: ANO | F31: SEM ALAVANCAGEM | L31: COM ALAVANCAGEM
B32: 2012 | F32: 0 | L32: 0
B33: =B32+1 -> 2013 | F33: 0 | L33: 0
B34: =B33+1 -> 2014 | F34: ='Resumo Ano'!E6 -> 68299.79 | L34: ='Resumo Ano'!K6 -> 68299.79
B35: =B34+1 -> 2015 | F35: ='Resumo Ano'!E7 -> -13246.93 | L35: ='Resumo Ano'!K7 -> -13246.93
B36: =B35+1 -> 2016 | F36: ='Resumo Ano'!E8 -> 42146.14 | L36: ='Resumo Ano'!K8 -> 42146.14
B37: =B36+1 -> 2017 | F37: ='Resumo Ano'!E9 -> -27785.75 | L37: ='Resumo Ano'!K9 -> -27785.75
B38: =B37+1 -> 2018 | F38: ='Resumo Ano'!E10 -> -7436490.6 | L38: ='Resumo Ano'!K10 -> 4573149.8
B39: =B38+1 -> 2019 | F39: ='Resumo Ano'!E11 -> -9204464.5 | L39: ='Resumo Ano'!K11 -> 7625157.6
B40: =B39+1 -> 2020 | F40: ='Resumo Ano'!E12 -> 26678325 | L40: ='Resumo Ano'!K12 -> 18545153
B41: =B40+1 -> 2021 | F41: ='Resumo Ano'!E13 -> 40254086 | L41: ='Resumo Ano'!K13 -> 28924881
B42: =B41+1 -> 2022 | F42: ='Resumo Ano'!E14 -> 39707620 | L42: ='Resumo Ano'!K14 -> 29280302
B43: =B42+1 -> 2023 | F43: ='Resumo Ano'!E15 -> 38226745 | L43: ='Resumo Ano'!K15 -> 28652409
B44: =B43+1 -> 2024 | F44: ='Resumo Ano'!E16 -> 36479903 | L44: ='Resumo Ano'!K16 -> 27723921
B45: =B44+1 -> 2025 | F45: ='Resumo Ano'!E17 -> 27624713 | L45: ='Resumo Ano'!K17 -> 19662563
... B50: =B49+1 -> 2030 | F50: ='Resumo Ano'!E22 -> 0 | L50: ='Resumo Ano'!K22 -> 0
B51: TOTAL | F51: =SUM(F32:K50) -> 2.0563692e+08 | L51: =SUM(L32:R50) -> 1.6036295e+08

Sheet Fluxo - Com Terreno
D1: =+D8+E8+F8+G8 -> 8142 | T1: 1 | AA1: 542145.24 | AH1: 0 | AJ1: -1400 | AN1: =+AN8/AN4 -> #DIV/0! | AP1: =+#REF!*0.5% -> #REF! | AY1: 0.04 | BW1: =IRR(BW64:BW189,1%) -> #VALUE! | BX1: TAXA ALL IN MÊS
AP2: 25 | AQ2: -0.06 | AW2: 0.012 | AY2: 0.0673
A4: VERIFICAÇÃO | T4: 0 | BL4: =BL8-BF8 -> 0 | BM4: =BM8-BG8 -> #REF! | BN4: =BN8-BH8 -> #REF! | BW4: =(1+BW1)^12-1 -> #VALUE! | BX4: TAXA ALL IN ANO
G5: =+G8+F8+E8+D8 -> 8142 | V5: =+V8+T8 -> 3.6716603e+08 | Y5: =+V5+Y8 -> 3.7071246e+08 | AN5: 0.035 | CE5: 0.01
CB6: =MIN(CB64:CB190) -> #REF! | CC6: =MIN(CC64:CC190) -> #REF!
D7: VELOCIDADE DE VENDA | K7: RECEITA | Z7: OBRA | AJ7: COMERCIALIZAÇÃO | AQ7: ADMINISTRATIVO | AV7: DISTRATO DE VENDA | AW7: DESPESAS BANCÁRIAS | AX7: AQUISIÇÃO DO TERRENO | AY7: IMPOSTOS | AZ7: OUTRAS DESPESAS | BF7: RESUMO SEM ALAVANCAGEM | BK7: RESUMO ANO SEM ALAVANCAGEM | BQ7: FLUXO CRI | BY7: RESUMO COM ALAVANCAGEM | CE7: FLUXO A VP
A8: CRONOGRAMA | D8: =SUM(D10:D190) -> 2005 | E8: =SUM(E10:E190) -> 3964 | F8: =SUM(F10:F190) -> 728 | G8: =SUM(G10:G190) -> 1445 | H8: =SUM(H10:H190) -> 1.2860081e+08 | I8: =SUM(I10:I190) -> 34610760 | J8: =SUM(J10:J190) -> 1.4726964e+08 | K8: =SUM(K10:K190) -> 1.0904974e+08 | ... N8: =SUM(N10:N190) -> 42199126 | P8: =SUM(P10:P190) -> -11265591 | Q8: =SUM(Q10:Q190) -> 11265591 | R8: 0.005 | T8: =SUM(T10:T190) -> -243226.04 | V8: =SUM(V10:V190) -> 3.6740925e+08 | W8: =SUM(W10:W190) -> 1000000 | X8: =SUM(X10:X190) -> 1493512 | Y8: =SUM(Y10:Y190) -> 3546437.8 | Z8: =SUM(Z10:Z190) -> 1 | AA8: =SUM(AA10:AA190) -> -542145.24 | AB8: =SUM(AB10:AB190) -> -50570768 | AC8: =SUM(AC10:AC190) -> -3617594.9 | ... AZ8: =SUM(AZ10:AZ190) -> -174962.81 | BB8: =SUM(BB10:BB190) -> -16649.28 | BC8: =SUM(BC10:BC190) -> -1416300 | BD8: =SUM(BD10:BD190) -> -1290090.5 | BF8: =SUM(BF10:BF190) -> 3.734492e+08 | BG8: =SUM(BG10:BG190) -> #REF! | BH8: =SUM(BH10:BH190) -> #REF! | BL8: =SUM(BL10:BL28) -> 3.734492e+08 | BM8: =SUM(BM10:BM28) -> #REF! | BN8: =+BL8+BM8 -> #REF! | BQ8: =SUM(BQ10:BQ190) -> 45000000 | BR8: =SUM(BR10:BR190) -> #REF! | BS8: =SUM(BS10:BS190) -> -5183823.9 | BT8: =SUM(BT10:BT190) -> -5878257.8 | BU8: =SUM(BU10:BU190) -> -3.2287682e+08 | BV8: =SUM(BV10:BV190) -> 3.1987682e+08 | BW8: =SUM(BW10:BW190) -> #REF! | BX8: =SUM(BX10:BX190) -> #REF! | ... CA8: =SUM(CA10:CA190) -> #REF! | CE8: =SUM(CE10:CE190) -> #REF! | CF8: =SUM(CF10:CF190) -> #REF!
A9: N° | B9: EVENTO | C9: MESES | D9: Cotas 1/4 (2*) | E9: Cotas 1/4 (3*) | F9: Cotas 2/4 (2*) | G9: Cotas 2/4 (3*) | H9: VGV REALIZADO 3 SEMANA | I9: VGV REALIZADO 2 SEMANA | J9: VGV ESTOQUE | K9: ESTOQUE | L9: AGING DA CARTERIA | M9: RECUPERAÇÃO INADIMPLÊNCIA AGING | N9: RECEBIDO | O9: INADIMPLÊNCIA | Q9: RECUPERAÇÃO | R9: CORREÇÃO 0,5% | T9: JUROS /DESCONTO | V9: RECEITA TOTAL | W9: EMPRESTIMO PF | X9: EMP. MUTUO ENTRE EMPRESAS | Y9: OUTRAS ENTRADAS | Z9: % | AA9: AREA ANEXA | AB9: CRONOGRAMA OBRA | AC9: TAXA DE ADMINISTRAÇÃO | AD9: FF&E | AE9: INFRAESTRUTURA | AF9: PARQUE AQ. | AG9: PROJETO | AH9: LEGALIZAÇÃO OBRA | AI9: GERENCIAMENTO OBRA | AJ9: VENDAS GERAL | AK9: APTO MODELO | AL9: COMISSÃO WAM | AM9: CLUB CIA | AN9: FÉRIAS CLUB | AO9: PASSAPORTE | AP9: MARKETING | AQ9: GESTÃO DA CARTEIRA | AR9: HONORÁRIOS ADV | AS9: HONORÁRIOS CONTABEIS / AUDITORIA | AT9: CUSTO CARTORIO / TAXAS E REGISTROS | AU9: CORRESPONDÊNCIA E MALOTE | AV9: DISTRATO DE VENDA | AW9: DESPESAS BANCÁRIAS | AX9: AQUISIÇÃO DO TERRENO | AY9: IMPOSTOS | AZ9: DEPOSITO JUDICIAL | BA9: DISTRIBUIÇÃO | BB9: OUTRAS DESPESAS | BC9: EMPRESTIMO EMPRESAS LIGADAS E PF - PJ | BD9: EMP. MUTUO ENTRE EMPRESAS | BF9: TOTAL RECEITA | BG9: TOTAL DESPESAS | BH9: SALDO MENSAL | BI9: SALDO ACUMULADO | BK9: ANO | BL9: TOTAL RECEITA | BM9: TOTAL DESPESAS | BN9: SALDO MENSAL | BO9: SALDO ACUMULADO | BQ9: LIBERAÇÃO DAS TRANCHES CONFORME MEDIÇÃO DE OBRA | BR9: PMT (AMORTIZAÇÃO + JUROS) | BS9: DESPESAS RECORRENTES / DESPESAS GESTÃO | BT9: CUSTOS FLAT - ESTRUTURAÇÃO | BU9: DEVOLUÇÃO DA CARTEIRA | BV9: DEVOLUÇÃO DO EXCEDENTE | BW9: FLUXO MENSAL ECONOMICO | BX9: FLUXO MENSAL FINANCEIRO | BY9: TOTAL RECEITA | BZ9: TOTAL DESPESAS | CA9: SALDO MENSAL | CB9: FLUXO ACUMULADO | CE9: FLUXO SEM CRI | CF9: FLUXO COM CRI
A10: 0 | C10: 41671 | D10: 0 | E10: 0 | F10: 0 | G10: 0 | H10: 0 | I10: 0 | J10: 0 | K10: 0 | L10: 0 | M10: 0 | N10: 0 | O10: 0 | P10: 0 | Q10: 0 | T10: 0 | V10: =SUM(P10:T10,K10:N10) -> 0 | W10: 0 | X10: 0 | Y10: 1000 | Z10: =IFERROR(SUM(AA10:AH10)/SUM($AA$8:$AH$8),0) -> 0 | AA10: 0 | AB10: 0 | AD10: 0 | AE10: 0 | AG10: 0 | AH10: 0 | AI10: 0 | AJ10: 0 | AK10: 0 | AL10: 0 | AM10: 0 | AN10: 0 | AO10: 0 | AP10: 0 | AQ10: 0 | AR10: 0 | AS10: 0 | AT10: 0 | AU10: 0 | AV10: 0 | AW10: 0 | AX10: -3900000 | AY10: 0 | AZ10: 0 | BA10: 0 | BB10: 0 | BC10: 0 | BD10: 0 | BF10: =V10+Y10+W10+X10 -> 1000 | BG10: =+SUM(AA10:BD10) -> -3900000 | BH10: =SUM(BF10:BG10) -> -3899000 | BI10: =+BH10 -> -3899000 | BJ10: =+BI10-$AX$8 -> 3127198.5 | BK10: 2014 | BL10: =SUMIFS($BF$10:$BF$208,$C$10:$C$208,">="&DATE(BK10,1,1),$C$10:$C$208,"<="&DATE(BK10,12,31)) -> 1964634 | BM10: =SUMIFS($BG$10:$BG$208,$C$10:$C$208,">="&DATE(BK10,1,1),$C$10:$C$208,"<="&DATE(BK10,12,31)) -> -8922532.7 | BN10: =SUM(BL10:BM10) -> -6957898.8 | BO10: =BN10 -> -6957898.8 | BQ10: 0 | BR10: 0 | BS10: 0 | BT10: 0 | BU10: 0 | BW10: =SUM(BQ10:BU10) -> 0 | BX10: 0 | BY10: =BF10 -> 1000 | BZ10: =BG10 -> -3900000 | CA10: =BH10 -> -3899000 | CB10: =BI10 -> -3899000 | CE10: =PV($CE$5,A10,,-BH10) -> -3899000 | CF10: =PV($CE$5,A10,,-CA10) -> -3899000
A11: 0 | C11: 41699 | D11: 0 | E11: 0 | F11: 0 | G11: 0 | H11: 0 | I11: 0 | J11: 0 | K11: 0 | L11: 0 | M11: 0 | N11: 0 | O11: 0 | P11: 0 | Q11: 0 | T11: 0 | V11: =SUM(P11:T11,K11:N11) -> 0 | W11: 0 | X11: 0 | Y11: 0 | Z11: =IFERROR(SUM(AA11:AH11)/SUM($AA$8:$AH$8),0) -> 0 | AA11: 0 | AB11: 0 | AD11: 0 | AE11: 0 | AG11: 0 | AH11: 0 | AI11: 0 | AJ11: 0 | AK11: 0 | AL11: 0 | AM11: 0 | AN11: 0 | AO11: 0 | AP11: 0 | AQ11: 0 | AR11: 0 | AS11: 0 | AT11: 0 | AU11: 0 | AV11: 0 | AW11: 0 | AX11: 0 | AY11: 0 | AZ11: 0 | BA11: 0 | BB11: 0 | BC11: 0 | BD11: 0 | BF11: =V11+Y11+W11+X11 -> 0 | BG11: =+SUM(AA11:BD11) -> 0 | BH11: =SUM(BF11:BG11) -> 0 | BI11: =BH11+BI10 -> -3899000 | BJ11: =+BI11-$AX$8 -> 3127198.5 | BK11: 2015 | BL11: =SUMIFS($BF$10:$BF$208,$C$10:$C$208,">="&DATE(BK11,1,1),$C$10:$C$208,"<="&DATE(BK11,12,31)) -> 5679311.6 | BM11: =SUMIFS($BG$10:$BG$208,$C$10:$C$208,">="&DATE(BK11,1,1),$C$10:$C$208,"<="&DATE(BK11,12,31)) -> -5692558.5 | BN11: =SUM(BL11:BM11) -> -13246.93 | BO11: =+BN11+BO10 -> -6971145.7 | BQ11: 0 | BR11: 0 | BS11: 0 | BT11: 0 | BU11: 0 | BW11: =SUM(BQ11:BT11) -> 0 | BX11: 0 | BY11: =BF11 -> 0 | BZ11: =BG11 -> 0 | CA11: =BH11 -> 0 | CB11: =BI11 -> -3899000 | CE11: =PV($CE$5,A11,,-BH11) -> 0 | CF11: =PV($CE$5,A11,,-CA11) -> 0
A12: 0 | C12: 41730 | D12: 0 | E12: 0 | F12: 0 | G12: 0 | H12: 0 | I12: 0 | J12: 0 | K12: 0 | L12: 0 | M12: 0 | N12: 0 | O12: 0 | P12: 0 | Q12: 0 | T12: 0 | V12: =SUM(P12:T12,K12:N12) -> 0 | W12: 0 | X12: 0 | Y12: 9245.14 | Z12: =IFERROR(SUM(AA12:AH12)/SUM($AA$8:$AH$8),0) -> 0.00010590902 | AA12: 0 | AB12: -547.69 | AD12: 0 | AE12: 0 | AG12: 0 | AH12: -7130.41 | AI12: 0 | AJ12: 0 | AK12: -1567.04 | AL12: 0 | AM12: 0 | AN12: 0 | AO12: 0 | AP12: 0 | AQ12: 0 | AR12: 0 | AS12: 0 | AT12: 0 | AU12: 0 | AV12: 0 | AW12: 0 | AX12: -1550000 | AY12: 0 | AZ12: 0 | BA12: 0 | BB12: 0 | BC12: 0 | BD12: 0 | BF12: =V12+Y12+W12+X12 -> 9245.14 | BG12: =+SUM(AA12:BD12) -> -1559245.1 | BH12: =SUM(BF12:BG12) -> -1550000 | BI12: =BH12+BI11 -> -5449000 | BJ12: =+BI12-$AX$8 -> 1577198.5 | BK12: 2016 | BL12: =SUMIFS($BF$10:$BF$208,$C$10:$C$208,">="&DATE(BK12,1,1),$C$10:$C$208,"<="&DATE(BK12,12,31)) -> 10104711 | BM12: =SUMIFS($BG$10:$BG$208,$C$10:$C$208,">="&DATE(BK12,1,1),$C$10:$C$208,"<="&DATE(BK12,12,31)) -> -10062564 | BN12: =SUM(BL12:BM12) -> 42146.14 | BO12: =BN12+BO11 -> -6928999.5 | BQ12: 0 | BR12: 0 | BS12: 0 | BT12: 0 | BU12: 0 | BW12: =SUM(BQ12:BT12) -> 0 | BX12: 0 | BY12: =BF12 -> 9245.14 | BZ12: =BG12 -> -1559245.1 | CA12: =BH12 -> -1550000 | CB12: =BI12 -> -5449000 | CE12: =PV($CE$5,A12,,-BH12) -> -1550000 | CF12: =PV($CE$5,A12,,-CA12) -> -1550000
A13: 0 | C13: 41760 | D13: 0 | E13: 0 | F13: 0 | G13: 0 | H13: 0 | I13: 0 | J13: 0 | K13: 0 | L13: 0 | M13: 0 | N13: 0 | O13: 0 | P13: 0 | Q13: 0 | T13: 0 | V13: =SUM(P13:T13,K13:N13) -> 0 | W13: 0 | X13: 46553.47 | Y13: 146407.45 | Z13: =IFERROR(SUM(AA13:AH13)/SUM($AA$8:$AH$8),0) -> 0.0015025763 | AA13: 0 | AB13: -43 | AD13: 0 | AE13: 0 | AG13: -19866.8 | AH13: -89022.67 | AI13: 0 | AJ13: 0 | AK13: -31126.25 | AL13: 0 | AM13: 0 | AN13: 0 | AO13: 0 | AP13: 0 | AQ13: 0 | AR13: 0 | AS13: 0 | AT13: 0 | AU13: 0 | AV13: 0 | AW13: -1700.03 | AX13: 0 | AY13: 0 | AZ13: 0 | BA13: 0 | BB13: 0 | BC13: 0 | BD13: -46553.47 | BF13: =V13+Y13+W13+X13 -> 192960.92 | BG13: =+SUM(AA13:BD13) -> -188312.22 | BH13: =SUM(BF13:BG13) -> 4648.7 | BI13: =BH13+BI12 -> -5444351.3 | BJ13: =+BI13-$AX$8 -> 1581847.2 | BK13: 2017 | BL13: =SUMIFS($BF$10:$BF$208,$C$10:$C$208,">="&DATE(BK13,1,1),$C$10:$C$208,"<="&DATE(BK13,12,31)) -> 19056114 | BM13: =SUMIFS($BG$10:$BG$208,$C$10:$C$208,">="&DATE(BK13,1,1),$C$10:$C$208,"<="&DATE(BK13,12,31)) -> -19083900 | BN13: =SUM(BL13:BM13) -> -27785.75 | BO13: =BN13+BO12 -> -6956785.3 | BQ13: 0 | BR13: 0 | BS13: 0 | BT13: 0 | BU13: 0 | BW13: =SUM(BQ13:BT13) -> 0 | BX13: 0 | BY13: =BF13 -> 192960.92 | BZ13: =BG13 -> -188312.22 | CA13: =BH13 -> 4648.7 | CB13: =BI13 -> -5444351.3 | CE13: =PV($CE$5,A13,,-BH13) -> 4648.7 | CF13: =PV($CE$5,A13,,-CA13) -> 4648.7
A14: 0 | C14: 41791 | D14: 0 | E14: 0 | F14: 0 | G14: 0 | H14: 0 | I14: 0 | J14: 0 | K14: 0 | L14: 0 | M14: 0 | N14: 0 | O14: 0 | P14: 0 | Q14: 0 | T14: 0 | V14: =SUM(P14:T14,K14:N14) -> 0 | W14: 0 | X14: 3142.34 | Y14: 56935.17 | Z14: =IFERROR(SUM(AA14:AH14)/SUM($AA$8:$AH$8),0) -> 6.5519836e-05 | AA14: 0 | AB14: 0 | AD14: 0 | AE14: 0 | AG14: -4750 | AH14: 0 | AI14: 0 | AJ14: -19463 | AK14: -25096.9 | AL14: 0 | AM14: 0 | AN14: 0 | AO14: 0 | AP14: 0 | AQ14: 0 | AR14: 0 | AS14: 0 | AT14: 0 | AU14: 0 | AV14: 0 | AW14: -1978.83 | AX14: -1576198.5 | AY14: 0 | AZ14: 0 | BA14: 0 | BB14: 0 | BC14: 0 | BD14: -3142.34 | BF14: =V14+Y14+W14+X14 -> 60077.51 | BG14: =+SUM(AA14:BD14) -> -1630629.6 | BH14: =SUM(BF14:BG14) -> -1570552.1 | BI14: =BH14+BI13 -> -7014903.4 | BJ14: =+BI14-$AX$8 -> 11295.14 | BK14: 2018 | BL14: =SUMIFS($BF$10:$BF$208,$C$10:$C$208,">="&DATE(BK14,1,1),$C$10:$C$208,"<="&DATE(BK14,12,31)) -> 22640314 | BM14: =SUMIFS($BG$10:$BG$208,$C$10:$C$208,">="&DATE(BK14,1,1),$C$10:$C$208,"<="&DATE(BK14,12,31)) -> #REF! | BN14: =SUM(BL14:BM14) -> #REF! | BO14: =BN14+BO13 -> #REF! | BQ14: 0 | BR14: 0 | BS14: 0 | BT14: 0 | BU14: 0 | BW14: =SUM(BQ14:BT14) -> 0 | BX14: 0 | BY14: =BF14 -> 60077.51 | BZ14: =BG14 -> -1630629.6 | CA14: =BH14 -> -1570552.1 | CB14: =BI14 -> -7014903.4 | CE14: =PV($CE$5,A14,,-BH14) -> -1570552.1 | CF14: =PV($CE$5,A14,,-CA14) -> -1570552.1
A15: 0 | C15: 41821 | D15: 0 | E15: 0 | F15: 0 | G15: 0 | H15: 0 | I15: 0 | J15: 0 | K15: 0 | L15: 0 | M15: 0 | N15: 0 | O15: 0 | P15: 0 | Q15: 0 | T15: 0 | V15: =SUM(P15:T15,K15:N15) -> 0 | W15: 0 | X15: 3568.76 | Y15: 235374.71 | Z15: =IFERROR(SUM(AA15:AH15)/SUM($AA$8:$AH$8),0) -> 0.00069883126 | AA15: 0 | AB15: 9.094947e-13 | AD15: 0 | AE15: 0 | AG15: -44043.55 | AH15: -6619.71 | AI15: 0 | AJ15: -5433.1 | AK15: -69333.75 | AL15: 0 | AM15: 0 | AN15: 0 | AO15: 0 | AP15: -36373 | AQ15: 0 | AR15: 0 | AS15: 0 | AT15: -79.68 | AU15: 0 | AV15: 0 | AW15: -3592.24 | AX15: 0 | AY15: 0 | AZ15: 0 | BA15: 0 | BB15: 0 | BC15: 0 | BD15: -40372.48 | BF15: =V15+Y15+W15+X15 -> 238943.47 | BG15: =+SUM(AA15:BD15) -> -205847.51 | BH15: =SUM(BF15:BG15) -> 33095.96 | BI15: =BH15+BI14 -> -6981807.4 | BJ15: =+BI15-$AX$8 -> 44391.1 | BK15: =BK14+1 -> 2019 | BL15: =SUMIFS($BF$10:$BF$208,$C$10:$C$208,">="&DATE(BK15,1,1),$C$10:$C$208,"<="&DATE(BK15,12,31)) -> 39597442 | BM15: =SUMIFS($BG$10:$BG$208,$C$10:$C$208,">="&DATE(BK15,1,1),$C$10:$C$208,"<="&DATE(BK15,12,31)) -> #REF! | BN15: =SUM(BL15:BM15) -> #REF! | BO15: =BN15+BO14 -> #REF! | BQ15: 0 | BR15: 0 | BS15: 0 | BT15: 0 | BU15: 0 | BW15: =SUM(BQ15:BT15) -> 0 | BX15: 0 | BY15: =BF15 -> 238943.47 | BZ15: =BG15 -> -205847.51 | CA15: =BH15 -> 33095.96 | CB15: =BI15 -> -6981807.4 | CE15: =PV($CE$5,A15,,-BH15) -> 33095.96 | CF15: =PV($CE$5,A15,,-CA15) -> 33095.96
A16: 0 | C16: 41852 | D16: 0 | E16: 0 | F16: 0 | G16: 0 | H16: 0 | I16: 0 | J16: 0 | K16: 0 | L16: 0 | M16: 0 | N16: 0 | O16: 0 | P16: 0 | Q16: 0 | T16: 0 | V16: =SUM(P16:T16,K16:N16) -> 0 | W16: 0 | X16: 0 | Y16: 281736.14 | Z16: =IFERROR(SUM(AA16:AH16)/SUM($AA$8:$AH$8),0) -> 0.00076911542 | AA16: 0 | AB16: 0 | AD16: 0 | AE16: 0 | AG16: -55758.66 | AH16: 0 | AI16: 0 | AJ16: -10637.93 | AK16: -57446.09 | AL16: 0 | AM16: 0 | AN16: 0 | AO16: 0 | AP16: -194500 | AQ16: 0 | AR16: 0 | AS16: 0 | AT16: 0 | AU16: 0 | AV16: 0 | AW16: -2518.77 | AX16: 0 | AY16: 0 | AZ16: 0 | BA16: 0 | BB16: 0 | BC16: 0 | BD16: 0 | BF16: =V16+Y16+W16+X16 -> 281736.14 | BG16: =+SUM(AA16:BD16) -> -320861.45 | BH16: =SUM(BF16:BG16) -> -39125.31 | BI16: =BH16+BI15 -> -7020932.8 | BJ16: =+BI16-$AX$8 -> 5265.79 | BK16: =BK15+1 -> 2020 | BL16: =SUMIFS($BF$10:$BF$208,$C$10:$C$208,">="&DATE(BK16,1,1),$C$10:$C$208,"<="&DATE(BK16,12,31)) -> 46601516 | BM16: =SUMIFS($BG$10:$BG$208,$C$10:$C$208,">="&DATE(BK16,1,1),$C$10:$C$208,"<="&DATE(BK16,12,31)) -> #REF! | BN16: =SUM(BL16:BM16) -> #REF! | BO16: =BN16+BO15 -> #REF! | BQ16: 0 | BR16: 0 | BS16: 0 | BT16: 0 | BU16: 0 | BW16: =SUM(BQ16:BT16) -> 0 | BX16: 0 | BY16: =BF16 -> 281736.14 | BZ16: =BG16 -> -320861.45 | CA16: =BH16 -> -39125.31 | CB16: =BI16 -> -7020932.8 | CE16: =PV($CE$5,A16,,-BH16) -> -39125.31 | CF16: =PV($CE$5,A16,,-CA16) -> -39125.31
A17: 0 | C17: 41883 | D17: 0 | E17: 0 | F17: 0 | G17: 0 | H17: 0 | I17: 0 | J17: 0 | K17: 0 | L17: 0 | M17: 0 | N17: 0 | O17: 0 | P17: 0 | Q17: 0 | T17: 0 | V17: =SUM(P17:T17,K17:N17) -> 0 | W17: 0 | X17: 0 | Y17: 294606.73 | Z17: =IFERROR(SUM(AA17:AH17)/SUM($AA$8:$AH$8),0) -> 0.00082523723 | AA17: 0 | AB17: 0 | AD17: 0 | AE17: 0 | AG17: -59827.33 | AH17: 0 | AI17: 0 | AJ17: -15750 | AK17: -100881.25 | AL17: 0 | AM17: 0 | AN17: 0 | AO17: 0 | AP17: -71899.19 | AQ17: -2966 | AR17: 0 | AS17: 0 | AT17: -438.24 | AU17: 0 | AV17: 0 | AW17: -1547.75 | AX17: 0 | AY17: -683 | AZ17: 0 | BA17: 0 | BB17: 0 | BC17: 0 | BD17: 0 | BF17: =V17+Y17+W17+X17 -> 294606.73 | BG17: =+SUM(AA17:BD17) -> -253992.76 | BH17: =SUM(BF17:BG17) -> 40613.97 | BI17: =BH17+BI16 -> -6980318.8 | BJ17: =+BI17-$AX$8 -> 45879.76 | BK17: =BK16+1 -> 2021 | BL17: =SUMIFS($BF$10:$BF$208,$C$10:$C$208,">="&DATE(BK17,1,1),$C$10:$C$208,"<="&DATE(BK17,12,31)) -> 47152874 | BM17: =SUMIFS($BG$10:$BG$208,$C$10:$C$208,">="&DATE(BK17,1,1),$C$10:$C$208,"<="&DATE(BK17,12,31)) -> #REF! | BN17: =SUM(BL17:BM17) -> #REF! | BO17: =BN17+BO16 -> #REF! | BQ17: 0 | BR17: 0 | BS17: 0 | BT17: 0 | BU17: 0 | BW17: =SUM(BQ17:BT17) -> 0 | BX17: 0 | BY17: =BF17 -> 294606.73 | BZ17: =BG17 -> -253992.76 | CA17: =BH17 -> 40613.97 | CB17: =BI17 -> -6980318.8 | CE17: =PV($CE$5,A17,,-BH17) -> 40613.97 | CF17: =PV($CE$5,A17,,-CA17) -> 40613.97
A18: 0 | C18: 41913 | D18: 0 | E18: 0 | F18: 0 | G18: 0 | H18: 0 | I18: 0 | J18: 0 | K18: 0 | L18: 0 | M18: 0 | N18: 0 | O18: 0 | P18: 0 | Q18: 0 | T18: 0 | V18: =SUM(P18:T18,K18:N18) -> 0 | W18: 0 | X18: 41112.59 | Y18: 336906.22 | Z18: =IFERROR(SUM(AA18:AH18)/SUM($AA$8:$AH$8),0) -> 0.0037541002 | AA18: 0 | AB18: 0 | AD18: 0 | AE18: 0 | AG18: -51859.52 | AH18: -220301.97 | AI18: 0 | AJ18: 0 | AK18: -27325.44 | AL18: 0 | AM18: 0 | AN18: 0 | AO18: 0 | AP18: -63850 | AQ18: -2653.45 | AR18: 0 | AS18: 0 | AT18: 0 | AU18: 0 | AV18: 0 | AW18: -1170.19 | AX18: 0 | AY18: 0 | AZ18: 0 | BA18: 0 | BB18: 0 | BC18: 0 | BD18: 0 | BF18: =V18+Y18+W18+X18 -> 378018.81 | BG18: =+SUM(AA18:BD18) -> -367160.57 | BH18: =SUM(BF18:BG18) -> 10858.24 | BI18: =BH18+BI17 -> -6969460.5 | BJ18: =+BI18-$AX$8 -> 56738 | BK18: =BK17+1 -> 2022 | BL18: =SUMIFS($BF$10:$BF$208,$C$10:$C$208,">="&DATE(BK18,1,1),$C$10:$C$208,"<="&DATE(BK18,12,31)) -> 46217630 | BM18: =SUMIFS($BG$10:$BG$208,$C$10:$C$208,">="&DATE(BK18,1,1),$C$10:$C$208,"<="&DATE(BK18,12,31)) -> #REF! | BN18: =SUM(BL18:BM18) -> #REF! | BO18: =BN18+BO17 -> #REF! | BQ18: 0 | BR18: 0 | BS18: 0 | BT18: 0 | BU18: 0 | BW18: =SUM(BQ18:BT18) -> 0 | BX18: 0 | BY18: =BF18 -> 378018.81 | BZ18: =BG18 -> -367160.57 | CA18: =BH18 -> 10858.24 | CB18: =BI18 -> -6969460.5 | CE18: =PV($CE$5,A18,,-BH18) -> 10858.24 | CF18: =PV($CE$5,A18,,-CA18) -> 10858.24
A19: 0 | C19: 41944 | D19: 0 | E19: 0 | F19: 0 | G19: 0 | H19: 0 | I19: 0 | J19: 0 | K19: 0 | L19: 0 | M19: 0 | N19: 0 | O19: 0 | P19: 0 | Q19: 0 | T19: 0 | V19: =SUM(P19:T19,K19:N19) -> 0 | W19: 0 | X19: 0 | Y19: 334185.6 | Z19: =IFERROR(SUM(AA19:AH19)/SUM($AA$8:$AH$8),0) -> 0.003555496 | AA19: 0 | AB19: 0 | AD19: 0 | AE19: 0 | AG19: -37590.5 | AH19: -220172.75 | AI19: 0 | AJ19: -6000 | AK19: -19423.36 | AL19: 0 | AM19: 0 | AN19: 0 | AO19: 0 | AP19: -44398 | AQ19: -1000 | AR19: 0 | AS19: 0 | AT19: -2067.43 | AU19: 0 | AV19: 0 | AW19: -856.52 | AX19: 0 | AY19: 0 | AZ19: 0 | BA19: 0 | BB19: 0 | BC19: 0 | BD19: -30000 | BF19: =V19+Y19+W19+X19 -> 334185.6 | BG19: =+SUM(AA19:BD19) -> -361508.56 | BH19: =SUM(BF19:BG19) -> -27322.96 | BI19: =BH19+BI18 -> -6996783.5 | BJ19: =+BI19-$AX$8 -> 29415.04 | BK19: =BK18+1 -> 2023 | BL19: =SUMIFS($BF$10:$BF$208,$C$10:$C$208,">="&DATE(BK19,1,1),$C$10:$C$208,"<="&DATE(BK19,12,31)) -> 44413686 | BM19: =SUMIFS($BG$10:$BG$208,$C$10:$C$208,">="&DATE(BK19,1,1),$C$10:$C$208,"<="&DATE(BK19,12,31)) -> #REF! | BN19: =SUM(BL19:BM19) -> #REF! | BO19: =BN19+BO18 -> #REF! | BQ19: 0 | BR19: 0 | BS19: 0 | BT19: 0 | BU19: 0 | BW19: =SUM(BQ19:BT19) -> 0 | BX19: 0 | BY19: =BF19 -> 334185.6 | BZ19: =BG19 -> -361508.56 | CA19: =BH19 -> -27322.96 | CB19: =BI19 -> -6996783.5 | CE19: =PV($CE$5,A19,,-BH19) -> -27322.96 | CF19: =PV($CE$5,A19,,-CA19) -> -27322.96
A20: 0 | B20: LANÇAMENTO | C20: 41974 | D20: 0 | E20: 41 | F20: 0 | G20: 57 | H20: 3194201.4 | I20: 0 | J20: 0 | K20: 0 | L20: 0 | M20: 0 | N20: 0 | O20: 0 | P20: 0 | Q20: 0 | T20: 0 | V20: =SUM(P20:T20,K20:N20) -> 0 | W20: 0 | X20: 30000 | Y20: 143859.64 | Z20: =IFERROR(SUM(AA20:AH20)/SUM($AA$8:$AH$8),0) -> 0.001011711 | AA20: 0 | AB20: 0 | AD20: 0 | AE20: 0 | AG20: -53346.14 | AH20: -20000 | AI20: 0 | AJ20: -10380 | AK20: -12393.67 | AL20: 0 | AM20: 0 | AN20: 0 | AO20: 0 | AP20: -31120 | AQ20: -144.8 | AR20: 0 | AS20: 0 | AT20: 0 | AU20: 0 | AV20: 0 | AW20: -755.61 | AX20: 0 | AY20: 0 | AZ20: 0 | BA20: 0 | BB20: 0 | BC20: 0 | BD20: -6834.67 | BF20: =V20+Y20+W20+X20 -> 173859.64 | BG20: =+SUM(AA20:BD20) -> -134974.89 | BH20: =SUM(BF20:BG20) -> 38884.75 | BI20: =BH20+BI19 -> -6957898.8 | BJ20: =+BI20-$AX$8 -> 68299.79 | BK20: =BK19+1 -> 2024 | BL20: =SUMIFS($BF$10:$BF$208,$C$10:$C$208,">="&DATE(BK20,1,1),$C$10:$C$208,"<="&DATE(BK20,12,31)) -> 42316319 | BM20: =SUMIFS($BG$10:$BG$208,$C$10:$C$208,">="&DATE(BK20,1,1),$C$10:$C$208,"<="&DATE(BK20,12,31)) -> #REF! | BN20: =SUM(BL20:BM20) -> #REF! | BO20: =BN20+BO19 -> #REF! | BQ20: 0 | BR20: 0 | BS20: 0 | BT20: 0 | BU20: 0 | BW20: =SUM(BQ20:BT20) -> 0 | BX20: 0 | BY20: =BF20 -> 173859.64 | BZ20: =BG20 -> -134974.89 | CA20: =BH20 -> 38884.75 | CB20: =BI20 -> -6957898.8 | CE20: =PV($CE$5,A20,,-BH20) -> 38884.75 | CF20: =PV($CE$5,A20,,-CA20) -> 38884.75
A21: 0 | C21: 42005 | D21: 0 | E21: 54 | F21: 0 | G21: 72 | H21: 4293670.3 | I21: 0 | J21: 0 | K21: 0 | L21: 0 | M21: 0 | N21: 22762.72 | O21: 0 | P21: 0 | Q21: 0 | T21: 37.38 | V21: =SUM(P21:T21,K21:N21) -> 22800.1 | W21: 0 | X21: 0 | Y21: 106536.84 | Z21: =IFERROR(SUM(AA21:AH21)/SUM($AA$8:$AH$8),0) -> 0.00061989806 | AA21: 0 | AB21: -1275 | AD21: 0 | AE21: 0 | AG21: -42180.83 | AH21: -1485 | AI21: 0 | AJ21: -10124 | AK21: -7680.33 | AL21: 0 | AM21: 0 | AN21: 0 | AO21: 0 | AP21: -59703.96 | AQ21: -1250 | AR21: 0 | AS21: 0 | AT21: 0 | AU21: 0 | AV21: 0 | AW21: -2488.7 | AX21: 0 | AY21: 0 | AZ21: 0 | BA21: 0 | BB21: 0 | BC21: 0 | BD21: 0 | BF21: =V21+Y21+W21+X21 -> 129336.94 | BG21: =+SUM(AA21:BD21) -> -126187.82 | BH21: =SUM(BF21:BG21) -> 3149.12 | BI21: =BH21+BI20 -> -6954749.6 | BJ21: =+BI21-$AX$8 -> 71448.91 | BK21: =BK20+1 -> 2025 | BL21: =SUMIFS($BF$10:$BF$208,$C$10:$C$208,">="&DATE(BK21,1,1),$C$10:$C$208,"<="&DATE(BK21,12,31)) -> 32113099 | BM21: =SUMIFS($BG$10:$BG$208,$C$10:$C$208,">="&DATE(BK21,1,1),$C$10:$C$208,"<="&DATE(BK21,12,31)) -> #REF! | BN21: =SUM(BL21:BM21) -> #REF! | BO21: =BN21+BO20 -> #REF! | BQ21: 0 | BR21: 0 | BS21: 0 | BT21: 0 | BU21: 0 | BW21: =SUM(BQ21:BT21) -> 0 | BX21: 0 | BY21: =BF21 -> 129336.94 | BZ21: =BG21 -> -126187.82 | CA21: =BH21 -> 3149.12 | CB21: =BI21 -> -6954749.6 | CE21: =PV($CE$5,A21,,-BH21) -> 3149.12 | CF21: =PV($CE$5,A21,,-CA21) -> 3149.12
A22: 0 | C22: 42036 | D22: 0 | E22: 27 | F22: 0 | G22: 22 | H22: 1623277.5 | I22: 0 | J22: 0 | K22: 0 | L22: 0 | M22: 0 | N22: 68289.21 | O22: 0 | P22: 0 | Q22: 0 | T22: 192.54 | V22: =SUM(P22:T22,K22:N22) -> 68481.75 | W22: 0 | X22: 40000 | Y22: 171915.91 | Z22: =IFERROR(SUM(AA22:AH22)/SUM($AA$8:$AH$8),0) -> 0.00058492799 | AA22: 0 | AB22: -8277.22 | AD22: 0 | AE22: 0 | AG22: -34085 | AH22: -43.38 | AI22: 0 | AJ22: -6290 | AK22: -12559.04 | AL22: -77739.84 | AM22: 0 | AN22: 0 | AO22: -20000 | AP22: -136044.76 | AQ22: -483.6 | AR22: 0 | AS22: 0 | AT22: -13142.08 | AU22: 0 | AV22: 0 | AW22: -6153.63 | AX22: 0 | AY22: -830.84 | AZ22: 0 | BA22: 0 | BB22: 0 | BC22: 0 | BD22: 0 | BF22: =V22+Y22+W22+X22 -> 280397.66 | BG22: =+SUM(AA22:BD22) -> -315649.39 | BH22: =SUM(BF22:BG22) -> -35251.73 | BI22: =BH22+BI21 -> -6990001.4 | BJ22: =+BI22-$AX$8 -> 36197.18 | BK22: =BK21+1 -> 2026 | BL22: =SUMIFS($BF$10:$BF$208,$C$10:$C$208,">="&DATE(BK22,1,1),$C$10:$C$208,"<="&DATE(BK22,12,31)) -> 12337893 | BM22: =SUMIFS($BG$10:$BG$208,$C$10:$C$208,">="&DATE(BK22,1,1),$C$10:$C$208,"<="&DATE(BK22,12,31)) -> #REF! | BN22: =SUM(BL22:BM22) -> #REF! | BO22: =BN22+BO21 -> #REF! | BQ22: 0 | BR22: 0 | BS22: 0 | BT22: 0 | BU22: 0 | BW22: =SUM(BQ22:BT22) -> 0 | BX22: 0 | BY22: =BF22 -> 280397.66 | BZ22: =BG22 -> -315649.39 | CA22: =BH22 -> -35251.73 | CB22: =BI22 -> -6990001.4 | CE22: =PV($CE$5,A22,,-BH22) -> -35251.73 | CF22: =PV($CE$5,A22,,-CA22) -> -35251.73
A23: 0 | C23: 42064 | D23: 0 | E23: 7 | F23: 0 | G23: 9 | H23: 544488 | I23: 0 | J23: 0 | K23: 0 | L23: 0 | M23: 0 | N23: 187309.38 | O23: 0 | P23: 0 | Q23: 0 | T23: 1073.48 | V23: =SUM(P23:T23,K23:N23) -> 188382.86 | W23: 0 | X23: 0 | Y23: 361130.16 | Z23: =IFERROR(SUM(AA23:AH23)/SUM($AA$8:$AH$8),0) -> 0.00069120227 | AA23: 0 | AB23: -9603.18 | AD23: 0 | AE23: 0 | AG23: -40507 | AH23: 0 | AI23: 0 | AJ23: -6000 | AK23: -10026.14 | AL23: -147088.77 | AM23: 0 | AN23: 0 | AO23: 0 | AP23: -150712.89 | AQ23: 0 | AR23: 0 | AS23: 0 | AT23: -24511.16 | AU23: -4973.2 | AV23: 0 | AW23: -872.34 | AX23: 0 | AY23: -2492.56 | AZ23: 0 | BA23: 0 | BB23: 0 | BC23: 0 | BD23: -40000 | BF23: =V23+Y23+W23+X23 -> 549513.02 | BG23: =+SUM(AA23:BD23) -> -436787.24 | BH23: =SUM(BF23:BG23) -> 112725.78 | BI23: =BH23+BI22 -> -6877275.6 | BJ23: =+BI23-$AX$8 -> 148922.96 | BK23: =BK22+1 -> 2027 | BL23: =SUMIFS($BF$10:$BF$208,$C$10:$C$208,">="&DATE(BK23,1,1),$C$10:$C$208,"<="&DATE(BK23,12,31)) -> 3074450 | BM23: =SUMIFS($BG$10:$BG$208,$C$10:$C$208,">="&DATE(BK23,1,1),$C$10:$C$208,"<="&DATE(BK23,12,31)) -> #REF! | BN23: =SUM(BL23:BM23) -> #REF! | BO23: =BN23+BO22 -> #REF! | BQ23: 0 | BR23: 0 | BS23: 0 | BT23: 0 | BU23: 0 | BW23: =SUM(BQ23:BT23) -> 0 | BX23: 0 | BY23: =BF23 -> 549513.02 | BZ23: =BG23 -> -436787.24 | CA23: =BH23 -> 112725.78 | CB23: =BI23 -> -6877275.6 | CE23: =PV($CE$5,A23,,-BH23) -> 112725.78 | CF23: =PV($CE$5,A23,,-CA23) -> 112725.78
A24: 0 | C24: 42095 | D24: 0 | E24: 18 | F24: 0 | G24: 26 | H24: 1575588.2 | I24: 0 | J24: 0 | K24: 0 | L24: 0 | M24: 0 | N24: 237247.2 | O24: 0 | P24: 0 | Q24: 0 | T24: 1678.86 | V24: =SUM(P24:T24,K24:N24) -> 238926.06 | W24: 0 | X24: 4948.26 | Y24: 148490.04 | Z24: =IFERROR(SUM(AA24:AH24)/SUM($AA$8:$AH$8),0) -> 0.00069491593 | AA24: 0 | AB24: -3551.4 | AD24: 0 | AE24: 0 | AG24: -46828.01 | AH24: 0 | AI24: 0 | AJ24: -6000 | AK24: -7071.64 | AL24: -110158.26 | AM24: -6392.22 | AN24: 0 | AO24: -168237.34 | AP24: -118783.71 | AQ24: -4875.2 | AR24: 0 | AS24: 0 | AT24: -30265.88 | AU24: -3500.45 | AV24: 0 | AW24: -2363.12 | AX24: 0 | AY24: -9056.6 | AZ24: 0 | BA24: 0 | BB24: 0 | BC24: 0 | BD24: -4948.26 | BF24: =V24+Y24+W24+X24 -> 392364.36 | BG24: =+SUM(AA24:BD24) -> -522032.09 | BH24: =SUM(BF24:BG24) -> -129667.73 | BI24: =BH24+BI23 -> -7006943.3 | BJ24: =+BI24-$AX$8 -> 19255.23 | BK24: =BK23+1 -> 2028 | BL24: =SUMIFS($BF$10:$BF$208,$C$10:$C$208,">="&DATE(BK24,1,1),$C$10:$C$208,"<="&DATE(BK24,12,31)) -> 179206.91 | BM24: =SUMIFS($BG$10:$BG$208,$C$10:$C$208,">="&DATE(BK24,1,1),$C$10:$C$208,"<="&DATE(BK24,12,31)) -> #REF! | BN24: =SUM(BL24:BM24) -> #REF! | BO24: =BN24+BO23 -> #REF! | BQ24: 0 | BR24: 0 | BS24: 0 | BT24: 0 | BU24: 0 | BW24: =SUM(BQ24:BT24) -> 0 | BX24: 0 | BY24: =BF24 -> 392364.36 | BZ24: =BG24 -> -522032.09 | CA24: =BH24 -> -129667.73 | CB24: =BI24 -> -7006943.3 | CE24: =PV($CE$5,A24,,-BH24) -> -129667.73 | CF24: =PV($CE$5,A24,,-CA24) -> -129667.73
A25: 0 | C25: 42125 | D25: 0 | E25: 4 | F25: 0 | G25: 1 | H25: 162965.89 | I25: 0 | J25: 0 | K25: 0 | L25: 0 | M25: 0 | N25: 273491.18 | O25: 0 | P25: 0 | Q25: 0 | T25: 2569.78 | V25: =SUM(P25:T25,K25:N25) -> 276060.96 | W25: 0 | X25: 6834.67 | Y25: 296905.35 | Z25: =IFERROR(SUM(AA25:AH25)/SUM($AA$8:$AH$8),0) -> 0.002838825 | AA25: -142923.59 | AB25: -3433.07 | AD25: 0 | AE25: 0 | AG25: -59450 | AH25: 0 | AI25: 0 | AJ25: -6000 | AK25: -8716.86 | AL25: -119639.56 | AM25: -5302.3 | AN25: 0 | AO25: -103031.78 | AP25: -83691.21 | AQ25: -9587.47 | AR25: 0 | AS25: 0 | AT25: -3743 | AU25: 0 | AV25: -545.47 | AW25: -2200.23 | AX25: 0 | AY25: -10879.34 | AZ25: 0 | BA25: 0 | BB25: 0 | BC25: 0 | BD25: 0 | BF25: =V25+Y25+W25+X25 -> 579800.98 | BG25: =+SUM(AA25:BD25) -> -559143.88 | BH25: =SUM(BF25:BG25) -> 20657.1 | BI25: =BH25+BI24 -> -6986286.2 | BJ25: =+BI25-$AX$8 -> 39912.33 | BK25: =BK24+1 -> 2029 | BL25: =SUMIFS($BF$10:$BF$208,$C$10:$C$208,">="&DATE(BK25,1,1),$C$10:$C$208,"<="&DATE(BK25,12,31)) -> 0 | BM25: =SUMIFS($BG$10:$BG$208,$C$10:$C$208,">="&DATE(BK25,1,1),$C$10:$C$208,"<="&DATE(BK25,12,31)) -> #REF! | BN25: =SUM(BL25:BM25) -> #REF! | BO25: =BN25+BO24 -> #REF! | BQ25: 0 | BR25: 0 | BS25: 0 | BT25: 0 | BU25: 0 | BW25: =SUM(BQ25:BT25) -> 0 | BX25: 0 | BY25: =BF25 -> 579800.98 | BZ25: =BG25 -> -559143.88 | CA25: =BH25 -> 20657.1 | CB25: =BI25 -> -6986286.2 | CE25: =PV($CE$5,A25,,-BH25) -> 20657.1 | CF25: =PV($CE$5,A25,,-CA25) -> 20657.1
A26: 0 | C26: 42156 | D26: 0 | E26: 10 | F26: 0 | G26: 4 | H26: 466297.66 | I26: 0 | J26: 0 | K26: 0 | L26: 0 | M26: 0 | N26: 310796.87 | O26: 0 | P26: 0 | Q26: 0 | T26: 3309.05 | V26: =SUM(P26:T26,K26:N26) -> 314105.92 | W26: 0 | X26: 0 | Y26: 195692.3 | Z26: =IFERROR(SUM(AA26:AH26)/SUM($AA$8:$AH$8),0) -> 0.0025497804 | AA26: -131489.7 | AB26: -3868.73 | AD26: 0 | AE26: 0 | AG26: -49493.33 | AH26: 0 | AI26: 0 | AJ26: -6000 | AK26: -1777 | AL26: -115534.5 | AM26: -6204.77 | AN26: 0 | AO26: -75963.08 | AP26: -62940.11 | AQ26: -9662 | AR26: 0 | AS26: 0 | AT26: -29041.72 | AU26: -1271.15 | AV26: -2171 | AW26: -2883.25 | AX26: 0 | AY26: -12182.34 | AZ26: 0 | BA26: 0 | BB26: 0 | BC26: 0 | BD26: 0 | BF26: =V26+Y26+W26+X26 -> 509798.22 | BG26: =+SUM(AA26:BD26) -> -510482.68 | BH26: =SUM(BF26:BG26) -> -684.46 | BI26: =BH26+BI25 -> -6986970.7 | BJ26: =+BI26-$AX$8 -> 39227.87 | BK26: =BK25+1 -> 2030 | BL26: =SUMIFS($BF$10:$BF$208,$C$10:$C$208,">="&DATE(BK26,1,1),$C$10:$C$208,"<="&DATE(BK26,12,31)) -> 0 | BM26: =SUMIFS($BG$10:$BG$208,$C$10:$C$208,">="&DATE(BK26,1,1),$C$10:$C$208,"<="&DATE(BK26,12,31)) -> 0 | BN26: =SUM(BL26:BM26) -> 0 | BO26: =BN26+BO25 -> #REF! | BQ26: 0 | BR26: 0 | BS26: 0 | BT26: 0 | BU26: 0 | BW26: =SUM(BQ26:BT26) -> 0 | BX26: 0 | BY26: =BF26 -> 509798.22 | BZ26: =BG26 -> -510482.68 | CA26: =BH26 -> -684.46 | CB26: =BI26 -> -6986970.7 | CE26: =PV($CE$5,A26,,-BH26) -> -684.46 | CF26: =PV($CE$5,A26,,-CA26) -> -684.46
A27: 0 | C27: 42186 | D27: 0 | E27: 135 | F27: 0 | G27: 89 | H27: 8005383.5 | I27: 0 | J27: 0 | K27: 0 | L27: 0 | M27: 0 | N27: 376495.52 | O27: 0 | P27: 0 | Q27: 0 | T27: 2272.66 | V27: =SUM(P27:T27,K27:N27) -> 378768.18 | W27: 0 | X27: 364.53 | Y27: 124705.75 | Z27: =IFERROR(SUM(AA27:AH27)/SUM($AA$8:$AH$8),0) -> 0.0019854325 | AA27: -133067.57 | AB27: -5740.59 | AD27: 0 | AE27: 0 | AG27: -5130 | AH27: 0 | AI27: 0 | AJ27: -6000 | AK27: -212.55 | AL27: -113627.72 | AM27: -7061.48 | AN27: 0 | AO27: -131297.67 | AP27: -51363 | AQ27: -11296.4 | AR27: 0 | AS27: 0 | AT27: -13085 | AU27: -1971.45 | AV27: -6750.3 | AW27: -3045.47 | AX27: 0 | AY27: -18528.05 | AZ27: 0 | BA27: 0 | BB27: 0 | BC27: 0 | BD27: 0 | BF27: =V27+Y27+W27+X27 -> 503838.46 | BG27: =+SUM(AA27:BD27) -> -508177.25 | BH27: =SUM(BF27:BG27) -> -4338.79 | BI27: =BH27+BI26 -> -6991309.5 | BJ27: =+BI27-$AX$8 -> 34889.08 | BK27: =BK26+1 -> 2031 | BL27: =SUMIFS($BF$10:$BF$208,$C$10:$C$208,">="&DATE(BK27,1,1),$C$10:$C$208,"<="&DATE(BK27,12,31)) -> 0 | BM27: =SUMIFS($BG$10:$BG$208,$C$10:$C$208,">="&DATE(BK27,1,1),$C$10:$C$208,"<="&DATE(BK27,12,31)) -> 0 | BN27: =SUM(BL27:BM27) -> 0 | BO27: =BN27+BO26 -> #REF! | BQ27: 0 | BR27: 0 | BS27: 0 | BT27: 0 | BU27: 0 | BW27: =SUM(BQ27:BT27) -> 0 | BX27: 0 | BY27: =BF27 -> 503838.46 | BZ27: =BG27 -> -508177.25 | CA27: =BH27 -> -4338.79 | CB27: =BI27 -> -6991309.5 | CE27: =PV($CE$5,A27,,-BH27) -> -4338.79 | CF27: =PV($CE$5,A27,,-CA27) -> -4338.79
A28: 0 | C28: 42217 | D28: 0 | E28: 16 | F28: 0 | G28: 9 | H28: 885760.03 | I28: 0 | J28: 0 | K28: 0 | L28: 0 | M28: 0 | N28: 419515.73 | O28: 0 | P28: 0 | Q28: 0 | T28: 1851.96 | V28: =SUM(P28:T28,K28:N28) -> 421367.69 | W28: 0 | X28: 0 | Y28: 177458.35 | Z28: =IFERROR(SUM(AA28:AH28)/SUM($AA$8:$AH$8),0) -> 0.0018641342 | AA28: -134664.38 | AB28: -480 | AD28: 0 | AE28: 0 | AG28: 0 | AH28: 0 | AI28: 0 | AJ28: -6000 | AK28: 0 | AL28: -210300.92 | AM28: -6848.84 | AN28: 0 | AO28: -144278.58 | AP28: -47692.18 | AQ28: -13256.89 | AR28: -5624.96 | AS28: 0 | AT28: -3593 | AU28: -1186.05 | AV28: -8681.37 | AW28: -5508.96 | AX28: 0 | AY28: -20773.54 | AZ28: -3193.55 | BA28: 0 | BB28: 0 | BC28: 0 | BD28: 0 | BF28: =V28+Y28+W28+X28 -> 598826.04 | BG28: =+SUM(AA28:BD28) -> -612083.22 | BH28: =SUM(BF28:BG28) -> -13257.18 | BI28: =BH28+BI27 -> -7004566.6 | BJ28: =+BI28-$AX$8 -> 21631.9 | BK28: =BK27+1 -> 2032 | BL28: =SUMIFS($BF$10:$BF$208,$C$10:$C$208,">="&DATE(BK28,1,1),$C$10:$C$208,"<="&DATE(BK28,12,31)) -> 0 | BM28: =SUMIFS($BG$10:$BG$208,$C$10:$C$208,">="&DATE(BK28,1,1),$C$10:$C$208,"<="&DATE(BK28,12,31)) -> 0 | BN28: =SUM(BL28:BM28) -> 0 | BO28: =BN28+BO27 -> #REF! | BQ28: 0 | BR28: 0 | BS28: 0 | BT28: 0 | BU28: 0 | BW28: =SUM(BQ28:BT28) -> 0 | BX28: 0 | BY28: =BF28 -> 598826.04 | BZ28: =BG28 -> -612083.22 | CA28: =BH28 -> -13257.18 | CB28: =BI28 -> -7004566.6 | CE28: =PV($CE$5,A28,,-BH28) -> -13257.18 | CF28: =PV($CE$5,A28,,-CA28) -> -13257.18
A29: 0 | C29: 42248 | D29: 0 | E29: 33 | F29: 3 | G29: 39 | H29: 2664865.6 | I29: 123007.05 | J29: 0 | K29: 0 | L29: 0 | M29: 0 | N29: 384790.14 | O29: 0 | P29: 0 | Q29: 0 | T29: 1313.87 | V29: =SUM(P29:T29,K29:N29) -> 386104.01 | W29: 0 | X29: 0 | Y29: 47261.62 | Z29: =IFERROR(SUM(AA29:AH29)/SUM($AA$8:$AH$8),0) -> 0.00012850164 | AA29: 0 | AB29: 0 | AD29: 0 | AE29: 0 | AG29: -9316 | AH29: 0 | AI29: 0 | AJ29: -6000 | AK29: 0 | AL29: -216514.58 | AM29: -8557.76 | AN29: 0 | AO29: -70000 | AP29: -53593.2 | AQ29: -14672.67 | AR29: -5624.96 | AS29: 0 | AT29: -24083.04 | AU29: -1180.3 | AV29: -23773.89 | AW29: -6296.45 | AX29: 0 | AY29: -22258.68 | AZ29: 0 | BA29: 0 | BB29: 0 | BC29: 0 | BD29: 0 | BF29: =V29+Y29+W29+X29 -> 433365.63 | BG29: =+SUM(AA29:BD29) -> -461871.53 | BH29: =SUM(BF29:BG29) -> -28505.9 | BI29: =BH29+BI28 -> -7033072.5 | BJ29: =+BI29-$AX$8 -> -6874 | BQ29: 0 | BR29: 0 | BS29: 0 | BT29: 0 | BU29: 0 | BW29: =SUM(BQ29:BT29) -> 0 | BX29: 0 | BY29: =BF29 -> 433365.63 | BZ29: =BG29 -> -461871.53 | CA29: =BH29 -> -28505.9 | CB29: =BI29 -> -7033072.5 | CE29: =PV($CE$5,A29,,-BH29) -> -28505.9 | CF29: =PV($CE$5,A29,,-CA29) -> -28505.9
A30: 0 | C30: 42278 | D30: 0 | E30: 14 | F30: 0 | G30: 8 | H30: 780165.32 | I30: 0 | J30: 0 | K30: 0 | L30: 0 | M30: 0 | N30: 545745.43 | O30: 0 | P30: 0 | Q30: 0 | T30: 2155.92 | V30: =SUM(P30:T30,K30:N30) -> 547901.35 | W30: 0 | X30: 943.46 | Y30: 874.28 | Z30: =IFERROR(SUM(AA30:AH30)/SUM($AA$8:$AH$8),0) -> 0 | AA30: 0 | AB30: 0 | AD30: 0 | AE30: 0 | AG30: 0 | AH30: 0 | AI30: -19000 | AJ30: 0 | AK30: -1900 | AL30: -221111.06 | AM30: -8344.03 | AN30: 0 | AO30: -100000 | AP30: -36813 | AQ30: -13714 | AR30: -6568.42 | AS30: 0 | AT30: -58614.88 | AU30: -2721.3 | AV30: -16418.03 | AW30: -6302.14 | AX30: 0 | AY30: -23570.56 | AZ30: 0 | BA30: 0 | BB30: 0 | BC30: 0 | BD30: -5037.93 | BF30: =V30+Y30+W30+X30 -> 549719.09 | BG30: =+SUM(AA30:BD30) -> -520115.35 | BH30: =SUM(BF30:BG30) -> 29603.74 | BI30: =BH30+BI29 -> -7003468.8 | BJ30: =+BI30-$AX$8 -> 22729.74 | BQ30: 0 | BR30: 0 | BS30: 0 | BT30: 0 | BU30: 0 | BW30: =SUM(BQ30:BT30) -> 0 | BX30: 0 | BY30: =BF30 -> 549719.09 | BZ30: =BG30 -> -520115.35 | CA30: =BH30 -> 29603.74 | CB30: =BI30 -> -7003468.8 | CE30: =PV($CE$5,A30,,-BH30) -> 29603.74 | CF30: =PV($CE$5,A30,,-CA30) -> 29603.74
A31: 0 | C31: 42309 | D31: 0 | E31: 13 | F31: 0 | G31: 2 | H31: 501855.04 | I31: 0 | J31: 0 | K31: 0 | L31: 0 | M31: 0 | N31: 512735.68 | O31: 0 | P31: 0 | Q31: 0 | T31: 1278 | V31: =SUM(P31:T31,K31:N31) -> 514013.68 | W31: 0 | X31: 1369.81 | Y31: 461.77 | Z31: =IFERROR(SUM(AA31:AH31)/SUM($AA$8:$AH$8),0) -> 0.00024369931 | AA31: 0 | AB31: -400 | AD31: 0 | AE31: 0 | AG31: -17267.5 | AH31: 0 | AI31: -19000 | AJ31: 0 | AK31: -1900 | AL31: -210235.18 | AM31: 0 | AN31: 0 | AO31: -114435.08 | AP31: -33345 | AQ31: -38738.97 | AR31: -6630.24 | AS31: 0 | AT31: -8952 | AU31: -3488.85 | AV31: -22037.2 | AW31: -5968.11 | AX31: 0 | AY31: -29871.11 | AZ31: 0 | BA31: 0 | BB31: 0 | BC31: 0 | BD31: 0 | BF31: =V31+Y31+W31+X31 -> 515845.26 | BG31: =+SUM(AA31:BD31) -> -512269.24 | BH31: =SUM(BF31:BG31) -> 3576.02 | BI31: =BH31+BI30 -> -6999892.8 | BJ31: =+BI31-$AX$8 -> 26305.76 | BQ31: 0 | BR31: 0 | BS31: 0 | BT31: 0 | BU31: 0 | BW31: =SUM(BQ31:BT31) -> 0 | BX31: 0 | BY31: =BF31 -> 515845.26 | BZ31: =BG31 -> -512269.24 | CA31: =BH31 -> 3576.02 | CB31: =BI31 -> -6999892.8 | CE31: =PV($CE$5,A31,,-BH31) -> 3576.02 | CF31: =PV($CE$5,A31,,-CA31) -> 3576.02
A32: 0 | C32: 42339 | D32: 0 | E32: 31 | F32: 5 | G32: 37 | H32: 2518268.5 | I32: 205011.75 | J32: 0 | K32: 0 | L32: 0 | M32: 0 | N32: 642188.64 | O32: 0 | P32: 0 | Q32: 0 | T32: -4285.92 | V32: =SUM(P32:T32,K32:N32) -> 637902.72 | W32: 0 | X32: 0 | Y32: -1396.77 | Z32: =IFERROR(SUM(AA32:AH32)/SUM($AA$8:$AH$8),0) -> 6.3178364e-05 | AA32: 0 | AB32: -824 | AD32: 0 | AE32: 0 | AG32: -3756.25 | AH32: 0 | AI32: 0 | AJ32: 0 | AK32: -1900 | AL32: -200825.8 | AM32: -22375.12 | AN32: 0 | AO32: -222677.57 | AP32: -42241 | AQ32: =-47147.52-185 -> -47332.52 | AR32: -5624.96 | AS32: 0 | AT32: -7090.77 | AU32: -898.25 | AV32: -18255.23 | AW32: -5649.45 | AX32: 0 | AY32: -28307.93 | AZ32: 0 | BA32: 0 | BB32: 0 | BC32: 0 | BD32: 0 | BF32: =V32+Y32+W32+X32 -> 636505.95 | BG32: =+SUM(AA32:BD32) -> -607758.85 | BH32: =SUM(BF32:BG32) -> 28747.1 | BI32: =BH32+BI31 -> -6971145.7 | BJ32: =+BI32-$AX$8 -> 55052.86 | BQ32: 0 | BR32: 0 | BS32: 0 | BT32: 0 | BU32: 0 | BW32: =SUM(BQ32:BT32) -> 0 | BX32: 0 | BY32: =BF32 -> 636505.95 | BZ32: =BG32 -> -607758.85 | CA32: =BH32 -> 28747.1 | CB32: =BI32 -> -6971145.7 | CE32: =PV($CE$5,A32,,-BH32) -> 28747.1 | CF32: =PV($CE$5,A32,,-CA32) -> 28747.1
A33: 0 | B33: INÍCIO OBRA | C33: 42370 | D33: 0 | E33: 62 | F33: 13 | G33: 52 | H33: 4134485.4 | I33: 533030.55 | J33: 0 | K33: 0 | L33: 0 | M33: 0 | N33: 606693.68 | O33: 0 | P33: 0 | Q33: 0 | T33: -6058.8 | V33: =SUM(P33:T33,K33:N33) -> 600634.88 | W33: 0 | X33: 1948.74 | Y33: 3657.41 | Z33: =IFERROR(SUM(AA33:AH33)/SUM($AA$8:$AH$8),0) -> 0.00041218156 | AA33: 0 | AB33: -1254 | AD33: 0 | AE33: 0 | AG33: -26292.25 | AH33: -2335.73 | AI33: -38000 | AJ33: 0 | AK33: 0 | AL33: -231626.31 | AM33: -13737.67 | AN33: 0 | AO33: -160000 | AP33: -44373 | AQ33: -28663.39 | AR33: -7719.11 | AS33: 0 | AT33: -544 | AU33: -5818.05 | AV33: -29113.13 | AW33: -5001.67 | AX33: 0 | AY33: -38206.68 | AZ33: 0 | BA33: 0 | BB33: 0 | BC33: 0 | BD33: 0 | BF33: =V33+Y33+W33+X33 -> 606241.03 | BG33: =+SUM(AA33:BD33) -> -632684.99 | BH33: =SUM(BF33:BG33) -> -26443.96 | BI33: =BH33+BI32 -> -6997589.6 | BJ33: =+BI33-$AX$8 -> 28608.9 | BQ33: 0 | BR33: 0 | BS33: 0 | BT33: 0 | BU33: 0 | BW33: =SUM(BQ33:BT33) -> 0 | BX33: 0 | BY33: =BF33 -> 606241.03 | BZ33: =BG33 -> -632684.99 | CA33: =BH33 -> -26443.96 | CB33: =BI33 -> -6997589.6 | CE33: =PV($CE$5,A33,,-BH33) -> -26443.96 | CF33: =PV($CE$5,A33,,-CA33) -> -26443.96
A34: 0 | C34: 42401 | D34: 1 | E34: 29 | F34: 8 | G34: 19 | H34: 1715633.9 | I34: 360314.98 | J34: 0 | K34: 0 | L34: 0 | M34: 0 | N34: 689093.91 | O34: 0 | P34: 0 | Q34: 0 | T34: -379.55 | V34: =SUM(P34:T34,K34:N34) -> 688714.36 | W34: 0 | X34: 1128.92 | Y34: 674.95 | Z34: =IFERROR(SUM(AA34:AH34)/SUM($AA$8:$AH$8),0) -> 0.0016371434 | AA34: 0 | AB34: -107270.2 | AD34: 0 | AE34: 0 | AG34: -11418 | AH34: 0 | AI34: -19000 | AJ34: 0 | AK34: 0 | AL34: -272659.9 | AM34: -12623.28 | AN34: 0 | AO34: -80000 | AP34: -32603.5 | AQ34: -37028.57 | AR34: -7960.22 | AS34: 0 | AT34: -1018.14 | AU34: -259.2 | AV34: -27728.66 | AW34: -5717.01 | AX34: 0 | AY34: -36537.7 | AZ34: 0 | BA34: 0 | BB34: 0 | BC34: 0 | BD34: 0 | BF34: =V34+Y34+W34+X34 -> 690518.23 | BG34: =+SUM(AA34:BD34) -> -651824.38 | BH34: =SUM(BF34:BG34) -> 38693.85 | BI34: =BH34+BI33 -> -6958895.8 | BJ34: =+BI34-$AX$8 -> 67302.75 | BQ34: 0 | BR34: 0 | BS34: 0 | BT34: 0 | BU34: 0 | BW34: =SUM(BQ34:BT34) -> 0 | BX34: 0 | BY34: =BF34 -> 690518.23 | BZ34: =BG34 -> -651824.38 | CA34: =BH34 -> 38693.85 | CB34: =BI34 -> -6958895.8 | CE34: =PV($CE$5,A34,,-BH34) -> 38693.85 | CF34: =PV($CE$5,A34,,-CA34) -> 38693.85
A35: 0 | C35: 42430 | D35: 0 | E35: 12 | F35: 0 | G35: 12 | H35: 879582.36 | I35: 0 | J35: 0 | K35: 0 | L35: 0 | M35: 0 | N35: 657959.45 | O35: 0 | P35: 0 | Q35: 0 | T35: 3445.58 | V35: =SUM(P35:T35,K35:N35) -> 661405.03 | W35: 0 | X35: 1005.25 | Y35: 1362.46 | Z35: =IFERROR(SUM(AA35:AH35)/SUM($AA$8:$AH$8),0) -> 0.0024337726 | AA35: 0 | AB35: -111829.03 | AD35: 0 | AE35: 0 | AG35: -64612.5 | AH35: 0 | AI35: 0 | AJ35: 0 | AK35: 0 | AL35: -287563.65 | AM35: 0 | AN35: 0 | AO35: -70000 | AP35: -31612.5 | AQ35: -31032.15 | AR35: -7836.55 | AS35: 0 | AT35: -5998.4 | AU35: -4839.05 | AV35: -27083.14 | AW35: -6797.07 | AX35: 0 | AY35: -41076.81 | AZ35: -9294.99 | BA35: 0 | BB35: 0 | BC35: 0 | BD35: 0 | BF35: =V35+Y35+W35+X35 -> 663772.74 | BG35: =+SUM(AA35:BD35) -> -699575.84 | BH35: =SUM(BF35:BG35) -> -35803.1 | BI35: =BH35+BI34 -> -6994698.9 | BJ35: =+BI35-$AX$8 -> 31499.65 | BQ35: 0 | BR35: 0 | BS35: 0 | BT35: 0 | BU35: 0 | BW35: =SUM(BQ35:BT35) -> 0 | BX35: 0 | BY35: =BF35 -> 663772.74 | BZ35: =BG35 -> -699575.84 | CA35: =BH35 -> -35803.1 | CB35: =BI35 -> -6994698.9 | CE35: =PV($CE$5,A35,,-BH35) -> -35803.1 | CF35: =PV($CE$5,A35,,-CA35) -> -35803.1
A36: 0 | C36: 42461 | D36: 0 | E36: 14 | F36: 0 | G36: 18 | H36: 1207402.4 | I36: 0 | J36: 0 | K36: 0 | L36: 0 | M36: 0 | N36: 721625.84 | O36: 0 | P36: 0 | Q36: 0 | T36: 1328.14 | V36: =SUM(P36:T36,K36:N36) -> 722953.98 | W36: 0 | X36: 1005.25 | Y36: 3264.27 | Z36: =IFERROR(SUM(AA36:AH36)/SUM($AA$8:$AH$8),0) -> 0.0015707331 | AA36: 0 | AB36: -53290.17 | AD36: 0 | AE36: 0 | AG36: -60583.47 | AH36: 0 | AI36: -19000 | AJ36: 0 | AK36: 0 | AL36: -285830.1 | AM36: -12022.29 | AN36: 0 | AO36: -130000 | AP36: -23840.4 | AQ36: -29763.23 | AR36: -7836.55 | AS36: 0 | AT36: -88 | AU36: -3899.45 | AV36: -31069.1 | AW36: -7205.74 | AX36: 0 | AY36: -41431.02 | AZ36: 0 | BA36: 0 | BB36: 0 | BC36: 0 | BD36: -10052.84 | BF36: =V36+Y36+W36+X36 -> 727223.5 | BG36: =+SUM(AA36:BD36) -> -715912.36 | BH36: =SUM(BF36:BG36) -> 11311.14 | BI36: =BH36+BI35 -> -6983387.8 | BJ36: =+BI36-$AX$8 -> 42810.79 | BQ36: 0 | BR36: 0 | BS36: 0 | BT36: 0 | BU36: 0 | BW36: =SUM(BQ36:BT36) -> 0 | BX36: 0 | BY36: =BF36 -> 727223.5 | BZ36: =BG36 -> -715912.36 | CA36: =BH36 -> 11311.14 | CB36: =BI36 -> -6983387.8 | CE36: =PV($CE$5,A36,,-BH36) -> 11311.14 | CF36: =PV($CE$5,A36,,-CA36) -> 11311.14
A37: 0 | C37: 42491 | D37: 1 | E37: 45 | F37: 0 | G37: 21 | H37: 2517521.7 | I37: 35133.24 | J37: 0 | K37: 0 | L37: 0 | M37: 0 | N37: 718195.03 | O37: 0 | P37: 0 | Q37: 0 | T37: 2872.67 | V37: =SUM(P37:T37,K37:N37) -> 721067.7 | W37: 0 | X37: 0 | Y37: 3017.13 | Z37: =IFERROR(SUM(AA37:AH37)/SUM($AA$8:$AH$8),0) -> 0.0017665586 | AA37: 0 | AB37: -107227.43 | AD37: 0 | AE37: 0 | AG37: -20843 | AH37: 0 | AI37: -92234.31 | AJ37: 0 | AK37: 0 | AL37: -244885.63 | AM37: -13562.43 | AN37: 0 | AO37: -112136.3 | AP37: -21168.15 | AQ37: -41954.42 | AR37: -6831.3 | AS37: 0 | AT37: -93.92 | AU37: -12420.9 | AV37: -21087.88 | AW37: -8394.31 | AX37: 0 | AY37: -43609.35 | AZ37: 0 | BA37: 0 | BB37: 0 | BC37: 0 | BD37: 0 | BF37: =V37+Y37+W37+X37 -> 724084.83 | BG37: =+SUM(AA37:BD37) -> -746449.33 | BH37: =SUM(BF37:BG37) -> -22364.5 | BI37: =BH37+BI36 -> -7005752.2 | BJ37: =+BI37-$AX$8 -> 20446.29 | BQ37: 0 | BR37: 0 | BS37: 0 | BT37: 0 | BU37: 0 | BW37: =SUM(BQ37:BT37) -> 0 | BX37: 0 | BY37: =BF37 -> 724084.83 | BZ37: =BG37 -> -746449.33 | CA37: =BH37 -> -22364.5 | CB37: =BI37 -> -7005752.2 | CE37: =PV($CE$5,A37,,-BH37) -> -22364.5 | CF37: =PV($CE$5,A37,,-CA37) -> -22364.5
A38: 0 | C38: 42522 | D38: 0 | E38: 23 | F38: 0 | G38: 5 | H38: 1027452.7 | I38: 0 | J38: 0 | K38: 0 | L38: 0 | M38: 0 | N38: 871219.61 | O38: 0 | P38: 0 | Q38: 0 | T38: 963.33 | V38: =SUM(P38:T38,K38:N38) -> 872182.94 | W38: 0 | X38: 5616.05 | Y38: -574.67 | Z38: =IFERROR(SUM(AA38:AH38)/SUM($AA$8:$AH$8),0) -> 0.0025495262 | AA38: 0 | AB38: -170625.83 | AD38: 0 | AE38: 0 | AG38: -14207.5 | AH38: 0 | AI38: -95490.03 | AJ38: 0 | AK38: 0 | AL38: -236136.32 | AM38: -14738.5 | AN38: 0 | AO38: -94667.69 | AP38: -42472 | AQ38: -32753.6 | AR38: -12447.35 | AS38: 0 | AT38: -44 | AU38: -4051.05 | AV38: -24280.05 | AW38: -9394.4 | AX38: 0 | AY38: -43848.44 | AZ38: 0 | BA38: 0 | BB38: 0 | BC38: 0 | BD38: -2521.13 | BF38: =V38+Y38+W38+X38 -> 877224.32 | BG38: =+SUM(AA38:BD38) -> -797677.89 | BH38: =SUM(BF38:BG38) -> 79546.43 | BI38: =BH38+BI37 -> -6926205.8 | BJ38: =+BI38-$AX$8 -> 99992.72 | BQ38: 0 | BR38: 0 | BS38: 0 | BT38: 0 | BU38: 0 | BW38: =SUM(BQ38:BT38) -> 0 | BX38: 0 | BY38: =BF38 -> 877224.32 | BZ38: =BG38 -> -797677.89 | CA38: =BH38 -> 79546.43 | CB38: =BI38 -> -6926205.8 | CE38: =PV($CE$5,A38,,-BH38) -> 79546.43 | CF38: =PV($CE$5,A38,,-CA38) -> 79546.43
A39: 0 | C39: 42552 | D39: 0 | E39: 85 | F39: 8 | G39: 86 | H39: 6822121.8 | I39: 356771.76 | J39: 0 | K39: 0 | L39: 0 | M39: 0 | N39: 868516.98 | O39: 0 | P39: 0 | Q39: 0 | T39: -20654.85 | V39: =SUM(P39:T39,K39:N39) -> 847862.13 | W39: 0 | X39: 1005.44 | Y39: -34146.81 | Z39: =IFERROR(SUM(AA39:AH39)/SUM($AA$8:$AH$8),0) -> 0.0026811711 | AA39: 0 | AB39: -169046.27 | AD39: 0 | AE39: 0 | AG39: -25330.94 | AH39: 0 | AI39: -96016.77 | AJ39: 0 | AK39: 0 | AL39: -282295.37 | AM39: -32297.77 | AN39: 0 | AO39: -100000 | AP39: -27741 | AQ39: -54330.98 | AR39: -7836.74 | AS39: 0 | AT39: -99.38 | AU39: -4286.9 | AV39: -13307.69 | AW39: -8320.13 | AX39: 0 | AY39: -53136 | AZ39: 0 | BA39: 0 | BB39: 0 | BC39: 0 | BD39: 0 | BF39: =V39+Y39+W39+X39 -> 814720.76 | BG39: =+SUM(AA39:BD39) -> -874045.94 | BH39: =SUM(BF39:BG39) -> -59325.18 | BI39: =BH39+BI38 -> -6985531 | BJ39: =+BI39-$AX$8 -> 40667.54 | BQ39: 0 | BR39: 0 | BS39: 0 | BT39: 0 | BU39: 0 | BW39: =SUM(BQ39:BT39) -> 0 | BX39: 0 | BY39: =BF39 -> 814720.76 | BZ39: =BG39 -> -874045.94 | CA39: =BH39 -> -59325.18 | CB39: =BI39 -> -6985531 | CE39: =PV($CE$5,A39,,-BH39) -> -59325.18 | CF39: =PV($CE$5,A39,,-CA39) -> -59325.18
A40: 0 | C40: 42583 | D40: 1 | E40: 26 | F40: 3 | G40: 24 | H40: 1972287.8 | I40: 168922.65 | J40: 0 | K40: 0 | L40: 0 | M40: 0 | N40: 916180.14 | O40: 0 | P40: 0 | Q40: 0 | T40: -12862.64 | V40: =SUM(P40:T40,K40:N40) -> 903317.5 | W40: 0 | X40: 453.33 | Y40: -7647.23 | Z40: =IFERROR(SUM(AA40:AH40)/SUM($AA$8:$AH$8),0) -> 0.003160961 | AA40: 0 | AB40: -219799.1 | AD40: 0 | AE40: 0 | AG40: -9361.5 | AH40: 0 | AI40: -96391.8 | AJ40: 0 | AK40: 0 | AL40: -275844.33 | AM40: 0 | AN40: 0 | AO40: -90000 | AP40: -35095 | AQ40: -69650.21 | AR40: -8187.95 | AS40: 0 | AT40: -647.56 | AU40: -2445.5 | AV40: -20887.7 | AW40: -9091.18 | AX40: 0 | AY40: -53627.71 | AZ40: -16298.27 | BA40: 0 | BB40: 0 | BC40: 0 | BD40: 0 | BF40: =V40+Y40+W40+X40 -> 896123.6 | BG40: =+SUM(AA40:BD40) -> -907327.81 | BH40: =SUM(BF40:BG40) -> -11204.21 | BI40: =BH40+BI39 -> -6996735.2 | BJ40: =+BI40-$AX$8 -> 29463.33 | BQ40: 0 | BR40: 0 | BS40: 0 | BT40: 0 | BU40: 0 | BW40: =SUM(BQ40:BT40) -> 0 | BX40: 0 | BY40: =BF40 -> 896123.6 | BZ40: =BG40 -> -907327.81 | CA40: =BH40 -> -11204.21 | CB40: =BI40 -> -6996735.2 | CE40: =PV($CE$5,A40,,-BH40) -> -11204.21 | CF40: =PV($CE$5,A40,,-CA40) -> -11204.21
A41: 0 | C41: 42614 | D41: 0 | E41: 36 | F41: 0 | G41: 16 | H41: 1978340.2 | I41: 0 | J41: 0 | K41: 0 | L41: 0 | M41: 0 | N41: 910901.16 | O41: 0 | P41: 0 | Q41: 0 | T41: 4832.68 | V41: =SUM(P41:T41,K41:N41) -> 915733.84 | W41: 0 | X41: 0 | Y41: 26693.43 | Z41: =IFERROR(SUM(AA41:AH41)/SUM($AA$8:$AH$8),0) -> 0.004093421 | AA41: 0 | AB41: -286354.6 | AD41: 0 | AE41: 0 | AG41: -10406.67 | AH41: 0 | AI41: -97227.46 | AJ41: 0 | AK41: 0 | AL41: -253949.99 | AM41: -17919.21 | AN41: 0 | AO41: -60000 | AP41: -30646 | AQ41: -6000 | AR41: -7666.04 | AS41: 0 | AT41: -2643.33 | AU41: -7475.65 | AV41: -84995.01 | AW41: -11673.68 | AX41: 0 | AY41: -54892 | AZ41: 0 | BA41: 0 | BB41: 0 | BC41: 0 | BD41: 0 | BF41: =V41+Y41+W41+X41 -> 942427.27 | BG41: =+SUM(AA41:BD41) -> -931849.64 | BH41: =SUM(BF41:BG41) -> 10577.63 | BI41: =BH41+BI40 -> -6986157.6 | BJ41: =+BI41-$AX$8 -> 40040.96 | BQ41: 0 | BR41: 0 | BS41: 0 | BT41: 0 | BU41: 0 | BW41: =SUM(BQ41:BT41) -> 0 | BX41: 0 | BY41: =BF41 -> 942427.27 | BZ41: =BG41 -> -931849.64 | CA41: =BH41 -> 10577.63 | CB41: =BI41 -> -6986157.6 | CE41: =PV($CE$5,A41,,-BH41) -> 10577.63 | CF41: =PV($CE$5,A41,,-CA41) -> 10577.63
A42: 0 | C42: 42644 | D42: 3 | E42: 65 | F42: 7 | G42: 42 | H42: 4156712.3 | I42: 417575.01 | J42: 0 | K42: 0 | L42: 0 | M42: 0 | N42: 1065192.4 | O42: 0 | P42: 0 | Q42: 0 | T42: -7446.73 | V42: =SUM(P42:T42,K42:N42) -> 1057745.6 | W42: 0 | X42: 2511.16 | Y42: -9906.72 | Z42: =IFERROR(SUM(AA42:AH42)/SUM($AA$8:$AH$8),0) -> 0.0039245022 | AA42: 0 | AB42: -264990.76 | AD42: 0 | AE42: 0 | AG42: -19524.38 | AH42: 0 | AI42: -97594.23 | AJ42: 0 | AK42: 0 | AL42: -313970.16 | AM42: -18462.01 | AN42: 0 | AO42: -60000 | AP42: -32574 | AQ42: -85248.17 | AR42: -10236.54 | AS42: 0 | AT42: -3587.95 | AU42: -4261.06 | AV42: -34975.45 | AW42: -10014.27 | AX42: 0 | AY42: -58243.13 | AZ42: -991.01 | BA42: 0 | BB42: 0 | BC42: 0 | BD42: -627.34 | BF42: =V42+Y42+W42+X42 -> 1050350.1 | BG42: =+SUM(AA42:BD42) -> -1015300.5 | BH42: =SUM(BF42:BG42) -> 35049.62 | BI42: =BH42+BI41 -> -6951108 | BJ42: =+BI42-$AX$8 -> 75090.58 | BQ42: 0 | BR42: 0 | BS42: 0 | BT42: 0 | BU42: 0 | BW42: =SUM(BQ42:BT42) -> 0 | BX42: 0 | BY42: =BF42 -> 1050350.1 | BZ42: =BG42 -> -1015300.5 | CA42: =BH42 -> 35049.62 | CB42: =BI42 -> -6951108 | CE42: =PV($CE$5,A42,,-BH42) -> 35049.62 | CF42: =PV($CE$5,A42,,-CA42) -> 35049.62
A43: 0 | C43: 42675 | D43: 2 | E43: 48 | F43: 5 | G43: 19 | H43: 2526228.4 | I43: 293248.83 | J43: 0 | K43: 0 | L43: 0 | M43: 0 | N43: 1100332.6 | O43: 0 | P43: 0 | Q43: 0 | T43: -12973.42 | V43: =SUM(P43:T43,K43:N43) -> 1087359.2 | W43: 0 | X43: 0 | Y43: -5039.55 | Z43: =IFERROR(SUM(AA43:AH43)/SUM($AA$8:$AH$8),0) -> 0.0055009672 | AA43: 0 | AB43: -359639.08 | AD43: 0 | AE43: 0 | AG43: -39165.25 | AH43: 0 | AI43: -98337.27 | AJ43: 0 | AK43: 0 | AL43: -298491.95 | AM43: -17530.05 | AN43: 0 | AO43: -15000 | AP43: -30836 | AQ43: -34800.71 | AR43: -17666.04 | AS43: 0 | AT43: -1082.7 | AU43: -8379.12 | AV43: -33585.1 | AW43: -11771.53 | AX43: 0 | AY43: -64438.84 | AZ43: 0 | BA43: 0 | BB43: 0 | BC43: 0 | BD43: 0 | BF43: =V43+Y43+W43+X43 -> 1082319.6 | BG43: =+SUM(AA43:BD43) -> -1030723.6 | BH43: =SUM(BF43:BG43) -> 51595.97 | BI43: =BH43+BI42 -> -6899512 | BJ43: =+BI43-$AX$8 -> 126686.55 | BQ43: 0 | BR43: 0 | BS43: 0 | BT43: 0 | BU43: 0 | BW43: =SUM(BQ43:BT43) -> 0 | BX43: 0 | BY43: =BF43 -> 1082319.6 | BZ43: =BG43 -> -1030723.6 | CA43: =BH43 -> 51595.97 | CB43: =BI43 -> -6899512 | CE43: =PV($CE$5,A43,,-BH43) -> 51595.97 | CF43: =PV($CE$5,A43,,-CA43) -> 51595.97
A44: 0 | C44: 42705 | D44: 14 | E44: 93 | F44: 13 | G44: 30 | H44: 5079311.1 | I44: 1003766.3 | J44: 0 | K44: 0 | L44: 0 | M44: 0 | N44: 1041476.3 | O44: 0 | P44: 0 | Q44: 0 | T44: -10847.48 | V44: =SUM(P44:T44,K44:N44) -> 1030628.8 | W44: 0 | X44: 0 | Y44: -924.16 | Z44: =IFERROR(SUM(AA44:AH44)/SUM($AA$8:$AH$8),0) -> 0.0056291463 | AA44: 0 | AB44: -395422.45 | AD44: 0 | AE44: 0 | AG44: -12674.5 | AH44: 0 | AI44: -97639.81 | AJ44: 0 | AK44: 0 | AL44: -304388.22 | AM44: -21634.49 | AN44: 0 | AO44: 0 | AP44: -31796 | AQ44: -68649.74 | AR44: -17666.04 | AS44: 0 | AT44: -2409 | AU44: -14403.23 | AV44: -11418.94 | AW44: -12544.03 | AX44: 0 | AY44: -65755.56 | AZ44: -2790.2 | BA44: 0 | BB44: 0 | BC44: 0 | BD44: 0 | BF44: =V44+Y44+W44+X44 -> 1029704.7 | BG44: =+SUM(AA44:BD44) -> -1059192.2 | BH44: =SUM(BF44:BG44) -> -29487.55 | BI44: =BH44+BI43 -> -6928999.5 | BJ44: =+BI44-$AX$8 -> 97199 | BQ44: 0 | BR44: 0 | BS44: 0 | BT44: 0 | BU44: 0 | BW44: =SUM(BQ44:BT44) -> 0 | BX44: 0 | BY44: =BF44 -> 1029704.7 | BZ44: =BG44 -> -1059192.2 | CA44: =BH44 -> -29487.55 | CB44: =BI44 -> -6928999.5 | CE44: =PV($CE$5,A44,,-BH44) -> -29487.55 | CF44: =PV($CE$5,A44,,-CA44) -> -29487.55
A45: 0 | C45: 42736 | D45: 61 | E45: 67 | F45: 26 | G45: 19 | H45: 4240899 | I45: 3007703.7 | J45: 0 | K45: 0 | L45: 0 | M45: 0 | N45: 1209216.2 | O45: 0 | P45: 0 | Q45: 0 | T45: -13991.08 | V45: =SUM(P45:T45,K45:N45) -> 1195225.1 | W45: 0 | X45: 0 | Y45: -2637.26 | Z45: =IFERROR(SUM(AA45:AH45)/SUM($AA$8:$AH$8),0) -> 0.0067108353 | AA45: 0 | AB45: -486035.29 | AD45: 0 | AE45: 0 | AG45: -481 | AH45: 0 | AI45: -97856.71 | AJ45: 0 | AK45: 0 | AL45: -376360.73 | AM45: 0 | AN45: 0 | AO45: 0 | AP45: -25125.47 | AQ45: -31334.63 | AR45: -17666.04 | AS45: 0 | AT45: -660 | AU45: -5493.7 | AV45: -55739.12 | AW45: -16155.42 | AX45: 0 | AY45: -69888.54 | AZ45: 0 | BA45: 0 | BB45: 0 | BC45: 0 | BD45: 0 | BF45: =V45+Y45+W45+X45 -> 1192587.8 | BG45: =+SUM(AA45:BD45) -> -1182796.6 | BH45: =SUM(BF45:BG45) -> 9791.2 | BI45: =BH45+BI44 -> -6919208.3 | BJ45: =+BI45-$AX$8 -> 106990.2 | BQ45: 0 | BR45: 0 | BS45: 0 | BT45: 0 | BU45: 0 | BW45: =SUM(BQ45:BT45) -> 0 | BX45: 0 | BY45: =BF45 -> 1192587.8 | BZ45: =BG45 -> -1182796.6 | CA45: =BH45 -> 9791.2 | CB45: =BI45 -> -6919208.3 | CE45: =PV($CE$5,A45,,-BH45) -> 9791.2 | CF45: =PV($CE$5,A45,,-CA45) -> 9791.2
... A47: 0 | C47: 42795 | D47: 12 | E47: 6 | F47: 5 | G47: 3 | H47: 443968.93 | I47: 587135.04 | J47: 0 | K47: 0 | L47: 0 | M47: 0 | N47: 1360804.2 | O47: 0 | P47: 0 | Q47: 0 | T47: -8134.63 | V47: =SUM(P47:T47,K47:N47) -> 1352669.6 | W47: 450000 | X47: 0 | Y47: 6024.62 | Z47: =IFERROR(SUM(AA47:AH47)/SUM($AA$8:$AH$8),0) -> 0.0094799379 | AA47: 0 | AB47: -678511.28 | AD47: 0 | AE47: 0 | AG47: -8757 | AH47: 0 | AI47: -95000 | AJ47: 0 | AK47: 0 | AL47: -604740.43 | AM47: -21628.56 | AN47: -7656 | AO47: -100000 | AP47: -70599.82 | AQ47: -72400.31 | AR47: -8708.54 | AS47: -7000 | AT47: -719.45 | AU47: -8437.91 | AV47: -85152.7 | AW47: -32180.18 | AX47: 0 | AY47: -74760.22 | AZ47: 0 | BA47: 0 | BB47: 0 | BC47: 0 | BD47: 0 | BF47: =V47+Y47+W47+X47 -> 1808694.2 | BG47: =+SUM(AA47:BD47) -> -1876252.4 | BH47: =SUM(BF47:BG47) -> -67558.16 | BI47: =BH47+BI46 -> -6951826.7 | BJ47: =+BI47-$AX$8 -> 74371.88 | BQ47: 0 | BR47: 0 | BS47: 0 | BT47: 0 | BU47: 0 | BW47: =SUM(BQ47:BT47) -> 0 | BX47: 0 | BY47: =BF47 -> 1808694.2 | BZ47: =BG47 -> -1876252.4 | CA47: =BH47 -> -67558.16 | CB47: =BI47 -> -6951826.7 | CE47: =PV($CE$5,A47,,-BH47) -> -67558.16 | CF47: =PV($CE$5,A47,,-CA47) -> -67558.16
A48: 0 | C48: 42826 | D48: 38 | E48: 28 | F48: 8 | G48: 13 | H48: 1665587.9 | I48: 1363318.3 | J48: 0 | K48: 0 | L48: 0 | M48: 0 | N48: 1186040.5 | O48: 0.1 | P48: 0 | Q48: =-P45 -> 0 | T48: 1790.53 | V48: =SUM(P48:T48,K48:N48) -> 1187831.1 | W48: 0 | X48: 0 | Y48: -22601.9 | Z48: =IFERROR(SUM(AA48:AH48)/SUM($AA$8:$AH$8),0) -> 0.006638881 | AA48: 0 | AB48: -479915.81 | AD48: 0 | AE48: 0 | AG48: -1384 | AH48: 0 | AI48: -95000 | AJ48: 0 | AK48: 0 | AL48: -158195.59 | AM48: -24144.17 | AN48: -10440 | AO48: -50000 | AP48: -27494.78 | AQ48: -81741.18 | AR48: -7666.04 | AS48: -9115 | AT48: -779.69 | AU48: -16097.83 | AV48: -78000.48 | AW48: -31460.54 | AX48: 0 | AY48: -85210.47 | AZ48: 0 | BA48: 0 | BB48: 0 | BC48: -6975 | BD48: 0 | BF48: =V48+Y48+W48+X48 -> 1165229.2 | BG48: =+SUM(AA48:BD48) -> -1163620.6 | BH48: =SUM(BF48:BG48) -> 1608.58 | BI48: =BH48+BI47 -> -6950218.1 | BJ48: =+BI48-$AX$8 -> 75980.46 | BQ48: 0 | BR48: 0 | BS48: 0 | BT48: 0 | BU48: 0 | BW48: =SUM(BQ48:BT48) -> 0 | BX48: 0 | BY48: =BF48 -> 1165229.2 | BZ48: =BG48 -> -1163620.6 | CA48: =BH48 -> 1608.58 | CB48: =BI48 -> -6950218.1 | CE48: =PV($CE$5,A48,,-BH48) -> 1608.58 | CF48: =PV($CE$5,A48,,-CA48) -> 1608.58
A49: 0 | C49: 42856 | D49: 35 | E49: 45 | F49: 13 | G49: 27 | H49: 3008057.3 | I49: 1364820.6 | J49: 0 | K49: 0 | L49: 0 | M49: 0 | N49: 1374800.6 | O49: =+O48 -> 0.1 | P49: 0 | Q49: =-P46 -> 0 | T49: -2929.23 | V49: =SUM(P49:T49,K49:N49) -> 1371871.4 | W49: 0 | X49: 0 | Y49: 12133.47 | Z49: =IFERROR(SUM(AA49:AH49)/SUM($AA$8:$AH$8),0) -> 0.0071595056 | AA49: 0 | AB49: -517507.1 | AD49: 0 | AE49: 0 | AG49: -1536.5 | AH49: 0 | AI49: -95000 | AJ49: 0 | AK49: 0 | AL49: -350815.93 | AM49: -24884.19 | AN49: 0 | AO49: -67438.04 | AP49: -22159.8 | AQ49: -71699.77 | AR49: -8164.37 | AS49: -9115 | AT49: -1189.5 | AU49: -11047.45 | AV49: -85829.5 | AW49: -35028.58 | AX49: 0 | AY49: -78927.65 | AZ49: 0 | BA49: 0 | BB49: 0 | BC49: -4500 | BD49: 0 | BF49: =V49+Y49+W49+X49 -> 1384004.8 | BG49: =+SUM(AA49:BD49) -> -1384843.4 | BH49: =SUM(BF49:BG49) -> -838.55 | BI49: =BH49+BI48 -> -6951056.6 | BJ49: =+BI49-$AX$8 -> 75141.91 | BQ49: 0 | BR49: 0 | BS49: 0 | BT49: 0 | BU49: 0 | BW49: =SUM(BQ49:BT49) -> 0 | BX49: 0 | BY49: =BF49 -> 1384004.8 | BZ49: =BG49 -> -1384843.4 | CA49: =BH49 -> -838.55 | CB49: =BI49 -> -6951056.6 | CE49: =PV($CE$5,A49,,-BH49) -> -838.55 | CF49: =PV($CE$5,A49,,-CA49) -> -838.55
A50: 0 | C50: 42887 | D50: 37 | E50: 58 | F50: 31 | G50: 31 | H50: 3625298.1 | I50: 1971857.3 | J50: 0 | K50: 0 | L50: 0 | M50: 0 | N50: 1478210.1 | O50: =+O49 -> 0.1 | P50: 0 | Q50: =-P47 -> 0 | T50: -37911.91 | V50: =SUM(P50:T50,K50:N50) -> 1440298.2 | W50: 0 | X50: 0 | Y50: -11818.97 | Z50: =IFERROR(SUM(AA50:AH50)/SUM($AA$8:$AH$8),0) -> 0.0089341151 | AA50: 0 | AB50: -635496.03 | AD50: 0 | AE50: 0 | AG50: -12201.67 | AH50: 0 | AI50: -95000 | AJ50: 0 | AK50: 0 | AL50: -222219.81 | AM50: 0 | AN50: 0 | AO50: -50000 | AP50: -11860 | AQ50: -56269.86 | AR50: -7666.04 | AS50: -9115 | AT50: -154.94 | AU50: -9093.96 | AV50: -81484.87 | AW50: -40546.35 | AX50: 0 | AY50: -85182.32 | AZ50: 0 | BA50: 0 | BB50: 0 | BC50: -4500 | BD50: 0 | BF50: =V50+Y50+W50+X50 -> 1428479.3 | BG50: =+SUM(AA50:BD50) -> -1320790.9 | BH50: =SUM(BF50:BG50) -> 107688.41 | BI50: =BH50+BI49 -> -6843368.2 | BJ50: =+BI50-$AX$8 -> 182830.32 | BQ50: 0 | BR50: 0 | BS50: 0 | BT50: 0 | BU50: 0 | BW50: =SUM(BQ50:BT50) -> 0 | BX50: 0 | BY50: =BF50 -> 1428479.3 | BZ50: =BG50 -> -1320790.9 | CA50: =BH50 -> 107688.41 | CB50: =BI50 -> -6843368.2 | CE50: =PV($CE$5,A50,,-BH50) -> 107688.41 | CF50: =PV($CE$5,A50,,-CA50) -> 107688.41
A51: 0 | C51: 42917 | D51: 115 | E51: 95 | F51: 73 | G51: 73 | H51: 6999590.9 | I51: 5359819.8 | J51: 0 | K51: 0 | L51: 0 | M51: 0 | N51: 1443116.4 | O51: =+O50 -> 0.1 | P51: 0 | Q51: =-P48 -> 0 | T51: -19988.65 | V51: =SUM(P51:T51,K51:N51) -> 1423127.7 | W51: 0 | X51: 0 | Y51: -6684.13 | Z51: =IFERROR(SUM(AA51:AH51)/SUM($AA$8:$AH$8),0) -> 0.010100378 | AA51: 0 | AB51: -726667.92 | AD51: 0 | AE51: 0 | AG51: -5580.5 | AH51: 0 | AI51: -95000 | AJ51: -7000 | AK51: 0 | AL51: -210439.84 | AM51: -27674.34 | AN51: 0 | AO51: 0 | AP51: -25810 | AQ51: -38079.34 | AR51: -11434.08 | AS51: -7480.21 | AT51: -263.84 | AU51: -7081.1 | AV51: -109792.78 | AW51: -35142.6 | AX51: 0 | AY51: -91591.21 | AZ51: 0 | BA51: 0 | BB51: 0 | BC51: -4500 | BD51: 0 | BF51: =V51+Y51+W51+X51 -> 1416443.6 | BG51: =+SUM(AA51:BD51) -> -1403537.8 | BH51: =SUM(BF51:BG51) -> 12905.82 | BI51: =BH51+BI50 -> -6830462.4 | BJ51: =+BI51-$AX$8 -> 195736.14 | BQ51: 0 | BR51: 0 | BS51: 0 | BT51: 0 | BU51: 0 | BW51: =SUM(BQ51:BT51) -> 0 | BX51: 0 | BY51: =BF51 -> 1416443.6 | BZ51: =BG51 -> -1403537.8 | CA51: =BH51 -> 12905.82 | CB51: =BI51 -> -6830462.4 | CE51: =PV($CE$5,A51,,-BH51) -> 12905.82 | CF51: =PV($CE$5,A51,,-CA51) -> 12905.82
A52: 0 | C52: 42948 | D52: 28 | E52: 23 | F52: 18 | G52: 32 | H52: 2317037.2 | I52: 1314665.8 | J52: 0 | K52: 0 | L52: 0 | M52: 0 | N52: 1494607.8 | O52: =+O51 -> 0.1 | P52: 0 | Q52: =-P49 -> 0 | T52: -11489.91 | V52: =SUM(P52:T52,K52:N52) -> 1483117.9 | W52: 0 | X52: 0 | Y52: 11852.06 | Z52: =IFERROR(SUM(AA52:AH52)/SUM($AA$8:$AH$8),0) -> 0.012278489 | AA52: 0 | AB52: -886984.73 | AD52: 0 | AE52: 0 | AG52: -3170.5 | AH52: 0 | AI52: -95000 | AJ52: -5000 | AK52: 0 | AL52: -224061.89 | AM52: -24142.08 | AN52: 0 | AO52: 0 | AP52: -13460 | AQ52: -51318.1 | AR52: -12514.85 | AS52: -24707.82 | AT52: -142.1 | AU52: -19046.42 | AV52: -105978.33 | AW52: -38750.1 | AX52: 0 | AY52: -88700.94 | AZ52: -13375.53 | BA52: 0 | BB52: 0 | BC52: -4225 | BD52: 0 | BF52: =V52+Y52+W52+X52 -> 1494970 | BG52: =+SUM(AA52:BD52) -> -1610578.4 | BH52: =SUM(BF52:BG52) -> -115608.42 | BI52: =BH52+BI51 -> -6946070.8 | BJ52: =+BI52-$AX$8 -> 80127.72 | BQ52: 0 | BR52: 0 | BS52: 0 | BT52: 0 | BU52: 0 | BW52: =SUM(BQ52:BT52) -> 0 | BX52: 0 | BY52: =BF52 -> 1494970 | BZ52: =BG52 -> -1610578.4 | CA52: =BH52 -> -115608.42 | CB52: =BI52 -> -6946070.8 | CE52: =PV($CE$5,A52,,-BH52) -> -115608.42 | CF52: =PV($CE$5,A52,,-CA52) -> -115608.42
A53: 0 | C53: 42979 | D53: 30 | E53: 32 | F53: 40 | G53: 30 | H53: 2575427.9 | I53: 2074161.6 | J53: 0 | K53: 0 | L53: 0 | M53: 0 | N53: 1353544.2 | O53: =+O52 -> 0.1 | P53: 0 | Q53: =-P50 -> 0 | T53: 2925.15 | V53: =SUM(P53:T53,K53:N53) -> 1356469.3 | W53: 0 | X53: 175000 | Y53: -12209.02 | Z53: =IFERROR(SUM(AA53:AH53)/SUM($AA$8:$AH$8),0) -> 0.012318366 | AA53: 0 | AB53: -889760.15 | AD53: 0 | AE53: 0 | AG53: -3286 | AH53: 0 | AI53: -95000 | AJ53: -5000 | AK53: 0 | AL53: -135800 | AM53: 0 | AN53: 0 | AO53: 0 | AP53: -27240 | AQ53: -73236.56 | AR53: -22423.93 | AS53: -8449.01 | AT53: -865.4 | AU53: -8597.47 | AV53: -62372.98 | AW53: -41374.28 | AX53: 0 | AY53: -49419.65 | AZ53: -155.76 | BA53: 0 | BB53: 0 | BC53: -4000 | BD53: 0 | BF53: =V53+Y53+W53+X53 -> 1519260.3 | BG53: =+SUM(AA53:BD53) -> -1426981.2 | BH53: =SUM(BF53:BG53) -> 92279.12 | BI53: =BH53+BI52 -> -6853791.7 | BJ53: =+BI53-$AX$8 -> 172406.84 | BQ53: 0 | BR53: 0 | BS53: 0 | BT53: 0 | BU53: 0 | BW53: =SUM(BQ53:BT53) -> 0 | BX53: 0 | BY53: =BF53 -> 1519260.3 | BZ53: =BG53 -> -1426981.2 | CA53: =BH53 -> 92279.12 | CB53: =BI53 -> -6853791.7 | CE53: =PV($CE$5,A53,,-BH53) -> 92279.12 | CF53: =PV($CE$5,A53,,-CA53) -> 92279.12
A54: 0 | C54: 43009 | D54: 100 | E54: 59 | F54: 46 | G54: 40 | H54: 4061197.5 | I54: 4080550.6 | J54: 0 | K54: 0 | L54: 0 | M54: 0 | N54: 1631016.6 | O54: =+O53 -> 0.1 | P54: 0 | Q54: =-P51 -> 0 | T54: -27987.97 | V54: =SUM(P54:T54,K54:N54) -> 1603028.6 | W54: 0 | X54: 25000 | Y54: -9653.72 | Z54: =IFERROR(SUM(AA54:AH54)/SUM($AA$8:$AH$8),0) -> 0.010774248 | AA54: 0 | AB54: -781102.05 | AD54: 0 | AE54: 0 | AG54: 0 | AH54: 0 | AI54: 0 | AJ54: -5000 | AK54: 0 | AL54: -179271.5 | AM54: 0 | AN54: -89900 | AO54: 0 | AP54: -55120.63 | AQ54: -222180.78 | AR54: -11944.81 | AS54: -24323.65 | AT54: -355.08 | AU54: -10349.9 | AV54: -97824.5 | AW54: -39533.78 | AX54: 0 | AY54: -90884.2 | AZ54: 0 | BA54: 0 | BB54: -14285.72 | BC54: -4000 | BD54: 0 | BF54: =V54+Y54+W54+X54 -> 1618374.9 | BG54: =+SUM(AA54:BD54) -> -1626076.6 | BH54: =SUM(BF54:BG54) -> -7701.7 | BI54: =BH54+BI53 -> -6861493.4 | BJ54: =+BI54-$AX$8 -> 164705.14 | BQ54: 0 | BR54: 0 | BS54: 0 | BT54: 0 | BU54: 0 | BW54: =SUM(BQ54:BT54) -> 0 | BX54: 0 | BY54: =BF54 -> 1618374.9 | BZ54: =BG54 -> -1626076.6 | CA54: =BH54 -> -7701.7 | CB54: =BI54 -> -6861493.4 | CE54: =PV($CE$5,A54,,-BH54) -> -7701.7 | CF54: =PV($CE$5,A54,,-CA54) -> -7701.7
A55: 0 | C55: 43040 | D55: 78 | E55: 22 | F55: 30 | G55: 22 | H55: 1840048.9 | I55: 3004167.6 | J55: 0 | K55: 0 | L55: 0 | M55: 0 | N55: 1595694.9 | O55: =+O54 -> 0.1 | P55: 0 | Q55: =-P52 -> 0 | T55: -12088.94 | V55: =SUM(P55:T55,K55:N55) -> 1583605.9 | W55: 0 | X55: 1000000 | Y55: 29683.66 | Z55: =IFERROR(SUM(AA55:AH55)/SUM($AA$8:$AH$8),0) -> 0.015014817 | AA55: 0 | AB55: -1088531.1 | AD55: 0 | AE55: 0 | AG55: 0 | AH55: 0 | AI55: -190000 | AJ55: =-5000-365.85 -> -5365.85 | AK55: 0 | AL55: -642825.49 | AM55: -87587.34 | AN55: -35525 | AO55: 0 | AP55: -54973.04 | AQ55: -114035.8 | AR55: -12418.14 | AS55: -8352.97 | AT55: -177.67 | AU55: -8033.55 | AV55: -172899.79 | AW55: -53982.38 | AX55: 0 | AY55: -141834.14 | AZ55: -13095.4 | BA55: 0 | BB55: 0 | BC55: =-4900-8000 -> -12900 | BD55: 0 | BF55: =V55+Y55+W55+X55 -> 2613289.6 | BG55: =+SUM(AA55:BD55) -> -2642537.7 | BH55: =SUM(BF55:BG55) -> -29248.1 | BI55: =BH55+BI54 -> -6890741.5 | BJ55: =+BI55-$AX$8 -> 135457.04 | BQ55: 0 | BR55: 0 | BS55: 0 | BT55: 0 | BU55: 0 | BW55: =SUM(BQ55:BT55) -> 0 | BX55: 0 | BY55: =BF55 -> 2613289.6 | BZ55: =BG55 -> -2642537.7 | CA55: =BH55 -> -29248.1 | CB55: =BI55 -> -6890741.5 | CE55: =PV($CE$5,A55,,-BH55) -> -29248.1 | CF55: =PV($CE$5,A55,,-CA55) -> -29248.1
A56: 0 | C56: 43070 | D56: 37 | E56: 110 | F56: 7 | G56: 64 | H56: 7522233.6 | I56: 1205509.4 | J56: 0 | K56: 0 | L56: 0 | M56: 0 | N56: 1664559.7 | O56: =+O55 -> 0.1 | P56: 0 | Q56: =-P53 -> 0 | T56: -20245.91 | V56: =SUM(P56:T56,K56:N56) -> 1644313.8 | W56: 0 | X56: 0 | Y56: 3298.09 | Z56: =IFERROR(SUM(AA56:AH56)/SUM($AA$8:$AH$8),0) -> 0.01314289 | AA56: 0 | AB56: -952821.82 | AD56: 0 | AE56: 0 | AG56: 0 | AH56: 0 | AI56: -95000 | AJ56: -5000 | AK56: 0 | AL56: -200601.54 | AM56: -58633.19 | AN56: -21325 | AO56: 0 | AP56: -11400 | AQ56: -76601.83 | AR56: -9275.17 | AS56: -15937.6 | AT56: -827.4 | AU56: -15811.99 | AV56: -101025.9 | AW56: -34611.08 | AX56: 0 | AY56: =-95528.71-10354.42 -> -105883.13 | AZ56: 0 | BA56: 0 | BB56: 0 | BC56: =-4900-4000 -> -8900 | BD56: 0 | BF56: =V56+Y56+W56+X56 -> 1647611.9 | BG56: =+SUM(AA56:BD56) -> -1713655.6 | BH56: =SUM(BF56:BG56) -> -66043.79 | BI56: =BH56+BI55 -> -6956785.3 | BJ56: =+BI56-$AX$8 -> 69413.25 | BQ56: 0 | BR56: 0 | BS56: 0 | BT56: 0 | BU56: 0 | BW56: =SUM(BQ56:BT56) -> 0 | BX56: 0 | BY56: =BF56 -> 1647611.9 | BZ56: =BG56 -> -1713655.6 | CA56: =BH56 -> -66043.79 | CB56: =BI56 -> -6956785.3 | CE56: =PV($CE$5,A56,,-BH56) -> -66043.79 | CF56: =PV($CE$5,A56,,-CA56) -> -66043.79
A57: 0 | C57: 43101 | D57: 36 | E57: 275 | F57: 14 | G57: 161 | H57: 20322655 | I57: 1501711.8 | J57: 0 | K57: 0 | L57: 0 | M57: 0 | N57: 1731293.3 | O57: =+O56 -> 0.1 | P57: 0 | Q57: =-P54 -> 0 | T57: 6723.57 | V57: =SUM(P57:T57,K57:N57) -> 1738016.9 | W57: 0 | X57: 0 | Y57: -7241.74 | Z57: =IFERROR(SUM(AA57:AH57)/SUM($AA$8:$AH$8),0) -> 0.010510764 | AA57: 0 | AB57: =-758089.53 -> -758089.53 | AD57: 0 | AE57: 0 | AG57: -3910.65 | AH57: 0 | AI57: -95000 | AJ57: -5000 | AK57: 0 | AL57: -250083.91 | AM57: -35468.36 | AN57: -20000 | AO57: 0 | AP57: -47233.34 | AQ57: -112074.63 | AR57: -9959.81 | AS57: -7968.8 | AT57: -74.88 | AU57: -11472.97 | AV57: -130895.07 | AW57: -34804.69 | AX57: 0 | AY57: -105377.54 | AZ57: 0 | BA57: 0 | BB57: 0 | BC57: =-4900-4000 -> -8900 | BD57: 0 | BF57: =V57+Y57+W57+X57 -> 1730775.1 | BG57: =+SUM(AA57:BD57) -> -1636314.2 | BH57: =SUM(BF57:BG57) -> 94460.94 | BI57: =BH57+BI56 -> -6862324.4 | BJ57: =+BI57-$AX$8 -> 163874.19 | BQ57: 0 | BR57: 0 | BS57: 0 | BT57: 0 | BU57: 0 | BW57: =SUM(BQ57:BT57) -> 0 | BX57: 0 | BY57: =BF57 -> 1730775.1 | BZ57: =BG57 -> -1636314.2 | CA57: =BH57 -> 94460.94 | CB57: =BI57 -> -6862324.4 | CE57: =PV($CE$5,A57,,-BH57) -> 94460.94 | CF57: =PV($CE$5,A57,,-CA57) -> 94460.94
A58: 0 | C58: 43132 | D58: 84 | E58: 140 | F58: 30 | G58: 46 | H58: 8325552.6 | I58: 3266424.1 | J58: 0 | K58: 0 | L58: 0 | M58: 0 | N58: 1655423.9 | O58: =+O57 -> 0.1 | P58: 0 | Q58: =-P55 -> 0 | T58: -2229.59 | V58: =SUM(P58:T58,K58:N58) -> 1653194.3 | W58: 0 | X58: 0 | Y58: 21679.28 | Z58: =IFERROR(SUM(AA58:AH58)/SUM($AA$8:$AH$8),0) -> 0.01103387 | AA58: 0 | AB58: -799923.88 | AD58: 0 | AE58: 0 | AG58: 0 | AH58: 0 | AI58: -95000 | AJ58: -5000 | AK58: 0 | AL58: -255412.06 | AM58: -68667.21 | AN58: -42775 | AO58: 0 | AP58: -28493.33 | AQ58: -107973 | AR58: -9209.81 | AS58: -8113.35 | AT58: -927.6 | AU58: -10645.24 | AV58: -133950.3 | AW58: -35222.17 | AX58: 0 | AY58: -106615.2 | AZ58: 0 | BA58: 0 | BB58: 0 | BC58: =-4900-4000 -> -8900 | BD58: 0 | BF58: =V58+Y58+W58+X58 -> 1674873.6 | BG58: =+SUM(AA58:BD58) -> -1716828.2 | BH58: =SUM(BF58:BG58) -> -41954.58 | BI58: =BH58+BI57 -> -6904278.9 | BJ58: =+BI58-$AX$8 -> 121919.61 | BQ58: 0 | BR58: 0 | BS58: 0 | BT58: 0 | BU58: 0 | BW58: =SUM(BQ58:BT58) -> 0 | BX58: 0 | BY58: =BF58 -> 1674873.6 | BZ58: =BG58 -> -1716828.2 | CA58: =BH58 -> -41954.58 | CB58: =BI58 -> -6904278.9 | CE58: =PV($CE$5,A58,,-BH58) -> -41954.58 | CF58: =PV($CE$5,A58,,-CA58) -> -41954.58
A59: 0 | C59: 43160 | D59: 50 | E59: 74 | F59: 26 | G59: 32 | H59: 0 | I59: 0 | J59: 7351803.8 | K59: 0 | L59: 0 | M59: 0 | N59: 1902417.5 | O59: =+O58 -> 0.1 | P59: 0 | Q59: =-P56 -> 0 | T59: -25339.8 | V59: =SUM(P59:T59,K59:N59) -> 1877077.7 | W59: 0 | X59: 0 | Y59: -18607.63 | Z59: =IFERROR(SUM(AA59:AH59)/SUM($AA$8:$AH$8),0) -> 0.011608851 | AA59: 0 | AB59: -841608.4 | AD59: 0 | AE59: 0 | AG59: 0 | AH59: 0 | AI59: -95000 | AJ59: -5000 | AK59: 0 | AL59: -165912.98 | AM59: 0 | AN59: 0 | AO59: 0 | AP59: -25591.83 | AQ59: -107651.47 | AR59: -720 | AS59: -8113.35 | AT59: -1208.03 | AU59: -5519.5 | AV59: -413571.37 | AW59: -15573.13 | AX59: 0 | AY59: -110803.75 | BA59: -10000 | BC59: -24000 | BD59: 0 | BF59: =V59+Y59+W59+X59 -> 1858470.1 | BG59: =+SUM(AA59:BD59) -> -1830273.8 | BH59: =SUM(BF59:BG59) -> 28196.3 | BI59: =BH59+BI58 -> -6876082.6 | BJ59: =+BI59-$AX$8 -> 150115.91 | BQ59: 0 | BR59: 0 | BS59: 0 | BT59: 0 | BU59: 0 | BW59: =SUM(BQ59:BT59) -> 0 | BX59: 0 | BY59: =BF59 -> 1858470.1 | BZ59: =BG59 -> -1830273.8 | CA59: =BH59 -> 28196.3 | CB59: =BI59 -> -6876082.6 | CE59: =PV($CE$5,A59,,-BH59) -> 28196.3 | CF59: =PV($CE$5,A59,,-CA59) -> 28196.3
A60: 0 | C60: 43191 | D60: 50 | E60: 80 | F60: 20 | G60: 21 | H60: 0 | I60: 0 | J60: 6808906 | K60: 0 | L60: 0 | M60: 0 | N60: 1873284.5 | O60: =+O59 -> 0.1 | P60: 0 | Q60: =-P57 -> 0 | T60: 10468.14 | V60: =SUM(P60:T60,K60:N60) -> 1883752.6 | W60: 0 | X60: 100000 | Y60: -5312.24 | Z60: =IFERROR(SUM(AA60:AH60)/SUM($AA$8:$AH$8),0) -> 0.011137637 | AA60: 0 | AB60: -767846.69 | AD60: 0 | AE60: 0 | AG60: -39600 | AH60: 0 | AI60: -70000 | AJ60: -5000 | AK60: 0 | AL60: -317890.89 | AM60: -36647.99 | AN60: -36250 | AO60: 0 | AP60: -42406 | AQ60: -126808.47 | AR60: -953.38 | AS60: -15000 | AT60: -861.3 | AU60: -14137.29 | AV60: -279038.49 | AW60: -14609.67 | AX60: 0 | AY60: -103206.7 | BA60: -37500 | BC60: -20000 | BD60: -100000 | BF60: =V60+Y60+W60+X60 -> 1978440.4 | BG60: =+SUM(AA60:BD60) -> -2027756.9 | BH60: =SUM(BF60:BG60) -> -49316.49 | BI60: =BH60+BI59 -> -6925399.1 | BJ60: =+BI60-$AX$8 -> 100799.42 | BQ60: 0 | BR60: 0 | BS60: 0 | BT60: 0 | BU60: 0 | BW60: =SUM(BQ60:BT60) -> 0 | BX60: 0 | BY60: =BF60 -> 1978440.4 | BZ60: =BG60 -> -2027756.9 | CA60: =BH60 -> -49316.49 | CB60: =BI60 -> -6925399.1 | CE60: =PV($CE$5,A60,,-BH60) -> -49316.49 | CF60: =PV($CE$5,A60,,-CA60) -> -49316.49
A61: 0 | C61: 43221 | D61: 50 | E61: 74 | F61: 20 | G61: 10 | H61: 0 | I61: 0 | J61: 5963701.3 | K61: 0 | L61: 0 | M61: 0 | N61: 2036985.2 | O61: =+O60 -> 0.1 | P61: 0 | Q61: 0 | T61: -8497.02 | V61: =SUM(P61:T61,K61:N61) -> 2028488.2 | W61: 0 | X61: 0 | Y61: 31658.19 | Z61: =IFERROR(SUM(AA61:AH61)/SUM($AA$8:$AH$8),0) -> 0.011128493 | AA61: 0 | AB61: -786983.78 | AD61: 0 | AE61: 0 | AG61: -19800 | AH61: 0 | AI61: -70000 | AJ61: -5000 | AK61: 0 | AL61: -179994.21 | AM61: -33395.66 | AN61: 0 | AO61: 0 | AP61: -53965 | AQ61: -127208.97 | AR61: -3170.36 | AS61: -17100.3 | AT61: -1323.2 | AU61: -8297.35 | AV61: -269317.4 | AW61: -32630.6 | AX61: 0 | AY61: -107362.51 | AZ61: -115768.1 | BA61: 0 | BB61: -1901 | BC61: -28000 | BD61: -130000 | BF61: =V61+Y61+W61+X61 -> 2060146.4 | BG61: =+SUM(AA61:BD61) -> -1991218.4 | BH61: =SUM(BF61:BG61) -> 68927.93 | BI61: =BH61+BI60 -> -6856471.2 | BJ61: =+BI61-$AX$8 -> 169727.35 | BR61: 0 | BS61: 0 | BT61: 0 | BU61: 0 | BW61: =SUM(BQ61:BT61) -> 0 | BX61: 0 | BY61: =BF61 -> 2060146.4 | BZ61: =BG61 -> -1991218.4 | CA61: =BH61 -> 68927.93 | CB61: =BI61 -> -6856471.2 | CE61: =PV($CE$5,A61,,-BH61) -> 68927.93 | CF61: =PV($CE$5,A61,,-CA61) -> 68927.93
C62: 43252 | K62: 0 | L62: 0 | M62: 0 | N62: 1812817.9 | O62: =+O61 -> 0.1 | P62: 0 | Q62: 0 | T62: 10566.9 | V62: =SUM(P62:T62,K62:N62) -> 1823384.8 | X62: 0 | Y62: 64988.56 | Z62: =IFERROR(SUM(AA62:AH62)/SUM($AA$8:$AH$8),0) -> 0.011079686 | AA62: 0 | AB62: =-782393.58-118.85 -> -782512.43 | AG62: -20733 | AH62: 0 | AI62: -70000 | AJ62: -5000 | AL62: -326696.25 | AM62: -69636.75 | AN62: -47850 | AP62: -33658.5 | AQ62: -147099.48 | AR62: -25894.97 | AS62: 0 | AT62: -426.7 | AU62: -8340.95 | AV62: -245693.98 | AW62: -16193.15 | AY62: -118639.79 | AZ62: 0 | BA62: 0 | BB62: =-202.85-259.71 -> -462.56 | BC62: -24000 | BD62: 0 | BE62: =SUM(BF62:BG62)-BH62 -> 0 | BF62: =V62+Y62+W62+X62 -> 1888373.4 | BG62: =+SUM(AA62:BD62) -> -1942838.5 | BH62: =SUM(BF62:BG62) -> -54465.13 | BI62: =BH62+BI61 -> -6910936.3 | BJ62: =+BI62-$AX$8 -> 115262.22 | BY62: =BF62 -> 1888373.4 | BZ62: =BG62 -> -1942838.5 | CA62: =BH62 -> -54465.13 | CB62: =BI62 -> -6910936.3 | CE62: =PV($CE$5,A62,,-BH62) -> -54465.13 | CF62: =PV($CE$5,A62,,-CA62) -> -54465.13
A63: =A61+1 -> 1 | B63: ACOMPANHAMENTO | C63: 43282 | D63: 114 | E63: 150 | F63: 50 | G63: 20 | H63: 0 | I63: 0 | J63: 12796052 | K63: =+'Fluxo Consolidado'!D58 -> 0 | L63: =+'Fluxo Consolidado'!E58 -> 0 | M63: =+'Fluxo Consolidado'!F58 -> 0 | N63: 0 | O63: =+O61 -> 0.1 | P63: =+'Fluxo Consolidado'!H58 -> 0 | Q63: =+'Fluxo Consolidado'!I58 -> 0 | R63: ='Fluxo Consolidado'!J58 -> 0 | S63: ='Fluxo Consolidado'!K58 -> 0 | T63: 0 | U63: 0 | V63: =SUM(P63:T63,K63:N63) -> 0 | W63: 0 | X63: 0 | Y63: 0 | Z63: =IFERROR(SUM(AA63:AH63)/SUM($AA$8:$AH$8),0) -> 0 | AA63: 0 | AB63: =+'Fluxo Consolidado'!P58 -> 0 | AC63: ='Fluxo Consolidado'!Q58 -> 0 | AD63: =+'Fluxo Consolidado'!R58 -> 0 | AE63: =+'Fluxo Consolidado'!S58 -> 0 | AF63: ='Fluxo Consolidado'!T58 -> 0 | AG63: =+'Fluxo Consolidado'!U58 -> 0 | AH63: =+'Fluxo Consolidado'!V58 -> 0 | AI63: =+'Fluxo Consolidado'!#REF! -> #REF! | AJ63: =+'Fluxo Consolidado'!X58 -> 0 | AK63: 0 | AL63: =+'Fluxo Consolidado'!Y58+'Fluxo Consolidado'!Z58+'Fluxo Consolidado'!AA58 -> 0 | AM63: =+'Fluxo Consolidado'!AB58+'Fluxo Consolidado'!AC58 -> 0 | AN63: =+'Fluxo Consolidado'!AD58 -> 0 | AO63: ='Fluxo Consolidado'!AE58+'Fluxo Consolidado'!AF58 -> 0 | AP63: =+'Fluxo Consolidado'!AG58 -> 0 | AQ63: =+'Fluxo Consolidado'!AH58 -> 0 | AR63: =+'Fluxo Consolidado'!AI58 -> 0 | AS63: =+'Fluxo Consolidado'!AJ58 -> 0 | AT63: 0 | AU63: =+'Fluxo Consolidado'!AK58 -> 0 | AV63: =+'Fluxo Consolidado'!AL58 -> 0 | AW63: =-V62*$AW$2 -> -21880.618 | AX63: 0 | AY63: =(-V62*$AY$1)+'Fluxo Consolidado'!AO58 -> -72935.393 | AZ63: 0 | BA63: 0 | BB63: 0 | BC63: =+'Fluxo Consolidado'!AP58 -> 0 | BD63: =+'Fluxo Consolidado'!AQ58 -> 0 | BF63: =V63+Y63+W63+X63 -> 0 | BG63: =+SUM(AA63:BD63) -> #REF! | BH63: =SUM(BF63:BG63) -> #REF! | BI63: =BH63+BI62 -> #REF! | BJ63: =+BI63-$AX$8 -> #REF! | BQ63: 0 | BR63: 0 | BS63: 0 | BT63: 0 | BU63: 0 | BV63: 0 | BW63: =SUM(BQ63:BT63) -> 0 | BX63: 0 | BY63: =V63+BQ63+BR63+BS63+BT63+BU63+BV63 -> 0 | BZ63: =BG63 -> #REF! | CA63: =SUM(BY63:BZ63) -> #REF! | CB63: =CA63+CB62 -> #REF! | CC63: =CB63-$AX$8 -> #REF! | CE63: =PV($CE$5,A63,,-BH63) -> #REF! | CF63: =PV($CE$5,A63,,-CA63) -> #REF!
A64: =A63+1 -> 2 | C64: 43313 | D64: 100 | E64: 90 | F64: 10 | G64: 20 | H64: 0 | I64: 0 | J64: 8316221.8 | K64: =+'Fluxo Consolidado'!D59 -> 0 | L64: =+'Fluxo Consolidado'!E59 -> 2221975.4 | M64: =+'Fluxo Consolidado'!F59 -> 0 | N64: 0 | O64: =+O63 -> 0.1 | P64: =+'Fluxo Consolidado'!H59 -> -222197.54 | Q64: =+'Fluxo Consolidado'!I59 -> 0 | R64: ='Fluxo Consolidado'!J59 -> 0 | S64: ='Fluxo Consolidado'!K59 -> 0 | T64: 0 | U64: 0 | V64: =SUM(P64:R64,K64:N64)+T64 -> 1999777.9 | W64: 0 | X64: 0 | Y64: 0 | Z64: =IFERROR(SUM(AA64:AH64)/SUM($AA$8:$AH$8),0) -> 0.024691858 | AA64: 0 | AB64: =+'Fluxo Consolidado'!P59 -> -1531774.3 | AC64: ='Fluxo Consolidado'!Q59 -> -154410.94 | AD64: =+'Fluxo Consolidado'!R59 -> 0 | AE64: =+'Fluxo Consolidado'!S59 -> 0 | AF64: ='Fluxo Consolidado'!T59 -> 0 | AG64: =+'Fluxo Consolidado'!U59 -> -103903.6 | AH64: =+'Fluxo Consolidado'!V59 -> 0 | AI64: =+'Fluxo Consolidado'!#REF! -> #REF! | AJ64: =+'Fluxo Consolidado'!X59 -> -5000 | AK64: 0 | AL64: =+'Fluxo Consolidado'!Y59+'Fluxo Consolidado'!Z59+'Fluxo Consolidado'!AA59 -> -620869.85 | AM64: =+'Fluxo Consolidado'!AB59+'Fluxo Consolidado'!AC59 -> -41454.85 | AN64: =+'Fluxo Consolidado'!AD59 -> -201192 | AO64: ='Fluxo Consolidado'!AE59+'Fluxo Consolidado'!AF59 -> -165643.69 | AP64: =+'Fluxo Consolidado'!AG59 -> -25711.75 | AQ64: =+'Fluxo Consolidado'!AH59 -> -120573.48 | AR64: =+'Fluxo Consolidado'!AI59 -> -9209.81 | AS64: =+'Fluxo Consolidado'!AJ59 -> -7969 | AT64: 0 | AU64: =+'Fluxo Consolidado'!AK59 -> -10571.835 | AV64: =+'Fluxo Consolidado'!AL59 -> -242823.02 | AW64: =-V63*$AW$2 -> 0 | AX64: 0 | AY64: =(-V63*$AY$1)+'Fluxo Consolidado'!AO59 -> 0 | AZ64: 0 | BA64: 0 | BB64: 0 | BC64: =+'Fluxo Consolidado'!AP59 -> -24000 | BD64: =+'Fluxo Consolidado'!AQ59 -> 0 | BF64: =V64+Y64+W64+X64 -> 1999777.9 | BG64: =+SUM(AA64:BD64) -> #REF! | BH64: =SUM(BF64:BG64) -> #REF! | BI64: =BH64+BI63 -> #REF! | BJ64: =+BI64-$AX$8 -> #REF! | BQ64: 15000000 | BR64: 0 | BS64: 0 | BT64: -5878257.8 | BU64: -1919871.9 | BV64: 0 | BW64: =SUM(BQ64:BT64) -> 9121742.2 | BX64: =SUM(BR64:BT64) -> -5878257.8 | BY64: =V64+BQ64+BR64+BS64+BT64+BU64+BV64 -> 9201648.2 | BZ64: =BG64 -> #REF! | CA64: =SUM(BY64:BZ64) -> #REF! | CB64: =CA64+CB63 -> #REF! | CC64: =CB64-$AX$8 -> #REF! | CE64: =PV($CE$5,A64,,-BH64) -> #REF! | CF64: =PV($CE$5,A64,,-CA64) -> #REF!
A65: =A64+1 -> 3 | C65: 43344 | D65: 25 | E65: 81 | F65: 10 | G65: 15 | H65: 0 | I65: 0 | J65: 5423586.2 | K65: =+'Fluxo Consolidado'!D60 -> 0 | L65: =+'Fluxo Consolidado'!E60 -> 2238986.8 | M65: =+'Fluxo Consolidado'!F60 -> 0 | N65: 0 | O65: =+O64 -> 0.1 | P65: =+'Fluxo Consolidado'!H60 -> -223898.68 | Q65: =+'Fluxo Consolidado'!I60 -> 0 | R65: ='Fluxo Consolidado'!J60 -> 0 | S65: ='Fluxo Consolidado'!K60 -> 0 | T65: =((1+$T$4)^U65-1)*(SUM(K65:L65)*$T$1) -> 0 | U65: 1 | V65: =SUM(P65:R65,K65:N65)+T65 -> 2015088.1 | W65: 0 | X65: 0 | Y65: 0 | Z65: =IFERROR(SUM(AA65:AH65)/SUM($AA$8:$AH$8),0) -> 0.024603137 | AA65: 0 | AB65: =+'Fluxo Consolidado'!P60 -> -1514312.9 | AC65: ='Fluxo Consolidado'!Q60 -> -165440.3 | AD65: =+'Fluxo Consolidado'!R60 -> 0 | AE65: =+'Fluxo Consolidado'!S60 -> 0 | AF65: ='Fluxo Consolidado'!T60 -> 0 | AG65: =+'Fluxo Consolidado'!U60 -> -103903.6 | AH65: =+'Fluxo Consolidado'!V60 -> 0 | AI65: =+'Fluxo Consolidado'!#REF! -> #REF! | AJ65: =+'Fluxo Consolidado'!X60 -> -5000 | AK65: 0 | AL65: =+'Fluxo Consolidado'!Y60+'Fluxo Consolidado'!Z60+'Fluxo Consolidado'!AA60 -> -633349.56 | AM65: =+'Fluxo Consolidado'!AB60+'Fluxo Consolidado'!AC60 -> -48379.83 | AN65: =+'Fluxo Consolidado'!AD60 -> -142042 | AO65: ='Fluxo Consolidado'!AE60+'Fluxo Consolidado'!AF60 -> -165643.69 | AP65: =+'Fluxo Consolidado'!AG60 -> -25711.75 | AQ65: =+'Fluxo Consolidado'!AH60 -> -119986.67 | AR65: =+'Fluxo Consolidado'!AI60 -> -9209.81 | AS65: =+'Fluxo Consolidado'!AJ60 -> -7969 | AT65: 0 | AU65: =+'Fluxo Consolidado'!AK60 -> -12106.458 | AV65: =+'Fluxo Consolidado'!AL60 -> -90637.79 | AW65: =-V64*$AW$2 -> -23997.335 | AX65: 0 | AY65: =(-V64*$AY$1)+'Fluxo Consolidado'!AO60 -> -79991.115 | AZ65: 0 | BA65: 0 | BB65: 0 | BC65: =+'Fluxo Consolidado'!AP60 -> -24000 | BD65: =+'Fluxo Consolidado'!AQ60 -> -870000 | BF65: =V65+Y65+W65+X65 -> 2015088.1 | BG65: =+SUM(AA65:BD65) -> #REF! | BH65: =SUM(BF65:BG65) -> #REF! | BI65: =BH65+BI64 -> #REF! | BJ65: =+BI65-$AX$8 -> #REF! | BQ65: 0 | BR65: -489562.42 | BS65: -65844.424 | BT65: 0 | BU65: -1966704.5 | BV65: 0 | BW65: =SUM(BQ65:BT65) -> -555406.84 | BX65: =SUM(BR65:BT65) -> -555406.84 | BY65: =V65+BQ65+BR65+BS65+BT65+BU65+BV65 -> -507023.19 | BZ65: =BG65 -> #REF! | CA65: =SUM(BY65:BZ65) -> #REF! | CB65: =CA65+CB64 -> #REF! | CC65: =CB65-$AX$8 -> #REF! | CE65: =PV($CE$5,A65,,-BH65) -> #REF! | CF65: =PV($CE$5,A65,,-CA65) -> #REF!
A66: =A65+1 -> 4 | C66: 43374 | D66: 50 | E66: 100 | F66: 3 | G66: 15 | H66: 0 | I66: 0 | J66: 6738720 | K66: =+'Fluxo Consolidado'!D61 -> 0 | L66: =+'Fluxo Consolidado'!E61 -> 2420664.7 | M66: =+'Fluxo Consolidado'!F61 -> 0 | N66: 0 | O66: =+O65 -> 0.1 | P66: =+'Fluxo Consolidado'!H61 -> -242066.47 | Q66: =+'Fluxo Consolidado'!I61 -> 0 | R66: ='Fluxo Consolidado'!J61 -> 0 | S66: ='Fluxo Consolidado'!K61 -> 0 | T66: =((1+$T$4)^U66-1)*(SUM(K66:L66)*$T$1) -> 0 | U66: 1 | V66: =SUM(P66:R66,K66:N66)+T66 -> 2178598.2 | W66: 0 | X66: 0 | Y66: 0 | Z66: =IFERROR(SUM(AA66:AH66)/SUM($AA$8:$AH$8),0) -> 0.028464792 | AA66: 0 | AB66: =+'Fluxo Consolidado'!P61 -> -1766698.4 | AC66: ='Fluxo Consolidado'!Q61 -> -193013.68 | AD66: =+'Fluxo Consolidado'!R61 -> 0 | AE66: =+'Fluxo Consolidado'!S61 -> 0 | AF66: ='Fluxo Consolidado'!T61 -> 0 | AG66: =+'Fluxo Consolidado'!U61 -> -103903.6 | AH66: =+'Fluxo Consolidado'!V61 -> 0 | AI66: =+'Fluxo Consolidado'!#REF! -> #REF! | AJ66: =+'Fluxo Consolidado'!X61 -> -5000 | AK66: 0 | AL66: =+'Fluxo Consolidado'!Y61+'Fluxo Consolidado'!Z61+'Fluxo Consolidado'!AA61 -> -535587.68 | AM66: =+'Fluxo Consolidado'!AB61+'Fluxo Consolidado'!AC61 -> -52259.88 | AN66: =+'Fluxo Consolidado'!AD61 -> -121742 | AO66: ='Fluxo Consolidado'!AE61+'Fluxo Consolidado'!AF61 -> -165643.69 | AP66: =+'Fluxo Consolidado'!AG61 -> -25711.75 | AQ66: =+'Fluxo Consolidado'!AH61 -> -120905.29 | AR66: =+'Fluxo Consolidado'!AI61 -> -9209.81 | AS66: =+'Fluxo Consolidado'!AJ61 -> -7969 | AT66: 0 | AU66: =+'Fluxo Consolidado'!AK61 -> -12529.674 | AV66: =+'Fluxo Consolidado'!AL61 -> -81235.26 | AW66: =-V65*$AW$2 -> -24181.058 | AX66: 0 | AY66: =(-V65*$AY$1)+'Fluxo Consolidado'!AO61 -> -80603.525 | AZ66: 0 | BA66: 0 | BB66: 0 | BC66: =+'Fluxo Consolidado'!AP61 -> -1200000 | BD66: =+'Fluxo Consolidado'!AQ61 -> 0 | BF66: =V66+Y66+W66+X66 -> 2178598.2 | BG66: =+SUM(AA66:BD66) -> #REF! | BH66: =SUM(BF66:BG66) -> #REF! | BI66: =BH66+BI65 -> #REF! | BJ66: =+BI66-$AX$8 -> #REF! | BQ66: 0 | BR66: -489562.42 | BS66: -67219.924 | BT66: 0 | BU66: -2398306.5 | BV66: 886576 | BW66: =SUM(BQ66:BT66) -> -556782.34 | BX66: =SUM(BR66:BT66) -> -556782.34 | BY66: =V66+BQ66+BR66+BS66+BT66+BU66+BV66 -> 110085.38 | BZ66: =BG66 -> #REF! | CA66: =SUM(BY66:BZ66) -> #REF! | CB66: =CA66+CB65 -> #REF! | CC66: =CB66-$AX$8 -> #REF! | CE66: =PV($CE$5,A66,,-BH66) -> #REF! | CF66: =PV($CE$5,A66,,-CA66) -> #REF!
A67: =A66+1 -> 5 | C67: 43405 | D67: 30 | E67: 50 | F67: 5 | G67: 20 | H67: 0 | I67: 0 | J67: 4310443.1 | K67: =+'Fluxo Consolidado'!D62 -> 95647.818 | L67: =+'Fluxo Consolidado'!E62 -> 2455737.2 | M67: =+'Fluxo Consolidado'!F62 -> 69110.337 | N67: 0 | O67: =+O66 -> 0.1 | P67: =+'Fluxo Consolidado'!H62 -> -245573.72 | Q67: =+'Fluxo Consolidado'!I62 -> 222197.54 | R67: ='Fluxo Consolidado'!J62 -> 0 | S67: ='Fluxo Consolidado'!K62 -> 0 | T67: =((1+$T$4)^U67-1)*(SUM(K67:L67)*$T$1) -> 0 | U67: 1 | V67: =SUM(P67:R67,K67:N67)+T67 -> 2597119.2 | W67: 0 | X67: 0 | Y67: 0 | Z67: =IFERROR(SUM(AA67:AH67)/SUM($AA$8:$AH$8),0) -> 0.030222692 | AA67: 0 | AB67: =+'Fluxo Consolidado'!P62 -> -1918129.7 | AC67: ='Fluxo Consolidado'!Q62 -> -209557.71 | AD67: =+'Fluxo Consolidado'!R62 -> 0 | AE67: =+'Fluxo Consolidado'!S62 -> 0 | AF67: ='Fluxo Consolidado'!T62 -> 0 | AG67: =+'Fluxo Consolidado'!U62 -> -63371 | AH67: =+'Fluxo Consolidado'!V62 -> 0 | AI67: =+'Fluxo Consolidado'!#REF! -> #REF! | AJ67: =+'Fluxo Consolidado'!X62 -> -5000 | AK67: 0 | AL67: =+'Fluxo Consolidado'!Y62+'Fluxo Consolidado'!Z62+'Fluxo Consolidado'!AA62 -> -546702.47 | AM67: =+'Fluxo Consolidado'!AB62+'Fluxo Consolidado'!AC62 -> -54711.597 | AN67: =+'Fluxo Consolidado'!AD62 -> -121742 | AO67: ='Fluxo Consolidado'!AE62+'Fluxo Consolidado'!AF62 -> -194977.02 | AP67: =+'Fluxo Consolidado'!AG62 -> -25711.75 | AQ67: =+'Fluxo Consolidado'!AH62 -> -130715.89 | AR67: =+'Fluxo Consolidado'!AI62 -> -9209.81 | AS67: =+'Fluxo Consolidado'!AJ62 -> -7969 | AT67: 0 | AU67: =+'Fluxo Consolidado'!AK62 -> -13034.914 | AV67: =+'Fluxo Consolidado'!AL62 -> -75391.28 | AW67: =-V66*$AW$2 -> -26143.179 | AX67: 0 | AY67: =(-V66*$AY$1)+'Fluxo Consolidado'!AO62 -> -87143.93 | AZ67: 0 | BA67: 0 | BB67: 0 | BC67: =+'Fluxo Consolidado'!AP62 -> 0 | BD67: =+'Fluxo Consolidado'!AQ62 -> 0 | BF67: =V67+Y67+W67+X67 -> 2597119.2 | BG67: =+SUM(AA67:BD67) -> #REF! | BH67: =SUM(BF67:BG67) -> #REF! | BI67: =BH67+BI66 -> #REF! | BJ67: =+BI67-$AX$8 -> #REF! | BQ67: 0 | BR67: -489562.42 | BS67: -68983.924 | BT67: 0 | BU67: -2486166.7 | BV67: 2398306.5 | BW67: =SUM(BQ67:BT67) -> -558546.34 | BX67: =SUM(BR67:BT67) -> -558546.34 | BY67: =V67+BQ67+BR67+BS67+BT67+BU67+BV67 -> 1950712.7 | BZ67: =BG67 -> #REF! | CA67: =SUM(BY67:BZ67) -> #REF! | CB67: =CA67+CB66 -> #REF! | CC67: =CB67-$AX$8 -> #REF! | CE67: =PV($CE$5,A67,,-BH67) -> #REF! | CF67: =PV($CE$5,A67,,-CA67) -> #REF!
A68: =A67+1 -> 6 | C68: 43435 | D68: 200 | E68: 300 | F68: 11 | G68: 8 | H68: 0 | I68: 0 | J68: 19812988 | K68: =+'Fluxo Consolidado'!D63 -> 150179.71 | L68: =+'Fluxo Consolidado'!E63 -> 2461625.4 | M68: =+'Fluxo Consolidado'!F63 -> 69110.337 | N68: 0 | O68: =+O67 -> 0.1 | P68: =+'Fluxo Consolidado'!H63 -> -246162.54 | Q68: =+'Fluxo Consolidado'!I63 -> 223898.68 | R68: ='Fluxo Consolidado'!J63 -> 0 | S68: ='Fluxo Consolidado'!K63 -> 0 | T68: =((1+$T$4)^U68-1)*(SUM(K68:L68)*$T$1) -> 0 | U68: 1 | V68: =SUM(P68:R68,K68:N68)+T68 -> 2658651.6 | W68: 0 | X68: 0 | Y68: 0 | Z68: =IFERROR(SUM(AA68:AH68)/SUM($AA$8:$AH$8),0) -> 0.029348575 | AA68: 0 | AB68: =+'Fluxo Consolidado'!P63 -> -1918129.7 | AC68: ='Fluxo Consolidado'!Q63 -> -209557.71 | AD68: =+'Fluxo Consolidado'!R63 -> 0 | AE68: =+'Fluxo Consolidado'!S63 -> 0 | AF68: ='Fluxo Consolidado'!T63 -> 0 | AG68: =+'Fluxo Consolidado'!U63 -> 0 | AH68: 0 | AI68: =+'Fluxo Consolidado'!#REF! -> #REF! | AJ68: =+'Fluxo Consolidado'!X63 -> -5000 | AK68: 0 | AL68: =+'Fluxo Consolidado'!Y63+'Fluxo Consolidado'!Z63+'Fluxo Consolidado'!AA63 -> -355347.98 | AM68: =+'Fluxo Consolidado'!AB63+'Fluxo Consolidado'!AC63 -> -55989.071 | AN68: =+'Fluxo Consolidado'!AD63 -> 0 | AO68: ='Fluxo Consolidado'!AE63+'Fluxo Consolidado'!AF63 -> -212443.69 | AP68: =+'Fluxo Consolidado'!AG63 -> -25711.75 | AQ68: =+'Fluxo Consolidado'!AH63 -> -155827.15 | AR68: =+'Fluxo Consolidado'!AI63 -> -9209.81 | AS68: =+'Fluxo Consolidado'!AJ63 -> -7969 | AT68: 0 | AU68: =+'Fluxo Consolidado'!AK63 -> -13197.86 | AV68: =+'Fluxo Consolidado'!AL63 -> -66303.71 | AW68: =-V67*$AW$2 -> -31165.43 | AX68: 0 | AY68: =(-V67*$AY$1)+'Fluxo Consolidado'!AO63 -> -103884.77 | AZ68: 0 | BA68: 0 | BB68: 0 | BC68: =+'Fluxo Consolidado'!AP63 -> 0 | BD68: =+'Fluxo Consolidado'!AQ63 -> 0 | BF68: =V68+Y68+W68+X68 -> 2658651.6 | BG68: =+SUM(AA68:BD68) -> #REF! | BH68: =SUM(BF68:BG68) -> #REF! | BI68: =BH68+BI67 -> #REF! | BJ68: =+BI68-$AX$8 -> #REF! | BQ68: 0 | BR68: -489562.42 | BS68: -70086.424 | BT68: 0 | BU68: -2558729.2 | BV68: 2486166.7 | BW68: =SUM(BQ68:BT68) -> -559648.84 | BX68: =SUM(BR68:BT68) -> -559648.84 | BY68: =V68+BQ68+BR68+BS68+BT68+BU68+BV68 -> 2026440.3 | BZ68: =BG68 -> #REF! | CA68: =SUM(BY68:BZ68) -> #REF! | CB68: =CA68+CB67 -> #REF! | CC68: =CB68-$AX$8 -> #REF! | CE68: =PV($CE$5,A68,,-BH68) -> #REF! | CF68: =PV($CE$5,A68,,-CA68) -> #REF!
A69: =A68+1 -> 7 | C69: 43466 | D69: 100 | E69: 150 | F69: 20 | G69: 0 | H69: 0 | I69: 0 | J69: 10222263 | K69: =+'Fluxo Consolidado'!D64 -> 228130.47 | L69: =+'Fluxo Consolidado'!E64 -> 2468998.5 | M69: =+'Fluxo Consolidado'!F64 -> 69110.337 | N69: 0 | O69: =+O68 -> 0.1 | P69: =+'Fluxo Consolidado'!H64 -> -246899.85 | Q69: =+'Fluxo Consolidado'!I64 -> 242066.47 | R69: ='Fluxo Consolidado'!J64 -> 0 | S69: ='Fluxo Consolidado'!K64 -> 0 | T69: =((1+$T$4)^U69-1)*(SUM(K69:L69)*$T$1) -> 0 | U69: 1 | V69: =SUM(P69:R69,K69:N69)+T69 -> 2761405.9 | W69: 0 | X69: 0 | Y69: 0 | Z69: =IFERROR(SUM(AA69:AH69)/SUM($AA$8:$AH$8),0) -> 0.029348575 | AA69: 0 | AB69: =+'Fluxo Consolidado'!P64 -> -1918129.7 | AC69: ='Fluxo Consolidado'!Q64 -> -209557.71 | AD69: =+'Fluxo Consolidado'!R64 -> 0 | AE69: =+'Fluxo Consolidado'!S64 -> 0 | AF69: ='Fluxo Consolidado'!T64 -> 0 | AG69: =+'Fluxo Consolidado'!U64 -> 0 | AH69: 0 | AI69: =+'Fluxo Consolidado'!#REF! -> #REF! | AJ69: =+'Fluxo Consolidado'!X64 -> -5000 | AK69: 0 | AL69: =+'Fluxo Consolidado'!Y64+'Fluxo Consolidado'!Z64+'Fluxo Consolidado'!AA64 -> -394572.61 | AM69: =+'Fluxo Consolidado'!AB64+'Fluxo Consolidado'!AC64 -> -57708.674 | AN69: =+'Fluxo Consolidado'!AD64 -> 0 | AO69: ='Fluxo Consolidado'!AE64+'Fluxo Consolidado'!AF64 -> -234843.69 | AP69: =+'Fluxo Consolidado'!AG64 -> 0 | AQ69: =+'Fluxo Consolidado'!AH64 -> -159519.1 | AR69: =+'Fluxo Consolidado'!AI64 -> -9209.81 | AS69: =+'Fluxo Consolidado'!AJ64 -> -7969 | AT69: 0 | AU69: =+'Fluxo Consolidado'!AK64 -> -13383.092 | AV69: =+'Fluxo Consolidado'!AL64 -> -58596.62 | AW69: =-V68*$AW$2 -> -31903.819 | AX69: 0 | AY69: =(-V68*$AY$1)+'Fluxo Consolidado'!AO64 -> -106346.06 | AZ69: 0 | BA69: 0 | BB69: 0 | BC69: =+'Fluxo Consolidado'!AP64 -> 0 | BD69: =+'Fluxo Consolidado'!AQ64 -> 0 | BF69: =V69+Y69+W69+X69 -> 2761405.9 | BG69: =+SUM(AA69:BD69) -> #REF! | BH69: =SUM(BF69:BG69) -> #REF! | BI69: =BH69+BI68 -> #REF! | BJ69: =+BI69-$AX$8 -> #REF! | BQ69: =-AB68 -> 1918129.7 | BR69: -489562.42 | BS69: -75535.924 | BT69: 0 | BU69: -2642515.4 | BV69: 2558729.2 | BW69: =SUM(BQ69:BT69) -> 1353031.3 | BX69: =SUM(BR69:BT69) -> -565098.34 | BY69: =V69+BQ69+BR69+BS69+BT69+BU69+BV69 -> 4030651 | BZ69: =BG69 -> #REF! | CA69: =SUM(BY69:BZ69) -> #REF! | CB69: =CA69+CB68 -> #REF! | CC69: =CB69-$AX$8 -> #REF! | CE69: =PV($CE$5,A69,,-BH69) -> #REF! | CF69: =PV($CE$5,A69,,-CA69) -> #REF!
A70: =A69+1 -> 8 | C70: 43497 | D70: 45 | E70: 100 | F70: 5 | G70: 0 | H70: 0 | I70: 0 | J70: 5865170.8 | K70: =+'Fluxo Consolidado'!D65 -> 273900.62 | L70: =+'Fluxo Consolidado'!E65 -> 2473272.1 | M70: =+'Fluxo Consolidado'!F65 -> 69110.337 | N70: 0 | O70: =+O69 -> 0.1 | P70: =+'Fluxo Consolidado'!H65 -> -247327.21 | Q70: =+'Fluxo Consolidado'!I65 -> 245573.72 | R70: ='Fluxo Consolidado'!J65 -> 0 | S70: ='Fluxo Consolidado'!K65 -> 0 | T70: =((1+$T$4)^U70-1)*(SUM(K70:L70)*$T$1) -> 0 | U70: 1 | V70: =SUM(P70:R70,K70:N70)+T70 -> 2814529.6 | W70: 0 | X70: 0 | Y70: 0 | Z70: =IFERROR(SUM(AA70:AH70)/SUM($AA$8:$AH$8),0) -> 0.029348575 | AA70: 0 | AB70: =+'Fluxo Consolidado'!P65 -> -1918129.7 | AC70: ='Fluxo Consolidado'!Q65 -> -209557.71 | AD70: =+'Fluxo Consolidado'!R65 -> 0 | AE70: =+'Fluxo Consolidado'!S65 -> 0 | AF70: ='Fluxo Consolidado'!T65 -> 0 | AG70: =+'Fluxo Consolidado'!U65 -> 0 | AH70: =+'Fluxo Consolidado'!V65 -> 0 | AI70: =+'Fluxo Consolidado'!#REF! -> #REF! | AJ70: =+'Fluxo Consolidado'!X65 -> -5000 | AK70: 0 | AL70: =+'Fluxo Consolidado'!Y65+'Fluxo Consolidado'!Z65+'Fluxo Consolidado'!AA65 -> -420167.17 | AM70: =+'Fluxo Consolidado'!AB65+'Fluxo Consolidado'!AC65 -> -58699.066 | AN70: =+'Fluxo Consolidado'!AD65 -> 0 | AO70: ='Fluxo Consolidado'!AE65+'Fluxo Consolidado'!AF65 -> -248843.69 | AP70: =+'Fluxo Consolidado'!AG65 -> 0 | AQ70: =+'Fluxo Consolidado'!AH65 -> -165684.35 | AR70: =+'Fluxo Consolidado'!AI65 -> -9209.81 | AS70: =+'Fluxo Consolidado'!AJ65 -> -7969 | AT70: 0 | AU70: =+'Fluxo Consolidado'!AK65 -> -13668.399 | AV70: =+'Fluxo Consolidado'!AL65 -> -51471.91 | AW70: =-V69*$AW$2 -> -33136.871 | AX70: 0 | AY70: =(-V69*$AY$1)+'Fluxo Consolidado'!AO65 -> -110456.24 | AZ70: 0 | BA70: 0 | BB70: 0 | BC70: =+'Fluxo Consolidado'!AP65 -> 0 | BD70: =+'Fluxo Consolidado'!AQ65 -> 0 | BF70: =V70+Y70+W70+X70 -> 2814529.6 | BG70: =+SUM(AA70:BD70) -> #REF! | BH70: =SUM(BF70:BG70) -> #REF! | BI70: =BH70+BI69 -> #REF! | BJ70: =+BI70-$AX$8 -> #REF! | BQ70: =-AB69 -> 1918129.7 | BR70: -489562.42 | BS70: -78370.924 | BT70: 0 | BU70: -2692945 | BV70: 2642515.4 | BW70: =SUM(BQ70:BT70) -> 1350196.3 | BX70: =SUM(BR70:BT70) -> -567933.34 | BY70: =V70+BQ70+BR70+BS70+BT70+BU70+BV70 -> 4114296.4 | BZ70: =BG70 -> #REF! | CA70: =SUM(BY70:BZ70) -> #REF! | CB70: =CA70+CB69 -> #REF! | CC70: =CB70-$AX$8 -> #REF! | CE70: =PV($CE$5,A70,,-BH70) -> #REF! | CF70: =PV($CE$5,A70,,-CA70) -> #REF!
A71: =A70+1 -> 9 | C71: 43525 | D71: 20 | E71: 20 | F71: 5 | G71: 0 | H71: 0 | I71: 0 | J71: 1646765.4 | K71: =+'Fluxo Consolidado'!D66 -> 513954.33 | L71: =+'Fluxo Consolidado'!E66 -> 2477068.1 | M71: =+'Fluxo Consolidado'!F66 -> 69110.337 | N71: 0 | O71: =+O70 -> 0.1 | P71: =+'Fluxo Consolidado'!H66 -> -247706.82 | Q71: =+'Fluxo Consolidado'!I66 -> 246162.54 | R71: ='Fluxo Consolidado'!J66 -> 0 | S71: ='Fluxo Consolidado'!K66 -> 0 | T71: =((1+$T$4)^U71-1)*(SUM(K71:L71)*$T$1) -> 0 | U71: 1 | V71: =SUM(P71:R71,K71:N71)+T71 -> 3058588.5 | W71: 0 | X71: 0 | Y71: 0 | Z71: =IFERROR(SUM(AA71:AH71)/SUM($AA$8:$AH$8),0) -> 0.029348575 | AA71: 0 | AB71: =+'Fluxo Consolidado'!P66 -> -1918129.7 | AC71: ='Fluxo Consolidado'!Q66 -> -209557.71 | AD71: =+'Fluxo Consolidado'!R66 -> 0 | AE71: =+'Fluxo Consolidado'!S66 -> 0 | AF71: ='Fluxo Consolidado'!T66 -> 0 | AG71: =+'Fluxo Consolidado'!U66 -> 0 | AH71: =+'Fluxo Consolidado'!V66 -> 0 | AI71: =+'Fluxo Consolidado'!#REF! -> #REF! | AJ71: =+'Fluxo Consolidado'!X66 -> -5000 | AK71: 0 | AL71: =+'Fluxo Consolidado'!Y66+'Fluxo Consolidado'!Z66+'Fluxo Consolidado'!AA66 -> -417549.34 | AM71: =+'Fluxo Consolidado'!AB66+'Fluxo Consolidado'!AC66 -> -63908.799 | AN71: =+'Fluxo Consolidado'!AD66 -> 0 | AO71: ='Fluxo Consolidado'!AE66+'Fluxo Consolidado'!AF66 -> -318043.69 | AP71: =+'Fluxo Consolidado'!AG66 -> 0 | AQ71: =+'Fluxo Consolidado'!AH66 -> -168871.78 | AR71: =+'Fluxo Consolidado'!AI66 -> -9209.81 | AS71: =+'Fluxo Consolidado'!AJ66 -> -7969 | AT71: 0 | AU71: =+'Fluxo Consolidado'!AK66 -> -13803.312 | AV71: =+'Fluxo Consolidado'!AL66 -> -42786.68 | AW71: =-V70*$AW$2 -> -33774.355 | AX71: 0 | AY71: =(-V70*$AY$1)+'Fluxo Consolidado'!AO66 -> -112581.18 | AZ71: 0 | BA71: 0 | BB71: 0 | BC71: =+'Fluxo Consolidado'!AP66 -> 0 | BD71: =+'Fluxo Consolidado'!AQ66 -> 0 | BF71: =V71+Y71+W71+X71 -> 3058588.5 | BG71: =+SUM(AA71:BD71) -> #REF! | BH71: =SUM(BF71:BG71) -> #REF! | BI71: =BH71+BI70 -> #REF! | BJ71: =+BI71-$AX$8 -> #REF! | BQ71: =-AB70 -> 1918129.7 | BR71: -489562.42 | BS71: -79945.924 | BT71: 0 | BU71: -2934506.8 | BV71: 2692945 | BW71: =SUM(BQ71:BT71) -> 1348621.3 | BX71: =SUM(BR71:BT71) -> -569508.34 | BY71: =V71+BQ71+BR71+BS71+BT71+BU71+BV71 -> 4165648.1 | BZ71: =BG71 -> #REF! | CA71: =SUM(BY71:BZ71) -> #REF! | CB71: =CA71+CB70 -> #REF! | CC71: =CB71-$AX$8 -> #REF! | CE71: =PV($CE$5,A71,,-BH71) -> #REF! | CF71: =PV($CE$5,A71,,-CA71) -> #REF!
A72: =A71+1 -> 10 | C72: 43556 | D72: 50 | E72: 40 | F72: 10 | G72: 0 | H72: 0 | I72: 0 | J72: 3591682.1 | K72: =+'Fluxo Consolidado'!D67 -> 638500.94 | L72: =+'Fluxo Consolidado'!E67 -> 2478316.3 | M72: =+'Fluxo Consolidado'!F67 -> 69110.337 | N72: 0 | O72: =+O71 -> 0.1 | P72: =+'Fluxo Consolidado'!H67 -> -247831.63 | Q72: =+'Fluxo Consolidado'!I67 -> 246899.85 | R72: ='Fluxo Consolidado'!J67 -> 0 | S72: ='Fluxo Consolidado'!K67 -> 0 | T72: =((1+$T$4)^U72-1)*(SUM(K72:L72)*$T$1) -> 0 | U72: 1 | V72: =SUM(P72:R72,K72:N72)+T72 -> 3184995.8 | W72: 0 | X72: 0 | Y72: 0 | Z72: =IFERROR(SUM(AA72:AH72)/SUM($AA$8:$AH$8),0) -> 0.029348575 | AA72: 0 | AB72: =+'Fluxo Consolidado'!P67 -> -1918129.7 | AC72: ='Fluxo Consolidado'!Q67 -> -209557.71 | AD72: =+'Fluxo Consolidado'!R67 -> 0 | AE72: =+'Fluxo Consolidado'!S67 -> 0 | AF72: ='Fluxo Consolidado'!T67 -> 0 | AG72: =+'Fluxo Consolidado'!U67 -> 0 | AH72: =+'Fluxo Consolidado'!V67 -> 0 | AI72: =+'Fluxo Consolidado'!#REF! -> #REF! | AJ72: =+'Fluxo Consolidado'!X67 -> -5000 | AK72: 0 | AL72: =+'Fluxo Consolidado'!Y67+'Fluxo Consolidado'!Z67+'Fluxo Consolidado'!AA67 -> -378185.05 | AM72: =+'Fluxo Consolidado'!AB67+'Fluxo Consolidado'!AC67 -> -66979.384 | AN72: =+'Fluxo Consolidado'!AD67 -> 0 | AO72: ='Fluxo Consolidado'!AE67+'Fluxo Consolidado'!AF67 -> -358843.69 | AP72: =+'Fluxo Consolidado'!AG67 -> 0 | AQ72: =+'Fluxo Consolidado'!AH67 -> -183515.31 | AR72: =+'Fluxo Consolidado'!AI67 -> -9209.81 | AS72: =+'Fluxo Consolidado'!AJ67 -> -23969 | AT72: 0 | AU72: =+'Fluxo Consolidado'!AK67 -> -14069.046 | AV72: =+'Fluxo Consolidado'!AL67 -> -40237.62 | AW72: =-V71*$AW$2 -> -36703.063 | AX72: 0 | AY72: =(-V71*$AY$1)+'Fluxo Consolidado'!AO67 -> -132343.54 | AZ72: 0 | BA72: 0 | BB72: 0 | BC72: =+'Fluxo Consolidado'!AP67 -> 0 | BD72: =+'Fluxo Consolidado'!AQ67 -> 0 | BF72: =V72+Y72+W72+X72 -> 3184995.8 | BG72: =+SUM(AA72:BD72) -> #REF! | BH72: =SUM(BF72:BG72) -> #REF! | BI72: =BH72+BI71 -> #REF! | BJ72: =+BI72-$AX$8 -> #REF! | BQ72: =-AB71 -> 1918129.7 | BR72: -489562.42 | BS72: -80418.424 | BT72: 0 | BU72: -3059461.7 | BV72: 2934506.8 | BW72: =SUM(BQ72:BT72) -> 1348148.8 | BX72: =SUM(BR72:BT72) -> -569980.84 | BY72: =V72+BQ72+BR72+BS72+BT72+BU72+BV72 -> 4408189.7 | BZ72: =BG72 -> #REF! | CA72: =SUM(BY72:BZ72) -> #REF! | CB72: =CA72+CB71 -> #REF! | CC72: =CB72-$AX$8 -> #REF! | CE72: =PV($CE$5,A72,,-BH72) -> #REF! | CF72: =PV($CE$5,A72,,-CA72) -> #REF!
A73: =A72+1 -> 11 | C73: 43586 | D73: 70 | E73: 50 | F73: 5 | G73: 0 | H73: 0 | I73: 0 | J73: 4439907.1 | K73: =+'Fluxo Consolidado'!D68 -> 725772.28 | L73: =+'Fluxo Consolidado'!E68 -> 2477298.6 | M73: =+'Fluxo Consolidado'!F68 -> 69110.337 | N73: 0 | O73: =+O72 -> 0.1 | P73: =+'Fluxo Consolidado'!H68 -> -247729.86 | Q73: =+'Fluxo Consolidado'!I68 -> 247327.21 | R73: ='Fluxo Consolidado'!J68 -> 0 | S73: ='Fluxo Consolidado'!K68 -> 0 | T73: =((1+$T$4)^U73-1)*(SUM(K73:L73)*$T$1) -> 0 | U73: 1 | V73: =SUM(P73:R73,K73:N73)+T73 -> 3271778.6 | W73: 0 | X73: 0 | Y73: 0 | Z73: =IFERROR(SUM(AA73:AH73)/SUM($AA$8:$AH$8),0) -> 0.029348575 | AA73: 0 | AB73: =+'Fluxo Consolidado'!P68 -> -1918129.7 | AC73: ='Fluxo Consolidado'!Q68 -> -209557.71 | AD73: =+'Fluxo Consolidado'!R68 -> 0 | AE73: =+'Fluxo Consolidado'!S68 -> 0 | AF73: ='Fluxo Consolidado'!T68 -> 0 | AG73: =+'Fluxo Consolidado'!U68 -> 0 | AH73: =+'Fluxo Consolidado'!V68 -> 0 | AI73: =+'Fluxo Consolidado'!#REF! -> #REF! | AJ73: =+'Fluxo Consolidado'!X68 -> -5000 | AK73: 0 | AL73: =+'Fluxo Consolidado'!Y68+'Fluxo Consolidado'!Z68+'Fluxo Consolidado'!AA68 -> -374204.63 | AM73: =+'Fluxo Consolidado'!AB68+'Fluxo Consolidado'!AC68 -> -68466.337 | AN73: =+'Fluxo Consolidado'!AD68 -> 0 | AO73: ='Fluxo Consolidado'!AE68+'Fluxo Consolidado'!AF68 -> -349510.36 | AP73: =+'Fluxo Consolidado'!AG68 -> 0 | AQ73: =+'Fluxo Consolidado'!AH68 -> -191099.75 | AR73: =+'Fluxo Consolidado'!AI68 -> -9209.81 | AS73: =+'Fluxo Consolidado'!AJ68 -> -23969 | AT73: 0 | AU73: =+'Fluxo Consolidado'!AK68 -> -14677.487 | AV73: =+'Fluxo Consolidado'!AL68 -> -34414.14 | AW73: =-V72*$AW$2 -> -38219.95 | AX73: 0 | AY73: =(-V72*$AY$1)+'Fluxo Consolidado'!AO68 -> -127399.83 | AZ73: 0 | BA73: 0 | BB73: 0 | BC73: =+'Fluxo Consolidado'!AP68 -> 0 | BD73: =+'Fluxo Consolidado'!AQ68 -> 0 | BF73: =V73+Y73+W73+X73 -> 3271778.6 | BG73: =+SUM(AA73:BD73) -> #REF! | BH73: =SUM(BF73:BG73) -> #REF! | BI73: =BH73+BI72 -> #REF! | BJ73: =+BI73-$AX$8 -> #REF! | BQ73: =-AB72 -> 1918129.7 | BR73: -489562.42 | BS73: -81468.424 | BT73: 0 | BU73: -3128191.9 | BV73: 3059461.7 | BW73: =SUM(BQ73:BT73) -> 1347098.8 | BX73: =SUM(BR73:BT73) -> -571030.84 | BY73: =V73+BQ73+BR73+BS73+BT73+BU73+BV73 -> 4550147.3 | BZ73: =BG73 -> #REF! | CA73: =SUM(BY73:BZ73) -> #REF! | CB73: =CA73+CB72 -> #REF! | CC73: =CB73-$AX$8 -> #REF! | CE73: =PV($CE$5,A73,,-BH73) -> #REF! | CF73: =PV($CE$5,A73,,-CA73) -> #REF!
A74: =A73+1 -> 12 | C74: 43617 | D74: 50 | E74: 95 | F74: 5 | G74: 0 | H74: 0 | I74: 0 | J74: 5797182.3 | K74: =+'Fluxo Consolidado'!D69 -> 745105.49 | L74: =+'Fluxo Consolidado'!E69 -> 2477603.4 | M74: =+'Fluxo Consolidado'!F69 -> 69110.337 | N74: 0 | O74: =+O73 -> 0.1 | P74: =+'Fluxo Consolidado'!H69 -> -247760.34 | Q74: =+'Fluxo Consolidado'!I69 -> 247706.82 | R74: ='Fluxo Consolidado'!J69 -> 0 | S74: ='Fluxo Consolidado'!K69 -> 0 | T74: =((1+$T$4)^U74-1)*(SUM(K74:L74)*$T$1) -> 0 | U74: 1 | V74: =SUM(P74:R74,K74:N74)+T74 -> 3291765.7 | W74: 0 | X74: 0 | Y74: 0 | Z74: =IFERROR(SUM(AA74:AH74)/SUM($AA$8:$AH$8),0) -> 0.043596035 | AA74: 0 | AB74: =+'Fluxo Consolidado'!P69 -> -1918129.7 | AC74: ='Fluxo Consolidado'!Q69 -> -209557.71 | AD74: =+'Fluxo Consolidado'!R69 -> -972900 | AE74: =+'Fluxo Consolidado'!S69 -> 0 | AF74: ='Fluxo Consolidado'!T69 -> -60000 | AG74: =+'Fluxo Consolidado'!U69 -> 0 | AH74: =+'Fluxo Consolidado'!V69 -> 0 | AI74: =+'Fluxo Consolidado'!#REF! -> #REF! | AJ74: =+'Fluxo Consolidado'!X69 -> -5000 | AK74: 0 | AL74: =+'Fluxo Consolidado'!Y69+'Fluxo Consolidado'!Z69+'Fluxo Consolidado'!AA69 -> -365814.7 | AM74: =+'Fluxo Consolidado'!AB69+'Fluxo Consolidado'!AC69 -> -68940.927 | AN74: =+'Fluxo Consolidado'!AD69 -> 0 | AO74: ='Fluxo Consolidado'!AE69+'Fluxo Consolidado'!AF69 -> -172400 | AP74: =+'Fluxo Consolidado'!AG69 -> 0 | AQ74: =+'Fluxo Consolidado'!AH69 -> -196306.71 | AR74: =+'Fluxo Consolidado'!AI69 -> -9209.81 | AS74: =+'Fluxo Consolidado'!AJ69 -> -7969 | AT74: 0 | AU74: =+'Fluxo Consolidado'!AK69 -> -15097.477 | AV74: =+'Fluxo Consolidado'!AL69 -> -29838.75 | AW74: =-V73*$AW$2 -> -39261.343 | AX74: 0 | AY74: =(-V73*$AY$1)+'Fluxo Consolidado'!AO69 -> -130871.14 | AZ74: 0 | BA74: 0 | BB74: 0 | BC74: =+'Fluxo Consolidado'!AP69 -> 0 | BD74: =+'Fluxo Consolidado'!AQ69 -> 0 | BF74: =V74+Y74+W74+X74 -> 3291765.7 | BG74: =+SUM(AA74:BD74) -> #REF! | BH74: =SUM(BF74:BG74) -> #REF! | BI74: =BH74+BI73 -> #REF! | BJ74: =+BI74-$AX$8 -> #REF! | BQ74: =-AB73 -> 1918129.7 | BR74: -489562.42 | BS74: -82780.924 | BT74: 0 | BU74: -3147521.3 | BV74: 3128191.9 | BW74: =SUM(BQ74:BT74) -> 1345786.3 | BX74: =SUM(BR74:BT74) -> -572343.34 | BY74: =V74+BQ74+BR74+BS74+BT74+BU74+BV74 -> 4618222.6 | BZ74: =BG74 -> #REF! | CA74: =SUM(BY74:BZ74) -> #REF! | CB74: =CA74+CB73 -> #REF! | CC74: =CB74-$AX$8 -> #REF! | CE74: =PV($CE$5,A74,,-BH74) -> #REF! | CF74: =PV($CE$5,A74,,-CA74) -> #REF!
A75: =A74+1 -> 13 | C75: 43647 | D75: 100 | E75: 475 | F75: 15 | G75: 0 | H75: 0 | I75: 0 | J75: 24149230 | K75: =+'Fluxo Consolidado'!D70 -> 787321.33 | L75: =+'Fluxo Consolidado'!E70 -> 2478692.8 | M75: =+'Fluxo Consolidado'!F70 -> 69110.337 | N75: 0 | O75: =+O74 -> 0.1 | P75: =+'Fluxo Consolidado'!H70 -> -247869.28 | Q75: =+'Fluxo Consolidado'!I70 -> 247831.63 | R75: ='Fluxo Consolidado'!J70 -> 0 | S75: ='Fluxo Consolidado'!K70 -> 0 | T75: =((1+$T$4)^U75-1)*(SUM(K75:L75)*$T$1) -> 0 | U75: 1 | V75: =SUM(P75:R75,K75:N75)+T75 -> 3335086.8 | W75: 0 | X75: 0 | Y75: 0 | Z75: =IFERROR(SUM(AA75:AH75)/SUM($AA$8:$AH$8),0) -> 0.047840235 | AA75: 0 | AB75: =+'Fluxo Consolidado'!P70 -> -1918129.7 | AC75: ='Fluxo Consolidado'!Q70 -> -209557.71 | AD75: =+'Fluxo Consolidado'!R70 -> -1280592.3 | AE75: =+'Fluxo Consolidado'!S70 -> 0 | AF75: ='Fluxo Consolidado'!T70 -> -60000 | AG75: =+'Fluxo Consolidado'!U70 -> 0 | AH75: =+'Fluxo Consolidado'!V70 -> 0 | AI75: =+'Fluxo Consolidado'!#REF! -> #REF! | AJ75: =+'Fluxo Consolidado'!X70 -> -2000 | AK75: 0 | AL75: =+'Fluxo Consolidado'!Y70+'Fluxo Consolidado'!Z70+'Fluxo Consolidado'!AA70 -> -353178.55 | AM75: =+'Fluxo Consolidado'!AB70+'Fluxo Consolidado'!AC70 -> -69968.568 | AN75: =+'Fluxo Consolidado'!AD70 -> 0 | AO75: ='Fluxo Consolidado'!AE70+'Fluxo Consolidado'!AF70 -> -163333.33 | AP75: =+'Fluxo Consolidado'!AG70 -> 0 | AQ75: =+'Fluxo Consolidado'!AH70 -> -197505.94 | AR75: =+'Fluxo Consolidado'!AI70 -> -9209.81 | AS75: =+'Fluxo Consolidado'!AJ70 -> -7969 | AT75: 0 | AU75: =+'Fluxo Consolidado'!AK70 -> -15746.698 | AV75: =+'Fluxo Consolidado'!AL70 -> -26964.79 | AW75: =-V74*$AW$2 -> -39501.189 | AX75: 0 | AY75: =(-V74*$AY$1)+'Fluxo Consolidado'!AO70 -> -131670.63 | AZ75: 0 | BA75: 0 | BB75: 0 | BC75: =+'Fluxo Consolidado'!AP70 -> 0 | BD75: =+'Fluxo Consolidado'!AQ70 -> 0 | BF75: =V75+Y75+W75+X75 -> 3335086.8 | BG75: =+SUM(AA75:BD75) -> #REF! | BH75: =SUM(BF75:BG75) -> #REF! | BI75: =BH75+BI74 -> #REF! | BJ75: =+BI75-$AX$8 -> #REF! | BQ75: =-AB74 -> 1918129.7 | BR75: -489562.42 | BS75: -84355.924 | BT75: 0 | BU75: -3190236.8 | BV75: 3147521.3 | BW75: =SUM(BQ75:BT75) -> 1344211.3 | BX75: =SUM(BR75:BT75) -> -573918.34 | BY75: =V75+BQ75+BR75+BS75+BT75+BU75+BV75 -> 4636582.6 | BZ75: =BG75 -> #REF! | CA75: =SUM(BY75:BZ75) -> #REF! | CB75: =CA75+CB74 -> #REF! | CC75: =CB75-$AX$8 -> #REF! | CE75: =PV($CE$5,A75,,-BH75) -> #REF! | CF75: =PV($CE$5,A75,,-CA75) -> #REF!
A76: =A75+1 -> 14 | C76: 43678 | D76: 57 | E76: 100 | F76: 15 | G76: 0 | H76: 0 | I76: 0 | J76: 6587364.4 | K76: =+'Fluxo Consolidado'!D71 -> 839906.23 | L76: =+'Fluxo Consolidado'!E71 -> 2478928.9 | M76: =+'Fluxo Consolidado'!F71 -> 69110.337 | N76: 0 | O76: =+O75 -> 0.1 | P76: =+'Fluxo Consolidado'!H71 -> -247892.89 | Q76: =+'Fluxo Consolidado'!I71 -> 247729.86 | R76: ='Fluxo Consolidado'!J71 -> 0 | S76: ='Fluxo Consolidado'!K71 -> 0 | T76: =((1+$T$4)^U76-1)*(SUM(K76:L76)*$T$1) -> 0 | U76: 1 | V76: =SUM(P76:R76,K76:N76)+T76 -> 3387782.4 | W76: 0 | X76: 0 | Y76: 0 | Z76: =IFERROR(SUM(AA76:AH76)/SUM($AA$8:$AH$8),0) -> 0.047840235 | AA76: 0 | AB76: =+'Fluxo Consolidado'!P71 -> -1918129.7 | AC76: ='Fluxo Consolidado'!Q71 -> -209557.71 | AD76: =+'Fluxo Consolidado'!R71 -> -1280592.3 | AE76: =+'Fluxo Consolidado'!S71 -> 0 | AF76: ='Fluxo Consolidado'!T71 -> -60000 | AG76: =+'Fluxo Consolidado'!U71 -> 0 | AH76: =+'Fluxo Consolidado'!V71 -> 0 | AI76: =+'Fluxo Consolidado'!#REF! -> #REF! | AJ76: =+'Fluxo Consolidado'!X71 -> -2000 | AK76: 0 | AL76: =+'Fluxo Consolidado'!Y71+'Fluxo Consolidado'!Z71+'Fluxo Consolidado'!AA71 -> -384118.07 | AM76: =+'Fluxo Consolidado'!AB71+'Fluxo Consolidado'!AC71 -> -71174.463 | AN76: =+'Fluxo Consolidado'!AD71 -> 0 | AO76: ='Fluxo Consolidado'!AE71+'Fluxo Consolidado'!AF71 -> -166000 | AP76: =+'Fluxo Consolidado'!AG71 -> 0 | AQ76: =+'Fluxo Consolidado'!AH71 -> -200105.21 | AR76: =+'Fluxo Consolidado'!AI71 -> -9209.81 | AS76: =+'Fluxo Consolidado'!AJ71 -> -7969 | AT76: 0 | AU76: =+'Fluxo Consolidado'!AK71 -> -16317.504 | AV76: =+'Fluxo Consolidado'!AL71 -> -24397.08 | AW76: =-V75*$AW$2 -> -40021.041 | AX76: 0 | AY76: =(-V75*$AY$1)+'Fluxo Consolidado'!AO71 -> -133403.47 | AZ76: 0 | BA76: 0 | BB76: 0 | BC76: =+'Fluxo Consolidado'!AP71 -> 0 | BD76: =+'Fluxo Consolidado'!AQ71 -> 0 | BF76: =V76+Y76+W76+X76 -> 3387782.4 | BG76: =+SUM(AA76:BD76) -> #REF! | BH76: =SUM(BF76:BG76) -> #REF! | BI76: =BH76+BI75 -> #REF! | BJ76: =+BI76-$AX$8 -> #REF! | BQ76: =-AB75 -> 1918129.7 | BR76: -489562.42 | BS76: -106112.68 | BT76: 0 | BU76: -3242484.4 | BV76: 3190236.8 | BW76: =SUM(BQ76:BT76) -> 1322454.6 | BX76: =SUM(BR76:BT76) -> -595675.1 | BY76: =V76+BQ76+BR76+BS76+BT76+BU76+BV76 -> 4657989.4 | BZ76: =BG76 -> #REF! | CA76: =SUM(BY76:BZ76) -> #REF! | CB76: =CA76+CB75 -> #REF! | CC76: =CB76-$AX$8 -> #REF! | CE76: =PV($CE$5,A76,,-BH76) -> #REF! | CF76: =PV($CE$5,A76,,-CA76) -> #REF!
A77: =A76+1 -> 15 | C77: 43709 | D77: 112 | E77: 30 | F77: 77 | G77: 0 | H77: 0 | I77: 0 | J77: 7447652.2 | K77: =+'Fluxo Consolidado'!D72 -> 908649.16 | L77: =+'Fluxo Consolidado'!E72 -> 2478205.6 | M77: =+'Fluxo Consolidado'!F72 -> 69110.337 | N77: 0 | O77: =+O76 -> 0.1 | P77: =+'Fluxo Consolidado'!H72 -> -247820.56 | Q77: =+'Fluxo Consolidado'!I72 -> 247760.34 | R77: ='Fluxo Consolidado'!J72 -> 0 | S77: ='Fluxo Consolidado'!K72 -> 0 | T77: =((1+$T$4)^U77-1)*(SUM(K77:L77)*$T$1) -> 0 | U77: 2 | V77: =SUM(P77:R77,K77:N77)+T77 -> 3455904.9 | W77: 0 | X77: 0 | Y77: 0 | Z77: =IFERROR(SUM(AA77:AH77)/SUM($AA$8:$AH$8),0) -> 0.04978352 | AA77: 0 | AB77: =+'Fluxo Consolidado'!P72 -> -1918129.7 | AC77: ='Fluxo Consolidado'!Q72 -> -209557.71 | AD77: =+'Fluxo Consolidado'!R72 -> -1280592.3 | AE77: =+'Fluxo Consolidado'!S72 -> -100000 | AF77: ='Fluxo Consolidado'!T72 -> -60000 | AG77: =+'Fluxo Consolidado'!U72 -> 0 | AH77: =+'Fluxo Consolidado'!V72 -> -40882.573 | AI77: =+'Fluxo Consolidado'!#REF! -> #REF! | AJ77: =+'Fluxo Consolidado'!X72 -> -2000 | AK77: 0 | AL77: =+'Fluxo Consolidado'!Y72+'Fluxo Consolidado'!Z72+'Fluxo Consolidado'!AA72 -> -372266.09 | AM77: =+'Fluxo Consolidado'!AB72+'Fluxo Consolidado'!AC72 -> -72697.426 | AN77: =+'Fluxo Consolidado'!AD72 -> 0 | AO77: ='Fluxo Consolidado'!AE72+'Fluxo Consolidado'!AF72 -> -116800 | AP77: =+'Fluxo Consolidado'!AG72 -> 0 | AQ77: =+'Fluxo Consolidado'!AH72 -> -203266.95 | AR77: =+'Fluxo Consolidado'!AI72 -> -9209.81 | AS77: =+'Fluxo Consolidado'!AJ72 -> -7969 | AT77: 0 | AU77: =+'Fluxo Consolidado'!AK72 -> -16466.781 | AV77: =+'Fluxo Consolidado'!AL72 -> -22365.19 | AW77: =-V76*$AW$2 -> -40653.389 | AX77: 0 | AY77: =(-V76*$AY$1)+'Fluxo Consolidado'!AO72 -> -135511.3 | AZ77: 0 | BA77: 0 | BB77: 0 | BC77: =+'Fluxo Consolidado'!AP72 -> 0 | BD77: =+'Fluxo Consolidado'!AQ72 -> 0 | BF77: =V77+Y77+W77+X77 -> 3455904.9 | BG77: =+SUM(AA77:BD77) -> #REF! | BH77: =SUM(BF77:BG77) -> #REF! | BI77: =BH77+BI76 -> #REF! | BJ77: =+BI77-$AX$8 -> #REF! | BQ77: =-AB76 -> 1918129.7 | BR77: -489562.42 | BS77: -92356.924 | BT77: 0 | BU77: -3310093.9 | BV77: 3242484.4 | BW77: =SUM(BQ77:BT77) -> 1336210.3 | BX77: =SUM(BR77:BT77) -> -581919.34 | BY77: =V77+BQ77+BR77+BS77+BT77+BU77+BV77 -> 4724505.7 | BZ77: =BG77 -> #REF! | CA77: =SUM(BY77:BZ77) -> #REF! | CB77: =CA77+CB76 -> #REF! | CC77: =CB77-$AX$8 -> #REF! | CE77: =PV($CE$5,A77,,-BH77) -> #REF! | CF77: =PV($CE$5,A77,,-CA77) -> #REF!
A78: =A77+1 -> 16 | C78: 43739 | D78: 0 | E78: 0 | F78: 0 | G78: 0 | H78: 0 | I78: 0 | J78: 0 | K78: =+'Fluxo Consolidado'!D73 -> 1102815.9 | L78: =+'Fluxo Consolidado'!E73 -> 2473443.2 | M78: =+'Fluxo Consolidado'!F73 -> 69110.337 | N78: 0 | O78: =+O77 -> 0.1 | P78: =+'Fluxo Consolidado'!H73 -> -247344.32 | Q78: =+'Fluxo Consolidado'!I73 -> 247869.28 | R78: ='Fluxo Consolidado'!J73 -> 0 | S78: ='Fluxo Consolidado'!K73 -> 0 | T78: =((1+$T$4)^U78-1)*(SUM(K78:L78)*$T$1) -> 0 | U78: 2 | V78: =SUM(P78:R78,K78:N78)+T78 -> 3645894.4 | W78: 0 | X78: 0 | Y78: 0 | Z78: =IFERROR(SUM(AA78:AH78)/SUM($AA$8:$AH$8),0) -> 0.04978352 | AA78: 0 | AB78: =+'Fluxo Consolidado'!P73 -> -1918129.7 | AC78: ='Fluxo Consolidado'!Q73 -> -209557.71 | AD78: =+'Fluxo Consolidado'!R73 -> -1280592.3 | AE78: =+'Fluxo Consolidado'!S73 -> -100000 | AF78: ='Fluxo Consolidado'!T73 -> -60000 | AG78: =+'Fluxo Consolidado'!U73 -> 0 | AH78: =+'Fluxo Consolidado'!V73 -> -40882.573 | AI78: =+'Fluxo Consolidado'!#REF! -> #REF! | AJ78: =+'Fluxo Consolidado'!X73 -> -2000 | AK78: 0 | AL78: =+'Fluxo Consolidado'!Y73+'Fluxo Consolidado'!Z73+'Fluxo Consolidado'!AA73 -> -316118.04 | AM78: =+'Fluxo Consolidado'!AB73+'Fluxo Consolidado'!AC73 -> -76812.622 | AN78: =+'Fluxo Consolidado'!AD73 -> 0 | AO78: ='Fluxo Consolidado'!AE73+'Fluxo Consolidado'!AF73 -> -130800 | AP78: =+'Fluxo Consolidado'!AG73 -> 0 | AQ78: =+'Fluxo Consolidado'!AH73 -> -207354.29 | AR78: =+'Fluxo Consolidado'!AI73 -> -9209.81 | AS78: =+'Fluxo Consolidado'!AJ73 -> -7969 | AT78: 0 | AU78: =+'Fluxo Consolidado'!AK73 -> -16646.083 | AV78: =+'Fluxo Consolidado'!AL73 -> -19689.79 | AW78: =-V77*$AW$2 -> -41470.858 | AX78: 0 | AY78: =(-V77*$AY$1)+'Fluxo Consolidado'!AO73 -> -138236.19 | AZ78: 0 | BA78: 0 | BB78: 0 | BC78: =+'Fluxo Consolidado'!AP73 -> 0 | BD78: =+'Fluxo Consolidado'!AQ73 -> 0 | BF78: =V78+Y78+W78+X78 -> 3645894.4 | BG78: =+SUM(AA78:BD78) -> #REF! | BH78: =SUM(BF78:BG78) -> #REF! | BI78: =BH78+BI77 -> #REF! | BJ78: =+BI78-$AX$8 -> #REF! | BQ78: =-AB77 -> 1918129.7 | BR78: -489562.42 | BS78: -94656.424 | BT78: 0 | BU78: -3592581.8 | BV78: 3310093.9 | BW78: =SUM(BQ78:BT78) -> 1333910.8 | BX78: =SUM(BR78:BT78) -> -584218.84 | BY78: =V78+BQ78+BR78+BS78+BT78+BU78+BV78 -> 4697317.3 | BZ78: =BG78 -> #REF! | CA78: =SUM(BY78:BZ78) -> #REF! | CB78: =CA78+CB77 -> #REF! | CC78: =CB78-$AX$8 -> #REF! | CE78: =PV($CE$5,A78,,-BH78) -> #REF! | CF78: =PV($CE$5,A78,,-CA78) -> #REF!
A79: =A78+1 -> 17 | C79: 43770 | D79: 0 | E79: 0 | F79: 0 | G79: 0 | H79: 0 | I79: 0 | J79: 0 | K79: =+'Fluxo Consolidado'!D74 -> 1128741.5 | L79: =+'Fluxo Consolidado'!E74 -> 2472474.6 | M79: =+'Fluxo Consolidado'!F74 -> 69110.337 | N79: 0 | O79: =+O78 -> 0.1 | P79: =+'Fluxo Consolidado'!H74 -> -247247.46 | Q79: =+'Fluxo Consolidado'!I74 -> 247892.89 | R79: ='Fluxo Consolidado'!J74 -> 0 | S79: ='Fluxo Consolidado'!K74 -> 0 | T79: =((1+$T$4)^U79-1)*(SUM(K79:L79)*$T$1) -> 0 | U79: 2 | V79: =SUM(P79:R79,K79:N79)+T79 -> 3670971.9 | W79: 0 | X79: 0 | Y79: 0 | Z79: =IFERROR(SUM(AA79:AH79)/SUM($AA$8:$AH$8),0) -> 0.04642856 | AA79: 0 | AB79: =+'Fluxo Consolidado'!P74 -> -1918129.7 | AC79: ='Fluxo Consolidado'!Q74 -> -209557.71 | AD79: =+'Fluxo Consolidado'!R74 -> -1037367.3 | AE79: =+'Fluxo Consolidado'!S74 -> -100000 | AF79: ='Fluxo Consolidado'!T74 -> -60000 | AG79: =+'Fluxo Consolidado'!U74 -> 0 | AH79: =+'Fluxo Consolidado'!V74 -> -40882.573 | AI79: =+'Fluxo Consolidado'!#REF! -> #REF! | AJ79: =+'Fluxo Consolidado'!X74 -> -2000 | AK79: 0 | AL79: =+'Fluxo Consolidado'!Y74+'Fluxo Consolidado'!Z74+'Fluxo Consolidado'!AA74 -> -313641.88 | AM79: =+'Fluxo Consolidado'!AB74+'Fluxo Consolidado'!AC74 -> -77498.356 | AN79: =+'Fluxo Consolidado'!AD74 -> 0 | AO79: ='Fluxo Consolidado'!AE74+'Fluxo Consolidado'!AF74 -> -120400 | AP79: =+'Fluxo Consolidado'!AG74 -> 0 | AQ79: =+'Fluxo Consolidado'!AH74 -> -218753.66 | AR79: =+'Fluxo Consolidado'!AI74 -> -9209.81 | AS79: =+'Fluxo Consolidado'!AJ74 -> -7969 | AT79: 0 | AU79: =+'Fluxo Consolidado'!AK74 -> -16934.841 | AV79: =+'Fluxo Consolidado'!AL74 -> -18481.86 | AW79: =-V78*$AW$2 -> -43750.733 | AX79: 0 | AY79: =(-V78*$AY$1)+'Fluxo Consolidado'!AO74 -> -145835.78 | AZ79: 0 | BA79: 0 | BB79: 0 | BC79: =+'Fluxo Consolidado'!AP74 -> 0 | BD79: =+'Fluxo Consolidado'!AQ74 -> 0 | BF79: =V79+Y79+W79+X79 -> 3670971.9 | BG79: =+SUM(AA79:BD79) -> #REF! | BH79: =SUM(BF79:BG79) -> #REF! | BI79: =BH79+BI78 -> #REF! | BJ79: =+BI79-$AX$8 -> #REF! | BQ79: =-AB78 -> 1918129.7 | BR79: -489562.42 | BS79: -92291.726 | BT79: 0 | BU79: -3669304.2 | BV79: 3592581.8 | BW79: =SUM(BQ79:BT79) -> 1336275.5 | BX79: =SUM(BR79:BT79) -> -581854.14 | BY79: =V79+BQ79+BR79+BS79+BT79+BU79+BV79 -> 4930525.1 | BZ79: =BG79 -> #REF! | CA79: =SUM(BY79:BZ79) -> #REF! | CB79: =CA79+CB78 -> #REF! | CC79: =CB79-$AX$8 -> #REF! | CE79: =PV($CE$5,A79,,-BH79) -> #REF! | CF79: =PV($CE$5,A79,,-CA79) -> #REF!
A80: =A79+1 -> 18 | B80: FIM OBRA | C80: 43800 | D80: 0 | E80: 0 | F80: 0 | G80: 0 | H80: 0 | I80: 0 | J80: 0 | K80: =+'Fluxo Consolidado'!D75 -> 1176086.9 | L80: =+'Fluxo Consolidado'!E75 -> 2473021.8 | M80: =+'Fluxo Consolidado'!F75 -> 69110.337 | N80: 0 | O80: =+O79 -> 0.1 | P80: =+'Fluxo Consolidado'!H75 -> -247302.18 | Q80: =+'Fluxo Consolidado'!I75 -> 247820.56 | R80: ='Fluxo Consolidado'!J75 -> 0 | S80: ='Fluxo Consolidado'!K75 -> 0 | T80: =((1+$T$4)^U80-1)*(SUM(K80:L80)*$T$1) -> 0 | U80: 2 | V80: =SUM(P80:R80,K80:N80)+T80 -> 3718737.5 | W80: 0 | X80: 0 | Y80: 0 | Z80: =IFERROR(SUM(AA80:AH80)/SUM($AA$8:$AH$8),0) -> 0.047302229 | AA80: 0 | AB80: =+'Fluxo Consolidado'!P75 -> -2019083.9 | AC80: ='Fluxo Consolidado'!Q75 -> -220587.06 | AD80: =+'Fluxo Consolidado'!R75 -> -988722.31 | AE80: =+'Fluxo Consolidado'!S75 -> -100000 | AF80: ='Fluxo Consolidado'!T75 -> -60000 | AG80: =+'Fluxo Consolidado'!U75 -> 0 | AH80: =+'Fluxo Consolidado'!V75 -> -40882.573 | AI80: =+'Fluxo Consolidado'!#REF! -> #REF! | AJ80: =+'Fluxo Consolidado'!X75 -> -2000 | AK80: 0 | AL80: =+'Fluxo Consolidado'!Y75+'Fluxo Consolidado'!Z75+'Fluxo Consolidado'!AA75 -> -298825.36 | AM80: =+'Fluxo Consolidado'!AB75+'Fluxo Consolidado'!AC75 -> -78840.86 | AN80: =+'Fluxo Consolidado'!AD75 -> 0 | AO80: ='Fluxo Consolidado'!AE75+'Fluxo Consolidado'!AF75 -> -132000 | AP80: =+'Fluxo Consolidado'!AG75 -> 0 | AQ80: =+'Fluxo Consolidado'!AH75 -> -220258.31 | AR80: =+'Fluxo Consolidado'!AI75 -> -9209.81 | AS80: =+'Fluxo Consolidado'!AJ75 -> -7969 | AT80: 0 | AU80: =+'Fluxo Consolidado'!AK75 -> -16761.086 | AV80: =+'Fluxo Consolidado'!AL75 -> -17629.73 | AW80: =-V79*$AW$2 -> -44051.662 | AX80: 0 | AY80: =(-V79*$AY$1)+'Fluxo Consolidado'!AO75 -> -146838.87 | AZ80: 0 | BA80: 0 | BB80: 0 | BC80: =+'Fluxo Consolidado'!AP75 -> 0 | BD80: =+'Fluxo Consolidado'!AQ75 -> 0 | BF80: =V80+Y80+W80+X80 -> 3718737.5 | BG80: =+SUM(AA80:BD80) -> #REF! | BH80: =SUM(BF80:BG80) -> #REF! | BI80: =BH80+BI79 -> #REF! | BJ80: =+BI80-$AX$8 -> #REF! | BQ80: =-AB79 -> 1918129.7 | BR80: -489562.42 | BS80: -89994.074 | BT80: 0 | BU80: -3754154.6 | BV80: 3669304.2 | BW80: =SUM(BQ80:BT80) -> 1338573.2 | BX80: =SUM(BR80:BT80) -> -579556.49 | BY80: =V80+BQ80+BR80+BS80+BT80+BU80+BV80 -> 4972460.2 | BZ80: =BG80 -> #REF! | CA80: =SUM(BY80:BZ80) -> #REF! | CB80: =CA80+CB79 -> #REF! | CC80: =CB80-$AX$8 -> #REF! | CE80: =PV($CE$5,A80,,-BH80) -> #REF! | CF80: =PV($CE$5,A80,,-CA80) -> #REF!
A81: =A80+1 -> 19 | C81: 43831 | D81: 0 | E81: 0 | F81: 0 | G81: 0 | H81: 0 | I81: 0 | J81: 0 | K81: =+'Fluxo Consolidado'!D76 -> 1259824.3 | L81: =+'Fluxo Consolidado'!E76 -> 2470659.1 | M81: =+'Fluxo Consolidado'!F76 -> 69110.337 | N81: 0 | O81: =+O80 -> 0.1 | P81: =+'Fluxo Consolidado'!H76 -> -247065.91 | Q81: =+'Fluxo Consolidado'!I76 -> 247344.32 | R81: ='Fluxo Consolidado'!J76 -> 0 | S81: ='Fluxo Consolidado'!K76 -> 0 | T81: =((1+$T$4)^U81-1)*(SUM(K81:L81)*$T$1) -> 0 | U81: 2 | V81: =SUM(P81:R81,K81:N81)+T81 -> 3799872.1 | W81: 0 | X81: 0 | Y81: 0 | Z81: =IFERROR(SUM(AA81:AH81)/SUM($AA$8:$AH$8),0) -> 0.036692274 | AA81: 0 | AB81: =+'Fluxo Consolidado'!P76 -> -1413358.7 | AC81: ='Fluxo Consolidado'!Q76 -> -154410.94 | AD81: =+'Fluxo Consolidado'!R76 -> -891432.31 | AE81: =+'Fluxo Consolidado'!S76 -> -100000 | AF81: ='Fluxo Consolidado'!T76 -> -60000 | AG81: =+'Fluxo Consolidado'!U76 -> 0 | AH81: =+'Fluxo Consolidado'!V76 -> -40882.573 | AI81: =+'Fluxo Consolidado'!#REF! -> #REF! | AJ81: =+'Fluxo Consolidado'!X76 -> -2000 | AK81: 0 | AL81: =+'Fluxo Consolidado'!Y76+'Fluxo Consolidado'!Z76+'Fluxo Consolidado'!AA76 -> -277661.99 | AM81: =+'Fluxo Consolidado'!AB76+'Fluxo Consolidado'!AC76 -> -82043.172 | AN81: =+'Fluxo Consolidado'!AD76 -> 0 | AO81: ='Fluxo Consolidado'!AE76+'Fluxo Consolidado'!AF76 -> -149066.67 | AP81: =+'Fluxo Consolidado'!AG76 -> 0 | AQ81: =+'Fluxo Consolidado'!AH76 -> -223124.25 | AR81: =+'Fluxo Consolidado'!AI76 -> -9209.81 | AS81: =+'Fluxo Consolidado'!AJ76 -> -7969 | AT81: 0 | AU81: =+'Fluxo Consolidado'!AK76 -> -16865.733 | AV81: =+'Fluxo Consolidado'!AL76 -> -22476.67 | AW81: =-V80*$AW$2 -> -44624.85 | AX81: 0 | AY81: =(-V80*$AY$1)+'Fluxo Consolidado'!AO76 -> -148749.5 | AZ81: 0 | BA81: 0 | BB81: 0 | BC81: =+'Fluxo Consolidado'!AP76 -> 0 | BD81: =+'Fluxo Consolidado'!AQ76 -> 0 | BF81: =V81+Y81+W81+X81 -> 3799872.1 | BG81: =+SUM(AA81:BD81) -> #REF! | BH81: =SUM(BF81:BG81) -> #REF! | BI81: =BH81+BI80 -> #REF! | BJ81: =+BI81-$AX$8 -> #REF! | BQ81: =-AB80 -> 2019083.9 | BR81: -489562.42 | BS81: -87761.569 | BT81: 0 | BU81: -3769632.3 | BV81: 3754154.6 | BW81: =SUM(BQ81:BT81) -> 1441759.9 | BX81: =SUM(BR81:BT81) -> -577323.99 | BY81: =V81+BQ81+BR81+BS81+BT81+BU81+BV81 -> 5226154.3 | BZ81: =BG81 -> #REF! | CA81: =SUM(BY81:BZ81) -> #REF! | CB81: =CA81+CB80 -> #REF! | CC81: =CB81-$AX$8 -> #REF! | CE81: =PV($CE$5,A81,,-BH81) -> #REF! | CF81: =PV($CE$5,A81,,-CA81) -> #REF!
A82: =A81+1 -> 20 | C82: 43862 | D82: 0 | E82: 0 | F82: 0 | G82: 0 | H82: 0 | I82: 0 | J82: 0 | K82: =+'Fluxo Consolidado'!D77 -> 1268342.9 | L82: =+'Fluxo Consolidado'!E77 -> 2466681.6 | M82: =+'Fluxo Consolidado'!F77 -> 69110.337 | N82: 0 | O82: =+O81 -> 0.1 | P82: =+'Fluxo Consolidado'!H77 -> -246668.16 | Q82: =+'Fluxo Consolidado'!I77 -> 247247.46 | R82: ='Fluxo Consolidado'!J77 -> 18675.123 | S82: ='Fluxo Consolidado'!K77 -> 1 | T82: =((1+$T$4)^U82-1)*(SUM(K82:L82)*$T$1) -> 0 | U82: 2 | V82: =SUM(P82:R82,K82:N82)+T82 -> 3823389.3 | W82: 0 | X82: 0 | Y82: 0 | Z82: =IFERROR(SUM(AA82:AH82)/SUM($AA$8:$AH$8),0) -> 0.029067889 | AA82: 0 | AB82: -1009541.9 | AC82: -5481.71 | AD82: =+'Fluxo Consolidado'!R77 -> -891432.31 | AE82: =+'Fluxo Consolidado'!S77 -> -100000 | AF82: ='Fluxo Consolidado'!T77 -> -60000 | AG82: =+'Fluxo Consolidado'!U77 -> 0 | AH82: =+'Fluxo Consolidado'!V77 -> -40882.573 | AI82: =+'Fluxo Consolidado'!#REF! -> #REF! | AJ82: =+'Fluxo Consolidado'!X77 -> -2000 | AK82: 0 | AL82: =+'Fluxo Consolidado'!Y77+'Fluxo Consolidado'!Z77+'Fluxo Consolidado'!AA77 -> -264117.5 | AM82: =+'Fluxo Consolidado'!AB77+'Fluxo Consolidado'!AC77 -> -82239.346 | AN82: =+'Fluxo Consolidado'!AD77 -> 0 | AO82: ='Fluxo Consolidado'!AE77+'Fluxo Consolidado'!AF77 -> -135600 | AP82: =+'Fluxo Consolidado'!AG77 -> 0 | AQ82: =+'Fluxo Consolidado'!AH77 -> -227992.32 | AR82: =+'Fluxo Consolidado'!AI77 -> -9209.81 | AS82: =+'Fluxo Consolidado'!AJ77 -> -7969 | AT82: 0 | AU82: =+'Fluxo Consolidado'!AK77 -> -17048.52 | AV82: =+'Fluxo Consolidado'!AL77 -> -12670.56 | AW82: =-V81*$AW$2 -> -45598.465 | AX82: 0 | AY82: =(-V81*$AY$1)+'Fluxo Consolidado'!AO77 -> -151994.88 | AZ82: 0 | BA82: 0 | BB82: 0 | BC82: =+'Fluxo Consolidado'!AP77 -> 0 | BD82: =+'Fluxo Consolidado'!AQ77 -> 0 | BF82: =V82+Y82+W82+X82 -> 3823389.3 | BG82: =+SUM(AA82:BD82) -> #REF! | BH82: =SUM(BF82:BG82) -> #REF! | BI82: =BH82+BI81 -> #REF! | BJ82: =+BI82-$AX$8 -> #REF! | BQ82: =-AB81 -> 1413358.7 | BR82: -489562.42 | BS82: -85592.362 | BT82: 0 | BU82: -3785174.8 | BV82: 3769632.3 | BW82: =SUM(BQ82:BT82) -> 838203.94 | BX82: =SUM(BR82:BT82) -> -575154.78 | BY82: =V82+BQ82+BR82+BS82+BT82+BU82+BV82 -> 4646050.6 | BZ82: =BG82 -> #REF! | CA82: =SUM(BY82:BZ82) -> #REF! | CB82: =CA82+CB81 -> #REF! | CC82: =CB82-$AX$8 -> #REF! | CE82: =PV($CE$5,A82,,-BH82) -> #REF! | CF82: =PV($CE$5,A82,,-CA82) -> #REF!
A83: =A82+1 -> 21 | C83: 43891 | D83: 0 | E83: 0 | F83: 0 | G83: 0 | H83: 0 | I83: 0 | J83: 0 | K83: =+'Fluxo Consolidado'!D78 -> 1268342.9 | L83: =+'Fluxo Consolidado'!E78 -> 2460818.4 | M83: =+'Fluxo Consolidado'!F78 -> 69110.337 | N83: 0 | O83: =+O82 -> 0.1 | P83: =+'Fluxo Consolidado'!H78 -> -246081.84 | Q83: =+'Fluxo Consolidado'!I78 -> 247302.18 | R83: ='Fluxo Consolidado'!J78 -> 37384.842 | S83: ='Fluxo Consolidado'!K78 -> 2 | T83: =((1+$T$4)^U83-1)*(SUM(K83:L83)*$T$1) -> 0 | U83: 2 | V83: =SUM(P83:R83,K83:N83)+T83 -> 3836876.8 | W83: 0 | X83: 0 | Y83: 0 | Z83: =IFERROR(SUM(AA83:AH83)/SUM($AA$8:$AH$8),0) -> 0.024209045 | AA83: 0 | AB83: -762771.36 | AC83: 0 | AD83: =+'Fluxo Consolidado'!R78 -> -891432.31 | AE83: =+'Fluxo Consolidado'!S78 -> 0 | AF83: ='Fluxo Consolidado'!T78 -> -60000 | AG83: =+'Fluxo Consolidado'!U78 -> 0 | AH83: =+'Fluxo Consolidado'!V78 -> -40882.573 | AI83: =+'Fluxo Consolidado'!#REF! -> #REF! | AJ83: =+'Fluxo Consolidado'!X78 -> -2000 | AK83: 0 | AL83: =+'Fluxo Consolidado'!Y78+'Fluxo Consolidado'!Z78+'Fluxo Consolidado'!AA78 -> -201967.65 | AM83: =+'Fluxo Consolidado'!AB78+'Fluxo Consolidado'!AC78 -> -82116.976 | AN83: =+'Fluxo Consolidado'!AD78 -> 0 | AO83: ='Fluxo Consolidado'!AE78+'Fluxo Consolidado'!AF78 -> -115600 | AP83: =+'Fluxo Consolidado'!AG78 -> 0 | AQ83: =+'Fluxo Consolidado'!AH78 -> -229403.36 | AR83: =+'Fluxo Consolidado'!AI78 -> -9209.81 | AS83: =+'Fluxo Consolidado'!AJ78 -> -7969 | AT83: 0 | AU83: =+'Fluxo Consolidado'!AK78 -> -17104.461 | AV83: =+'Fluxo Consolidado'!AL78 -> -11864.03 | AW83: =-V82*$AW$2 -> -45880.671 | AX83: 0 | AY83: =(-V82*$AY$1)+'Fluxo Consolidado'!AO78 -> -152935.57 | AZ83: 0 | BA83: 0 | BB83: 0 | BC83: =+'Fluxo Consolidado'!AP78 -> 0 | BD83: =+'Fluxo Consolidado'!AQ78 -> 0 | BF83: =V83+Y83+W83+X83 -> 3836876.8 | BG83: =+SUM(AA83:BD83) -> #REF! | BH83: =SUM(BF83:BG83) -> #REF! | BI83: =BH83+BI82 -> #REF! | BJ83: =+BI83-$AX$8 -> #REF! | BQ83: 550001.14 | BR83: -489562.42 | BS83: -83484.659 | BT83: 0 | BU83: -3798597.8 | BV83: 3785174.8 | BW83: =SUM(BQ83:BT83) -> -23045.935 | BX83: =SUM(BR83:BT83) -> -573047.08 | BY83: =V83+BQ83+BR83+BS83+BT83+BU83+BV83 -> 3800407.9 | BZ83: =BG83 -> #REF! | CA83: =SUM(BY83:BZ83) -> #REF! | CB83: =CA83+CB82 -> #REF! | CC83: =CB83-$AX$8 -> #REF! | CE83: =PV($CE$5,A83,,-BH83) -> #REF! | CF83: =PV($CE$5,A83,,-CA83) -> #REF!
A84: =A83+1 -> 22 | C84: 43922 | D84: 0 | E84: 0 | F84: 0 | G84: 0 | H84: 0 | I84: 0 | J84: 0 | K84: =+'Fluxo Consolidado'!D79 -> 1268342.9 | L84: =+'Fluxo Consolidado'!E79 -> 2459122.3 | M84: =+'Fluxo Consolidado'!F79 -> 69110.337 | N84: 0 | O84: 0.05 | P84: =+'Fluxo Consolidado'!H79 -> -245912.23 | Q84: =+'Fluxo Consolidado'!I79 -> 247065.91 | R84: ='Fluxo Consolidado'!J79 -> 56192.003 | S84: ='Fluxo Consolidado'!K79 -> 3 | T84: =((1+$T$4)^U84-1)*(SUM(K84:L84)*$T$1) -> 0 | U84: 2 | V84: =SUM(P84:R84,K84:N84)+T84 -> 3853921.2 | W84: 0 | X84: 0 | Y84: 0 | Z84: =IFERROR(SUM(AA84:AH84)/SUM($AA$8:$AH$8),0) -> 0.012860025 | AA84: 0 | AB84: =+'Fluxo Consolidado'!P79 -> 0 | AC84: ='Fluxo Consolidado'!Q79 -> 0 | AD84: =+'Fluxo Consolidado'!R79 -> -891432.31 | AE84: =+'Fluxo Consolidado'!S79 -> 0 | AF84: ='Fluxo Consolidado'!T79 -> 0 | AG84: =+'Fluxo Consolidado'!U79 -> 0 | AH84: =+'Fluxo Consolidado'!V79 -> -40882.573 | AI84: =+'Fluxo Consolidado'!#REF! -> #REF! | AJ84: =+'Fluxo Consolidado'!X79 -> -2000 | AK84: 0 | AL84: =+'Fluxo Consolidado'!Y79+'Fluxo Consolidado'!Z79+'Fluxo Consolidado'!AA79 -> -163864.23 | AM84: =+'Fluxo Consolidado'!AB79+'Fluxo Consolidado'!AC79 -> -82077.136 | AN84: =+'Fluxo Consolidado'!AD79 -> 0 | AO84: ='Fluxo Consolidado'!AE79+'Fluxo Consolidado'!AF79 -> -60800 | AP84: =+'Fluxo Consolidado'!AG79 -> 0 | AQ84: =+'Fluxo Consolidado'!AH79 -> -230212.61 | AR84: =+'Fluxo Consolidado'!AI79 -> -9209.81 | AS84: =+'Fluxo Consolidado'!AJ79 -> -23969 | AT84: 0 | AU84: =+'Fluxo Consolidado'!AK79 -> -17294.414 | AV84: =+'Fluxo Consolidado'!AL79 -> -9614.48 | AW84: =-V83*$AW$2 -> -46042.522 | AX84: 0 | AY84: =(-V83*$AY$1)+'Fluxo Consolidado'!AO79 -> -163475.07 | AZ84: 0 | BA84: 0 | BB84: 0 | BC84: =+'Fluxo Consolidado'!AP79 -> 0 | BD84: =+'Fluxo Consolidado'!AQ79 -> 0 | BF84: =V84+Y84+W84+X84 -> 3853921.2 | BG84: =+SUM(AA84:BD84) -> #REF! | BH84: =SUM(BF84:BG84) -> #REF! | BI84: =BH84+BI83 -> #REF! | BJ84: =+BI84-$AX$8 -> #REF! | BQ84: 0 | BR84: -489562.42 | BS84: -81436.716 | BT84: 0 | BU84: -3815512 | BV84: 3798597.8 | BW84: =SUM(BQ84:BT84) -> -570999.13 | BX84: =SUM(BR84:BT84) -> -570999.13 | BY84: =V84+BQ84+BR84+BS84+BT84+BU84+BV84 -> 3266007.8 | BZ84: =BG84 -> #REF! | CA84: =SUM(BY84:BZ84) -> #REF! | CB84: =CA84+CB83 -> #REF! | CC84: =CB84-$AX$8 -> #REF! | CE84: =PV($CE$5,A84,,-BH84) -> #REF! | CF84: =PV($CE$5,A84,,-CA84) -> #REF!
